Workbook
Name a: #REF!
Name a: #REF!
Name a: #REF!
Name a: #REF!
Name AGGREGATION: #REF!
Name AGGREGATION: #REF!
Name AGGREGATION: #REF!
Name AGGREGATION: #REF!
Name BankCode: [1]Cover!$E$3
Name CHECK: #REF!
Name CHECK: #REF!
Name CHECK: #REF!
Name CHECK: #REF!
Name CurrencyCode: OFFSET([1]wksCurrency!$B$2:$B$27,1,0,ROWS([1]wksCurrency!$B$2:$B$27)-2)
Name CurrencyName: OFFSET([1]wksCurrency!$A$2:$A$27,1,0,ROWS([1]wksCurrency!$A$2:$A$27)-2)
Name date: [2]BSY_현지화!#REF!
Name date: [2]BSY_현지화!#REF!
Name date: [2]BSY_현지화!#REF!
Name date: [2]BSY_현지화!#REF!
Name DOMAIN: #REF!
Name DOMAIN: #REF!
Name DOMAIN: #REF!
Name DOMAIN: #REF!
Name ENTITY: #REF!
Name ENTITY: #REF!
Name ENTITY: #REF!
Name ENTITY: #REF!
Name FORMAT: #REF!
Name FORMAT: #REF!
Name FORMAT: #REF!
Name FORMAT: #REF!
Name half: [2]BSY_현지화!#REF!
Name half: [2]BSY_현지화!#REF!
Name half: [2]BSY_현지화!#REF!
Name half: [2]BSY_현지화!#REF!
Name ODB_DATA_TYPE: #REF!
Name ODB_DATA_TYPE: #REF!
Name ODB_DATA_TYPE: #REF!
Name ODB_DATA_TYPE: #REF!
Name PREPOPULATE: #REF!
Name PREPOPULATE: #REF!
Name PREPOPULATE: #REF!
Name PREPOPULATE: #REF!
Name REPORTING_CONS: [3]Lists!$J$2:$J$7
Name SEVERITY: #REF!
Name SEVERITY: #REF!
Name SEVERITY: #REF!
Name SEVERITY: #REF!
Name STATUS: #REF!
Name STATUS: #REF!
Name STATUS: #REF!
Name STATUS: #REF!
Name term: [2]BSY_현지화!#REF!
Name term: [2]BSY_현지화!#REF!
Name term: [2]BSY_현지화!#REF!
Name term: [2]BSY_현지화!#REF!
Name YD: [2]BSY_현지화!#REF!
Name YD: [2]BSY_현지화!#REF!
Name YD: [2]BSY_현지화!#REF!
Name YD: [2]BSY_현지화!#REF!

Sheet Reviews
B1: Reviews & Comments
B3: Form Code | C3: Form Name | D3: Form Items | E3: Questions/Comments | F3: By | G3: Date (DD/MM/YY) | H3: Responses | I3: By | J3: Date (DD/MM/YY)
B4: ARF 117_0A | C4: Repricing analysis - denominated in AUD | D4: N/A | E4: N/A | F4: YH | G4: ='[5]Checklist & Lodgement'!K17 -> 44868
B5: ARF 117_0B_1 | C5: Repricing analysis - denominated in foreign currency_1 | D5: N/A | E5: N/A | F5: YH | G5: =G4 -> 44868
B6: ARF 117_0B_2 | C6: Repricing analysis - denominated in foreign currency_2 | D6: N/A | E6: N/A | F6: YH | G6: =G5 -> 44868
B7: ARF 117_0B_3 | C7: Repricing analysis - denominated in foreign currency_3 | D7: N/A | E7: N/A | F7: YH | G7: =G6 -> 44868
B8: ARF 117_0B_4 | C8: Repricing analysis - denominated in foreign currency_4 | D8: N/A | E8: N/A | F8: YH | G8: =G7 -> 44868

Sheet RE33(IRRBB)
A1: ※ 주의
A2: 10690001 | B2: --Allowance For Loan Losses - General | C2: 계수 부호 변경 및 Liability 항목 | K2: Compounded SOFR (Repricing: Overnight (O/N)) | L2: 10630001_USD_100000014_PERDAMAN CHEMICALS & FERTILISERS (FINANCE)PTY LTD | P2: =ROUND(SUM(Q3:AG3)-SUM(Q4:AG4),0)=ROUND(SUM(Q5:AG5),0) -> TRUE | Q2: Overnight (O/N) | R2: 0 to <1 month (excluding O/N) | S2: 1 to < 2 months | T2: 2 to < 3 months | U2: 3 to < 6 months | V2: 6 to < 9 months | W2: 9 to < 12 months | X2: 1 to < 2 years | Y2: 2 to < 3 years | Z2: 3 to < 4 years | AA2: 4 to < 5 years | AB2: 5 to < 7 years | AC2: 7 to < 10 years | AD2: 10 to < 15 years | AE2: 15 to < 20 years | AF2: 20+ years | AG2: Non-interest rate sensitive
A3: 10690001 | B3: Allowance For Loan Losses - General | L3: 10620001_USD_100000033_MACQUARIE GROUP LIMITED | P3: Asset | Q3: =SUMIF($P$12:$P$681,$P$3,Q12:Q681) -> 1.3026423e+08 | R3: =SUMIF($P$12:$P$681,$P$3,R12:R681) -> 82224385 | S3: =SUMIF($P$12:$P$681,$P$3,S12:S681) -> 17184061 | T3: =SUMIF($P$12:$P$681,$P$3,T12:T681) -> 28000000 | U3: =SUMIF($P$12:$P$681,$P$3,U12:U681) -> 10000000 | V3: =SUMIF($P$12:$P$681,$P$3,V12:V681) -> 5053962.5 | W3: =SUMIF($P$12:$P$681,$P$3,W12:W681) -> 0 | X3: =SUMIF($P$12:$P$681,$P$3,X12:X681) -> 16463021 | ... AG3: =SUMIF($P$12:$P$681,$P$3,AG12:AG681) -> 2765808.7
A4: 10690003 | B4: --Allowance for Due from Banks | P4: Liability | Q4: =SUMIF($P$12:$P$681,$P$4,Q12:Q681) -> 0 | R4: =SUMIF($P$12:$P$681,$P$4,R12:R681) -> 1.1426042e+08 | S4: =SUMIF($P$12:$P$681,$P$4,S12:S681) -> 74955979 | T4: =SUMIF($P$12:$P$681,$P$4,T12:T681) -> 31437554 | U4: =SUMIF($P$12:$P$681,$P$4,U12:U681) -> 15718777 | V4: =SUMIF($P$12:$P$681,$P$4,V12:V681) -> 0 | W4: =SUMIF($P$12:$P$681,$P$4,W12:W681) -> 0 | X4: =SUMIF($P$12:$P$681,$P$4,X12:X681) -> 0 | ... AG4: =SUMIF($P$12:$P$681,$P$4,AG12:AG681) -> 55129544
A5: 10690004 | B5: Allowance for NCD | P5: Equity | Q5: =SUMIF($P$12:$P$681,$P$5,Q12:Q681) -> 0 | R5: =SUMIF($P$12:$P$681,$P$5,R12:R681) -> 138.06 | S5: =SUMIF($P$12:$P$681,$P$5,S12:S681) -> 66917.51 | T5: =SUMIF($P$12:$P$681,$P$5,T12:T681) -> 0 | U5: =SUMIF($P$12:$P$681,$P$5,U12:U681) -> 0 | V5: =SUMIF($P$12:$P$681,$P$5,V12:V681) -> 712.5 | W5: =SUMIF($P$12:$P$681,$P$5,W12:W681) -> 0 | X5: =SUMIF($P$12:$P$681,$P$5,X12:X681) -> 66354.42 | ... AG5: =SUMIF($P$12:$P$681,$P$5,AG12:AG681) -> 319075.03
A6: 10690006 | B6: Allowance for Lending
A7: 10690007 | B7: Allowance for Call Loan | P7: Net position/gap | Q7: =Q3-Q4 -> 1.3026423e+08 | R7: =R3-R4 -> -32036037 | S7: =S3-S4 -> -57771918 | T7: =T3-T4 -> -3437553.6 | U7: =U3-U4 -> -5718776.8 | V7: =V3-V4 -> 5053962.5 | W7: =W3-W4 -> 0 | X7: =X3-X4 -> 16463021 | ... AG7: =AG3-AG4 -> -52363735
A8: 20920006 | B8: Unearned Income ON SYNDICATED LOANS | C8: 계수 부호 변경 및 Asset 항목
N9: Repricing Maturity Buckets | P9: From | Q9: =M10 -> 46058 | R9: =Q10 -> 46059 | S9: =R10 -> 46112 | T9: =S10 -> 46142 | U9: =T10 -> 46173 | V9: =U10 -> 46265 | W9: =V10 -> 46356 | X9: =W10 -> 46446 | Y9: =X10 -> 46812 | ... AF9: =AE10 -> 53386 | AG9: Non_sensitive
M10: 46058 | P10: To | Q10: =Q9+1 -> 46059 | R10: =EOMONTH(Q9,1) -> 46112 | S10: =EOMONTH(S9,1) -> 46142 | T10: =EOMONTH(T9,1) -> 46173 | U10: =EOMONTH(U9,3) -> 46265 | V10: =EOMONTH(V9,3) -> 46356 | W10: =EOMONTH(W9,3) -> 46446 | X10: =EOMONTH(X9,12) -> 46812 | Y10: =EOMONTH(Y9,12) -> 47177 | Z10: =EOMONTH(Z9,12) -> 47542 | AA10: =EOMONTH(AA9,12) -> 47907 | AB10: =EOMONTH(AB9,24) -> 48638 | AC10: =EOMONTH(AC9,36) -> 49734 | AD10: =EOMONTH(AD9,60) -> 51560 | AE10: =EOMONTH(AE9,60) -> 53386 | AF10: =EOMONTH(AF9,120) -> 57039
A11: A/C Code | B11: A/C Name | C11: Ref No | D11: Counterparty/Customer No | E11: Counterparty/Customer Name | F11: Ccy | G11: Balance Amt | H11: Base Ccy Amt | I11: Approval/Contract Date | J11: Maturity Date | K11: Next Interest Reset Date | L11: Ref. | M11: Adjusted Amount | N11: Repricing Date | O11: Check | P11: Asset / Liability | Q11: Overnight (O/N) | R11: 0 to <1 month (excluding O/N) | S11: 1 to < 2 months | T11: 2 to < 3 months | U11: 3 to < 6 months | V11: 6 to < 9 months | W11: 9 to < 12 months | X11: 1 to < 2 years | Y11: 2 to < 3 years | Z11: 3 to < 4 years | AA11: 4 to < 5 years | AB11: 5 to < 7 years | AC11: 7 to < 10 years | AD11: 10 to < 15 years | AE11: 15 to < 20 years | AF11: 20+ years | AG11: Non-interest rate sensitive
A12: 10212001 | B12: Due from Domestic Banks on Demand | C12: RCH3001AUD | D12: 100000006 | E12: AUSTRALIA AND NEW ZEALAND BANKING GROUP LTD | F12: AUD | G12: 7807.52 | H12: 7807.52 | L12: =A12&"_"&F12&"_"&D12&"_"&E12 -> 10212001_AUD_100000006_AUSTRALIA AND NEW ZEALAND BANKING GROUP LTD | M12: =IF(COUNTIF($A$2:$A$8,A12)>0,-H12,H12) -> 7807.52 | N12: =IF(OR(L12=$L$2,L12=$L$3),$M$10+1,IFERROR(VLOOKUP(A12,'Repricing Maturity Adj.'!$A$3:$C$170,3,0),(IF(K12<$M$10,"Check",K12)))) -> 46059 | O12: =M12=SUM(Q12:AG12) -> TRUE | P12: =IF(A12="","N/A",IF(COUNTIF($A$2:$A$7,A12)>0,"Liability",IF(COUNTIF($A$8,A12)>0,"Asset",IF(A12<20000000,"Asset",IF(AND(A12>20000000,A12<28800000),"Liability",IF(A12>28800000,"Equity","")))))) -> Asset | Q12: =IF(AND(N12>$Q$9,N12<$Q$10),M12,IF(N12=$Q$10,M12,0)) -> 7807.52 | R12: =IF(AND(N12>$R$9,N12<$R$10),M12,IF(N12=$R$10,M12,0)) -> 0 | S12: =IF(AND(N12>$S$9,N12<$S$10),M12,IF(N12=$S$10,M12,0)) -> 0 | T12: =IF(AND(N12>$T$9,N12<$T$10),M12,IF(N12=$T$10,M12,0)) -> 0 | U12: =IF(AND(N12>$U$9,N12<$U$10),M12,IF(N12=$U$10,M12,0)) -> 0 | V12: =IF(AND(N12>$V$9,N12<$V$10),M12,IF(N12=$V$10,M12,0)) -> 0 | W12: =IF(AND(N12>$W$9,N12<$W$10),M12,IF(N12=$W$10,M12,0)) -> 0 | X12: =IF(AND(N12>$X$9,N12<$X$10),M12,IF(N12=$X$10,M12,0)) -> 0 | Y12: =IF(AND(N12>$Y$9,N12<$Y$10),M12,IF(N12=$Y$10,M12,0)) -> 0 | Z12: =IF(AND(N12>$Z$9,N12<$Z$10),M12,IF(N12=$Z$10,M12,0)) -> 0 | AA12: =IF(AND(N12>$AA$9,N12<$AA$10),M12,IF(N12=$AA$10,M12,0)) -> 0 | AB12: =IF(AND(N12>$AB$9,N12<$AB$10),M12,IF(N12=$AB$10,M12,0)) -> 0 | AC12: =IF(AND(N12>$AC$9,N12<$AC$10),M12,IF(N12=$AC$10,M12,0)) -> 0 | AD12: =IF(AND(N12>$AD$9,N12<$AD$10),M12,IF(N12=$AD$10,M12,0)) -> 0 | AE12: =IF(AND(N12>$AE$9,N12<$AE$10),M12,IF(N12=$AE$10,M12,0)) -> 0 | AF12: =IF(AND(N12>$AF$9,N12<$AF$10),M12,IF(N12=$AF$10,M12,0)) -> 0 | AG12: =IF(N12=$AG$9,M12,0) -> 0
A13: 10212001 | B13: Due from Domestic Banks on Demand | C13: RCH3002AUD | D13: 100000006 | E13: AUSTRALIA AND NEW ZEALAND BANKING GROUP LTD | F13: AUD | G13: 4896.04 | H13: 4896.04 | L13: =A13&"_"&F13&"_"&D13&"_"&E13 -> 10212001_AUD_100000006_AUSTRALIA AND NEW ZEALAND BANKING GROUP LTD | M13: =IF(COUNTIF($A$2:$A$8,A13)>0,-H13,H13) -> 4896.04 | N13: =IF(OR(L13=$L$2,L13=$L$3),$M$10+1,IFERROR(VLOOKUP(A13,'Repricing Maturity Adj.'!$A$3:$C$170,3,0),(IF(K13<$M$10,"Check",K13)))) -> 46059 | O13: =M13=SUM(Q13:AG13) -> TRUE | P13: =IF(A13="","N/A",IF(COUNTIF($A$2:$A$7,A13)>0,"Liability",IF(COUNTIF($A$8,A13)>0,"Asset",IF(A13<20000000,"Asset",IF(AND(A13>20000000,A13<28800000),"Liability",IF(A13>28800000,"Equity","")))))) -> Asset | Q13: =IF(AND(N13>$Q$9,N13<$Q$10),M13,IF(N13=$Q$10,M13,0)) -> 4896.04 | R13: =IF(AND(N13>$R$9,N13<$R$10),M13,IF(N13=$R$10,M13,0)) -> 0 | S13: =IF(AND(N13>$S$9,N13<$S$10),M13,IF(N13=$S$10,M13,0)) -> 0 | T13: =IF(AND(N13>$T$9,N13<$T$10),M13,IF(N13=$T$10,M13,0)) -> 0 | U13: =IF(AND(N13>$U$9,N13<$U$10),M13,IF(N13=$U$10,M13,0)) -> 0 | V13: =IF(AND(N13>$V$9,N13<$V$10),M13,IF(N13=$V$10,M13,0)) -> 0 | W13: =IF(AND(N13>$W$9,N13<$W$10),M13,IF(N13=$W$10,M13,0)) -> 0 | X13: =IF(AND(N13>$X$9,N13<$X$10),M13,IF(N13=$X$10,M13,0)) -> 0 | Y13: =IF(AND(N13>$Y$9,N13<$Y$10),M13,IF(N13=$Y$10,M13,0)) -> 0 | Z13: =IF(AND(N13>$Z$9,N13<$Z$10),M13,IF(N13=$Z$10,M13,0)) -> 0 | AA13: =IF(AND(N13>$AA$9,N13<$AA$10),M13,IF(N13=$AA$10,M13,0)) -> 0 | AB13: =IF(AND(N13>$AB$9,N13<$AB$10),M13,IF(N13=$AB$10,M13,0)) -> 0 | AC13: =IF(AND(N13>$AC$9,N13<$AC$10),M13,IF(N13=$AC$10,M13,0)) -> 0 | AD13: =IF(AND(N13>$AD$9,N13<$AD$10),M13,IF(N13=$AD$10,M13,0)) -> 0 | AE13: =IF(AND(N13>$AE$9,N13<$AE$10),M13,IF(N13=$AE$10,M13,0)) -> 0 | AF13: =IF(AND(N13>$AF$9,N13<$AF$10),M13,IF(N13=$AF$10,M13,0)) -> 0 | AG13: =IF(N13=$AG$9,M13,0) -> 0
A14: 10212001 | B14: Due from Domestic Banks on Demand | C14: RCH3003AUD | D14: 100000006 | E14: AUSTRALIA AND NEW ZEALAND BANKING GROUP LTD | F14: AUD | G14: 87377.23 | H14: 87377.23 | L14: =A14&"_"&F14&"_"&D14&"_"&E14 -> 10212001_AUD_100000006_AUSTRALIA AND NEW ZEALAND BANKING GROUP LTD | M14: =IF(COUNTIF($A$2:$A$8,A14)>0,-H14,H14) -> 87377.23 | N14: =IF(OR(L14=$L$2,L14=$L$3),$M$10+1,IFERROR(VLOOKUP(A14,'Repricing Maturity Adj.'!$A$3:$C$170,3,0),(IF(K14<$M$10,"Check",K14)))) -> 46059 | O14: =M14=SUM(Q14:AG14) -> TRUE | P14: =IF(A14="","N/A",IF(COUNTIF($A$2:$A$7,A14)>0,"Liability",IF(COUNTIF($A$8,A14)>0,"Asset",IF(A14<20000000,"Asset",IF(AND(A14>20000000,A14<28800000),"Liability",IF(A14>28800000,"Equity","")))))) -> Asset | Q14: =IF(AND(N14>$Q$9,N14<$Q$10),M14,IF(N14=$Q$10,M14,0)) -> 87377.23 | R14: =IF(AND(N14>$R$9,N14<$R$10),M14,IF(N14=$R$10,M14,0)) -> 0 | S14: =IF(AND(N14>$S$9,N14<$S$10),M14,IF(N14=$S$10,M14,0)) -> 0 | T14: =IF(AND(N14>$T$9,N14<$T$10),M14,IF(N14=$T$10,M14,0)) -> 0 | U14: =IF(AND(N14>$U$9,N14<$U$10),M14,IF(N14=$U$10,M14,0)) -> 0 | V14: =IF(AND(N14>$V$9,N14<$V$10),M14,IF(N14=$V$10,M14,0)) -> 0 | W14: =IF(AND(N14>$W$9,N14<$W$10),M14,IF(N14=$W$10,M14,0)) -> 0 | X14: =IF(AND(N14>$X$9,N14<$X$10),M14,IF(N14=$X$10,M14,0)) -> 0 | Y14: =IF(AND(N14>$Y$9,N14<$Y$10),M14,IF(N14=$Y$10,M14,0)) -> 0 | Z14: =IF(AND(N14>$Z$9,N14<$Z$10),M14,IF(N14=$Z$10,M14,0)) -> 0 | AA14: =IF(AND(N14>$AA$9,N14<$AA$10),M14,IF(N14=$AA$10,M14,0)) -> 0 | AB14: =IF(AND(N14>$AB$9,N14<$AB$10),M14,IF(N14=$AB$10,M14,0)) -> 0 | AC14: =IF(AND(N14>$AC$9,N14<$AC$10),M14,IF(N14=$AC$10,M14,0)) -> 0 | AD14: =IF(AND(N14>$AD$9,N14<$AD$10),M14,IF(N14=$AD$10,M14,0)) -> 0 | AE14: =IF(AND(N14>$AE$9,N14<$AE$10),M14,IF(N14=$AE$10,M14,0)) -> 0 | AF14: =IF(AND(N14>$AF$9,N14<$AF$10),M14,IF(N14=$AF$10,M14,0)) -> 0 | AG14: =IF(N14=$AG$9,M14,0) -> 0
A15: 10212001 | B15: Due from Domestic Banks on Demand | C15: RCH3004AUD | D15: 100000013 | E15: KEB HANA BANK | F15: AUD | G15: 4600972.1 | H15: 4600972.1 | L15: =A15&"_"&F15&"_"&D15&"_"&E15 -> 10212001_AUD_100000013_KEB HANA BANK | M15: =IF(COUNTIF($A$2:$A$8,A15)>0,-H15,H15) -> 4600972.1 | N15: =IF(OR(L15=$L$2,L15=$L$3),$M$10+1,IFERROR(VLOOKUP(A15,'Repricing Maturity Adj.'!$A$3:$C$170,3,0),(IF(K15<$M$10,"Check",K15)))) -> 46059 | O15: =M15=SUM(Q15:AG15) -> TRUE | P15: =IF(A15="","N/A",IF(COUNTIF($A$2:$A$7,A15)>0,"Liability",IF(COUNTIF($A$8,A15)>0,"Asset",IF(A15<20000000,"Asset",IF(AND(A15>20000000,A15<28800000),"Liability",IF(A15>28800000,"Equity","")))))) -> Asset | Q15: =IF(AND(N15>$Q$9,N15<$Q$10),M15,IF(N15=$Q$10,M15,0)) -> 4600972.1 | R15: =IF(AND(N15>$R$9,N15<$R$10),M15,IF(N15=$R$10,M15,0)) -> 0 | S15: =IF(AND(N15>$S$9,N15<$S$10),M15,IF(N15=$S$10,M15,0)) -> 0 | T15: =IF(AND(N15>$T$9,N15<$T$10),M15,IF(N15=$T$10,M15,0)) -> 0 | U15: =IF(AND(N15>$U$9,N15<$U$10),M15,IF(N15=$U$10,M15,0)) -> 0 | V15: =IF(AND(N15>$V$9,N15<$V$10),M15,IF(N15=$V$10,M15,0)) -> 0 | W15: =IF(AND(N15>$W$9,N15<$W$10),M15,IF(N15=$W$10,M15,0)) -> 0 | X15: =IF(AND(N15>$X$9,N15<$X$10),M15,IF(N15=$X$10,M15,0)) -> 0 | Y15: =IF(AND(N15>$Y$9,N15<$Y$10),M15,IF(N15=$Y$10,M15,0)) -> 0 | Z15: =IF(AND(N15>$Z$9,N15<$Z$10),M15,IF(N15=$Z$10,M15,0)) -> 0 | AA15: =IF(AND(N15>$AA$9,N15<$AA$10),M15,IF(N15=$AA$10,M15,0)) -> 0 | AB15: =IF(AND(N15>$AB$9,N15<$AB$10),M15,IF(N15=$AB$10,M15,0)) -> 0 | AC15: =IF(AND(N15>$AC$9,N15<$AC$10),M15,IF(N15=$AC$10,M15,0)) -> 0 | AD15: =IF(AND(N15>$AD$9,N15<$AD$10),M15,IF(N15=$AD$10,M15,0)) -> 0 | AE15: =IF(AND(N15>$AE$9,N15<$AE$10),M15,IF(N15=$AE$10,M15,0)) -> 0 | AF15: =IF(AND(N15>$AF$9,N15<$AF$10),M15,IF(N15=$AF$10,M15,0)) -> 0 | AG15: =IF(N15=$AG$9,M15,0) -> 0
A16: 10212001 | B16: Due from Domestic Banks on Demand | C16: RCH3004USD | D16: 100000013 | E16: KEB HANA BANK | F16: USD | G16: 1351406.1 | H16: 1931131.9 | L16: =A16&"_"&F16&"_"&D16&"_"&E16 -> 10212001_USD_100000013_KEB HANA BANK | M16: =IF(COUNTIF($A$2:$A$8,A16)>0,-H16,H16) -> 1931131.9 | N16: =IF(OR(L16=$L$2,L16=$L$3),$M$10+1,IFERROR(VLOOKUP(A16,'Repricing Maturity Adj.'!$A$3:$C$170,3,0),(IF(K16<$M$10,"Check",K16)))) -> 46059 | O16: =M16=SUM(Q16:AG16) -> TRUE | P16: =IF(A16="","N/A",IF(COUNTIF($A$2:$A$7,A16)>0,"Liability",IF(COUNTIF($A$8,A16)>0,"Asset",IF(A16<20000000,"Asset",IF(AND(A16>20000000,A16<28800000),"Liability",IF(A16>28800000,"Equity","")))))) -> Asset | Q16: =IF(AND(N16>$Q$9,N16<$Q$10),M16,IF(N16=$Q$10,M16,0)) -> 1931131.9 | R16: =IF(AND(N16>$R$9,N16<$R$10),M16,IF(N16=$R$10,M16,0)) -> 0 | S16: =IF(AND(N16>$S$9,N16<$S$10),M16,IF(N16=$S$10,M16,0)) -> 0 | T16: =IF(AND(N16>$T$9,N16<$T$10),M16,IF(N16=$T$10,M16,0)) -> 0 | U16: =IF(AND(N16>$U$9,N16<$U$10),M16,IF(N16=$U$10,M16,0)) -> 0 | V16: =IF(AND(N16>$V$9,N16<$V$10),M16,IF(N16=$V$10,M16,0)) -> 0 | W16: =IF(AND(N16>$W$9,N16<$W$10),M16,IF(N16=$W$10,M16,0)) -> 0 | X16: =IF(AND(N16>$X$9,N16<$X$10),M16,IF(N16=$X$10,M16,0)) -> 0 | Y16: =IF(AND(N16>$Y$9,N16<$Y$10),M16,IF(N16=$Y$10,M16,0)) -> 0 | Z16: =IF(AND(N16>$Z$9,N16<$Z$10),M16,IF(N16=$Z$10,M16,0)) -> 0 | AA16: =IF(AND(N16>$AA$9,N16<$AA$10),M16,IF(N16=$AA$10,M16,0)) -> 0 | AB16: =IF(AND(N16>$AB$9,N16<$AB$10),M16,IF(N16=$AB$10,M16,0)) -> 0 | AC16: =IF(AND(N16>$AC$9,N16<$AC$10),M16,IF(N16=$AC$10,M16,0)) -> 0 | AD16: =IF(AND(N16>$AD$9,N16<$AD$10),M16,IF(N16=$AD$10,M16,0)) -> 0 | AE16: =IF(AND(N16>$AE$9,N16<$AE$10),M16,IF(N16=$AE$10,M16,0)) -> 0 | AF16: =IF(AND(N16>$AF$9,N16<$AF$10),M16,IF(N16=$AF$10,M16,0)) -> 0 | AG16: =IF(N16=$AG$9,M16,0) -> 0
A17: 10212002 | B17: Due from Oversea Banks on Demand | C17: RCH4001USD | D17: 100000016 | E17: BANK OF AMERICA N.A.(H.O.) | F17: USD | G17: 2889.33 | H17: 4128.79 | L17: =A17&"_"&F17&"_"&D17&"_"&E17 -> 10212002_USD_100000016_BANK OF AMERICA N.A.(H.O.) | M17: =IF(COUNTIF($A$2:$A$8,A17)>0,-H17,H17) -> 4128.79 | N17: =IF(OR(L17=$L$2,L17=$L$3),$M$10+1,IFERROR(VLOOKUP(A17,'Repricing Maturity Adj.'!$A$3:$C$170,3,0),(IF(K17<$M$10,"Check",K17)))) -> 46059 | O17: =M17=SUM(Q17:AG17) -> TRUE | P17: =IF(A17="","N/A",IF(COUNTIF($A$2:$A$7,A17)>0,"Liability",IF(COUNTIF($A$8,A17)>0,"Asset",IF(A17<20000000,"Asset",IF(AND(A17>20000000,A17<28800000),"Liability",IF(A17>28800000,"Equity","")))))) -> Asset | Q17: =IF(AND(N17>$Q$9,N17<$Q$10),M17,IF(N17=$Q$10,M17,0)) -> 4128.79 | R17: =IF(AND(N17>$R$9,N17<$R$10),M17,IF(N17=$R$10,M17,0)) -> 0 | S17: =IF(AND(N17>$S$9,N17<$S$10),M17,IF(N17=$S$10,M17,0)) -> 0 | T17: =IF(AND(N17>$T$9,N17<$T$10),M17,IF(N17=$T$10,M17,0)) -> 0 | U17: =IF(AND(N17>$U$9,N17<$U$10),M17,IF(N17=$U$10,M17,0)) -> 0 | V17: =IF(AND(N17>$V$9,N17<$V$10),M17,IF(N17=$V$10,M17,0)) -> 0 | W17: =IF(AND(N17>$W$9,N17<$W$10),M17,IF(N17=$W$10,M17,0)) -> 0 | X17: =IF(AND(N17>$X$9,N17<$X$10),M17,IF(N17=$X$10,M17,0)) -> 0 | Y17: =IF(AND(N17>$Y$9,N17<$Y$10),M17,IF(N17=$Y$10,M17,0)) -> 0 | Z17: =IF(AND(N17>$Z$9,N17<$Z$10),M17,IF(N17=$Z$10,M17,0)) -> 0 | AA17: =IF(AND(N17>$AA$9,N17<$AA$10),M17,IF(N17=$AA$10,M17,0)) -> 0 | AB17: =IF(AND(N17>$AB$9,N17<$AB$10),M17,IF(N17=$AB$10,M17,0)) -> 0 | AC17: =IF(AND(N17>$AC$9,N17<$AC$10),M17,IF(N17=$AC$10,M17,0)) -> 0 | AD17: =IF(AND(N17>$AD$9,N17<$AD$10),M17,IF(N17=$AD$10,M17,0)) -> 0 | AE17: =IF(AND(N17>$AE$9,N17<$AE$10),M17,IF(N17=$AE$10,M17,0)) -> 0 | AF17: =IF(AND(N17>$AF$9,N17<$AF$10),M17,IF(N17=$AF$10,M17,0)) -> 0 | AG17: =IF(N17=$AG$9,M17,0) -> 0
A18: 10251002 | B18: Call Loan within 3M - Domestic | C18: FM5904250000051 | D18: 100000008 | E18: E.SUN COMMERCIAL BANK LTD | F18: AUD | G18: 10000000 | H18: 10000000 | I18: 46015 | J18: 46106 | K18: 46106 | L18: =A18&"_"&F18&"_"&D18&"_"&E18 -> 10251002_AUD_100000008_E.SUN COMMERCIAL BANK LTD | M18: =IF(COUNTIF($A$2:$A$8,A18)>0,-H18,H18) -> 10000000 | N18: =IF(OR(L18=$L$2,L18=$L$3),$M$10+1,IFERROR(VLOOKUP(A18,'Repricing Maturity Adj.'!$A$3:$C$170,3,0),(IF(K18<$M$10,"Check",K18)))) -> 46106 | O18: =M18=SUM(Q18:AG18) -> TRUE | P18: =IF(A18="","N/A",IF(COUNTIF($A$2:$A$7,A18)>0,"Liability",IF(COUNTIF($A$8,A18)>0,"Asset",IF(A18<20000000,"Asset",IF(AND(A18>20000000,A18<28800000),"Liability",IF(A18>28800000,"Equity","")))))) -> Asset | Q18: =IF(AND(N18>$Q$9,N18<$Q$10),M18,IF(N18=$Q$10,M18,0)) -> 0 | R18: =IF(AND(N18>$R$9,N18<$R$10),M18,IF(N18=$R$10,M18,0)) -> 10000000 | S18: =IF(AND(N18>$S$9,N18<$S$10),M18,IF(N18=$S$10,M18,0)) -> 0 | T18: =IF(AND(N18>$T$9,N18<$T$10),M18,IF(N18=$T$10,M18,0)) -> 0 | U18: =IF(AND(N18>$U$9,N18<$U$10),M18,IF(N18=$U$10,M18,0)) -> 0 | V18: =IF(AND(N18>$V$9,N18<$V$10),M18,IF(N18=$V$10,M18,0)) -> 0 | W18: =IF(AND(N18>$W$9,N18<$W$10),M18,IF(N18=$W$10,M18,0)) -> 0 | X18: =IF(AND(N18>$X$9,N18<$X$10),M18,IF(N18=$X$10,M18,0)) -> 0 | Y18: =IF(AND(N18>$Y$9,N18<$Y$10),M18,IF(N18=$Y$10,M18,0)) -> 0 | Z18: =IF(AND(N18>$Z$9,N18<$Z$10),M18,IF(N18=$Z$10,M18,0)) -> 0 | AA18: =IF(AND(N18>$AA$9,N18<$AA$10),M18,IF(N18=$AA$10,M18,0)) -> 0 | AB18: =IF(AND(N18>$AB$9,N18<$AB$10),M18,IF(N18=$AB$10,M18,0)) -> 0 | AC18: =IF(AND(N18>$AC$9,N18<$AC$10),M18,IF(N18=$AC$10,M18,0)) -> 0 | AD18: =IF(AND(N18>$AD$9,N18<$AD$10),M18,IF(N18=$AD$10,M18,0)) -> 0 | AE18: =IF(AND(N18>$AE$9,N18<$AE$10),M18,IF(N18=$AE$10,M18,0)) -> 0 | AF18: =IF(AND(N18>$AF$9,N18<$AF$10),M18,IF(N18=$AF$10,M18,0)) -> 0 | AG18: =IF(N18=$AG$9,M18,0) -> 0
A19: 10251002 | B19: Call Loan within 3M - Domestic | C19: FM5904260000003 | D19: 100000008 | E19: E.SUN COMMERCIAL BANK LTD | F19: AUD | G19: 3000000 | H19: 3000000 | I19: 46035 | J19: 46090 | K19: 46090 | L19: =A19&"_"&F19&"_"&D19&"_"&E19 -> 10251002_AUD_100000008_E.SUN COMMERCIAL BANK LTD | M19: =IF(COUNTIF($A$2:$A$8,A19)>0,-H19,H19) -> 3000000 | N19: =IF(OR(L19=$L$2,L19=$L$3),$M$10+1,IFERROR(VLOOKUP(A19,'Repricing Maturity Adj.'!$A$3:$C$170,3,0),(IF(K19<$M$10,"Check",K19)))) -> 46090 | O19: =M19=SUM(Q19:AG19) -> TRUE | P19: =IF(A19="","N/A",IF(COUNTIF($A$2:$A$7,A19)>0,"Liability",IF(COUNTIF($A$8,A19)>0,"Asset",IF(A19<20000000,"Asset",IF(AND(A19>20000000,A19<28800000),"Liability",IF(A19>28800000,"Equity","")))))) -> Asset | Q19: =IF(AND(N19>$Q$9,N19<$Q$10),M19,IF(N19=$Q$10,M19,0)) -> 0 | R19: =IF(AND(N19>$R$9,N19<$R$10),M19,IF(N19=$R$10,M19,0)) -> 3000000 | S19: =IF(AND(N19>$S$9,N19<$S$10),M19,IF(N19=$S$10,M19,0)) -> 0 | T19: =IF(AND(N19>$T$9,N19<$T$10),M19,IF(N19=$T$10,M19,0)) -> 0 | U19: =IF(AND(N19>$U$9,N19<$U$10),M19,IF(N19=$U$10,M19,0)) -> 0 | V19: =IF(AND(N19>$V$9,N19<$V$10),M19,IF(N19=$V$10,M19,0)) -> 0 | W19: =IF(AND(N19>$W$9,N19<$W$10),M19,IF(N19=$W$10,M19,0)) -> 0 | X19: =IF(AND(N19>$X$9,N19<$X$10),M19,IF(N19=$X$10,M19,0)) -> 0 | Y19: =IF(AND(N19>$Y$9,N19<$Y$10),M19,IF(N19=$Y$10,M19,0)) -> 0 | Z19: =IF(AND(N19>$Z$9,N19<$Z$10),M19,IF(N19=$Z$10,M19,0)) -> 0 | AA19: =IF(AND(N19>$AA$9,N19<$AA$10),M19,IF(N19=$AA$10,M19,0)) -> 0 | AB19: =IF(AND(N19>$AB$9,N19<$AB$10),M19,IF(N19=$AB$10,M19,0)) -> 0 | AC19: =IF(AND(N19>$AC$9,N19<$AC$10),M19,IF(N19=$AC$10,M19,0)) -> 0 | AD19: =IF(AND(N19>$AD$9,N19<$AD$10),M19,IF(N19=$AD$10,M19,0)) -> 0 | AE19: =IF(AND(N19>$AE$9,N19<$AE$10),M19,IF(N19=$AE$10,M19,0)) -> 0 | AF19: =IF(AND(N19>$AF$9,N19<$AF$10),M19,IF(N19=$AF$10,M19,0)) -> 0 | AG19: =IF(N19=$AG$9,M19,0) -> 0
A20: 10251002 | B20: Call Loan within 3M - Domestic | C20: FM5904260000004 | D20: 100000008 | E20: E.SUN COMMERCIAL BANK LTD | F20: AUD | G20: 4000000 | H20: 4000000 | I20: 46035 | J20: 46125 | K20: 46125 | L20: =A20&"_"&F20&"_"&D20&"_"&E20 -> 10251002_AUD_100000008_E.SUN COMMERCIAL BANK LTD | M20: =IF(COUNTIF($A$2:$A$8,A20)>0,-H20,H20) -> 4000000 | N20: =IF(OR(L20=$L$2,L20=$L$3),$M$10+1,IFERROR(VLOOKUP(A20,'Repricing Maturity Adj.'!$A$3:$C$170,3,0),(IF(K20<$M$10,"Check",K20)))) -> 46125 | O20: =M20=SUM(Q20:AG20) -> TRUE | P20: =IF(A20="","N/A",IF(COUNTIF($A$2:$A$7,A20)>0,"Liability",IF(COUNTIF($A$8,A20)>0,"Asset",IF(A20<20000000,"Asset",IF(AND(A20>20000000,A20<28800000),"Liability",IF(A20>28800000,"Equity","")))))) -> Asset | Q20: =IF(AND(N20>$Q$9,N20<$Q$10),M20,IF(N20=$Q$10,M20,0)) -> 0 | R20: =IF(AND(N20>$R$9,N20<$R$10),M20,IF(N20=$R$10,M20,0)) -> 0 | S20: =IF(AND(N20>$S$9,N20<$S$10),M20,IF(N20=$S$10,M20,0)) -> 4000000 | T20: =IF(AND(N20>$T$9,N20<$T$10),M20,IF(N20=$T$10,M20,0)) -> 0 | U20: =IF(AND(N20>$U$9,N20<$U$10),M20,IF(N20=$U$10,M20,0)) -> 0 | V20: =IF(AND(N20>$V$9,N20<$V$10),M20,IF(N20=$V$10,M20,0)) -> 0 | W20: =IF(AND(N20>$W$9,N20<$W$10),M20,IF(N20=$W$10,M20,0)) -> 0 | X20: =IF(AND(N20>$X$9,N20<$X$10),M20,IF(N20=$X$10,M20,0)) -> 0 | Y20: =IF(AND(N20>$Y$9,N20<$Y$10),M20,IF(N20=$Y$10,M20,0)) -> 0 | Z20: =IF(AND(N20>$Z$9,N20<$Z$10),M20,IF(N20=$Z$10,M20,0)) -> 0 | AA20: =IF(AND(N20>$AA$9,N20<$AA$10),M20,IF(N20=$AA$10,M20,0)) -> 0 | AB20: =IF(AND(N20>$AB$9,N20<$AB$10),M20,IF(N20=$AB$10,M20,0)) -> 0 | AC20: =IF(AND(N20>$AC$9,N20<$AC$10),M20,IF(N20=$AC$10,M20,0)) -> 0 | AD20: =IF(AND(N20>$AD$9,N20<$AD$10),M20,IF(N20=$AD$10,M20,0)) -> 0 | AE20: =IF(AND(N20>$AE$9,N20<$AE$10),M20,IF(N20=$AE$10,M20,0)) -> 0 | AF20: =IF(AND(N20>$AF$9,N20<$AF$10),M20,IF(N20=$AF$10,M20,0)) -> 0 | AG20: =IF(N20=$AG$9,M20,0) -> 0
A21: 10310002 | B21: Securities - FVOCI State | C21: FB5904240000001 | D21: 100000027 | E21: TREASURY CORPORATION OF VICTORIA | F21: AUD | G21: 5053962.5 | H21: 5053962.5 | I21: 45387 | J21: 46343 | K21: 46342 | L21: =A21&"_"&F21&"_"&D21&"_"&E21 -> 10310002_AUD_100000027_TREASURY CORPORATION OF VICTORIA | M21: =IF(COUNTIF($A$2:$A$8,A21)>0,-H21,H21) -> 5053962.5 | N21: =IF(OR(L21=$L$2,L21=$L$3),$M$10+1,IFERROR(VLOOKUP(A21,'Repricing Maturity Adj.'!$A$3:$C$170,3,0),(IF(K21<$M$10,"Check",K21)))) -> 46342 | O21: =M21=SUM(Q21:AG21) -> TRUE | P21: =IF(A21="","N/A",IF(COUNTIF($A$2:$A$7,A21)>0,"Liability",IF(COUNTIF($A$8,A21)>0,"Asset",IF(A21<20000000,"Asset",IF(AND(A21>20000000,A21<28800000),"Liability",IF(A21>28800000,"Equity","")))))) -> Asset | Q21: =IF(AND(N21>$Q$9,N21<$Q$10),M21,IF(N21=$Q$10,M21,0)) -> 0 | R21: =IF(AND(N21>$R$9,N21<$R$10),M21,IF(N21=$R$10,M21,0)) -> 0 | S21: =IF(AND(N21>$S$9,N21<$S$10),M21,IF(N21=$S$10,M21,0)) -> 0 | T21: =IF(AND(N21>$T$9,N21<$T$10),M21,IF(N21=$T$10,M21,0)) -> 0 | U21: =IF(AND(N21>$U$9,N21<$U$10),M21,IF(N21=$U$10,M21,0)) -> 0 | V21: =IF(AND(N21>$V$9,N21<$V$10),M21,IF(N21=$V$10,M21,0)) -> 5053962.5 | W21: =IF(AND(N21>$W$9,N21<$W$10),M21,IF(N21=$W$10,M21,0)) -> 0 | X21: =IF(AND(N21>$X$9,N21<$X$10),M21,IF(N21=$X$10,M21,0)) -> 0 | Y21: =IF(AND(N21>$Y$9,N21<$Y$10),M21,IF(N21=$Y$10,M21,0)) -> 0 | Z21: =IF(AND(N21>$Z$9,N21<$Z$10),M21,IF(N21=$Z$10,M21,0)) -> 0 | AA21: =IF(AND(N21>$AA$9,N21<$AA$10),M21,IF(N21=$AA$10,M21,0)) -> 0 | AB21: =IF(AND(N21>$AB$9,N21<$AB$10),M21,IF(N21=$AB$10,M21,0)) -> 0 | AC21: =IF(AND(N21>$AC$9,N21<$AC$10),M21,IF(N21=$AC$10,M21,0)) -> 0 | AD21: =IF(AND(N21>$AD$9,N21<$AD$10),M21,IF(N21=$AD$10,M21,0)) -> 0 | AE21: =IF(AND(N21>$AE$9,N21<$AE$10),M21,IF(N21=$AE$10,M21,0)) -> 0 | AF21: =IF(AND(N21>$AF$9,N21<$AF$10),M21,IF(N21=$AF$10,M21,0)) -> 0 | AG21: =IF(N21=$AG$9,M21,0) -> 0
A22: 10310002 | B22: Securities - FVOCI State | C22: FB5904240000003 | D22: 100000034 | E22: WESTERN AUSTRALIAN TREASURY CORPORATION | F22: AUD | G22: 4000347.4 | H22: 4000347.4 | I22: 45552 | J22: 46091 | K22: 46090 | L22: =A22&"_"&F22&"_"&D22&"_"&E22 -> 10310002_AUD_100000034_WESTERN AUSTRALIAN TREASURY CORPORATION | M22: =IF(COUNTIF($A$2:$A$8,A22)>0,-H22,H22) -> 4000347.4 | N22: =IF(OR(L22=$L$2,L22=$L$3),$M$10+1,IFERROR(VLOOKUP(A22,'Repricing Maturity Adj.'!$A$3:$C$170,3,0),(IF(K22<$M$10,"Check",K22)))) -> 46090 | O22: =M22=SUM(Q22:AG22) -> TRUE | P22: =IF(A22="","N/A",IF(COUNTIF($A$2:$A$7,A22)>0,"Liability",IF(COUNTIF($A$8,A22)>0,"Asset",IF(A22<20000000,"Asset",IF(AND(A22>20000000,A22<28800000),"Liability",IF(A22>28800000,"Equity","")))))) -> Asset | Q22: =IF(AND(N22>$Q$9,N22<$Q$10),M22,IF(N22=$Q$10,M22,0)) -> 0 | R22: =IF(AND(N22>$R$9,N22<$R$10),M22,IF(N22=$R$10,M22,0)) -> 4000347.4 | S22: =IF(AND(N22>$S$9,N22<$S$10),M22,IF(N22=$S$10,M22,0)) -> 0 | T22: =IF(AND(N22>$T$9,N22<$T$10),M22,IF(N22=$T$10,M22,0)) -> 0 | U22: =IF(AND(N22>$U$9,N22<$U$10),M22,IF(N22=$U$10,M22,0)) -> 0 | V22: =IF(AND(N22>$V$9,N22<$V$10),M22,IF(N22=$V$10,M22,0)) -> 0 | W22: =IF(AND(N22>$W$9,N22<$W$10),M22,IF(N22=$W$10,M22,0)) -> 0 | X22: =IF(AND(N22>$X$9,N22<$X$10),M22,IF(N22=$X$10,M22,0)) -> 0 | Y22: =IF(AND(N22>$Y$9,N22<$Y$10),M22,IF(N22=$Y$10,M22,0)) -> 0 | Z22: =IF(AND(N22>$Z$9,N22<$Z$10),M22,IF(N22=$Z$10,M22,0)) -> 0 | AA22: =IF(AND(N22>$AA$9,N22<$AA$10),M22,IF(N22=$AA$10,M22,0)) -> 0 | AB22: =IF(AND(N22>$AB$9,N22<$AB$10),M22,IF(N22=$AB$10,M22,0)) -> 0 | AC22: =IF(AND(N22>$AC$9,N22<$AC$10),M22,IF(N22=$AC$10,M22,0)) -> 0 | AD22: =IF(AND(N22>$AD$9,N22<$AD$10),M22,IF(N22=$AD$10,M22,0)) -> 0 | AE22: =IF(AND(N22>$AE$9,N22<$AE$10),M22,IF(N22=$AE$10,M22,0)) -> 0 | AF22: =IF(AND(N22>$AF$9,N22<$AF$10),M22,IF(N22=$AF$10,M22,0)) -> 0 | AG22: =IF(N22=$AG$9,M22,0) -> 0
A23: 10310002 | B23: Securities - FVOCI State | C23: FB5904250000003 | D23: 100000038 | E23: TASMANIAN PUBLIC FINANCE CORPORATION | F23: AUD | G23: 4891657.6 | H23: 4891657.6 | I23: 45755 | J23: 46776 | K23: 46775 | L23: =A23&"_"&F23&"_"&D23&"_"&E23 -> 10310002_AUD_100000038_TASMANIAN PUBLIC FINANCE CORPORATION | M23: =IF(COUNTIF($A$2:$A$8,A23)>0,-H23,H23) -> 4891657.6 | N23: =IF(OR(L23=$L$2,L23=$L$3),$M$10+1,IFERROR(VLOOKUP(A23,'Repricing Maturity Adj.'!$A$3:$C$170,3,0),(IF(K23<$M$10,"Check",K23)))) -> 46775 | O23: =M23=SUM(Q23:AG23) -> TRUE | P23: =IF(A23="","N/A",IF(COUNTIF($A$2:$A$7,A23)>0,"Liability",IF(COUNTIF($A$8,A23)>0,"Asset",IF(A23<20000000,"Asset",IF(AND(A23>20000000,A23<28800000),"Liability",IF(A23>28800000,"Equity","")))))) -> Asset | Q23: =IF(AND(N23>$Q$9,N23<$Q$10),M23,IF(N23=$Q$10,M23,0)) -> 0 | R23: =IF(AND(N23>$R$9,N23<$R$10),M23,IF(N23=$R$10,M23,0)) -> 0 | S23: =IF(AND(N23>$S$9,N23<$S$10),M23,IF(N23=$S$10,M23,0)) -> 0 | T23: =IF(AND(N23>$T$9,N23<$T$10),M23,IF(N23=$T$10,M23,0)) -> 0 | U23: =IF(AND(N23>$U$9,N23<$U$10),M23,IF(N23=$U$10,M23,0)) -> 0 | V23: =IF(AND(N23>$V$9,N23<$V$10),M23,IF(N23=$V$10,M23,0)) -> 0 | W23: =IF(AND(N23>$W$9,N23<$W$10),M23,IF(N23=$W$10,M23,0)) -> 0 | X23: =IF(AND(N23>$X$9,N23<$X$10),M23,IF(N23=$X$10,M23,0)) -> 4891657.6 | Y23: =IF(AND(N23>$Y$9,N23<$Y$10),M23,IF(N23=$Y$10,M23,0)) -> 0 | Z23: =IF(AND(N23>$Z$9,N23<$Z$10),M23,IF(N23=$Z$10,M23,0)) -> 0 | AA23: =IF(AND(N23>$AA$9,N23<$AA$10),M23,IF(N23=$AA$10,M23,0)) -> 0 | AB23: =IF(AND(N23>$AB$9,N23<$AB$10),M23,IF(N23=$AB$10,M23,0)) -> 0 | AC23: =IF(AND(N23>$AC$9,N23<$AC$10),M23,IF(N23=$AC$10,M23,0)) -> 0 | AD23: =IF(AND(N23>$AD$9,N23<$AD$10),M23,IF(N23=$AD$10,M23,0)) -> 0 | AE23: =IF(AND(N23>$AE$9,N23<$AE$10),M23,IF(N23=$AE$10,M23,0)) -> 0 | AF23: =IF(AND(N23>$AF$9,N23<$AF$10),M23,IF(N23=$AF$10,M23,0)) -> 0 | AG23: =IF(N23=$AG$9,M23,0) -> 0
A24: 10310003 | B24: Foreign GovT & Official Institution - FVOCI | C24: FB5904240000005 | D24: 100000037 | E24: THE EXPORT-IMPORT BANK OF KOREA | F24: USD | G24: 5027405.6 | H24: 7184060.6 | I24: 45624 | J24: 46677 | K24: 46128 | L24: =A24&"_"&F24&"_"&D24&"_"&E24 -> 10310003_USD_100000037_THE EXPORT-IMPORT BANK OF KOREA | M24: =IF(COUNTIF($A$2:$A$8,A24)>0,-H24,H24) -> 7184060.6 | N24: =IF(OR(L24=$L$2,L24=$L$3),$M$10+1,IFERROR(VLOOKUP(A24,'Repricing Maturity Adj.'!$A$3:$C$170,3,0),(IF(K24<$M$10,"Check",K24)))) -> 46128 | O24: =M24=SUM(Q24:AG24) -> TRUE | P24: =IF(A24="","N/A",IF(COUNTIF($A$2:$A$7,A24)>0,"Liability",IF(COUNTIF($A$8,A24)>0,"Asset",IF(A24<20000000,"Asset",IF(AND(A24>20000000,A24<28800000),"Liability",IF(A24>28800000,"Equity","")))))) -> Asset | Q24: =IF(AND(N24>$Q$9,N24<$Q$10),M24,IF(N24=$Q$10,M24,0)) -> 0 | R24: =IF(AND(N24>$R$9,N24<$R$10),M24,IF(N24=$R$10,M24,0)) -> 0 | S24: =IF(AND(N24>$S$9,N24<$S$10),M24,IF(N24=$S$10,M24,0)) -> 7184060.6 | T24: =IF(AND(N24>$T$9,N24<$T$10),M24,IF(N24=$T$10,M24,0)) -> 0 | U24: =IF(AND(N24>$U$9,N24<$U$10),M24,IF(N24=$U$10,M24,0)) -> 0 | V24: =IF(AND(N24>$V$9,N24<$V$10),M24,IF(N24=$V$10,M24,0)) -> 0 | W24: =IF(AND(N24>$W$9,N24<$W$10),M24,IF(N24=$W$10,M24,0)) -> 0 | X24: =IF(AND(N24>$X$9,N24<$X$10),M24,IF(N24=$X$10,M24,0)) -> 0 | Y24: =IF(AND(N24>$Y$9,N24<$Y$10),M24,IF(N24=$Y$10,M24,0)) -> 0 | Z24: =IF(AND(N24>$Z$9,N24<$Z$10),M24,IF(N24=$Z$10,M24,0)) -> 0 | AA24: =IF(AND(N24>$AA$9,N24<$AA$10),M24,IF(N24=$AA$10,M24,0)) -> 0 | AB24: =IF(AND(N24>$AB$9,N24<$AB$10),M24,IF(N24=$AB$10,M24,0)) -> 0 | AC24: =IF(AND(N24>$AC$9,N24<$AC$10),M24,IF(N24=$AC$10,M24,0)) -> 0 | AD24: =IF(AND(N24>$AD$9,N24<$AD$10),M24,IF(N24=$AD$10,M24,0)) -> 0 | AE24: =IF(AND(N24>$AE$9,N24<$AE$10),M24,IF(N24=$AE$10,M24,0)) -> 0 | AF24: =IF(AND(N24>$AF$9,N24<$AF$10),M24,IF(N24=$AF$10,M24,0)) -> 0 | AG24: =IF(N24=$AG$9,M24,0) -> 0
A25: 10310003 | B25: Foreign GovT & Official Institution - FVOCI | C25: FB5904250000001 | D25: 100000037 | E25: THE EXPORT-IMPORT BANK OF KOREA | F25: USD | G25: -15.6 | H25: -22.29 | I25: 45692 | J25: 46766 | L25: =A25&"_"&F25&"_"&D25&"_"&E25 -> 10310003_USD_100000037_THE EXPORT-IMPORT BANK OF KOREA | M25: =IF(COUNTIF($A$2:$A$8,A25)>0,-H25,H25) -> -22.29 | N25: =IF(OR(L25=$L$2,L25=$L$3),$M$10+1,IFERROR(VLOOKUP(A25,'Repricing Maturity Adj.'!$A$3:$C$170,3,0),(IF(K25<$M$10,"Check",K25)))) -> Check | O25: =M25=SUM(Q25:AG25) -> FALSE | P25: =IF(A25="","N/A",IF(COUNTIF($A$2:$A$7,A25)>0,"Liability",IF(COUNTIF($A$8,A25)>0,"Asset",IF(A25<20000000,"Asset",IF(AND(A25>20000000,A25<28800000),"Liability",IF(A25>28800000,"Equity","")))))) -> Asset | Q25: =IF(AND(N25>$Q$9,N25<$Q$10),M25,IF(N25=$Q$10,M25,0)) -> 0 | R25: =IF(AND(N25>$R$9,N25<$R$10),M25,IF(N25=$R$10,M25,0)) -> 0 | S25: =IF(AND(N25>$S$9,N25<$S$10),M25,IF(N25=$S$10,M25,0)) -> 0 | T25: =IF(AND(N25>$T$9,N25<$T$10),M25,IF(N25=$T$10,M25,0)) -> 0 | U25: =IF(AND(N25>$U$9,N25<$U$10),M25,IF(N25=$U$10,M25,0)) -> 0 | V25: =IF(AND(N25>$V$9,N25<$V$10),M25,IF(N25=$V$10,M25,0)) -> 0 | W25: =IF(AND(N25>$W$9,N25<$W$10),M25,IF(N25=$W$10,M25,0)) -> 0 | X25: =IF(AND(N25>$X$9,N25<$X$10),M25,IF(N25=$X$10,M25,0)) -> 0 | Y25: =IF(AND(N25>$Y$9,N25<$Y$10),M25,IF(N25=$Y$10,M25,0)) -> 0 | Z25: =IF(AND(N25>$Z$9,N25<$Z$10),M25,IF(N25=$Z$10,M25,0)) -> 0 | AA25: =IF(AND(N25>$AA$9,N25<$AA$10),M25,IF(N25=$AA$10,M25,0)) -> 0 | AB25: =IF(AND(N25>$AB$9,N25<$AB$10),M25,IF(N25=$AB$10,M25,0)) -> 0 | AC25: =IF(AND(N25>$AC$9,N25<$AC$10),M25,IF(N25=$AC$10,M25,0)) -> 0 | AD25: =IF(AND(N25>$AD$9,N25<$AD$10),M25,IF(N25=$AD$10,M25,0)) -> 0 | AE25: =IF(AND(N25>$AE$9,N25<$AE$10),M25,IF(N25=$AE$10,M25,0)) -> 0 | AF25: =IF(AND(N25>$AF$9,N25<$AF$10),M25,IF(N25=$AF$10,M25,0)) -> 0 | AG25: =IF(N25=$AG$9,M25,0) -> 0
A26: 10310003 | B26: Foreign GovT & Official Institution - FVOCI | C26: FB5904250000002 | D26: 100000037 | E26: THE EXPORT-IMPORT BANK OF KOREA | F26: USD | G26: 5076634.8 | H26: 7254408.2 | I26: 45692 | J26: 46766 | K26: 46765 | L26: =A26&"_"&F26&"_"&D26&"_"&E26 -> 10310003_USD_100000037_THE EXPORT-IMPORT BANK OF KOREA | M26: =IF(COUNTIF($A$2:$A$8,A26)>0,-H26,H26) -> 7254408.2 | N26: =IF(OR(L26=$L$2,L26=$L$3),$M$10+1,IFERROR(VLOOKUP(A26,'Repricing Maturity Adj.'!$A$3:$C$170,3,0),(IF(K26<$M$10,"Check",K26)))) -> 46765 | O26: =M26=SUM(Q26:AG26) -> TRUE | P26: =IF(A26="","N/A",IF(COUNTIF($A$2:$A$7,A26)>0,"Liability",IF(COUNTIF($A$8,A26)>0,"Asset",IF(A26<20000000,"Asset",IF(AND(A26>20000000,A26<28800000),"Liability",IF(A26>28800000,"Equity","")))))) -> Asset | Q26: =IF(AND(N26>$Q$9,N26<$Q$10),M26,IF(N26=$Q$10,M26,0)) -> 0 | R26: =IF(AND(N26>$R$9,N26<$R$10),M26,IF(N26=$R$10,M26,0)) -> 0 | S26: =IF(AND(N26>$S$9,N26<$S$10),M26,IF(N26=$S$10,M26,0)) -> 0 | T26: =IF(AND(N26>$T$9,N26<$T$10),M26,IF(N26=$T$10,M26,0)) -> 0 | U26: =IF(AND(N26>$U$9,N26<$U$10),M26,IF(N26=$U$10,M26,0)) -> 0 | V26: =IF(AND(N26>$V$9,N26<$V$10),M26,IF(N26=$V$10,M26,0)) -> 0 | W26: =IF(AND(N26>$W$9,N26<$W$10),M26,IF(N26=$W$10,M26,0)) -> 0 | X26: =IF(AND(N26>$X$9,N26<$X$10),M26,IF(N26=$X$10,M26,0)) -> 7254408.2 | Y26: =IF(AND(N26>$Y$9,N26<$Y$10),M26,IF(N26=$Y$10,M26,0)) -> 0 | Z26: =IF(AND(N26>$Z$9,N26<$Z$10),M26,IF(N26=$Z$10,M26,0)) -> 0 | AA26: =IF(AND(N26>$AA$9,N26<$AA$10),M26,IF(N26=$AA$10,M26,0)) -> 0 | AB26: =IF(AND(N26>$AB$9,N26<$AB$10),M26,IF(N26=$AB$10,M26,0)) -> 0 | AC26: =IF(AND(N26>$AC$9,N26<$AC$10),M26,IF(N26=$AC$10,M26,0)) -> 0 | AD26: =IF(AND(N26>$AD$9,N26<$AD$10),M26,IF(N26=$AD$10,M26,0)) -> 0 | AE26: =IF(AND(N26>$AE$9,N26<$AE$10),M26,IF(N26=$AE$10,M26,0)) -> 0 | AF26: =IF(AND(N26>$AF$9,N26<$AF$10),M26,IF(N26=$AF$10,M26,0)) -> 0 | AG26: =IF(N26=$AG$9,M26,0) -> 0
A27: 10310003 | B27: Foreign GovT & Official Institution - FVOCI | C27: FB5904250000004 | D27: 100000037 | E27: THE EXPORT-IMPORT BANK OF KOREA | F27: USD | G27: 3021005.4 | H27: 4316955.4 | I27: 45818 | J27: 46645 | K27: 46644 | L27: =A27&"_"&F27&"_"&D27&"_"&E27 -> 10310003_USD_100000037_THE EXPORT-IMPORT BANK OF KOREA | M27: =IF(COUNTIF($A$2:$A$8,A27)>0,-H27,H27) -> 4316955.4 | N27: =IF(OR(L27=$L$2,L27=$L$3),$M$10+1,IFERROR(VLOOKUP(A27,'Repricing Maturity Adj.'!$A$3:$C$170,3,0),(IF(K27<$M$10,"Check",K27)))) -> 46644 | O27: =M27=SUM(Q27:AG27) -> TRUE | P27: =IF(A27="","N/A",IF(COUNTIF($A$2:$A$7,A27)>0,"Liability",IF(COUNTIF($A$8,A27)>0,"Asset",IF(A27<20000000,"Asset",IF(AND(A27>20000000,A27<28800000),"Liability",IF(A27>28800000,"Equity","")))))) -> Asset | Q27: =IF(AND(N27>$Q$9,N27<$Q$10),M27,IF(N27=$Q$10,M27,0)) -> 0 | R27: =IF(AND(N27>$R$9,N27<$R$10),M27,IF(N27=$R$10,M27,0)) -> 0 | S27: =IF(AND(N27>$S$9,N27<$S$10),M27,IF(N27=$S$10,M27,0)) -> 0 | T27: =IF(AND(N27>$T$9,N27<$T$10),M27,IF(N27=$T$10,M27,0)) -> 0 | U27: =IF(AND(N27>$U$9,N27<$U$10),M27,IF(N27=$U$10,M27,0)) -> 0 | V27: =IF(AND(N27>$V$9,N27<$V$10),M27,IF(N27=$V$10,M27,0)) -> 0 | W27: =IF(AND(N27>$W$9,N27<$W$10),M27,IF(N27=$W$10,M27,0)) -> 0 | X27: =IF(AND(N27>$X$9,N27<$X$10),M27,IF(N27=$X$10,M27,0)) -> 4316955.4 | Y27: =IF(AND(N27>$Y$9,N27<$Y$10),M27,IF(N27=$Y$10,M27,0)) -> 0 | Z27: =IF(AND(N27>$Z$9,N27<$Z$10),M27,IF(N27=$Z$10,M27,0)) -> 0 | AA27: =IF(AND(N27>$AA$9,N27<$AA$10),M27,IF(N27=$AA$10,M27,0)) -> 0 | AB27: =IF(AND(N27>$AB$9,N27<$AB$10),M27,IF(N27=$AB$10,M27,0)) -> 0 | AC27: =IF(AND(N27>$AC$9,N27<$AC$10),M27,IF(N27=$AC$10,M27,0)) -> 0 | AD27: =IF(AND(N27>$AD$9,N27<$AD$10),M27,IF(N27=$AD$10,M27,0)) -> 0 | AE27: =IF(AND(N27>$AE$9,N27<$AE$10),M27,IF(N27=$AE$10,M27,0)) -> 0 | AF27: =IF(AND(N27>$AF$9,N27<$AF$10),M27,IF(N27=$AF$10,M27,0)) -> 0 | AG27: =IF(N27=$AG$9,M27,0) -> 0
A28: 10310003 | B28: Foreign GovT & Official Institution - FVOCI | C28: OT5904250000017 | D28: 100000037 | E28: THE EXPORT-IMPORT BANK OF KOREA | F28: USD | G28: 15.6 | H28: 22.29 | L28: =A28&"_"&F28&"_"&D28&"_"&E28 -> 10310003_USD_100000037_THE EXPORT-IMPORT BANK OF KOREA | M28: =IF(COUNTIF($A$2:$A$8,A28)>0,-H28,H28) -> 22.29 | N28: =IF(OR(L28=$L$2,L28=$L$3),$M$10+1,IFERROR(VLOOKUP(A28,'Repricing Maturity Adj.'!$A$3:$C$170,3,0),(IF(K28<$M$10,"Check",K28)))) -> Check | O28: =M28=SUM(Q28:AG28) -> FALSE | P28: =IF(A28="","N/A",IF(COUNTIF($A$2:$A$7,A28)>0,"Liability",IF(COUNTIF($A$8,A28)>0,"Asset",IF(A28<20000000,"Asset",IF(AND(A28>20000000,A28<28800000),"Liability",IF(A28>28800000,"Equity","")))))) -> Asset | Q28: =IF(AND(N28>$Q$9,N28<$Q$10),M28,IF(N28=$Q$10,M28,0)) -> 0 | R28: =IF(AND(N28>$R$9,N28<$R$10),M28,IF(N28=$R$10,M28,0)) -> 0 | S28: =IF(AND(N28>$S$9,N28<$S$10),M28,IF(N28=$S$10,M28,0)) -> 0 | T28: =IF(AND(N28>$T$9,N28<$T$10),M28,IF(N28=$T$10,M28,0)) -> 0 | U28: =IF(AND(N28>$U$9,N28<$U$10),M28,IF(N28=$U$10,M28,0)) -> 0 | V28: =IF(AND(N28>$V$9,N28<$V$10),M28,IF(N28=$V$10,M28,0)) -> 0 | W28: =IF(AND(N28>$W$9,N28<$W$10),M28,IF(N28=$W$10,M28,0)) -> 0 | X28: =IF(AND(N28>$X$9,N28<$X$10),M28,IF(N28=$X$10,M28,0)) -> 0 | Y28: =IF(AND(N28>$Y$9,N28<$Y$10),M28,IF(N28=$Y$10,M28,0)) -> 0 | Z28: =IF(AND(N28>$Z$9,N28<$Z$10),M28,IF(N28=$Z$10,M28,0)) -> 0 | AA28: =IF(AND(N28>$AA$9,N28<$AA$10),M28,IF(N28=$AA$10,M28,0)) -> 0 | AB28: =IF(AND(N28>$AB$9,N28<$AB$10),M28,IF(N28=$AB$10,M28,0)) -> 0 | AC28: =IF(AND(N28>$AC$9,N28<$AC$10),M28,IF(N28=$AC$10,M28,0)) -> 0 | AD28: =IF(AND(N28>$AD$9,N28<$AD$10),M28,IF(N28=$AD$10,M28,0)) -> 0 | AE28: =IF(AND(N28>$AE$9,N28<$AE$10),M28,IF(N28=$AE$10,M28,0)) -> 0 | AF28: =IF(AND(N28>$AF$9,N28<$AF$10),M28,IF(N28=$AF$10,M28,0)) -> 0 | AG28: =IF(N28=$AG$9,M28,0) -> 0
A29: 10610005 | B29: Loans On Bills (Operation-Short Term-Domestic) | C29: 6115904000018 | D29: 100000003 | E29: COSMAX NBT AUSTRALIA PTY LTD | F29: AUD | G29: 6000000 | H29: 6000000 | I29: 44859 | J29: 46318 | K29: 46136 | L29: =A29&"_"&F29&"_"&D29&"_"&E29 -> 10610005_AUD_100000003_COSMAX NBT AUSTRALIA PTY LTD | M29: =IF(COUNTIF($A$2:$A$8,A29)>0,-H29,H29) -> 6000000 | N29: =IF(OR(L29=$L$2,L29=$L$3),$M$10+1,IFERROR(VLOOKUP(A29,'Repricing Maturity Adj.'!$A$3:$C$170,3,0),(IF(K29<$M$10,"Check",K29)))) -> 46136 | O29: =M29=SUM(Q29:AG29) -> TRUE | P29: =IF(A29="","N/A",IF(COUNTIF($A$2:$A$7,A29)>0,"Liability",IF(COUNTIF($A$8,A29)>0,"Asset",IF(A29<20000000,"Asset",IF(AND(A29>20000000,A29<28800000),"Liability",IF(A29>28800000,"Equity","")))))) -> Asset | Q29: =IF(AND(N29>$Q$9,N29<$Q$10),M29,IF(N29=$Q$10,M29,0)) -> 0 | R29: =IF(AND(N29>$R$9,N29<$R$10),M29,IF(N29=$R$10,M29,0)) -> 0 | S29: =IF(AND(N29>$S$9,N29<$S$10),M29,IF(N29=$S$10,M29,0)) -> 6000000 | T29: =IF(AND(N29>$T$9,N29<$T$10),M29,IF(N29=$T$10,M29,0)) -> 0 | U29: =IF(AND(N29>$U$9,N29<$U$10),M29,IF(N29=$U$10,M29,0)) -> 0 | V29: =IF(AND(N29>$V$9,N29<$V$10),M29,IF(N29=$V$10,M29,0)) -> 0 | W29: =IF(AND(N29>$W$9,N29<$W$10),M29,IF(N29=$W$10,M29,0)) -> 0 | X29: =IF(AND(N29>$X$9,N29<$X$10),M29,IF(N29=$X$10,M29,0)) -> 0 | Y29: =IF(AND(N29>$Y$9,N29<$Y$10),M29,IF(N29=$Y$10,M29,0)) -> 0 | Z29: =IF(AND(N29>$Z$9,N29<$Z$10),M29,IF(N29=$Z$10,M29,0)) -> 0 | AA29: =IF(AND(N29>$AA$9,N29<$AA$10),M29,IF(N29=$AA$10,M29,0)) -> 0 | AB29: =IF(AND(N29>$AB$9,N29<$AB$10),M29,IF(N29=$AB$10,M29,0)) -> 0 | AC29: =IF(AND(N29>$AC$9,N29<$AC$10),M29,IF(N29=$AC$10,M29,0)) -> 0 | AD29: =IF(AND(N29>$AD$9,N29<$AD$10),M29,IF(N29=$AD$10,M29,0)) -> 0 | AE29: =IF(AND(N29>$AE$9,N29<$AE$10),M29,IF(N29=$AE$10,M29,0)) -> 0 | AF29: =IF(AND(N29>$AF$9,N29<$AF$10),M29,IF(N29=$AF$10,M29,0)) -> 0 | AG29: =IF(N29=$AG$9,M29,0) -> 0
A30: 10620001 | B30: SYN-Working Capital Loan - Domestic | C30: 6115904000139 | D30: 100000020 | E30: APA INFRASTRUCTURE LIMITED | F30: AUD | G30: 8000000 | H30: 8000000 | I30: 45240 | J30: 48883 | K30: 46153 | L30: =A30&"_"&F30&"_"&D30&"_"&E30 -> 10620001_AUD_100000020_APA INFRASTRUCTURE LIMITED | M30: =IF(COUNTIF($A$2:$A$8,A30)>0,-H30,H30) -> 8000000 | N30: =IF(OR(L30=$L$2,L30=$L$3),$M$10+1,IFERROR(VLOOKUP(A30,'Repricing Maturity Adj.'!$A$3:$C$170,3,0),(IF(K30<$M$10,"Check",K30)))) -> 46153 | O30: =M30=SUM(Q30:AG30) -> TRUE | P30: =IF(A30="","N/A",IF(COUNTIF($A$2:$A$7,A30)>0,"Liability",IF(COUNTIF($A$8,A30)>0,"Asset",IF(A30<20000000,"Asset",IF(AND(A30>20000000,A30<28800000),"Liability",IF(A30>28800000,"Equity","")))))) -> Asset | Q30: =IF(AND(N30>$Q$9,N30<$Q$10),M30,IF(N30=$Q$10,M30,0)) -> 0 | R30: =IF(AND(N30>$R$9,N30<$R$10),M30,IF(N30=$R$10,M30,0)) -> 0 | S30: =IF(AND(N30>$S$9,N30<$S$10),M30,IF(N30=$S$10,M30,0)) -> 0 | T30: =IF(AND(N30>$T$9,N30<$T$10),M30,IF(N30=$T$10,M30,0)) -> 8000000 | U30: =IF(AND(N30>$U$9,N30<$U$10),M30,IF(N30=$U$10,M30,0)) -> 0 | V30: =IF(AND(N30>$V$9,N30<$V$10),M30,IF(N30=$V$10,M30,0)) -> 0 | W30: =IF(AND(N30>$W$9,N30<$W$10),M30,IF(N30=$W$10,M30,0)) -> 0 | X30: =IF(AND(N30>$X$9,N30<$X$10),M30,IF(N30=$X$10,M30,0)) -> 0 | Y30: =IF(AND(N30>$Y$9,N30<$Y$10),M30,IF(N30=$Y$10,M30,0)) -> 0 | Z30: =IF(AND(N30>$Z$9,N30<$Z$10),M30,IF(N30=$Z$10,M30,0)) -> 0 | AA30: =IF(AND(N30>$AA$9,N30<$AA$10),M30,IF(N30=$AA$10,M30,0)) -> 0 | AB30: =IF(AND(N30>$AB$9,N30<$AB$10),M30,IF(N30=$AB$10,M30,0)) -> 0 | AC30: =IF(AND(N30>$AC$9,N30<$AC$10),M30,IF(N30=$AC$10,M30,0)) -> 0 | AD30: =IF(AND(N30>$AD$9,N30<$AD$10),M30,IF(N30=$AD$10,M30,0)) -> 0 | AE30: =IF(AND(N30>$AE$9,N30<$AE$10),M30,IF(N30=$AE$10,M30,0)) -> 0 | AF30: =IF(AND(N30>$AF$9,N30<$AF$10),M30,IF(N30=$AF$10,M30,0)) -> 0 | AG30: =IF(N30=$AG$9,M30,0) -> 0
A31: 10620001 | B31: SYN-Working Capital Loan - Domestic | C31: 6115904000300 | D31: 100000031 | E31: ORIGIN ENERGY LIMITED | F31: AUD | G31: 10000000 | H31: 10000000 | I31: 45463 | J31: 48005 | K31: 46195 | L31: =A31&"_"&F31&"_"&D31&"_"&E31 -> 10620001_AUD_100000031_ORIGIN ENERGY LIMITED | M31: =IF(COUNTIF($A$2:$A$8,A31)>0,-H31,H31) -> 10000000 | N31: =IF(OR(L31=$L$2,L31=$L$3),$M$10+1,IFERROR(VLOOKUP(A31,'Repricing Maturity Adj.'!$A$3:$C$170,3,0),(IF(K31<$M$10,"Check",K31)))) -> 46195 | O31: =M31=SUM(Q31:AG31) -> TRUE | P31: =IF(A31="","N/A",IF(COUNTIF($A$2:$A$7,A31)>0,"Liability",IF(COUNTIF($A$8,A31)>0,"Asset",IF(A31<20000000,"Asset",IF(AND(A31>20000000,A31<28800000),"Liability",IF(A31>28800000,"Equity","")))))) -> Asset | Q31: =IF(AND(N31>$Q$9,N31<$Q$10),M31,IF(N31=$Q$10,M31,0)) -> 0 | R31: =IF(AND(N31>$R$9,N31<$R$10),M31,IF(N31=$R$10,M31,0)) -> 0 | S31: =IF(AND(N31>$S$9,N31<$S$10),M31,IF(N31=$S$10,M31,0)) -> 0 | T31: =IF(AND(N31>$T$9,N31<$T$10),M31,IF(N31=$T$10,M31,0)) -> 0 | U31: =IF(AND(N31>$U$9,N31<$U$10),M31,IF(N31=$U$10,M31,0)) -> 10000000 | V31: =IF(AND(N31>$V$9,N31<$V$10),M31,IF(N31=$V$10,M31,0)) -> 0 | W31: =IF(AND(N31>$W$9,N31<$W$10),M31,IF(N31=$W$10,M31,0)) -> 0 | X31: =IF(AND(N31>$X$9,N31<$X$10),M31,IF(N31=$X$10,M31,0)) -> 0 | Y31: =IF(AND(N31>$Y$9,N31<$Y$10),M31,IF(N31=$Y$10,M31,0)) -> 0 | Z31: =IF(AND(N31>$Z$9,N31<$Z$10),M31,IF(N31=$Z$10,M31,0)) -> 0 | AA31: =IF(AND(N31>$AA$9,N31<$AA$10),M31,IF(N31=$AA$10,M31,0)) -> 0 | AB31: =IF(AND(N31>$AB$9,N31<$AB$10),M31,IF(N31=$AB$10,M31,0)) -> 0 | AC31: =IF(AND(N31>$AC$9,N31<$AC$10),M31,IF(N31=$AC$10,M31,0)) -> 0 | AD31: =IF(AND(N31>$AD$9,N31<$AD$10),M31,IF(N31=$AD$10,M31,0)) -> 0 | AE31: =IF(AND(N31>$AE$9,N31<$AE$10),M31,IF(N31=$AE$10,M31,0)) -> 0 | AF31: =IF(AND(N31>$AF$9,N31<$AF$10),M31,IF(N31=$AF$10,M31,0)) -> 0 | AG31: =IF(N31=$AG$9,M31,0) -> 0
A32: 10620001 | B32: SYN-Working Capital Loan - Domestic | C32: 6115904000395 | D32: 100000033 | E32: MACQUARIE GROUP LIMITED | F32: USD | G32: 30000000 | H32: 42869391 | I32: 45565 | J32: 48136 | K32: 46107 | L32: =A32&"_"&F32&"_"&D32&"_"&E32 -> 10620001_USD_100000033_MACQUARIE GROUP LIMITED | M32: =IF(COUNTIF($A$2:$A$8,A32)>0,-H32,H32) -> 42869391 | N32: =IF(OR(L32=$L$2,L32=$L$3),$M$10+1,IFERROR(VLOOKUP(A32,'Repricing Maturity Adj.'!$A$3:$C$170,3,0),(IF(K32<$M$10,"Check",K32)))) -> 46059 | O32: =M32=SUM(Q32:AG32) -> TRUE | P32: =IF(A32="","N/A",IF(COUNTIF($A$2:$A$7,A32)>0,"Liability",IF(COUNTIF($A$8,A32)>0,"Asset",IF(A32<20000000,"Asset",IF(AND(A32>20000000,A32<28800000),"Liability",IF(A32>28800000,"Equity","")))))) -> Asset | Q32: =IF(AND(N32>$Q$9,N32<$Q$10),M32,IF(N32=$Q$10,M32,0)) -> 42869391 | R32: =IF(AND(N32>$R$9,N32<$R$10),M32,IF(N32=$R$10,M32,0)) -> 0 | S32: =IF(AND(N32>$S$9,N32<$S$10),M32,IF(N32=$S$10,M32,0)) -> 0 | T32: =IF(AND(N32>$T$9,N32<$T$10),M32,IF(N32=$T$10,M32,0)) -> 0 | U32: =IF(AND(N32>$U$9,N32<$U$10),M32,IF(N32=$U$10,M32,0)) -> 0 | V32: =IF(AND(N32>$V$9,N32<$V$10),M32,IF(N32=$V$10,M32,0)) -> 0 | W32: =IF(AND(N32>$W$9,N32<$W$10),M32,IF(N32=$W$10,M32,0)) -> 0 | X32: =IF(AND(N32>$X$9,N32<$X$10),M32,IF(N32=$X$10,M32,0)) -> 0 | Y32: =IF(AND(N32>$Y$9,N32<$Y$10),M32,IF(N32=$Y$10,M32,0)) -> 0 | Z32: =IF(AND(N32>$Z$9,N32<$Z$10),M32,IF(N32=$Z$10,M32,0)) -> 0 | AA32: =IF(AND(N32>$AA$9,N32<$AA$10),M32,IF(N32=$AA$10,M32,0)) -> 0 | AB32: =IF(AND(N32>$AB$9,N32<$AB$10),M32,IF(N32=$AB$10,M32,0)) -> 0 | AC32: =IF(AND(N32>$AC$9,N32<$AC$10),M32,IF(N32=$AC$10,M32,0)) -> 0 | AD32: =IF(AND(N32>$AD$9,N32<$AD$10),M32,IF(N32=$AD$10,M32,0)) -> 0 | AE32: =IF(AND(N32>$AE$9,N32<$AE$10),M32,IF(N32=$AE$10,M32,0)) -> 0 | AF32: =IF(AND(N32>$AF$9,N32<$AF$10),M32,IF(N32=$AF$10,M32,0)) -> 0 | AG32: =IF(N32=$AG$9,M32,0) -> 0
A33: 10620001 | B33: SYN-Working Capital Loan - Domestic | C33: 6115904000452 | D33: 100000035 | E33: NEXTDC LIMITED | F33: AUD | G33: 20000000 | H33: 20000000 | I33: 45629 | J33: 48185 | K33: 46084 | L33: =A33&"_"&F33&"_"&D33&"_"&E33 -> 10620001_AUD_100000035_NEXTDC LIMITED | M33: =IF(COUNTIF($A$2:$A$8,A33)>0,-H33,H33) -> 20000000 | N33: =IF(OR(L33=$L$2,L33=$L$3),$M$10+1,IFERROR(VLOOKUP(A33,'Repricing Maturity Adj.'!$A$3:$C$170,3,0),(IF(K33<$M$10,"Check",K33)))) -> 46084 | O33: =M33=SUM(Q33:AG33) -> TRUE | P33: =IF(A33="","N/A",IF(COUNTIF($A$2:$A$7,A33)>0,"Liability",IF(COUNTIF($A$8,A33)>0,"Asset",IF(A33<20000000,"Asset",IF(AND(A33>20000000,A33<28800000),"Liability",IF(A33>28800000,"Equity","")))))) -> Asset | Q33: =IF(AND(N33>$Q$9,N33<$Q$10),M33,IF(N33=$Q$10,M33,0)) -> 0 | R33: =IF(AND(N33>$R$9,N33<$R$10),M33,IF(N33=$R$10,M33,0)) -> 20000000 | S33: =IF(AND(N33>$S$9,N33<$S$10),M33,IF(N33=$S$10,M33,0)) -> 0 | T33: =IF(AND(N33>$T$9,N33<$T$10),M33,IF(N33=$T$10,M33,0)) -> 0 | U33: =IF(AND(N33>$U$9,N33<$U$10),M33,IF(N33=$U$10,M33,0)) -> 0 | V33: =IF(AND(N33>$V$9,N33<$V$10),M33,IF(N33=$V$10,M33,0)) -> 0 | W33: =IF(AND(N33>$W$9,N33<$W$10),M33,IF(N33=$W$10,M33,0)) -> 0 | X33: =IF(AND(N33>$X$9,N33<$X$10),M33,IF(N33=$X$10,M33,0)) -> 0 | Y33: =IF(AND(N33>$Y$9,N33<$Y$10),M33,IF(N33=$Y$10,M33,0)) -> 0 | Z33: =IF(AND(N33>$Z$9,N33<$Z$10),M33,IF(N33=$Z$10,M33,0)) -> 0 | AA33: =IF(AND(N33>$AA$9,N33<$AA$10),M33,IF(N33=$AA$10,M33,0)) -> 0 | AB33: =IF(AND(N33>$AB$9,N33<$AB$10),M33,IF(N33=$AB$10,M33,0)) -> 0 | AC33: =IF(AND(N33>$AC$9,N33<$AC$10),M33,IF(N33=$AC$10,M33,0)) -> 0 | AD33: =IF(AND(N33>$AD$9,N33<$AD$10),M33,IF(N33=$AD$10,M33,0)) -> 0 | AE33: =IF(AND(N33>$AE$9,N33<$AE$10),M33,IF(N33=$AE$10,M33,0)) -> 0 | AF33: =IF(AND(N33>$AF$9,N33<$AF$10),M33,IF(N33=$AF$10,M33,0)) -> 0 | AG33: =IF(N33=$AG$9,M33,0) -> 0
A34: 10620001 | B34: SYN-Working Capital Loan - Domestic | C34: 6115904000573 | D34: 100000039 | E34: QANTAS AIRWAYS LIMITED | F34: AUD | G34: 5000000 | H34: 5000000 | I34: 45791 | J34: 48341 | K34: 46066 | L34: =A34&"_"&F34&"_"&D34&"_"&E34 -> 10620001_AUD_100000039_QANTAS AIRWAYS LIMITED | M34: =IF(COUNTIF($A$2:$A$8,A34)>0,-H34,H34) -> 5000000 | N34: =IF(OR(L34=$L$2,L34=$L$3),$M$10+1,IFERROR(VLOOKUP(A34,'Repricing Maturity Adj.'!$A$3:$C$170,3,0),(IF(K34<$M$10,"Check",K34)))) -> 46066 | O34: =M34=SUM(Q34:AG34) -> TRUE | P34: =IF(A34="","N/A",IF(COUNTIF($A$2:$A$7,A34)>0,"Liability",IF(COUNTIF($A$8,A34)>0,"Asset",IF(A34<20000000,"Asset",IF(AND(A34>20000000,A34<28800000),"Liability",IF(A34>28800000,"Equity","")))))) -> Asset | Q34: =IF(AND(N34>$Q$9,N34<$Q$10),M34,IF(N34=$Q$10,M34,0)) -> 0 | R34: =IF(AND(N34>$R$9,N34<$R$10),M34,IF(N34=$R$10,M34,0)) -> 5000000 | S34: =IF(AND(N34>$S$9,N34<$S$10),M34,IF(N34=$S$10,M34,0)) -> 0 | T34: =IF(AND(N34>$T$9,N34<$T$10),M34,IF(N34=$T$10,M34,0)) -> 0 | U34: =IF(AND(N34>$U$9,N34<$U$10),M34,IF(N34=$U$10,M34,0)) -> 0 | V34: =IF(AND(N34>$V$9,N34<$V$10),M34,IF(N34=$V$10,M34,0)) -> 0 | W34: =IF(AND(N34>$W$9,N34<$W$10),M34,IF(N34=$W$10,M34,0)) -> 0 | X34: =IF(AND(N34>$X$9,N34<$X$10),M34,IF(N34=$X$10,M34,0)) -> 0 | Y34: =IF(AND(N34>$Y$9,N34<$Y$10),M34,IF(N34=$Y$10,M34,0)) -> 0 | Z34: =IF(AND(N34>$Z$9,N34<$Z$10),M34,IF(N34=$Z$10,M34,0)) -> 0 | AA34: =IF(AND(N34>$AA$9,N34<$AA$10),M34,IF(N34=$AA$10,M34,0)) -> 0 | AB34: =IF(AND(N34>$AB$9,N34<$AB$10),M34,IF(N34=$AB$10,M34,0)) -> 0 | AC34: =IF(AND(N34>$AC$9,N34<$AC$10),M34,IF(N34=$AC$10,M34,0)) -> 0 | AD34: =IF(AND(N34>$AD$9,N34<$AD$10),M34,IF(N34=$AD$10,M34,0)) -> 0 | AE34: =IF(AND(N34>$AE$9,N34<$AE$10),M34,IF(N34=$AE$10,M34,0)) -> 0 | AF34: =IF(AND(N34>$AF$9,N34<$AF$10),M34,IF(N34=$AF$10,M34,0)) -> 0 | AG34: =IF(N34=$AG$9,M34,0) -> 0
A35: 10620001 | B35: SYN-Working Capital Loan - Domestic | C35: 6115904000609 | D35: 100000040 | E35: DOWNER GROUP FINANCE PTY LIMITED | F35: AUD | G35: 35000000 | H35: 35000000 | I35: 45828 | J35: 48383 | K35: 46080 | L35: =A35&"_"&F35&"_"&D35&"_"&E35 -> 10620001_AUD_100000040_DOWNER GROUP FINANCE PTY LIMITED | M35: =IF(COUNTIF($A$2:$A$8,A35)>0,-H35,H35) -> 35000000 | N35: =IF(OR(L35=$L$2,L35=$L$3),$M$10+1,IFERROR(VLOOKUP(A35,'Repricing Maturity Adj.'!$A$3:$C$170,3,0),(IF(K35<$M$10,"Check",K35)))) -> 46080 | O35: =M35=SUM(Q35:AG35) -> TRUE | P35: =IF(A35="","N/A",IF(COUNTIF($A$2:$A$7,A35)>0,"Liability",IF(COUNTIF($A$8,A35)>0,"Asset",IF(A35<20000000,"Asset",IF(AND(A35>20000000,A35<28800000),"Liability",IF(A35>28800000,"Equity","")))))) -> Asset | Q35: =IF(AND(N35>$Q$9,N35<$Q$10),M35,IF(N35=$Q$10,M35,0)) -> 0 | R35: =IF(AND(N35>$R$9,N35<$R$10),M35,IF(N35=$R$10,M35,0)) -> 35000000 | S35: =IF(AND(N35>$S$9,N35<$S$10),M35,IF(N35=$S$10,M35,0)) -> 0 | T35: =IF(AND(N35>$T$9,N35<$T$10),M35,IF(N35=$T$10,M35,0)) -> 0 | U35: =IF(AND(N35>$U$9,N35<$U$10),M35,IF(N35=$U$10,M35,0)) -> 0 | V35: =IF(AND(N35>$V$9,N35<$V$10),M35,IF(N35=$V$10,M35,0)) -> 0 | W35: =IF(AND(N35>$W$9,N35<$W$10),M35,IF(N35=$W$10,M35,0)) -> 0 | X35: =IF(AND(N35>$X$9,N35<$X$10),M35,IF(N35=$X$10,M35,0)) -> 0 | Y35: =IF(AND(N35>$Y$9,N35<$Y$10),M35,IF(N35=$Y$10,M35,0)) -> 0 | Z35: =IF(AND(N35>$Z$9,N35<$Z$10),M35,IF(N35=$Z$10,M35,0)) -> 0 | AA35: =IF(AND(N35>$AA$9,N35<$AA$10),M35,IF(N35=$AA$10,M35,0)) -> 0 | AB35: =IF(AND(N35>$AB$9,N35<$AB$10),M35,IF(N35=$AB$10,M35,0)) -> 0 | AC35: =IF(AND(N35>$AC$9,N35<$AC$10),M35,IF(N35=$AC$10,M35,0)) -> 0 | AD35: =IF(AND(N35>$AD$9,N35<$AD$10),M35,IF(N35=$AD$10,M35,0)) -> 0 | AE35: =IF(AND(N35>$AE$9,N35<$AE$10),M35,IF(N35=$AE$10,M35,0)) -> 0 | AF35: =IF(AND(N35>$AF$9,N35<$AF$10),M35,IF(N35=$AF$10,M35,0)) -> 0 | AG35: =IF(N35=$AG$9,M35,0) -> 0
A36: 10620001 | B36: SYN-Working Capital Loan - Domestic | C36: 6115904000623 | D36: 100000020 | E36: APA INFRASTRUCTURE LIMITED | F36: AUD | G36: 20000000 | H36: 20000000 | I36: 45833 | J36: 48426 | K36: 46153 | L36: =A36&"_"&F36&"_"&D36&"_"&E36 -> 10620001_AUD_100000020_APA INFRASTRUCTURE LIMITED | M36: =IF(COUNTIF($A$2:$A$8,A36)>0,-H36,H36) -> 20000000 | N36: =IF(OR(L36=$L$2,L36=$L$3),$M$10+1,IFERROR(VLOOKUP(A36,'Repricing Maturity Adj.'!$A$3:$C$170,3,0),(IF(K36<$M$10,"Check",K36)))) -> 46153 | O36: =M36=SUM(Q36:AG36) -> TRUE | P36: =IF(A36="","N/A",IF(COUNTIF($A$2:$A$7,A36)>0,"Liability",IF(COUNTIF($A$8,A36)>0,"Asset",IF(A36<20000000,"Asset",IF(AND(A36>20000000,A36<28800000),"Liability",IF(A36>28800000,"Equity","")))))) -> Asset | Q36: =IF(AND(N36>$Q$9,N36<$Q$10),M36,IF(N36=$Q$10,M36,0)) -> 0 | R36: =IF(AND(N36>$R$9,N36<$R$10),M36,IF(N36=$R$10,M36,0)) -> 0 | S36: =IF(AND(N36>$S$9,N36<$S$10),M36,IF(N36=$S$10,M36,0)) -> 0 | T36: =IF(AND(N36>$T$9,N36<$T$10),M36,IF(N36=$T$10,M36,0)) -> 20000000 | U36: =IF(AND(N36>$U$9,N36<$U$10),M36,IF(N36=$U$10,M36,0)) -> 0 | V36: =IF(AND(N36>$V$9,N36<$V$10),M36,IF(N36=$V$10,M36,0)) -> 0 | W36: =IF(AND(N36>$W$9,N36<$W$10),M36,IF(N36=$W$10,M36,0)) -> 0 | X36: =IF(AND(N36>$X$9,N36<$X$10),M36,IF(N36=$X$10,M36,0)) -> 0 | Y36: =IF(AND(N36>$Y$9,N36<$Y$10),M36,IF(N36=$Y$10,M36,0)) -> 0 | Z36: =IF(AND(N36>$Z$9,N36<$Z$10),M36,IF(N36=$Z$10,M36,0)) -> 0 | AA36: =IF(AND(N36>$AA$9,N36<$AA$10),M36,IF(N36=$AA$10,M36,0)) -> 0 | AB36: =IF(AND(N36>$AB$9,N36<$AB$10),M36,IF(N36=$AB$10,M36,0)) -> 0 | AC36: =IF(AND(N36>$AC$9,N36<$AC$10),M36,IF(N36=$AC$10,M36,0)) -> 0 | AD36: =IF(AND(N36>$AD$9,N36<$AD$10),M36,IF(N36=$AD$10,M36,0)) -> 0 | AE36: =IF(AND(N36>$AE$9,N36<$AE$10),M36,IF(N36=$AE$10,M36,0)) -> 0 | AF36: =IF(AND(N36>$AF$9,N36<$AF$10),M36,IF(N36=$AF$10,M36,0)) -> 0 | AG36: =IF(N36=$AG$9,M36,0) -> 0
A37: 10620001 | B37: SYN-Working Capital Loan - Domestic | C37: 6115904000705 | D37: 100000039 | E37: QANTAS AIRWAYS LIMITED | F37: AUD | G37: 5000000 | H37: 5000000 | I37: 45924 | J37: 48487 | K37: 46105 | L37: =A37&"_"&F37&"_"&D37&"_"&E37 -> 10620001_AUD_100000039_QANTAS AIRWAYS LIMITED | M37: =IF(COUNTIF($A$2:$A$8,A37)>0,-H37,H37) -> 5000000 | N37: =IF(OR(L37=$L$2,L37=$L$3),$M$10+1,IFERROR(VLOOKUP(A37,'Repricing Maturity Adj.'!$A$3:$C$170,3,0),(IF(K37<$M$10,"Check",K37)))) -> 46105 | O37: =M37=SUM(Q37:AG37) -> TRUE | P37: =IF(A37="","N/A",IF(COUNTIF($A$2:$A$7,A37)>0,"Liability",IF(COUNTIF($A$8,A37)>0,"Asset",IF(A37<20000000,"Asset",IF(AND(A37>20000000,A37<28800000),"Liability",IF(A37>28800000,"Equity","")))))) -> Asset | Q37: =IF(AND(N37>$Q$9,N37<$Q$10),M37,IF(N37=$Q$10,M37,0)) -> 0 | R37: =IF(AND(N37>$R$9,N37<$R$10),M37,IF(N37=$R$10,M37,0)) -> 5000000 | S37: =IF(AND(N37>$S$9,N37<$S$10),M37,IF(N37=$S$10,M37,0)) -> 0 | T37: =IF(AND(N37>$T$9,N37<$T$10),M37,IF(N37=$T$10,M37,0)) -> 0 | U37: =IF(AND(N37>$U$9,N37<$U$10),M37,IF(N37=$U$10,M37,0)) -> 0 | V37: =IF(AND(N37>$V$9,N37<$V$10),M37,IF(N37=$V$10,M37,0)) -> 0 | W37: =IF(AND(N37>$W$9,N37<$W$10),M37,IF(N37=$W$10,M37,0)) -> 0 | X37: =IF(AND(N37>$X$9,N37<$X$10),M37,IF(N37=$X$10,M37,0)) -> 0 | Y37: =IF(AND(N37>$Y$9,N37<$Y$10),M37,IF(N37=$Y$10,M37,0)) -> 0 | Z37: =IF(AND(N37>$Z$9,N37<$Z$10),M37,IF(N37=$Z$10,M37,0)) -> 0 | AA37: =IF(AND(N37>$AA$9,N37<$AA$10),M37,IF(N37=$AA$10,M37,0)) -> 0 | AB37: =IF(AND(N37>$AB$9,N37<$AB$10),M37,IF(N37=$AB$10,M37,0)) -> 0 | AC37: =IF(AND(N37>$AC$9,N37<$AC$10),M37,IF(N37=$AC$10,M37,0)) -> 0 | AD37: =IF(AND(N37>$AD$9,N37<$AD$10),M37,IF(N37=$AD$10,M37,0)) -> 0 | AE37: =IF(AND(N37>$AE$9,N37<$AE$10),M37,IF(N37=$AE$10,M37,0)) -> 0 | AF37: =IF(AND(N37>$AF$9,N37<$AF$10),M37,IF(N37=$AF$10,M37,0)) -> 0 | AG37: =IF(N37=$AG$9,M37,0) -> 0
A38: 10620001 | B38: SYN-Working Capital Loan - Domestic | C38: 6115904000744 | D38: 100000033 | E38: MACQUARIE GROUP LIMITED | F38: USD | G38: 10000000 | H38: 14289797 | I38: 45974 | J38: 48136 | K38: 46066 | L38: =A38&"_"&F38&"_"&D38&"_"&E38 -> 10620001_USD_100000033_MACQUARIE GROUP LIMITED | M38: =IF(COUNTIF($A$2:$A$8,A38)>0,-H38,H38) -> 14289797 | N38: =IF(OR(L38=$L$2,L38=$L$3),$M$10+1,IFERROR(VLOOKUP(A38,'Repricing Maturity Adj.'!$A$3:$C$170,3,0),(IF(K38<$M$10,"Check",K38)))) -> 46059 | O38: =M38=SUM(Q38:AG38) -> TRUE | P38: =IF(A38="","N/A",IF(COUNTIF($A$2:$A$7,A38)>0,"Liability",IF(COUNTIF($A$8,A38)>0,"Asset",IF(A38<20000000,"Asset",IF(AND(A38>20000000,A38<28800000),"Liability",IF(A38>28800000,"Equity","")))))) -> Asset | Q38: =IF(AND(N38>$Q$9,N38<$Q$10),M38,IF(N38=$Q$10,M38,0)) -> 14289797 | R38: =IF(AND(N38>$R$9,N38<$R$10),M38,IF(N38=$R$10,M38,0)) -> 0 | S38: =IF(AND(N38>$S$9,N38<$S$10),M38,IF(N38=$S$10,M38,0)) -> 0 | T38: =IF(AND(N38>$T$9,N38<$T$10),M38,IF(N38=$T$10,M38,0)) -> 0 | U38: =IF(AND(N38>$U$9,N38<$U$10),M38,IF(N38=$U$10,M38,0)) -> 0 | V38: =IF(AND(N38>$V$9,N38<$V$10),M38,IF(N38=$V$10,M38,0)) -> 0 | W38: =IF(AND(N38>$W$9,N38<$W$10),M38,IF(N38=$W$10,M38,0)) -> 0 | X38: =IF(AND(N38>$X$9,N38<$X$10),M38,IF(N38=$X$10,M38,0)) -> 0 | Y38: =IF(AND(N38>$Y$9,N38<$Y$10),M38,IF(N38=$Y$10,M38,0)) -> 0 | Z38: =IF(AND(N38>$Z$9,N38<$Z$10),M38,IF(N38=$Z$10,M38,0)) -> 0 | AA38: =IF(AND(N38>$AA$9,N38<$AA$10),M38,IF(N38=$AA$10,M38,0)) -> 0 | AB38: =IF(AND(N38>$AB$9,N38<$AB$10),M38,IF(N38=$AB$10,M38,0)) -> 0 | AC38: =IF(AND(N38>$AC$9,N38<$AC$10),M38,IF(N38=$AC$10,M38,0)) -> 0 | AD38: =IF(AND(N38>$AD$9,N38<$AD$10),M38,IF(N38=$AD$10,M38,0)) -> 0 | AE38: =IF(AND(N38>$AE$9,N38<$AE$10),M38,IF(N38=$AE$10,M38,0)) -> 0 | AF38: =IF(AND(N38>$AF$9,N38<$AF$10),M38,IF(N38=$AF$10,M38,0)) -> 0 | AG38: =IF(N38=$AG$9,M38,0) -> 0
A39: 10630001 | B39: Syndicated Loans (Long Term) - Domestic | C39: 6115904000025 | D39: 100000014 | E39: PERDAMAN CHEMICALS & FERTILISERS (FINANCE)PTY LTD | F39: USD | G39: 7591892 | H39: 10848660 | I39: 45106 | J39: 47579 | K39: 46087 | L39: =A39&"_"&F39&"_"&D39&"_"&E39 -> 10630001_USD_100000014_PERDAMAN CHEMICALS & FERTILISERS (FINANCE)PTY LTD | M39: =IF(COUNTIF($A$2:$A$8,A39)>0,-H39,H39) -> 10848660 | N39: =IF(OR(L39=$L$2,L39=$L$3),$M$10+1,IFERROR(VLOOKUP(A39,'Repricing Maturity Adj.'!$A$3:$C$170,3,0),(IF(K39<$M$10,"Check",K39)))) -> 46059 | O39: =M39=SUM(Q39:AG39) -> TRUE | P39: =IF(A39="","N/A",IF(COUNTIF($A$2:$A$7,A39)>0,"Liability",IF(COUNTIF($A$8,A39)>0,"Asset",IF(A39<20000000,"Asset",IF(AND(A39>20000000,A39<28800000),"Liability",IF(A39>28800000,"Equity","")))))) -> Asset | Q39: =IF(AND(N39>$Q$9,N39<$Q$10),M39,IF(N39=$Q$10,M39,0)) -> 10848660 | R39: =IF(AND(N39>$R$9,N39<$R$10),M39,IF(N39=$R$10,M39,0)) -> 0 | S39: =IF(AND(N39>$S$9,N39<$S$10),M39,IF(N39=$S$10,M39,0)) -> 0 | T39: =IF(AND(N39>$T$9,N39<$T$10),M39,IF(N39=$T$10,M39,0)) -> 0 | U39: =IF(AND(N39>$U$9,N39<$U$10),M39,IF(N39=$U$10,M39,0)) -> 0 | V39: =IF(AND(N39>$V$9,N39<$V$10),M39,IF(N39=$V$10,M39,0)) -> 0 | W39: =IF(AND(N39>$W$9,N39<$W$10),M39,IF(N39=$W$10,M39,0)) -> 0 | X39: =IF(AND(N39>$X$9,N39<$X$10),M39,IF(N39=$X$10,M39,0)) -> 0 | Y39: =IF(AND(N39>$Y$9,N39<$Y$10),M39,IF(N39=$Y$10,M39,0)) -> 0 | Z39: =IF(AND(N39>$Z$9,N39<$Z$10),M39,IF(N39=$Z$10,M39,0)) -> 0 | AA39: =IF(AND(N39>$AA$9,N39<$AA$10),M39,IF(N39=$AA$10,M39,0)) -> 0 | AB39: =IF(AND(N39>$AB$9,N39<$AB$10),M39,IF(N39=$AB$10,M39,0)) -> 0 | AC39: =IF(AND(N39>$AC$9,N39<$AC$10),M39,IF(N39=$AC$10,M39,0)) -> 0 | AD39: =IF(AND(N39>$AD$9,N39<$AD$10),M39,IF(N39=$AD$10,M39,0)) -> 0 | AE39: =IF(AND(N39>$AE$9,N39<$AE$10),M39,IF(N39=$AE$10,M39,0)) -> 0 | AF39: =IF(AND(N39>$AF$9,N39<$AF$10),M39,IF(N39=$AF$10,M39,0)) -> 0 | AG39: =IF(N39=$AG$9,M39,0) -> 0
A40: 10630001 | B40: Syndicated Loans (Long Term) - Domestic | C40: 6115904000032 | D40: 100000014 | E40: PERDAMAN CHEMICALS & FERTILISERS (FINANCE)PTY LTD | F40: USD | G40: 129689.8 | H40: 185324.09 | I40: 45107 | J40: 47579 | K40: 46112 | L40: =A40&"_"&F40&"_"&D40&"_"&E40 -> 10630001_USD_100000014_PERDAMAN CHEMICALS & FERTILISERS (FINANCE)PTY LTD | M40: =IF(COUNTIF($A$2:$A$8,A40)>0,-H40,H40) -> 185324.09 | N40: =IF(OR(L40=$L$2,L40=$L$3),$M$10+1,IFERROR(VLOOKUP(A40,'Repricing Maturity Adj.'!$A$3:$C$170,3,0),(IF(K40<$M$10,"Check",K40)))) -> 46059 | O40: =M40=SUM(Q40:AG40) -> TRUE | P40: =IF(A40="","N/A",IF(COUNTIF($A$2:$A$7,A40)>0,"Liability",IF(COUNTIF($A$8,A40)>0,"Asset",IF(A40<20000000,"Asset",IF(AND(A40>20000000,A40<28800000),"Liability",IF(A40>28800000,"Equity","")))))) -> Asset | Q40: =IF(AND(N40>$Q$9,N40<$Q$10),M40,IF(N40=$Q$10,M40,0)) -> 185324.09 | R40: =IF(AND(N40>$R$9,N40<$R$10),M40,IF(N40=$R$10,M40,0)) -> 0 | S40: =IF(AND(N40>$S$9,N40<$S$10),M40,IF(N40=$S$10,M40,0)) -> 0 | T40: =IF(AND(N40>$T$9,N40<$T$10),M40,IF(N40=$T$10,M40,0)) -> 0 | U40: =IF(AND(N40>$U$9,N40<$U$10),M40,IF(N40=$U$10,M40,0)) -> 0 | V40: =IF(AND(N40>$V$9,N40<$V$10),M40,IF(N40=$V$10,M40,0)) -> 0 | W40: =IF(AND(N40>$W$9,N40<$W$10),M40,IF(N40=$W$10,M40,0)) -> 0 | X40: =IF(AND(N40>$X$9,N40<$X$10),M40,IF(N40=$X$10,M40,0)) -> 0 | Y40: =IF(AND(N40>$Y$9,N40<$Y$10),M40,IF(N40=$Y$10,M40,0)) -> 0 | Z40: =IF(AND(N40>$Z$9,N40<$Z$10),M40,IF(N40=$Z$10,M40,0)) -> 0 | AA40: =IF(AND(N40>$AA$9,N40<$AA$10),M40,IF(N40=$AA$10,M40,0)) -> 0 | AB40: =IF(AND(N40>$AB$9,N40<$AB$10),M40,IF(N40=$AB$10,M40,0)) -> 0 | AC40: =IF(AND(N40>$AC$9,N40<$AC$10),M40,IF(N40=$AC$10,M40,0)) -> 0 | AD40: =IF(AND(N40>$AD$9,N40<$AD$10),M40,IF(N40=$AD$10,M40,0)) -> 0 | AE40: =IF(AND(N40>$AE$9,N40<$AE$10),M40,IF(N40=$AE$10,M40,0)) -> 0 | AF40: =IF(AND(N40>$AF$9,N40<$AF$10),M40,IF(N40=$AF$10,M40,0)) -> 0 | AG40: =IF(N40=$AG$9,M40,0) -> 0
... A101: 10630001 | B101: Syndicated Loans (Long Term) - Domestic | C101: 6115904000791 | D101: 100000014 | E101: PERDAMAN CHEMICALS & FERTILISERS (FINANCE)PTY LTD | F101: USD | G101: 274478.25 | H101: 392223.85 | I101: 46058 | J101: 47579 | K101: 46086 | L101: =A101&"_"&F101&"_"&D101&"_"&E101 -> 10630001_USD_100000014_PERDAMAN CHEMICALS & FERTILISERS (FINANCE)PTY LTD | M101: =IF(COUNTIF($A$2:$A$8,A101)>0,-H101,H101) -> 392223.85 | N101: =IF(OR(L101=$L$2,L101=$L$3),$M$10+1,IFERROR(VLOOKUP(A101,'Repricing Maturity Adj.'!$A$3:$C$170,3,0),(IF(K101<$M$10,"Check",K101)))) -> 46059 | O101: =M101=SUM(Q101:AG101) -> TRUE | P101: =IF(A101="","N/A",IF(COUNTIF($A$2:$A$7,A101)>0,"Liability",IF(COUNTIF($A$8,A101)>0,"Asset",IF(A101<20000000,"Asset",IF(AND(A101>20000000,A101<28800000),"Liability",IF(A101>28800000,"Equity","")))))) -> Asset | Q101: =IF(AND(N101>$Q$9,N101<$Q$10),M101,IF(N101=$Q$10,M101,0)) -> 392223.85 | R101: =IF(AND(N101>$R$9,N101<$R$10),M101,IF(N101=$R$10,M101,0)) -> 0 | S101: =IF(AND(N101>$S$9,N101<$S$10),M101,IF(N101=$S$10,M101,0)) -> 0 | T101: =IF(AND(N101>$T$9,N101<$T$10),M101,IF(N101=$T$10,M101,0)) -> 0 | U101: =IF(AND(N101>$U$9,N101<$U$10),M101,IF(N101=$U$10,M101,0)) -> 0 | V101: =IF(AND(N101>$V$9,N101<$V$10),M101,IF(N101=$V$10,M101,0)) -> 0 | W101: =IF(AND(N101>$W$9,N101<$W$10),M101,IF(N101=$W$10,M101,0)) -> 0 | X101: =IF(AND(N101>$X$9,N101<$X$10),M101,IF(N101=$X$10,M101,0)) -> 0 | Y101: =IF(AND(N101>$Y$9,N101<$Y$10),M101,IF(N101=$Y$10,M101,0)) -> 0 | Z101: =IF(AND(N101>$Z$9,N101<$Z$10),M101,IF(N101=$Z$10,M101,0)) -> 0 | AA101: =IF(AND(N101>$AA$9,N101<$AA$10),M101,IF(N101=$AA$10,M101,0)) -> 0 | AB101: =IF(AND(N101>$AB$9,N101<$AB$10),M101,IF(N101=$AB$10,M101,0)) -> 0 | AC101: =IF(AND(N101>$AC$9,N101<$AC$10),M101,IF(N101=$AC$10,M101,0)) -> 0 | AD101: =IF(AND(N101>$AD$9,N101<$AD$10),M101,IF(N101=$AD$10,M101,0)) -> 0 | AE101: =IF(AND(N101>$AE$9,N101<$AE$10),M101,IF(N101=$AE$10,M101,0)) -> 0 | AF101: =IF(AND(N101>$AF$9,N101<$AF$10),M101,IF(N101=$AF$10,M101,0)) -> 0 | AG101: =IF(N101=$AG$9,M101,0) -> 0
A102: 10690001 | B102: Allowance For Loan Losses - General | C102: OL5904220000001 | D102: 100000003 | E102: COSMAX NBT AUSTRALIA PTY LTD | F102: AUD | G102: -66801.6 | H102: -66801.6 | L102: =A102&"_"&F102&"_"&D102&"_"&E102 -> 10690001_AUD_100000003_COSMAX NBT AUSTRALIA PTY LTD | M102: =IF(COUNTIF($A$2:$A$8,A102)>0,-H102,H102) -> 66801.6 | N102: =IF(OR(L102=$L$2,L102=$L$3),$M$10+1,IFERROR(VLOOKUP(A102,'Repricing Maturity Adj.'!$A$3:$C$170,3,0),(IF(K102<$M$10,"Check",K102)))) -> Non_sensitive | O102: =M102=SUM(Q102:AG102) -> TRUE | P102: =IF(A102="","N/A",IF(COUNTIF($A$2:$A$7,A102)>0,"Liability",IF(COUNTIF($A$8,A102)>0,"Asset",IF(A102<20000000,"Asset",IF(AND(A102>20000000,A102<28800000),"Liability",IF(A102>28800000,"Equity","")))))) -> Liability | Q102: =IF(AND(N102>$Q$9,N102<$Q$10),M102,IF(N102=$Q$10,M102,0)) -> 0 | R102: =IF(AND(N102>$R$9,N102<$R$10),M102,IF(N102=$R$10,M102,0)) -> 0 | S102: =IF(AND(N102>$S$9,N102<$S$10),M102,IF(N102=$S$10,M102,0)) -> 0 | T102: =IF(AND(N102>$T$9,N102<$T$10),M102,IF(N102=$T$10,M102,0)) -> 0 | U102: =IF(AND(N102>$U$9,N102<$U$10),M102,IF(N102=$U$10,M102,0)) -> 0 | V102: =IF(AND(N102>$V$9,N102<$V$10),M102,IF(N102=$V$10,M102,0)) -> 0 | W102: =IF(AND(N102>$W$9,N102<$W$10),M102,IF(N102=$W$10,M102,0)) -> 0 | X102: =IF(AND(N102>$X$9,N102<$X$10),M102,IF(N102=$X$10,M102,0)) -> 0 | Y102: =IF(AND(N102>$Y$9,N102<$Y$10),M102,IF(N102=$Y$10,M102,0)) -> 0 | Z102: =IF(AND(N102>$Z$9,N102<$Z$10),M102,IF(N102=$Z$10,M102,0)) -> 0 | AA102: =IF(AND(N102>$AA$9,N102<$AA$10),M102,IF(N102=$AA$10,M102,0)) -> 0 | AB102: =IF(AND(N102>$AB$9,N102<$AB$10),M102,IF(N102=$AB$10,M102,0)) -> 0 | AC102: =IF(AND(N102>$AC$9,N102<$AC$10),M102,IF(N102=$AC$10,M102,0)) -> 0 | AD102: =IF(AND(N102>$AD$9,N102<$AD$10),M102,IF(N102=$AD$10,M102,0)) -> 0 | AE102: =IF(AND(N102>$AE$9,N102<$AE$10),M102,IF(N102=$AE$10,M102,0)) -> 0 | AF102: =IF(AND(N102>$AF$9,N102<$AF$10),M102,IF(N102=$AF$10,M102,0)) -> 0 | AG102: =IF(N102=$AG$9,M102,0) -> 66801.6
A103: 10690001 | B103: Allowance For Loan Losses - General | C103: OL5904230000006 | D103: 100000014 | E103: PERDAMAN CHEMICALS & FERTILISERS (FINANCE)PTY LTD | F103: USD | G103: -833.7 | H103: -1191.34 | L103: =A103&"_"&F103&"_"&D103&"_"&E103 -> 10690001_USD_100000014_PERDAMAN CHEMICALS & FERTILISERS (FINANCE)PTY LTD | M103: =IF(COUNTIF($A$2:$A$8,A103)>0,-H103,H103) -> 1191.34 | N103: =IF(OR(L103=$L$2,L103=$L$3),$M$10+1,IFERROR(VLOOKUP(A103,'Repricing Maturity Adj.'!$A$3:$C$170,3,0),(IF(K103<$M$10,"Check",K103)))) -> Non_sensitive | O103: =M103=SUM(Q103:AG103) -> TRUE | P103: =IF(A103="","N/A",IF(COUNTIF($A$2:$A$7,A103)>0,"Liability",IF(COUNTIF($A$8,A103)>0,"Asset",IF(A103<20000000,"Asset",IF(AND(A103>20000000,A103<28800000),"Liability",IF(A103>28800000,"Equity","")))))) -> Liability | Q103: =IF(AND(N103>$Q$9,N103<$Q$10),M103,IF(N103=$Q$10,M103,0)) -> 0 | R103: =IF(AND(N103>$R$9,N103<$R$10),M103,IF(N103=$R$10,M103,0)) -> 0 | S103: =IF(AND(N103>$S$9,N103<$S$10),M103,IF(N103=$S$10,M103,0)) -> 0 | T103: =IF(AND(N103>$T$9,N103<$T$10),M103,IF(N103=$T$10,M103,0)) -> 0 | U103: =IF(AND(N103>$U$9,N103<$U$10),M103,IF(N103=$U$10,M103,0)) -> 0 | V103: =IF(AND(N103>$V$9,N103<$V$10),M103,IF(N103=$V$10,M103,0)) -> 0 | W103: =IF(AND(N103>$W$9,N103<$W$10),M103,IF(N103=$W$10,M103,0)) -> 0 | X103: =IF(AND(N103>$X$9,N103<$X$10),M103,IF(N103=$X$10,M103,0)) -> 0 | Y103: =IF(AND(N103>$Y$9,N103<$Y$10),M103,IF(N103=$Y$10,M103,0)) -> 0 | Z103: =IF(AND(N103>$Z$9,N103<$Z$10),M103,IF(N103=$Z$10,M103,0)) -> 0 | AA103: =IF(AND(N103>$AA$9,N103<$AA$10),M103,IF(N103=$AA$10,M103,0)) -> 0 | AB103: =IF(AND(N103>$AB$9,N103<$AB$10),M103,IF(N103=$AB$10,M103,0)) -> 0 | AC103: =IF(AND(N103>$AC$9,N103<$AC$10),M103,IF(N103=$AC$10,M103,0)) -> 0 | AD103: =IF(AND(N103>$AD$9,N103<$AD$10),M103,IF(N103=$AD$10,M103,0)) -> 0 | AE103: =IF(AND(N103>$AE$9,N103<$AE$10),M103,IF(N103=$AE$10,M103,0)) -> 0 | AF103: =IF(AND(N103>$AF$9,N103<$AF$10),M103,IF(N103=$AF$10,M103,0)) -> 0 | AG103: =IF(N103=$AG$9,M103,0) -> 1191.34
A104: 10690001 | B104: Allowance For Loan Losses - General | C104: OL5904230000007 | D104: 100000014 | E104: PERDAMAN CHEMICALS & FERTILISERS (FINANCE)PTY LTD | F104: USD | G104: -48803.72 | H104: -69739.53 | L104: =A104&"_"&F104&"_"&D104&"_"&E104 -> 10690001_USD_100000014_PERDAMAN CHEMICALS & FERTILISERS (FINANCE)PTY LTD | M104: =IF(COUNTIF($A$2:$A$8,A104)>0,-H104,H104) -> 69739.53 | N104: =IF(OR(L104=$L$2,L104=$L$3),$M$10+1,IFERROR(VLOOKUP(A104,'Repricing Maturity Adj.'!$A$3:$C$170,3,0),(IF(K104<$M$10,"Check",K104)))) -> Non_sensitive | O104: =M104=SUM(Q104:AG104) -> TRUE | P104: =IF(A104="","N/A",IF(COUNTIF($A$2:$A$7,A104)>0,"Liability",IF(COUNTIF($A$8,A104)>0,"Asset",IF(A104<20000000,"Asset",IF(AND(A104>20000000,A104<28800000),"Liability",IF(A104>28800000,"Equity","")))))) -> Liability | Q104: =IF(AND(N104>$Q$9,N104<$Q$10),M104,IF(N104=$Q$10,M104,0)) -> 0 | R104: =IF(AND(N104>$R$9,N104<$R$10),M104,IF(N104=$R$10,M104,0)) -> 0 | S104: =IF(AND(N104>$S$9,N104<$S$10),M104,IF(N104=$S$10,M104,0)) -> 0 | T104: =IF(AND(N104>$T$9,N104<$T$10),M104,IF(N104=$T$10,M104,0)) -> 0 | U104: =IF(AND(N104>$U$9,N104<$U$10),M104,IF(N104=$U$10,M104,0)) -> 0 | V104: =IF(AND(N104>$V$9,N104<$V$10),M104,IF(N104=$V$10,M104,0)) -> 0 | W104: =IF(AND(N104>$W$9,N104<$W$10),M104,IF(N104=$W$10,M104,0)) -> 0 | X104: =IF(AND(N104>$X$9,N104<$X$10),M104,IF(N104=$X$10,M104,0)) -> 0 | Y104: =IF(AND(N104>$Y$9,N104<$Y$10),M104,IF(N104=$Y$10,M104,0)) -> 0 | Z104: =IF(AND(N104>$Z$9,N104<$Z$10),M104,IF(N104=$Z$10,M104,0)) -> 0 | AA104: =IF(AND(N104>$AA$9,N104<$AA$10),M104,IF(N104=$AA$10,M104,0)) -> 0 | AB104: =IF(AND(N104>$AB$9,N104<$AB$10),M104,IF(N104=$AB$10,M104,0)) -> 0 | AC104: =IF(AND(N104>$AC$9,N104<$AC$10),M104,IF(N104=$AC$10,M104,0)) -> 0 | AD104: =IF(AND(N104>$AD$9,N104<$AD$10),M104,IF(N104=$AD$10,M104,0)) -> 0 | AE104: =IF(AND(N104>$AE$9,N104<$AE$10),M104,IF(N104=$AE$10,M104,0)) -> 0 | AF104: =IF(AND(N104>$AF$9,N104<$AF$10),M104,IF(N104=$AF$10,M104,0)) -> 0 | AG104: =IF(N104=$AG$9,M104,0) -> 69739.53
A105: 10690001 | B105: Allowance For Loan Losses - General | C105: OL5904230000008 | D105: 100000014 | E105: PERDAMAN CHEMICALS & FERTILISERS (FINANCE)PTY LTD | F105: USD | G105: -633.31 | H105: -904.99 | L105: =A105&"_"&F105&"_"&D105&"_"&E105 -> 10690001_USD_100000014_PERDAMAN CHEMICALS & FERTILISERS (FINANCE)PTY LTD | M105: =IF(COUNTIF($A$2:$A$8,A105)>0,-H105,H105) -> 904.99 | N105: =IF(OR(L105=$L$2,L105=$L$3),$M$10+1,IFERROR(VLOOKUP(A105,'Repricing Maturity Adj.'!$A$3:$C$170,3,0),(IF(K105<$M$10,"Check",K105)))) -> Non_sensitive | O105: =M105=SUM(Q105:AG105) -> TRUE | P105: =IF(A105="","N/A",IF(COUNTIF($A$2:$A$7,A105)>0,"Liability",IF(COUNTIF($A$8,A105)>0,"Asset",IF(A105<20000000,"Asset",IF(AND(A105>20000000,A105<28800000),"Liability",IF(A105>28800000,"Equity","")))))) -> Liability | Q105: =IF(AND(N105>$Q$9,N105<$Q$10),M105,IF(N105=$Q$10,M105,0)) -> 0 | R105: =IF(AND(N105>$R$9,N105<$R$10),M105,IF(N105=$R$10,M105,0)) -> 0 | S105: =IF(AND(N105>$S$9,N105<$S$10),M105,IF(N105=$S$10,M105,0)) -> 0 | T105: =IF(AND(N105>$T$9,N105<$T$10),M105,IF(N105=$T$10,M105,0)) -> 0 | U105: =IF(AND(N105>$U$9,N105<$U$10),M105,IF(N105=$U$10,M105,0)) -> 0 | V105: =IF(AND(N105>$V$9,N105<$V$10),M105,IF(N105=$V$10,M105,0)) -> 0 | W105: =IF(AND(N105>$W$9,N105<$W$10),M105,IF(N105=$W$10,M105,0)) -> 0 | X105: =IF(AND(N105>$X$9,N105<$X$10),M105,IF(N105=$X$10,M105,0)) -> 0 | Y105: =IF(AND(N105>$Y$9,N105<$Y$10),M105,IF(N105=$Y$10,M105,0)) -> 0 | Z105: =IF(AND(N105>$Z$9,N105<$Z$10),M105,IF(N105=$Z$10,M105,0)) -> 0 | AA105: =IF(AND(N105>$AA$9,N105<$AA$10),M105,IF(N105=$AA$10,M105,0)) -> 0 | AB105: =IF(AND(N105>$AB$9,N105<$AB$10),M105,IF(N105=$AB$10,M105,0)) -> 0 | AC105: =IF(AND(N105>$AC$9,N105<$AC$10),M105,IF(N105=$AC$10,M105,0)) -> 0 | AD105: =IF(AND(N105>$AD$9,N105<$AD$10),M105,IF(N105=$AD$10,M105,0)) -> 0 | AE105: =IF(AND(N105>$AE$9,N105<$AE$10),M105,IF(N105=$AE$10,M105,0)) -> 0 | AF105: =IF(AND(N105>$AF$9,N105<$AF$10),M105,IF(N105=$AF$10,M105,0)) -> 0 | AG105: =IF(N105=$AG$9,M105,0) -> 904.99
A106: 10690001 | B106: Allowance For Loan Losses - General | C106: OL5904230000009 | D106: 100000014 | E106: PERDAMAN CHEMICALS & FERTILISERS (FINANCE)PTY LTD | F106: USD | G106: -11491.72 | H106: -16421.43 | L106: =A106&"_"&F106&"_"&D106&"_"&E106 -> 10690001_USD_100000014_PERDAMAN CHEMICALS & FERTILISERS (FINANCE)PTY LTD | M106: =IF(COUNTIF($A$2:$A$8,A106)>0,-H106,H106) -> 16421.43 | N106: =IF(OR(L106=$L$2,L106=$L$3),$M$10+1,IFERROR(VLOOKUP(A106,'Repricing Maturity Adj.'!$A$3:$C$170,3,0),(IF(K106<$M$10,"Check",K106)))) -> Non_sensitive | O106: =M106=SUM(Q106:AG106) -> TRUE | P106: =IF(A106="","N/A",IF(COUNTIF($A$2:$A$7,A106)>0,"Liability",IF(COUNTIF($A$8,A106)>0,"Asset",IF(A106<20000000,"Asset",IF(AND(A106>20000000,A106<28800000),"Liability",IF(A106>28800000,"Equity","")))))) -> Liability | Q106: =IF(AND(N106>$Q$9,N106<$Q$10),M106,IF(N106=$Q$10,M106,0)) -> 0 | R106: =IF(AND(N106>$R$9,N106<$R$10),M106,IF(N106=$R$10,M106,0)) -> 0 | S106: =IF(AND(N106>$S$9,N106<$S$10),M106,IF(N106=$S$10,M106,0)) -> 0 | T106: =IF(AND(N106>$T$9,N106<$T$10),M106,IF(N106=$T$10,M106,0)) -> 0 | U106: =IF(AND(N106>$U$9,N106<$U$10),M106,IF(N106=$U$10,M106,0)) -> 0 | V106: =IF(AND(N106>$V$9,N106<$V$10),M106,IF(N106=$V$10,M106,0)) -> 0 | W106: =IF(AND(N106>$W$9,N106<$W$10),M106,IF(N106=$W$10,M106,0)) -> 0 | X106: =IF(AND(N106>$X$9,N106<$X$10),M106,IF(N106=$X$10,M106,0)) -> 0 | Y106: =IF(AND(N106>$Y$9,N106<$Y$10),M106,IF(N106=$Y$10,M106,0)) -> 0 | Z106: =IF(AND(N106>$Z$9,N106<$Z$10),M106,IF(N106=$Z$10,M106,0)) -> 0 | AA106: =IF(AND(N106>$AA$9,N106<$AA$10),M106,IF(N106=$AA$10,M106,0)) -> 0 | AB106: =IF(AND(N106>$AB$9,N106<$AB$10),M106,IF(N106=$AB$10,M106,0)) -> 0 | AC106: =IF(AND(N106>$AC$9,N106<$AC$10),M106,IF(N106=$AC$10,M106,0)) -> 0 | AD106: =IF(AND(N106>$AD$9,N106<$AD$10),M106,IF(N106=$AD$10,M106,0)) -> 0 | AE106: =IF(AND(N106>$AE$9,N106<$AE$10),M106,IF(N106=$AE$10,M106,0)) -> 0 | AF106: =IF(AND(N106>$AF$9,N106<$AF$10),M106,IF(N106=$AF$10,M106,0)) -> 0 | AG106: =IF(N106=$AG$9,M106,0) -> 16421.43
A107: 10690001 | B107: Allowance For Loan Losses - General | C107: OL5904230000010 | D107: 100000014 | E107: PERDAMAN CHEMICALS & FERTILISERS (FINANCE)PTY LTD | F107: USD | G107: -715.23 | H107: -1022.05 | L107: =A107&"_"&F107&"_"&D107&"_"&E107 -> 10690001_USD_100000014_PERDAMAN CHEMICALS & FERTILISERS (FINANCE)PTY LTD | M107: =IF(COUNTIF($A$2:$A$8,A107)>0,-H107,H107) -> 1022.05 | N107: =IF(OR(L107=$L$2,L107=$L$3),$M$10+1,IFERROR(VLOOKUP(A107,'Repricing Maturity Adj.'!$A$3:$C$170,3,0),(IF(K107<$M$10,"Check",K107)))) -> Non_sensitive | O107: =M107=SUM(Q107:AG107) -> TRUE | P107: =IF(A107="","N/A",IF(COUNTIF($A$2:$A$7,A107)>0,"Liability",IF(COUNTIF($A$8,A107)>0,"Asset",IF(A107<20000000,"Asset",IF(AND(A107>20000000,A107<28800000),"Liability",IF(A107>28800000,"Equity","")))))) -> Liability | Q107: =IF(AND(N107>$Q$9,N107<$Q$10),M107,IF(N107=$Q$10,M107,0)) -> 0 | R107: =IF(AND(N107>$R$9,N107<$R$10),M107,IF(N107=$R$10,M107,0)) -> 0 | S107: =IF(AND(N107>$S$9,N107<$S$10),M107,IF(N107=$S$10,M107,0)) -> 0 | T107: =IF(AND(N107>$T$9,N107<$T$10),M107,IF(N107=$T$10,M107,0)) -> 0 | U107: =IF(AND(N107>$U$9,N107<$U$10),M107,IF(N107=$U$10,M107,0)) -> 0 | V107: =IF(AND(N107>$V$9,N107<$V$10),M107,IF(N107=$V$10,M107,0)) -> 0 | W107: =IF(AND(N107>$W$9,N107<$W$10),M107,IF(N107=$W$10,M107,0)) -> 0 | X107: =IF(AND(N107>$X$9,N107<$X$10),M107,IF(N107=$X$10,M107,0)) -> 0 | Y107: =IF(AND(N107>$Y$9,N107<$Y$10),M107,IF(N107=$Y$10,M107,0)) -> 0 | Z107: =IF(AND(N107>$Z$9,N107<$Z$10),M107,IF(N107=$Z$10,M107,0)) -> 0 | AA107: =IF(AND(N107>$AA$9,N107<$AA$10),M107,IF(N107=$AA$10,M107,0)) -> 0 | AB107: =IF(AND(N107>$AB$9,N107<$AB$10),M107,IF(N107=$AB$10,M107,0)) -> 0 | AC107: =IF(AND(N107>$AC$9,N107<$AC$10),M107,IF(N107=$AC$10,M107,0)) -> 0 | AD107: =IF(AND(N107>$AD$9,N107<$AD$10),M107,IF(N107=$AD$10,M107,0)) -> 0 | AE107: =IF(AND(N107>$AE$9,N107<$AE$10),M107,IF(N107=$AE$10,M107,0)) -> 0 | AF107: =IF(AND(N107>$AF$9,N107<$AF$10),M107,IF(N107=$AF$10,M107,0)) -> 0 | AG107: =IF(N107=$AG$9,M107,0) -> 1022.05
A108: 10690001 | B108: Allowance For Loan Losses - General | C108: OL5904230000011 | D108: 100000014 | E108: PERDAMAN CHEMICALS & FERTILISERS (FINANCE)PTY LTD | F108: USD | G108: -3012.73 | H108: -4305.13 | L108: =A108&"_"&F108&"_"&D108&"_"&E108 -> 10690001_USD_100000014_PERDAMAN CHEMICALS & FERTILISERS (FINANCE)PTY LTD | M108: =IF(COUNTIF($A$2:$A$8,A108)>0,-H108,H108) -> 4305.13 | N108: =IF(OR(L108=$L$2,L108=$L$3),$M$10+1,IFERROR(VLOOKUP(A108,'Repricing Maturity Adj.'!$A$3:$C$170,3,0),(IF(K108<$M$10,"Check",K108)))) -> Non_sensitive | O108: =M108=SUM(Q108:AG108) -> TRUE | P108: =IF(A108="","N/A",IF(COUNTIF($A$2:$A$7,A108)>0,"Liability",IF(COUNTIF($A$8,A108)>0,"Asset",IF(A108<20000000,"Asset",IF(AND(A108>20000000,A108<28800000),"Liability",IF(A108>28800000,"Equity","")))))) -> Liability | Q108: =IF(AND(N108>$Q$9,N108<$Q$10),M108,IF(N108=$Q$10,M108,0)) -> 0 | R108: =IF(AND(N108>$R$9,N108<$R$10),M108,IF(N108=$R$10,M108,0)) -> 0 | S108: =IF(AND(N108>$S$9,N108<$S$10),M108,IF(N108=$S$10,M108,0)) -> 0 | T108: =IF(AND(N108>$T$9,N108<$T$10),M108,IF(N108=$T$10,M108,0)) -> 0 | U108: =IF(AND(N108>$U$9,N108<$U$10),M108,IF(N108=$U$10,M108,0)) -> 0 | V108: =IF(AND(N108>$V$9,N108<$V$10),M108,IF(N108=$V$10,M108,0)) -> 0 | W108: =IF(AND(N108>$W$9,N108<$W$10),M108,IF(N108=$W$10,M108,0)) -> 0 | X108: =IF(AND(N108>$X$9,N108<$X$10),M108,IF(N108=$X$10,M108,0)) -> 0 | Y108: =IF(AND(N108>$Y$9,N108<$Y$10),M108,IF(N108=$Y$10,M108,0)) -> 0 | Z108: =IF(AND(N108>$Z$9,N108<$Z$10),M108,IF(N108=$Z$10,M108,0)) -> 0 | AA108: =IF(AND(N108>$AA$9,N108<$AA$10),M108,IF(N108=$AA$10,M108,0)) -> 0 | AB108: =IF(AND(N108>$AB$9,N108<$AB$10),M108,IF(N108=$AB$10,M108,0)) -> 0 | AC108: =IF(AND(N108>$AC$9,N108<$AC$10),M108,IF(N108=$AC$10,M108,0)) -> 0 | AD108: =IF(AND(N108>$AD$9,N108<$AD$10),M108,IF(N108=$AD$10,M108,0)) -> 0 | AE108: =IF(AND(N108>$AE$9,N108<$AE$10),M108,IF(N108=$AE$10,M108,0)) -> 0 | AF108: =IF(AND(N108>$AF$9,N108<$AF$10),M108,IF(N108=$AF$10,M108,0)) -> 0 | AG108: =IF(N108=$AG$9,M108,0) -> 4305.13
A109: 10690001 | B109: Allowance For Loan Losses - General | C109: OL5904230000012 | D109: 100000014 | E109: PERDAMAN CHEMICALS & FERTILISERS (FINANCE)PTY LTD | F109: USD | G109: -10335.54 | H109: -14769.28 | L109: =A109&"_"&F109&"_"&D109&"_"&E109 -> 10690001_USD_100000014_PERDAMAN CHEMICALS & FERTILISERS (FINANCE)PTY LTD | M109: =IF(COUNTIF($A$2:$A$8,A109)>0,-H109,H109) -> 14769.28 | N109: =IF(OR(L109=$L$2,L109=$L$3),$M$10+1,IFERROR(VLOOKUP(A109,'Repricing Maturity Adj.'!$A$3:$C$170,3,0),(IF(K109<$M$10,"Check",K109)))) -> Non_sensitive | O109: =M109=SUM(Q109:AG109) -> TRUE | P109: =IF(A109="","N/A",IF(COUNTIF($A$2:$A$7,A109)>0,"Liability",IF(COUNTIF($A$8,A109)>0,"Asset",IF(A109<20000000,"Asset",IF(AND(A109>20000000,A109<28800000),"Liability",IF(A109>28800000,"Equity","")))))) -> Liability | Q109: =IF(AND(N109>$Q$9,N109<$Q$10),M109,IF(N109=$Q$10,M109,0)) -> 0 | R109: =IF(AND(N109>$R$9,N109<$R$10),M109,IF(N109=$R$10,M109,0)) -> 0 | S109: =IF(AND(N109>$S$9,N109<$S$10),M109,IF(N109=$S$10,M109,0)) -> 0 | T109: =IF(AND(N109>$T$9,N109<$T$10),M109,IF(N109=$T$10,M109,0)) -> 0 | U109: =IF(AND(N109>$U$9,N109<$U$10),M109,IF(N109=$U$10,M109,0)) -> 0 | V109: =IF(AND(N109>$V$9,N109<$V$10),M109,IF(N109=$V$10,M109,0)) -> 0 | W109: =IF(AND(N109>$W$9,N109<$W$10),M109,IF(N109=$W$10,M109,0)) -> 0 | X109: =IF(AND(N109>$X$9,N109<$X$10),M109,IF(N109=$X$10,M109,0)) -> 0 | Y109: =IF(AND(N109>$Y$9,N109<$Y$10),M109,IF(N109=$Y$10,M109,0)) -> 0 | Z109: =IF(AND(N109>$Z$9,N109<$Z$10),M109,IF(N109=$Z$10,M109,0)) -> 0 | AA109: =IF(AND(N109>$AA$9,N109<$AA$10),M109,IF(N109=$AA$10,M109,0)) -> 0 | AB109: =IF(AND(N109>$AB$9,N109<$AB$10),M109,IF(N109=$AB$10,M109,0)) -> 0 | AC109: =IF(AND(N109>$AC$9,N109<$AC$10),M109,IF(N109=$AC$10,M109,0)) -> 0 | AD109: =IF(AND(N109>$AD$9,N109<$AD$10),M109,IF(N109=$AD$10,M109,0)) -> 0 | AE109: =IF(AND(N109>$AE$9,N109<$AE$10),M109,IF(N109=$AE$10,M109,0)) -> 0 | AF109: =IF(AND(N109>$AF$9,N109<$AF$10),M109,IF(N109=$AF$10,M109,0)) -> 0 | AG109: =IF(N109=$AG$9,M109,0) -> 14769.28
A110: 10690001 | B110: Allowance For Loan Losses - General | C110: OL5904230000013 | D110: 100000014 | E110: PERDAMAN CHEMICALS & FERTILISERS (FINANCE)PTY LTD | F110: USD | G110: -665.78 | H110: -951.39 | L110: =A110&"_"&F110&"_"&D110&"_"&E110 -> 10690001_USD_100000014_PERDAMAN CHEMICALS & FERTILISERS (FINANCE)PTY LTD | M110: =IF(COUNTIF($A$2:$A$8,A110)>0,-H110,H110) -> 951.39 | N110: =IF(OR(L110=$L$2,L110=$L$3),$M$10+1,IFERROR(VLOOKUP(A110,'Repricing Maturity Adj.'!$A$3:$C$170,3,0),(IF(K110<$M$10,"Check",K110)))) -> Non_sensitive | O110: =M110=SUM(Q110:AG110) -> TRUE | P110: =IF(A110="","N/A",IF(COUNTIF($A$2:$A$7,A110)>0,"Liability",IF(COUNTIF($A$8,A110)>0,"Asset",IF(A110<20000000,"Asset",IF(AND(A110>20000000,A110<28800000),"Liability",IF(A110>28800000,"Equity","")))))) -> Liability | Q110: =IF(AND(N110>$Q$9,N110<$Q$10),M110,IF(N110=$Q$10,M110,0)) -> 0 | R110: =IF(AND(N110>$R$9,N110<$R$10),M110,IF(N110=$R$10,M110,0)) -> 0 | S110: =IF(AND(N110>$S$9,N110<$S$10),M110,IF(N110=$S$10,M110,0)) -> 0 | T110: =IF(AND(N110>$T$9,N110<$T$10),M110,IF(N110=$T$10,M110,0)) -> 0 | U110: =IF(AND(N110>$U$9,N110<$U$10),M110,IF(N110=$U$10,M110,0)) -> 0 | V110: =IF(AND(N110>$V$9,N110<$V$10),M110,IF(N110=$V$10,M110,0)) -> 0 | W110: =IF(AND(N110>$W$9,N110<$W$10),M110,IF(N110=$W$10,M110,0)) -> 0 | X110: =IF(AND(N110>$X$9,N110<$X$10),M110,IF(N110=$X$10,M110,0)) -> 0 | Y110: =IF(AND(N110>$Y$9,N110<$Y$10),M110,IF(N110=$Y$10,M110,0)) -> 0 | Z110: =IF(AND(N110>$Z$9,N110<$Z$10),M110,IF(N110=$Z$10,M110,0)) -> 0 | AA110: =IF(AND(N110>$AA$9,N110<$AA$10),M110,IF(N110=$AA$10,M110,0)) -> 0 | AB110: =IF(AND(N110>$AB$9,N110<$AB$10),M110,IF(N110=$AB$10,M110,0)) -> 0 | AC110: =IF(AND(N110>$AC$9,N110<$AC$10),M110,IF(N110=$AC$10,M110,0)) -> 0 | AD110: =IF(AND(N110>$AD$9,N110<$AD$10),M110,IF(N110=$AD$10,M110,0)) -> 0 | AE110: =IF(AND(N110>$AE$9,N110<$AE$10),M110,IF(N110=$AE$10,M110,0)) -> 0 | AF110: =IF(AND(N110>$AF$9,N110<$AF$10),M110,IF(N110=$AF$10,M110,0)) -> 0 | AG110: =IF(N110=$AG$9,M110,0) -> 951.39
A111: 10690001 | B111: Allowance For Loan Losses - General | C111: OL5904230000014 | D111: 100000014 | E111: PERDAMAN CHEMICALS & FERTILISERS (FINANCE)PTY LTD | F111: USD | G111: -7119.78 | H111: -10174.02 | L111: =A111&"_"&F111&"_"&D111&"_"&E111 -> 10690001_USD_100000014_PERDAMAN CHEMICALS & FERTILISERS (FINANCE)PTY LTD | M111: =IF(COUNTIF($A$2:$A$8,A111)>0,-H111,H111) -> 10174.02 | N111: =IF(OR(L111=$L$2,L111=$L$3),$M$10+1,IFERROR(VLOOKUP(A111,'Repricing Maturity Adj.'!$A$3:$C$170,3,0),(IF(K111<$M$10,"Check",K111)))) -> Non_sensitive | O111: =M111=SUM(Q111:AG111) -> TRUE | P111: =IF(A111="","N/A",IF(COUNTIF($A$2:$A$7,A111)>0,"Liability",IF(COUNTIF($A$8,A111)>0,"Asset",IF(A111<20000000,"Asset",IF(AND(A111>20000000,A111<28800000),"Liability",IF(A111>28800000,"Equity","")))))) -> Liability | Q111: =IF(AND(N111>$Q$9,N111<$Q$10),M111,IF(N111=$Q$10,M111,0)) -> 0 | R111: =IF(AND(N111>$R$9,N111<$R$10),M111,IF(N111=$R$10,M111,0)) -> 0 | S111: =IF(AND(N111>$S$9,N111<$S$10),M111,IF(N111=$S$10,M111,0)) -> 0 | T111: =IF(AND(N111>$T$9,N111<$T$10),M111,IF(N111=$T$10,M111,0)) -> 0 | U111: =IF(AND(N111>$U$9,N111<$U$10),M111,IF(N111=$U$10,M111,0)) -> 0 | V111: =IF(AND(N111>$V$9,N111<$V$10),M111,IF(N111=$V$10,M111,0)) -> 0 | W111: =IF(AND(N111>$W$9,N111<$W$10),M111,IF(N111=$W$10,M111,0)) -> 0 | X111: =IF(AND(N111>$X$9,N111<$X$10),M111,IF(N111=$X$10,M111,0)) -> 0 | Y111: =IF(AND(N111>$Y$9,N111<$Y$10),M111,IF(N111=$Y$10,M111,0)) -> 0 | Z111: =IF(AND(N111>$Z$9,N111<$Z$10),M111,IF(N111=$Z$10,M111,0)) -> 0 | AA111: =IF(AND(N111>$AA$9,N111<$AA$10),M111,IF(N111=$AA$10,M111,0)) -> 0 | AB111: =IF(AND(N111>$AB$9,N111<$AB$10),M111,IF(N111=$AB$10,M111,0)) -> 0 | AC111: =IF(AND(N111>$AC$9,N111<$AC$10),M111,IF(N111=$AC$10,M111,0)) -> 0 | AD111: =IF(AND(N111>$AD$9,N111<$AD$10),M111,IF(N111=$AD$10,M111,0)) -> 0 | AE111: =IF(AND(N111>$AE$9,N111<$AE$10),M111,IF(N111=$AE$10,M111,0)) -> 0 | AF111: =IF(AND(N111>$AF$9,N111<$AF$10),M111,IF(N111=$AF$10,M111,0)) -> 0 | AG111: =IF(N111=$AG$9,M111,0) -> 10174.02
A112: 10690001 | B112: Allowance For Loan Losses - General | C112: OL5904230000015 | D112: 100000014 | E112: PERDAMAN CHEMICALS & FERTILISERS (FINANCE)PTY LTD | F112: USD | G112: -775.06 | H112: -1107.55 | L112: =A112&"_"&F112&"_"&D112&"_"&E112 -> 10690001_USD_100000014_PERDAMAN CHEMICALS & FERTILISERS (FINANCE)PTY LTD | M112: =IF(COUNTIF($A$2:$A$8,A112)>0,-H112,H112) -> 1107.55 | N112: =IF(OR(L112=$L$2,L112=$L$3),$M$10+1,IFERROR(VLOOKUP(A112,'Repricing Maturity Adj.'!$A$3:$C$170,3,0),(IF(K112<$M$10,"Check",K112)))) -> Non_sensitive | O112: =M112=SUM(Q112:AG112) -> TRUE | P112: =IF(A112="","N/A",IF(COUNTIF($A$2:$A$7,A112)>0,"Liability",IF(COUNTIF($A$8,A112)>0,"Asset",IF(A112<20000000,"Asset",IF(AND(A112>20000000,A112<28800000),"Liability",IF(A112>28800000,"Equity","")))))) -> Liability | Q112: =IF(AND(N112>$Q$9,N112<$Q$10),M112,IF(N112=$Q$10,M112,0)) -> 0 | R112: =IF(AND(N112>$R$9,N112<$R$10),M112,IF(N112=$R$10,M112,0)) -> 0 | S112: =IF(AND(N112>$S$9,N112<$S$10),M112,IF(N112=$S$10,M112,0)) -> 0 | T112: =IF(AND(N112>$T$9,N112<$T$10),M112,IF(N112=$T$10,M112,0)) -> 0 | U112: =IF(AND(N112>$U$9,N112<$U$10),M112,IF(N112=$U$10,M112,0)) -> 0 | V112: =IF(AND(N112>$V$9,N112<$V$10),M112,IF(N112=$V$10,M112,0)) -> 0 | W112: =IF(AND(N112>$W$9,N112<$W$10),M112,IF(N112=$W$10,M112,0)) -> 0 | X112: =IF(AND(N112>$X$9,N112<$X$10),M112,IF(N112=$X$10,M112,0)) -> 0 | Y112: =IF(AND(N112>$Y$9,N112<$Y$10),M112,IF(N112=$Y$10,M112,0)) -> 0 | Z112: =IF(AND(N112>$Z$9,N112<$Z$10),M112,IF(N112=$Z$10,M112,0)) -> 0 | AA112: =IF(AND(N112>$AA$9,N112<$AA$10),M112,IF(N112=$AA$10,M112,0)) -> 0 | AB112: =IF(AND(N112>$AB$9,N112<$AB$10),M112,IF(N112=$AB$10,M112,0)) -> 0 | AC112: =IF(AND(N112>$AC$9,N112<$AC$10),M112,IF(N112=$AC$10,M112,0)) -> 0 | AD112: =IF(AND(N112>$AD$9,N112<$AD$10),M112,IF(N112=$AD$10,M112,0)) -> 0 | AE112: =IF(AND(N112>$AE$9,N112<$AE$10),M112,IF(N112=$AE$10,M112,0)) -> 0 | AF112: =IF(AND(N112>$AF$9,N112<$AF$10),M112,IF(N112=$AF$10,M112,0)) -> 0 | AG112: =IF(N112=$AG$9,M112,0) -> 1107.55
A113: 10690001 | B113: Allowance For Loan Losses - General | C113: OL5904230000017 | D113: 100000020 | E113: APA INFRASTRUCTURE LIMITED | F113: AUD | G113: -17200.8 | H113: -17200.8 | L113: =A113&"_"&F113&"_"&D113&"_"&E113 -> 10690001_AUD_100000020_APA INFRASTRUCTURE LIMITED | M113: =IF(COUNTIF($A$2:$A$8,A113)>0,-H113,H113) -> 17200.8 | N113: =IF(OR(L113=$L$2,L113=$L$3),$M$10+1,IFERROR(VLOOKUP(A113,'Repricing Maturity Adj.'!$A$3:$C$170,3,0),(IF(K113<$M$10,"Check",K113)))) -> Non_sensitive | O113: =M113=SUM(Q113:AG113) -> TRUE | P113: =IF(A113="","N/A",IF(COUNTIF($A$2:$A$7,A113)>0,"Liability",IF(COUNTIF($A$8,A113)>0,"Asset",IF(A113<20000000,"Asset",IF(AND(A113>20000000,A113<28800000),"Liability",IF(A113>28800000,"Equity","")))))) -> Liability | Q113: =IF(AND(N113>$Q$9,N113<$Q$10),M113,IF(N113=$Q$10,M113,0)) -> 0 | R113: =IF(AND(N113>$R$9,N113<$R$10),M113,IF(N113=$R$10,M113,0)) -> 0 | S113: =IF(AND(N113>$S$9,N113<$S$10),M113,IF(N113=$S$10,M113,0)) -> 0 | T113: =IF(AND(N113>$T$9,N113<$T$10),M113,IF(N113=$T$10,M113,0)) -> 0 | U113: =IF(AND(N113>$U$9,N113<$U$10),M113,IF(N113=$U$10,M113,0)) -> 0 | V113: =IF(AND(N113>$V$9,N113<$V$10),M113,IF(N113=$V$10,M113,0)) -> 0 | W113: =IF(AND(N113>$W$9,N113<$W$10),M113,IF(N113=$W$10,M113,0)) -> 0 | X113: =IF(AND(N113>$X$9,N113<$X$10),M113,IF(N113=$X$10,M113,0)) -> 0 | Y113: =IF(AND(N113>$Y$9,N113<$Y$10),M113,IF(N113=$Y$10,M113,0)) -> 0 | Z113: =IF(AND(N113>$Z$9,N113<$Z$10),M113,IF(N113=$Z$10,M113,0)) -> 0 | AA113: =IF(AND(N113>$AA$9,N113<$AA$10),M113,IF(N113=$AA$10,M113,0)) -> 0 | AB113: =IF(AND(N113>$AB$9,N113<$AB$10),M113,IF(N113=$AB$10,M113,0)) -> 0 | AC113: =IF(AND(N113>$AC$9,N113<$AC$10),M113,IF(N113=$AC$10,M113,0)) -> 0 | AD113: =IF(AND(N113>$AD$9,N113<$AD$10),M113,IF(N113=$AD$10,M113,0)) -> 0 | AE113: =IF(AND(N113>$AE$9,N113<$AE$10),M113,IF(N113=$AE$10,M113,0)) -> 0 | AF113: =IF(AND(N113>$AF$9,N113<$AF$10),M113,IF(N113=$AF$10,M113,0)) -> 0 | AG113: =IF(N113=$AG$9,M113,0) -> 17200.8
... A176: 10690007 | B176: Allowance for Call Loan | C176: OL5904260000002 | D176: 100000008 | E176: E.SUN COMMERCIAL BANK LTD | F176: AUD | G176: -2504.3 | H176: -2504.3 | L176: =A176&"_"&F176&"_"&D176&"_"&E176 -> 10690007_AUD_100000008_E.SUN COMMERCIAL BANK LTD | M176: =IF(COUNTIF($A$2:$A$8,A176)>0,-H176,H176) -> 2504.3 | N176: =IF(OR(L176=$L$2,L176=$L$3),$M$10+1,IFERROR(VLOOKUP(A176,'Repricing Maturity Adj.'!$A$3:$C$170,3,0),(IF(K176<$M$10,"Check",K176)))) -> Non_sensitive | O176: =M176=SUM(Q176:AG176) -> TRUE | P176: =IF(A176="","N/A",IF(COUNTIF($A$2:$A$7,A176)>0,"Liability",IF(COUNTIF($A$8,A176)>0,"Asset",IF(A176<20000000,"Asset",IF(AND(A176>20000000,A176<28800000),"Liability",IF(A176>28800000,"Equity","")))))) -> Liability | Q176: =IF(AND(N176>$Q$9,N176<$Q$10),M176,IF(N176=$Q$10,M176,0)) -> 0 | R176: =IF(AND(N176>$R$9,N176<$R$10),M176,IF(N176=$R$10,M176,0)) -> 0 | S176: =IF(AND(N176>$S$9,N176<$S$10),M176,IF(N176=$S$10,M176,0)) -> 0 | T176: =IF(AND(N176>$T$9,N176<$T$10),M176,IF(N176=$T$10,M176,0)) -> 0 | U176: =IF(AND(N176>$U$9,N176<$U$10),M176,IF(N176=$U$10,M176,0)) -> 0 | V176: =IF(AND(N176>$V$9,N176<$V$10),M176,IF(N176=$V$10,M176,0)) -> 0 | W176: =IF(AND(N176>$W$9,N176<$W$10),M176,IF(N176=$W$10,M176,0)) -> 0 | X176: =IF(AND(N176>$X$9,N176<$X$10),M176,IF(N176=$X$10,M176,0)) -> 0 | Y176: =IF(AND(N176>$Y$9,N176<$Y$10),M176,IF(N176=$Y$10,M176,0)) -> 0 | Z176: =IF(AND(N176>$Z$9,N176<$Z$10),M176,IF(N176=$Z$10,M176,0)) -> 0 | AA176: =IF(AND(N176>$AA$9,N176<$AA$10),M176,IF(N176=$AA$10,M176,0)) -> 0 | AB176: =IF(AND(N176>$AB$9,N176<$AB$10),M176,IF(N176=$AB$10,M176,0)) -> 0 | AC176: =IF(AND(N176>$AC$9,N176<$AC$10),M176,IF(N176=$AC$10,M176,0)) -> 0 | AD176: =IF(AND(N176>$AD$9,N176<$AD$10),M176,IF(N176=$AD$10,M176,0)) -> 0 | AE176: =IF(AND(N176>$AE$9,N176<$AE$10),M176,IF(N176=$AE$10,M176,0)) -> 0 | AF176: =IF(AND(N176>$AF$9,N176<$AF$10),M176,IF(N176=$AF$10,M176,0)) -> 0 | AG176: =IF(N176=$AG$9,M176,0) -> 2504.3
A177: 10910003 | B177: A.I.R ON OPERATION LOANS | C177: 6115904000018 | D177: 100000003 | E177: COSMAX NBT AUSTRALIA PTY LTD | F177: AUD | G177: 13126.44 | H177: 13126.44 | I177: 46046 | J177: 46136 | K177: 46136 | L177: =A177&"_"&F177&"_"&D177&"_"&E177 -> 10910003_AUD_100000003_COSMAX NBT AUSTRALIA PTY LTD | M177: =IF(COUNTIF($A$2:$A$8,A177)>0,-H177,H177) -> 13126.44 | N177: =IF(OR(L177=$L$2,L177=$L$3),$M$10+1,IFERROR(VLOOKUP(A177,'Repricing Maturity Adj.'!$A$3:$C$170,3,0),(IF(K177<$M$10,"Check",K177)))) -> Non_sensitive | O177: =M177=SUM(Q177:AG177) -> TRUE | P177: =IF(A177="","N/A",IF(COUNTIF($A$2:$A$7,A177)>0,"Liability",IF(COUNTIF($A$8,A177)>0,"Asset",IF(A177<20000000,"Asset",IF(AND(A177>20000000,A177<28800000),"Liability",IF(A177>28800000,"Equity","")))))) -> Asset | Q177: =IF(AND(N177>$Q$9,N177<$Q$10),M177,IF(N177=$Q$10,M177,0)) -> 0 | R177: =IF(AND(N177>$R$9,N177<$R$10),M177,IF(N177=$R$10,M177,0)) -> 0 | S177: =IF(AND(N177>$S$9,N177<$S$10),M177,IF(N177=$S$10,M177,0)) -> 0 | T177: =IF(AND(N177>$T$9,N177<$T$10),M177,IF(N177=$T$10,M177,0)) -> 0 | U177: =IF(AND(N177>$U$9,N177<$U$10),M177,IF(N177=$U$10,M177,0)) -> 0 | V177: =IF(AND(N177>$V$9,N177<$V$10),M177,IF(N177=$V$10,M177,0)) -> 0 | W177: =IF(AND(N177>$W$9,N177<$W$10),M177,IF(N177=$W$10,M177,0)) -> 0 | X177: =IF(AND(N177>$X$9,N177<$X$10),M177,IF(N177=$X$10,M177,0)) -> 0 | Y177: =IF(AND(N177>$Y$9,N177<$Y$10),M177,IF(N177=$Y$10,M177,0)) -> 0 | Z177: =IF(AND(N177>$Z$9,N177<$Z$10),M177,IF(N177=$Z$10,M177,0)) -> 0 | AA177: =IF(AND(N177>$AA$9,N177<$AA$10),M177,IF(N177=$AA$10,M177,0)) -> 0 | AB177: =IF(AND(N177>$AB$9,N177<$AB$10),M177,IF(N177=$AB$10,M177,0)) -> 0 | AC177: =IF(AND(N177>$AC$9,N177<$AC$10),M177,IF(N177=$AC$10,M177,0)) -> 0 | AD177: =IF(AND(N177>$AD$9,N177<$AD$10),M177,IF(N177=$AD$10,M177,0)) -> 0 | AE177: =IF(AND(N177>$AE$9,N177<$AE$10),M177,IF(N177=$AE$10,M177,0)) -> 0 | AF177: =IF(AND(N177>$AF$9,N177<$AF$10),M177,IF(N177=$AF$10,M177,0)) -> 0 | AG177: =IF(N177=$AG$9,M177,0) -> 13126.44
A178: 10910006 | B178: A.I.R ON SYNDICATED LOANS | C178: 6115904000025 | D178: 100000014 | E178: PERDAMAN CHEMICALS & FERTILISERS (FINANCE)PTY LTD | F178: USD | G178: 656.8 | H178: 938.55 | I178: 46058 | J178: 46086 | K178: 46086 | L178: =A178&"_"&F178&"_"&D178&"_"&E178 -> 10910006_USD_100000014_PERDAMAN CHEMICALS & FERTILISERS (FINANCE)PTY LTD | M178: =IF(COUNTIF($A$2:$A$8,A178)>0,-H178,H178) -> 938.55 | N178: =IF(OR(L178=$L$2,L178=$L$3),$M$10+1,IFERROR(VLOOKUP(A178,'Repricing Maturity Adj.'!$A$3:$C$170,3,0),(IF(K178<$M$10,"Check",K178)))) -> Non_sensitive | O178: =M178=SUM(Q178:AG178) -> TRUE | P178: =IF(A178="","N/A",IF(COUNTIF($A$2:$A$7,A178)>0,"Liability",IF(COUNTIF($A$8,A178)>0,"Asset",IF(A178<20000000,"Asset",IF(AND(A178>20000000,A178<28800000),"Liability",IF(A178>28800000,"Equity","")))))) -> Asset | Q178: =IF(AND(N178>$Q$9,N178<$Q$10),M178,IF(N178=$Q$10,M178,0)) -> 0 | R178: =IF(AND(N178>$R$9,N178<$R$10),M178,IF(N178=$R$10,M178,0)) -> 0 | S178: =IF(AND(N178>$S$9,N178<$S$10),M178,IF(N178=$S$10,M178,0)) -> 0 | T178: =IF(AND(N178>$T$9,N178<$T$10),M178,IF(N178=$T$10,M178,0)) -> 0 | U178: =IF(AND(N178>$U$9,N178<$U$10),M178,IF(N178=$U$10,M178,0)) -> 0 | V178: =IF(AND(N178>$V$9,N178<$V$10),M178,IF(N178=$V$10,M178,0)) -> 0 | W178: =IF(AND(N178>$W$9,N178<$W$10),M178,IF(N178=$W$10,M178,0)) -> 0 | X178: =IF(AND(N178>$X$9,N178<$X$10),M178,IF(N178=$X$10,M178,0)) -> 0 | Y178: =IF(AND(N178>$Y$9,N178<$Y$10),M178,IF(N178=$Y$10,M178,0)) -> 0 | Z178: =IF(AND(N178>$Z$9,N178<$Z$10),M178,IF(N178=$Z$10,M178,0)) -> 0 | AA178: =IF(AND(N178>$AA$9,N178<$AA$10),M178,IF(N178=$AA$10,M178,0)) -> 0 | AB178: =IF(AND(N178>$AB$9,N178<$AB$10),M178,IF(N178=$AB$10,M178,0)) -> 0 | AC178: =IF(AND(N178>$AC$9,N178<$AC$10),M178,IF(N178=$AC$10,M178,0)) -> 0 | AD178: =IF(AND(N178>$AD$9,N178<$AD$10),M178,IF(N178=$AD$10,M178,0)) -> 0 | AE178: =IF(AND(N178>$AE$9,N178<$AE$10),M178,IF(N178=$AE$10,M178,0)) -> 0 | AF178: =IF(AND(N178>$AF$9,N178<$AF$10),M178,IF(N178=$AF$10,M178,0)) -> 0 | AG178: =IF(N178=$AG$9,M178,0) -> 938.55
A179: 10910006 | B179: A.I.R ON SYNDICATED LOANS | C179: 6115904000032 | D179: 100000014 | E179: PERDAMAN CHEMICALS & FERTILISERS (FINANCE)PTY LTD | F179: USD | G179: 24.48 | H179: 34.98 | I179: 46058 | J179: 46086 | K179: 46086 | L179: =A179&"_"&F179&"_"&D179&"_"&E179 -> 10910006_USD_100000014_PERDAMAN CHEMICALS & FERTILISERS (FINANCE)PTY LTD | M179: =IF(COUNTIF($A$2:$A$8,A179)>0,-H179,H179) -> 34.98 | N179: =IF(OR(L179=$L$2,L179=$L$3),$M$10+1,IFERROR(VLOOKUP(A179,'Repricing Maturity Adj.'!$A$3:$C$170,3,0),(IF(K179<$M$10,"Check",K179)))) -> Non_sensitive | O179: =M179=SUM(Q179:AG179) -> TRUE | P179: =IF(A179="","N/A",IF(COUNTIF($A$2:$A$7,A179)>0,"Liability",IF(COUNTIF($A$8,A179)>0,"Asset",IF(A179<20000000,"Asset",IF(AND(A179>20000000,A179<28800000),"Liability",IF(A179>28800000,"Equity","")))))) -> Asset | Q179: =IF(AND(N179>$Q$9,N179<$Q$10),M179,IF(N179=$Q$10,M179,0)) -> 0 | R179: =IF(AND(N179>$R$9,N179<$R$10),M179,IF(N179=$R$10,M179,0)) -> 0 | S179: =IF(AND(N179>$S$9,N179<$S$10),M179,IF(N179=$S$10,M179,0)) -> 0 | T179: =IF(AND(N179>$T$9,N179<$T$10),M179,IF(N179=$T$10,M179,0)) -> 0 | U179: =IF(AND(N179>$U$9,N179<$U$10),M179,IF(N179=$U$10,M179,0)) -> 0 | V179: =IF(AND(N179>$V$9,N179<$V$10),M179,IF(N179=$V$10,M179,0)) -> 0 | W179: =IF(AND(N179>$W$9,N179<$W$10),M179,IF(N179=$W$10,M179,0)) -> 0 | X179: =IF(AND(N179>$X$9,N179<$X$10),M179,IF(N179=$X$10,M179,0)) -> 0 | Y179: =IF(AND(N179>$Y$9,N179<$Y$10),M179,IF(N179=$Y$10,M179,0)) -> 0 | Z179: =IF(AND(N179>$Z$9,N179<$Z$10),M179,IF(N179=$Z$10,M179,0)) -> 0 | AA179: =IF(AND(N179>$AA$9,N179<$AA$10),M179,IF(N179=$AA$10,M179,0)) -> 0 | AB179: =IF(AND(N179>$AB$9,N179<$AB$10),M179,IF(N179=$AB$10,M179,0)) -> 0 | AC179: =IF(AND(N179>$AC$9,N179<$AC$10),M179,IF(N179=$AC$10,M179,0)) -> 0 | AD179: =IF(AND(N179>$AD$9,N179<$AD$10),M179,IF(N179=$AD$10,M179,0)) -> 0 | AE179: =IF(AND(N179>$AE$9,N179<$AE$10),M179,IF(N179=$AE$10,M179,0)) -> 0 | AF179: =IF(AND(N179>$AF$9,N179<$AF$10),M179,IF(N179=$AF$10,M179,0)) -> 0 | AG179: =IF(N179=$AG$9,M179,0) -> 34.98
A180: 10910006 | B180: A.I.R ON SYNDICATED LOANS | C180: 6115904000040 | D180: 100000014 | E180: PERDAMAN CHEMICALS & FERTILISERS (FINANCE)PTY LTD | F180: USD | G180: 337.46 | H180: 482.22 | I180: 46058 | J180: 46086 | K180: 46086 | L180: =A180&"_"&F180&"_"&D180&"_"&E180 -> 10910006_USD_100000014_PERDAMAN CHEMICALS & FERTILISERS (FINANCE)PTY LTD | M180: =IF(COUNTIF($A$2:$A$8,A180)>0,-H180,H180) -> 482.22 | N180: =IF(OR(L180=$L$2,L180=$L$3),$M$10+1,IFERROR(VLOOKUP(A180,'Repricing Maturity Adj.'!$A$3:$C$170,3,0),(IF(K180<$M$10,"Check",K180)))) -> Non_sensitive | O180: =M180=SUM(Q180:AG180) -> TRUE | P180: =IF(A180="","N/A",IF(COUNTIF($A$2:$A$7,A180)>0,"Liability",IF(COUNTIF($A$8,A180)>0,"Asset",IF(A180<20000000,"Asset",IF(AND(A180>20000000,A180<28800000),"Liability",IF(A180>28800000,"Equity","")))))) -> Asset | Q180: =IF(AND(N180>$Q$9,N180<$Q$10),M180,IF(N180=$Q$10,M180,0)) -> 0 | R180: =IF(AND(N180>$R$9,N180<$R$10),M180,IF(N180=$R$10,M180,0)) -> 0 | S180: =IF(AND(N180>$S$9,N180<$S$10),M180,IF(N180=$S$10,M180,0)) -> 0 | T180: =IF(AND(N180>$T$9,N180<$T$10),M180,IF(N180=$T$10,M180,0)) -> 0 | U180: =IF(AND(N180>$U$9,N180<$U$10),M180,IF(N180=$U$10,M180,0)) -> 0 | V180: =IF(AND(N180>$V$9,N180<$V$10),M180,IF(N180=$V$10,M180,0)) -> 0 | W180: =IF(AND(N180>$W$9,N180<$W$10),M180,IF(N180=$W$10,M180,0)) -> 0 | X180: =IF(AND(N180>$X$9,N180<$X$10),M180,IF(N180=$X$10,M180,0)) -> 0 | Y180: =IF(AND(N180>$Y$9,N180<$Y$10),M180,IF(N180=$Y$10,M180,0)) -> 0 | Z180: =IF(AND(N180>$Z$9,N180<$Z$10),M180,IF(N180=$Z$10,M180,0)) -> 0 | AA180: =IF(AND(N180>$AA$9,N180<$AA$10),M180,IF(N180=$AA$10,M180,0)) -> 0 | AB180: =IF(AND(N180>$AB$9,N180<$AB$10),M180,IF(N180=$AB$10,M180,0)) -> 0 | AC180: =IF(AND(N180>$AC$9,N180<$AC$10),M180,IF(N180=$AC$10,M180,0)) -> 0 | AD180: =IF(AND(N180>$AD$9,N180<$AD$10),M180,IF(N180=$AD$10,M180,0)) -> 0 | AE180: =IF(AND(N180>$AE$9,N180<$AE$10),M180,IF(N180=$AE$10,M180,0)) -> 0 | AF180: =IF(AND(N180>$AF$9,N180<$AF$10),M180,IF(N180=$AF$10,M180,0)) -> 0 | AG180: =IF(N180=$AG$9,M180,0) -> 482.22
A181: 10910006 | B181: A.I.R ON SYNDICATED LOANS | C181: 6115904000057 | D181: 100000014 | E181: PERDAMAN CHEMICALS & FERTILISERS (FINANCE)PTY LTD | F181: USD | G181: 18.6 | H181: 26.58 | I181: 46058 | J181: 46086 | K181: 46086 | L181: =A181&"_"&F181&"_"&D181&"_"&E181 -> 10910006_USD_100000014_PERDAMAN CHEMICALS & FERTILISERS (FINANCE)PTY LTD | M181: =IF(COUNTIF($A$2:$A$8,A181)>0,-H181,H181) -> 26.58 | N181: =IF(OR(L181=$L$2,L181=$L$3),$M$10+1,IFERROR(VLOOKUP(A181,'Repricing Maturity Adj.'!$A$3:$C$170,3,0),(IF(K181<$M$10,"Check",K181)))) -> Non_sensitive | O181: =M181=SUM(Q181:AG181) -> TRUE | P181: =IF(A181="","N/A",IF(COUNTIF($A$2:$A$7,A181)>0,"Liability",IF(COUNTIF($A$8,A181)>0,"Asset",IF(A181<20000000,"Asset",IF(AND(A181>20000000,A181<28800000),"Liability",IF(A181>28800000,"Equity","")))))) -> Asset | Q181: =IF(AND(N181>$Q$9,N181<$Q$10),M181,IF(N181=$Q$10,M181,0)) -> 0 | R181: =IF(AND(N181>$R$9,N181<$R$10),M181,IF(N181=$R$10,M181,0)) -> 0 | S181: =IF(AND(N181>$S$9,N181<$S$10),M181,IF(N181=$S$10,M181,0)) -> 0 | T181: =IF(AND(N181>$T$9,N181<$T$10),M181,IF(N181=$T$10,M181,0)) -> 0 | U181: =IF(AND(N181>$U$9,N181<$U$10),M181,IF(N181=$U$10,M181,0)) -> 0 | V181: =IF(AND(N181>$V$9,N181<$V$10),M181,IF(N181=$V$10,M181,0)) -> 0 | W181: =IF(AND(N181>$W$9,N181<$W$10),M181,IF(N181=$W$10,M181,0)) -> 0 | X181: =IF(AND(N181>$X$9,N181<$X$10),M181,IF(N181=$X$10,M181,0)) -> 0 | Y181: =IF(AND(N181>$Y$9,N181<$Y$10),M181,IF(N181=$Y$10,M181,0)) -> 0 | Z181: =IF(AND(N181>$Z$9,N181<$Z$10),M181,IF(N181=$Z$10,M181,0)) -> 0 | AA181: =IF(AND(N181>$AA$9,N181<$AA$10),M181,IF(N181=$AA$10,M181,0)) -> 0 | AB181: =IF(AND(N181>$AB$9,N181<$AB$10),M181,IF(N181=$AB$10,M181,0)) -> 0 | AC181: =IF(AND(N181>$AC$9,N181<$AC$10),M181,IF(N181=$AC$10,M181,0)) -> 0 | AD181: =IF(AND(N181>$AD$9,N181<$AD$10),M181,IF(N181=$AD$10,M181,0)) -> 0 | AE181: =IF(AND(N181>$AE$9,N181<$AE$10),M181,IF(N181=$AE$10,M181,0)) -> 0 | AF181: =IF(AND(N181>$AF$9,N181<$AF$10),M181,IF(N181=$AF$10,M181,0)) -> 0 | AG181: =IF(N181=$AG$9,M181,0) -> 26.58
A182: 10910006 | B182: A.I.R ON SYNDICATED LOANS | C182: 6115904000064 | D182: 100000014 | E182: PERDAMAN CHEMICALS & FERTILISERS (FINANCE)PTY LTD | F182: USD | G182: 88.47 | H182: 126.42 | I182: 46058 | J182: 46086 | K182: 46086 | L182: =A182&"_"&F182&"_"&D182&"_"&E182 -> 10910006_USD_100000014_PERDAMAN CHEMICALS & FERTILISERS (FINANCE)PTY LTD | M182: =IF(COUNTIF($A$2:$A$8,A182)>0,-H182,H182) -> 126.42 | N182: =IF(OR(L182=$L$2,L182=$L$3),$M$10+1,IFERROR(VLOOKUP(A182,'Repricing Maturity Adj.'!$A$3:$C$170,3,0),(IF(K182<$M$10,"Check",K182)))) -> Non_sensitive | O182: =M182=SUM(Q182:AG182) -> TRUE | P182: =IF(A182="","N/A",IF(COUNTIF($A$2:$A$7,A182)>0,"Liability",IF(COUNTIF($A$8,A182)>0,"Asset",IF(A182<20000000,"Asset",IF(AND(A182>20000000,A182<28800000),"Liability",IF(A182>28800000,"Equity","")))))) -> Asset | Q182: =IF(AND(N182>$Q$9,N182<$Q$10),M182,IF(N182=$Q$10,M182,0)) -> 0 | R182: =IF(AND(N182>$R$9,N182<$R$10),M182,IF(N182=$R$10,M182,0)) -> 0 | S182: =IF(AND(N182>$S$9,N182<$S$10),M182,IF(N182=$S$10,M182,0)) -> 0 | T182: =IF(AND(N182>$T$9,N182<$T$10),M182,IF(N182=$T$10,M182,0)) -> 0 | U182: =IF(AND(N182>$U$9,N182<$U$10),M182,IF(N182=$U$10,M182,0)) -> 0 | V182: =IF(AND(N182>$V$9,N182<$V$10),M182,IF(N182=$V$10,M182,0)) -> 0 | W182: =IF(AND(N182>$W$9,N182<$W$10),M182,IF(N182=$W$10,M182,0)) -> 0 | X182: =IF(AND(N182>$X$9,N182<$X$10),M182,IF(N182=$X$10,M182,0)) -> 0 | Y182: =IF(AND(N182>$Y$9,N182<$Y$10),M182,IF(N182=$Y$10,M182,0)) -> 0 | Z182: =IF(AND(N182>$Z$9,N182<$Z$10),M182,IF(N182=$Z$10,M182,0)) -> 0 | AA182: =IF(AND(N182>$AA$9,N182<$AA$10),M182,IF(N182=$AA$10,M182,0)) -> 0 | AB182: =IF(AND(N182>$AB$9,N182<$AB$10),M182,IF(N182=$AB$10,M182,0)) -> 0 | AC182: =IF(AND(N182>$AC$9,N182<$AC$10),M182,IF(N182=$AC$10,M182,0)) -> 0 | AD182: =IF(AND(N182>$AD$9,N182<$AD$10),M182,IF(N182=$AD$10,M182,0)) -> 0 | AE182: =IF(AND(N182>$AE$9,N182<$AE$10),M182,IF(N182=$AE$10,M182,0)) -> 0 | AF182: =IF(AND(N182>$AF$9,N182<$AF$10),M182,IF(N182=$AF$10,M182,0)) -> 0 | AG182: =IF(N182=$AG$9,M182,0) -> 126.42
A183: 10910006 | B183: A.I.R ON SYNDICATED LOANS | C183: 6115904000071 | D183: 100000014 | E183: PERDAMAN CHEMICALS & FERTILISERS (FINANCE)PTY LTD | F183: USD | G183: 21 | H183: 30.01 | I183: 46058 | J183: 46086 | K183: 46086 | L183: =A183&"_"&F183&"_"&D183&"_"&E183 -> 10910006_USD_100000014_PERDAMAN CHEMICALS & FERTILISERS (FINANCE)PTY LTD | M183: =IF(COUNTIF($A$2:$A$8,A183)>0,-H183,H183) -> 30.01 | N183: =IF(OR(L183=$L$2,L183=$L$3),$M$10+1,IFERROR(VLOOKUP(A183,'Repricing Maturity Adj.'!$A$3:$C$170,3,0),(IF(K183<$M$10,"Check",K183)))) -> Non_sensitive | O183: =M183=SUM(Q183:AG183) -> TRUE | P183: =IF(A183="","N/A",IF(COUNTIF($A$2:$A$7,A183)>0,"Liability",IF(COUNTIF($A$8,A183)>0,"Asset",IF(A183<20000000,"Asset",IF(AND(A183>20000000,A183<28800000),"Liability",IF(A183>28800000,"Equity","")))))) -> Asset | Q183: =IF(AND(N183>$Q$9,N183<$Q$10),M183,IF(N183=$Q$10,M183,0)) -> 0 | R183: =IF(AND(N183>$R$9,N183<$R$10),M183,IF(N183=$R$10,M183,0)) -> 0 | S183: =IF(AND(N183>$S$9,N183<$S$10),M183,IF(N183=$S$10,M183,0)) -> 0 | T183: =IF(AND(N183>$T$9,N183<$T$10),M183,IF(N183=$T$10,M183,0)) -> 0 | U183: =IF(AND(N183>$U$9,N183<$U$10),M183,IF(N183=$U$10,M183,0)) -> 0 | V183: =IF(AND(N183>$V$9,N183<$V$10),M183,IF(N183=$V$10,M183,0)) -> 0 | W183: =IF(AND(N183>$W$9,N183<$W$10),M183,IF(N183=$W$10,M183,0)) -> 0 | X183: =IF(AND(N183>$X$9,N183<$X$10),M183,IF(N183=$X$10,M183,0)) -> 0 | Y183: =IF(AND(N183>$Y$9,N183<$Y$10),M183,IF(N183=$Y$10,M183,0)) -> 0 | Z183: =IF(AND(N183>$Z$9,N183<$Z$10),M183,IF(N183=$Z$10,M183,0)) -> 0 | AA183: =IF(AND(N183>$AA$9,N183<$AA$10),M183,IF(N183=$AA$10,M183,0)) -> 0 | AB183: =IF(AND(N183>$AB$9,N183<$AB$10),M183,IF(N183=$AB$10,M183,0)) -> 0 | AC183: =IF(AND(N183>$AC$9,N183<$AC$10),M183,IF(N183=$AC$10,M183,0)) -> 0 | AD183: =IF(AND(N183>$AD$9,N183<$AD$10),M183,IF(N183=$AD$10,M183,0)) -> 0 | AE183: =IF(AND(N183>$AE$9,N183<$AE$10),M183,IF(N183=$AE$10,M183,0)) -> 0 | AF183: =IF(AND(N183>$AF$9,N183<$AF$10),M183,IF(N183=$AF$10,M183,0)) -> 0 | AG183: =IF(N183=$AG$9,M183,0) -> 30.01
A184: 10910006 | B184: A.I.R ON SYNDICATED LOANS | C184: 6115904000089 | D184: 100000014 | E184: PERDAMAN CHEMICALS & FERTILISERS (FINANCE)PTY LTD | F184: USD | G184: 303.5 | H184: 433.7 | I184: 46058 | J184: 46086 | K184: 46086 | L184: =A184&"_"&F184&"_"&D184&"_"&E184 -> 10910006_USD_100000014_PERDAMAN CHEMICALS & FERTILISERS (FINANCE)PTY LTD | M184: =IF(COUNTIF($A$2:$A$8,A184)>0,-H184,H184) -> 433.7 | N184: =IF(OR(L184=$L$2,L184=$L$3),$M$10+1,IFERROR(VLOOKUP(A184,'Repricing Maturity Adj.'!$A$3:$C$170,3,0),(IF(K184<$M$10,"Check",K184)))) -> Non_sensitive | O184: =M184=SUM(Q184:AG184) -> TRUE | P184: =IF(A184="","N/A",IF(COUNTIF($A$2:$A$7,A184)>0,"Liability",IF(COUNTIF($A$8,A184)>0,"Asset",IF(A184<20000000,"Asset",IF(AND(A184>20000000,A184<28800000),"Liability",IF(A184>28800000,"Equity","")))))) -> Asset | Q184: =IF(AND(N184>$Q$9,N184<$Q$10),M184,IF(N184=$Q$10,M184,0)) -> 0 | R184: =IF(AND(N184>$R$9,N184<$R$10),M184,IF(N184=$R$10,M184,0)) -> 0 | S184: =IF(AND(N184>$S$9,N184<$S$10),M184,IF(N184=$S$10,M184,0)) -> 0 | T184: =IF(AND(N184>$T$9,N184<$T$10),M184,IF(N184=$T$10,M184,0)) -> 0 | U184: =IF(AND(N184>$U$9,N184<$U$10),M184,IF(N184=$U$10,M184,0)) -> 0 | V184: =IF(AND(N184>$V$9,N184<$V$10),M184,IF(N184=$V$10,M184,0)) -> 0 | W184: =IF(AND(N184>$W$9,N184<$W$10),M184,IF(N184=$W$10,M184,0)) -> 0 | X184: =IF(AND(N184>$X$9,N184<$X$10),M184,IF(N184=$X$10,M184,0)) -> 0 | Y184: =IF(AND(N184>$Y$9,N184<$Y$10),M184,IF(N184=$Y$10,M184,0)) -> 0 | Z184: =IF(AND(N184>$Z$9,N184<$Z$10),M184,IF(N184=$Z$10,M184,0)) -> 0 | AA184: =IF(AND(N184>$AA$9,N184<$AA$10),M184,IF(N184=$AA$10,M184,0)) -> 0 | AB184: =IF(AND(N184>$AB$9,N184<$AB$10),M184,IF(N184=$AB$10,M184,0)) -> 0 | AC184: =IF(AND(N184>$AC$9,N184<$AC$10),M184,IF(N184=$AC$10,M184,0)) -> 0 | AD184: =IF(AND(N184>$AD$9,N184<$AD$10),M184,IF(N184=$AD$10,M184,0)) -> 0 | AE184: =IF(AND(N184>$AE$9,N184<$AE$10),M184,IF(N184=$AE$10,M184,0)) -> 0 | AF184: =IF(AND(N184>$AF$9,N184<$AF$10),M184,IF(N184=$AF$10,M184,0)) -> 0 | AG184: =IF(N184=$AG$9,M184,0) -> 433.7
A185: 10910006 | B185: A.I.R ON SYNDICATED LOANS | C185: 6115904000096 | D185: 100000014 | E185: PERDAMAN CHEMICALS & FERTILISERS (FINANCE)PTY LTD | F185: USD | G185: 19.55 | H185: 27.94 | I185: 46058 | J185: 46086 | K185: 46086 | L185: =A185&"_"&F185&"_"&D185&"_"&E185 -> 10910006_USD_100000014_PERDAMAN CHEMICALS & FERTILISERS (FINANCE)PTY LTD | M185: =IF(COUNTIF($A$2:$A$8,A185)>0,-H185,H185) -> 27.94 | N185: =IF(OR(L185=$L$2,L185=$L$3),$M$10+1,IFERROR(VLOOKUP(A185,'Repricing Maturity Adj.'!$A$3:$C$170,3,0),(IF(K185<$M$10,"Check",K185)))) -> Non_sensitive | O185: =M185=SUM(Q185:AG185) -> TRUE | P185: =IF(A185="","N/A",IF(COUNTIF($A$2:$A$7,A185)>0,"Liability",IF(COUNTIF($A$8,A185)>0,"Asset",IF(A185<20000000,"Asset",IF(AND(A185>20000000,A185<28800000),"Liability",IF(A185>28800000,"Equity","")))))) -> Asset | Q185: =IF(AND(N185>$Q$9,N185<$Q$10),M185,IF(N185=$Q$10,M185,0)) -> 0 | R185: =IF(AND(N185>$R$9,N185<$R$10),M185,IF(N185=$R$10,M185,0)) -> 0 | S185: =IF(AND(N185>$S$9,N185<$S$10),M185,IF(N185=$S$10,M185,0)) -> 0 | T185: =IF(AND(N185>$T$9,N185<$T$10),M185,IF(N185=$T$10,M185,0)) -> 0 | U185: =IF(AND(N185>$U$9,N185<$U$10),M185,IF(N185=$U$10,M185,0)) -> 0 | V185: =IF(AND(N185>$V$9,N185<$V$10),M185,IF(N185=$V$10,M185,0)) -> 0 | W185: =IF(AND(N185>$W$9,N185<$W$10),M185,IF(N185=$W$10,M185,0)) -> 0 | X185: =IF(AND(N185>$X$9,N185<$X$10),M185,IF(N185=$X$10,M185,0)) -> 0 | Y185: =IF(AND(N185>$Y$9,N185<$Y$10),M185,IF(N185=$Y$10,M185,0)) -> 0 | Z185: =IF(AND(N185>$Z$9,N185<$Z$10),M185,IF(N185=$Z$10,M185,0)) -> 0 | AA185: =IF(AND(N185>$AA$9,N185<$AA$10),M185,IF(N185=$AA$10,M185,0)) -> 0 | AB185: =IF(AND(N185>$AB$9,N185<$AB$10),M185,IF(N185=$AB$10,M185,0)) -> 0 | AC185: =IF(AND(N185>$AC$9,N185<$AC$10),M185,IF(N185=$AC$10,M185,0)) -> 0 | AD185: =IF(AND(N185>$AD$9,N185<$AD$10),M185,IF(N185=$AD$10,M185,0)) -> 0 | AE185: =IF(AND(N185>$AE$9,N185<$AE$10),M185,IF(N185=$AE$10,M185,0)) -> 0 | AF185: =IF(AND(N185>$AF$9,N185<$AF$10),M185,IF(N185=$AF$10,M185,0)) -> 0 | AG185: =IF(N185=$AG$9,M185,0) -> 27.94
A186: 10910006 | B186: A.I.R ON SYNDICATED LOANS | C186: 6115904000107 | D186: 100000014 | E186: PERDAMAN CHEMICALS & FERTILISERS (FINANCE)PTY LTD | F186: USD | G186: 22.76 | H186: 32.52 | I186: 46058 | J186: 46086 | K186: 46086 | L186: =A186&"_"&F186&"_"&D186&"_"&E186 -> 10910006_USD_100000014_PERDAMAN CHEMICALS & FERTILISERS (FINANCE)PTY LTD | M186: =IF(COUNTIF($A$2:$A$8,A186)>0,-H186,H186) -> 32.52 | N186: =IF(OR(L186=$L$2,L186=$L$3),$M$10+1,IFERROR(VLOOKUP(A186,'Repricing Maturity Adj.'!$A$3:$C$170,3,0),(IF(K186<$M$10,"Check",K186)))) -> Non_sensitive | O186: =M186=SUM(Q186:AG186) -> TRUE | P186: =IF(A186="","N/A",IF(COUNTIF($A$2:$A$7,A186)>0,"Liability",IF(COUNTIF($A$8,A186)>0,"Asset",IF(A186<20000000,"Asset",IF(AND(A186>20000000,A186<28800000),"Liability",IF(A186>28800000,"Equity","")))))) -> Asset | Q186: =IF(AND(N186>$Q$9,N186<$Q$10),M186,IF(N186=$Q$10,M186,0)) -> 0 | R186: =IF(AND(N186>$R$9,N186<$R$10),M186,IF(N186=$R$10,M186,0)) -> 0 | S186: =IF(AND(N186>$S$9,N186<$S$10),M186,IF(N186=$S$10,M186,0)) -> 0 | T186: =IF(AND(N186>$T$9,N186<$T$10),M186,IF(N186=$T$10,M186,0)) -> 0 | U186: =IF(AND(N186>$U$9,N186<$U$10),M186,IF(N186=$U$10,M186,0)) -> 0 | V186: =IF(AND(N186>$V$9,N186<$V$10),M186,IF(N186=$V$10,M186,0)) -> 0 | W186: =IF(AND(N186>$W$9,N186<$W$10),M186,IF(N186=$W$10,M186,0)) -> 0 | X186: =IF(AND(N186>$X$9,N186<$X$10),M186,IF(N186=$X$10,M186,0)) -> 0 | Y186: =IF(AND(N186>$Y$9,N186<$Y$10),M186,IF(N186=$Y$10,M186,0)) -> 0 | Z186: =IF(AND(N186>$Z$9,N186<$Z$10),M186,IF(N186=$Z$10,M186,0)) -> 0 | AA186: =IF(AND(N186>$AA$9,N186<$AA$10),M186,IF(N186=$AA$10,M186,0)) -> 0 | AB186: =IF(AND(N186>$AB$9,N186<$AB$10),M186,IF(N186=$AB$10,M186,0)) -> 0 | AC186: =IF(AND(N186>$AC$9,N186<$AC$10),M186,IF(N186=$AC$10,M186,0)) -> 0 | AD186: =IF(AND(N186>$AD$9,N186<$AD$10),M186,IF(N186=$AD$10,M186,0)) -> 0 | AE186: =IF(AND(N186>$AE$9,N186<$AE$10),M186,IF(N186=$AE$10,M186,0)) -> 0 | AF186: =IF(AND(N186>$AF$9,N186<$AF$10),M186,IF(N186=$AF$10,M186,0)) -> 0 | AG186: =IF(N186=$AG$9,M186,0) -> 32.52
A187: 10910006 | B187: A.I.R ON SYNDICATED LOANS | C187: 6115904000114 | D187: 100000014 | E187: PERDAMAN CHEMICALS & FERTILISERS (FINANCE)PTY LTD | F187: USD | G187: 209.07 | H187: 298.76 | I187: 46058 | J187: 46086 | K187: 46086 | L187: =A187&"_"&F187&"_"&D187&"_"&E187 -> 10910006_USD_100000014_PERDAMAN CHEMICALS & FERTILISERS (FINANCE)PTY LTD | M187: =IF(COUNTIF($A$2:$A$8,A187)>0,-H187,H187) -> 298.76 | N187: =IF(OR(L187=$L$2,L187=$L$3),$M$10+1,IFERROR(VLOOKUP(A187,'Repricing Maturity Adj.'!$A$3:$C$170,3,0),(IF(K187<$M$10,"Check",K187)))) -> Non_sensitive | O187: =M187=SUM(Q187:AG187) -> TRUE | P187: =IF(A187="","N/A",IF(COUNTIF($A$2:$A$7,A187)>0,"Liability",IF(COUNTIF($A$8,A187)>0,"Asset",IF(A187<20000000,"Asset",IF(AND(A187>20000000,A187<28800000),"Liability",IF(A187>28800000,"Equity","")))))) -> Asset | Q187: =IF(AND(N187>$Q$9,N187<$Q$10),M187,IF(N187=$Q$10,M187,0)) -> 0 | R187: =IF(AND(N187>$R$9,N187<$R$10),M187,IF(N187=$R$10,M187,0)) -> 0 | S187: =IF(AND(N187>$S$9,N187<$S$10),M187,IF(N187=$S$10,M187,0)) -> 0 | T187: =IF(AND(N187>$T$9,N187<$T$10),M187,IF(N187=$T$10,M187,0)) -> 0 | U187: =IF(AND(N187>$U$9,N187<$U$10),M187,IF(N187=$U$10,M187,0)) -> 0 | V187: =IF(AND(N187>$V$9,N187<$V$10),M187,IF(N187=$V$10,M187,0)) -> 0 | W187: =IF(AND(N187>$W$9,N187<$W$10),M187,IF(N187=$W$10,M187,0)) -> 0 | X187: =IF(AND(N187>$X$9,N187<$X$10),M187,IF(N187=$X$10,M187,0)) -> 0 | Y187: =IF(AND(N187>$Y$9,N187<$Y$10),M187,IF(N187=$Y$10,M187,0)) -> 0 | Z187: =IF(AND(N187>$Z$9,N187<$Z$10),M187,IF(N187=$Z$10,M187,0)) -> 0 | AA187: =IF(AND(N187>$AA$9,N187<$AA$10),M187,IF(N187=$AA$10,M187,0)) -> 0 | AB187: =IF(AND(N187>$AB$9,N187<$AB$10),M187,IF(N187=$AB$10,M187,0)) -> 0 | AC187: =IF(AND(N187>$AC$9,N187<$AC$10),M187,IF(N187=$AC$10,M187,0)) -> 0 | AD187: =IF(AND(N187>$AD$9,N187<$AD$10),M187,IF(N187=$AD$10,M187,0)) -> 0 | AE187: =IF(AND(N187>$AE$9,N187<$AE$10),M187,IF(N187=$AE$10,M187,0)) -> 0 | AF187: =IF(AND(N187>$AF$9,N187<$AF$10),M187,IF(N187=$AF$10,M187,0)) -> 0 | AG187: =IF(N187=$AG$9,M187,0) -> 298.76
A188: 10910006 | B188: A.I.R ON SYNDICATED LOANS | C188: 6115904000139 | D188: 100000020 | E188: APA INFRASTRUCTURE LIMITED | F188: AUD | G188: 113160.77 | H188: 113160.77 | I188: 45971 | J188: 46153 | K188: 46153 | L188: =A188&"_"&F188&"_"&D188&"_"&E188 -> 10910006_AUD_100000020_APA INFRASTRUCTURE LIMITED | M188: =IF(COUNTIF($A$2:$A$8,A188)>0,-H188,H188) -> 113160.77 | N188: =IF(OR(L188=$L$2,L188=$L$3),$M$10+1,IFERROR(VLOOKUP(A188,'Repricing Maturity Adj.'!$A$3:$C$170,3,0),(IF(K188<$M$10,"Check",K188)))) -> Non_sensitive | O188: =M188=SUM(Q188:AG188) -> TRUE | P188: =IF(A188="","N/A",IF(COUNTIF($A$2:$A$7,A188)>0,"Liability",IF(COUNTIF($A$8,A188)>0,"Asset",IF(A188<20000000,"Asset",IF(AND(A188>20000000,A188<28800000),"Liability",IF(A188>28800000,"Equity","")))))) -> Asset | Q188: =IF(AND(N188>$Q$9,N188<$Q$10),M188,IF(N188=$Q$10,M188,0)) -> 0 | R188: =IF(AND(N188>$R$9,N188<$R$10),M188,IF(N188=$R$10,M188,0)) -> 0 | S188: =IF(AND(N188>$S$9,N188<$S$10),M188,IF(N188=$S$10,M188,0)) -> 0 | T188: =IF(AND(N188>$T$9,N188<$T$10),M188,IF(N188=$T$10,M188,0)) -> 0 | U188: =IF(AND(N188>$U$9,N188<$U$10),M188,IF(N188=$U$10,M188,0)) -> 0 | V188: =IF(AND(N188>$V$9,N188<$V$10),M188,IF(N188=$V$10,M188,0)) -> 0 | W188: =IF(AND(N188>$W$9,N188<$W$10),M188,IF(N188=$W$10,M188,0)) -> 0 | X188: =IF(AND(N188>$X$9,N188<$X$10),M188,IF(N188=$X$10,M188,0)) -> 0 | Y188: =IF(AND(N188>$Y$9,N188<$Y$10),M188,IF(N188=$Y$10,M188,0)) -> 0 | Z188: =IF(AND(N188>$Z$9,N188<$Z$10),M188,IF(N188=$Z$10,M188,0)) -> 0 | AA188: =IF(AND(N188>$AA$9,N188<$AA$10),M188,IF(N188=$AA$10,M188,0)) -> 0 | AB188: =IF(AND(N188>$AB$9,N188<$AB$10),M188,IF(N188=$AB$10,M188,0)) -> 0 | AC188: =IF(AND(N188>$AC$9,N188<$AC$10),M188,IF(N188=$AC$10,M188,0)) -> 0 | AD188: =IF(AND(N188>$AD$9,N188<$AD$10),M188,IF(N188=$AD$10,M188,0)) -> 0 | AE188: =IF(AND(N188>$AE$9,N188<$AE$10),M188,IF(N188=$AE$10,M188,0)) -> 0 | AF188: =IF(AND(N188>$AF$9,N188<$AF$10),M188,IF(N188=$AF$10,M188,0)) -> 0 | AG188: =IF(N188=$AG$9,M188,0) -> 113160.77
... A258: 10910021 | B258: A.I.R ON CALL LOAN | C258: FM5904260000004 | D258: 100000008 | E258: E.SUN COMMERCIAL BANK LTD | F258: AUD | G258: 11151.78 | H258: 11151.78 | I258: 46035 | J258: 46125 | K258: 46125 | L258: =A258&"_"&F258&"_"&D258&"_"&E258 -> 10910021_AUD_100000008_E.SUN COMMERCIAL BANK LTD | M258: =IF(COUNTIF($A$2:$A$8,A258)>0,-H258,H258) -> 11151.78 | N258: =IF(OR(L258=$L$2,L258=$L$3),$M$10+1,IFERROR(VLOOKUP(A258,'Repricing Maturity Adj.'!$A$3:$C$170,3,0),(IF(K258<$M$10,"Check",K258)))) -> Non_sensitive | O258: =M258=SUM(Q258:AG258) -> TRUE | P258: =IF(A258="","N/A",IF(COUNTIF($A$2:$A$7,A258)>0,"Liability",IF(COUNTIF($A$8,A258)>0,"Asset",IF(A258<20000000,"Asset",IF(AND(A258>20000000,A258<28800000),"Liability",IF(A258>28800000,"Equity","")))))) -> Asset | Q258: =IF(AND(N258>$Q$9,N258<$Q$10),M258,IF(N258=$Q$10,M258,0)) -> 0 | R258: =IF(AND(N258>$R$9,N258<$R$10),M258,IF(N258=$R$10,M258,0)) -> 0 | S258: =IF(AND(N258>$S$9,N258<$S$10),M258,IF(N258=$S$10,M258,0)) -> 0 | T258: =IF(AND(N258>$T$9,N258<$T$10),M258,IF(N258=$T$10,M258,0)) -> 0 | U258: =IF(AND(N258>$U$9,N258<$U$10),M258,IF(N258=$U$10,M258,0)) -> 0 | V258: =IF(AND(N258>$V$9,N258<$V$10),M258,IF(N258=$V$10,M258,0)) -> 0 | W258: =IF(AND(N258>$W$9,N258<$W$10),M258,IF(N258=$W$10,M258,0)) -> 0 | X258: =IF(AND(N258>$X$9,N258<$X$10),M258,IF(N258=$X$10,M258,0)) -> 0 | Y258: =IF(AND(N258>$Y$9,N258<$Y$10),M258,IF(N258=$Y$10,M258,0)) -> 0 | Z258: =IF(AND(N258>$Z$9,N258<$Z$10),M258,IF(N258=$Z$10,M258,0)) -> 0 | AA258: =IF(AND(N258>$AA$9,N258<$AA$10),M258,IF(N258=$AA$10,M258,0)) -> 0 | AB258: =IF(AND(N258>$AB$9,N258<$AB$10),M258,IF(N258=$AB$10,M258,0)) -> 0 | AC258: =IF(AND(N258>$AC$9,N258<$AC$10),M258,IF(N258=$AC$10,M258,0)) -> 0 | AD258: =IF(AND(N258>$AD$9,N258<$AD$10),M258,IF(N258=$AD$10,M258,0)) -> 0 | AE258: =IF(AND(N258>$AE$9,N258<$AE$10),M258,IF(N258=$AE$10,M258,0)) -> 0 | AF258: =IF(AND(N258>$AF$9,N258<$AF$10),M258,IF(N258=$AF$10,M258,0)) -> 0 | AG258: =IF(N258=$AG$9,M258,0) -> 11151.78
A259: 10920011 | B259: PREPAID VALUE ADDED TAX(VAT) | C259: EP5904220000002 | D259: 100000001 | E259: NONGHYUP BANK SYDNEY BRANCH | F259: AUD | G259: 70.98 | H259: 70.98 | L259: =A259&"_"&F259&"_"&D259&"_"&E259 -> 10920011_AUD_100000001_NONGHYUP BANK SYDNEY BRANCH | M259: =IF(COUNTIF($A$2:$A$8,A259)>0,-H259,H259) -> 70.98 | N259: =IF(OR(L259=$L$2,L259=$L$3),$M$10+1,IFERROR(VLOOKUP(A259,'Repricing Maturity Adj.'!$A$3:$C$170,3,0),(IF(K259<$M$10,"Check",K259)))) -> Non_sensitive | O259: =M259=SUM(Q259:AG259) -> TRUE | P259: =IF(A259="","N/A",IF(COUNTIF($A$2:$A$7,A259)>0,"Liability",IF(COUNTIF($A$8,A259)>0,"Asset",IF(A259<20000000,"Asset",IF(AND(A259>20000000,A259<28800000),"Liability",IF(A259>28800000,"Equity","")))))) -> Asset | Q259: =IF(AND(N259>$Q$9,N259<$Q$10),M259,IF(N259=$Q$10,M259,0)) -> 0 | R259: =IF(AND(N259>$R$9,N259<$R$10),M259,IF(N259=$R$10,M259,0)) -> 0 | S259: =IF(AND(N259>$S$9,N259<$S$10),M259,IF(N259=$S$10,M259,0)) -> 0 | T259: =IF(AND(N259>$T$9,N259<$T$10),M259,IF(N259=$T$10,M259,0)) -> 0 | U259: =IF(AND(N259>$U$9,N259<$U$10),M259,IF(N259=$U$10,M259,0)) -> 0 | V259: =IF(AND(N259>$V$9,N259<$V$10),M259,IF(N259=$V$10,M259,0)) -> 0 | W259: =IF(AND(N259>$W$9,N259<$W$10),M259,IF(N259=$W$10,M259,0)) -> 0 | X259: =IF(AND(N259>$X$9,N259<$X$10),M259,IF(N259=$X$10,M259,0)) -> 0 | Y259: =IF(AND(N259>$Y$9,N259<$Y$10),M259,IF(N259=$Y$10,M259,0)) -> 0 | Z259: =IF(AND(N259>$Z$9,N259<$Z$10),M259,IF(N259=$Z$10,M259,0)) -> 0 | AA259: =IF(AND(N259>$AA$9,N259<$AA$10),M259,IF(N259=$AA$10,M259,0)) -> 0 | AB259: =IF(AND(N259>$AB$9,N259<$AB$10),M259,IF(N259=$AB$10,M259,0)) -> 0 | AC259: =IF(AND(N259>$AC$9,N259<$AC$10),M259,IF(N259=$AC$10,M259,0)) -> 0 | AD259: =IF(AND(N259>$AD$9,N259<$AD$10),M259,IF(N259=$AD$10,M259,0)) -> 0 | AE259: =IF(AND(N259>$AE$9,N259<$AE$10),M259,IF(N259=$AE$10,M259,0)) -> 0 | AF259: =IF(AND(N259>$AF$9,N259<$AF$10),M259,IF(N259=$AF$10,M259,0)) -> 0 | AG259: =IF(N259=$AG$9,M259,0) -> 70.98
A260: 10920011 | B260: PREPAID VALUE ADDED TAX(VAT) | C260: EP5904220000007 | D260: 100000001 | E260: NONGHYUP BANK SYDNEY BRANCH | F260: AUD | G260: 51.78 | H260: 51.78 | L260: =A260&"_"&F260&"_"&D260&"_"&E260 -> 10920011_AUD_100000001_NONGHYUP BANK SYDNEY BRANCH | M260: =IF(COUNTIF($A$2:$A$8,A260)>0,-H260,H260) -> 51.78 | N260: =IF(OR(L260=$L$2,L260=$L$3),$M$10+1,IFERROR(VLOOKUP(A260,'Repricing Maturity Adj.'!$A$3:$C$170,3,0),(IF(K260<$M$10,"Check",K260)))) -> Non_sensitive | O260: =M260=SUM(Q260:AG260) -> TRUE | P260: =IF(A260="","N/A",IF(COUNTIF($A$2:$A$7,A260)>0,"Liability",IF(COUNTIF($A$8,A260)>0,"Asset",IF(A260<20000000,"Asset",IF(AND(A260>20000000,A260<28800000),"Liability",IF(A260>28800000,"Equity","")))))) -> Asset | Q260: =IF(AND(N260>$Q$9,N260<$Q$10),M260,IF(N260=$Q$10,M260,0)) -> 0 | R260: =IF(AND(N260>$R$9,N260<$R$10),M260,IF(N260=$R$10,M260,0)) -> 0 | S260: =IF(AND(N260>$S$9,N260<$S$10),M260,IF(N260=$S$10,M260,0)) -> 0 | T260: =IF(AND(N260>$T$9,N260<$T$10),M260,IF(N260=$T$10,M260,0)) -> 0 | U260: =IF(AND(N260>$U$9,N260<$U$10),M260,IF(N260=$U$10,M260,0)) -> 0 | V260: =IF(AND(N260>$V$9,N260<$V$10),M260,IF(N260=$V$10,M260,0)) -> 0 | W260: =IF(AND(N260>$W$9,N260<$W$10),M260,IF(N260=$W$10,M260,0)) -> 0 | X260: =IF(AND(N260>$X$9,N260<$X$10),M260,IF(N260=$X$10,M260,0)) -> 0 | Y260: =IF(AND(N260>$Y$9,N260<$Y$10),M260,IF(N260=$Y$10,M260,0)) -> 0 | Z260: =IF(AND(N260>$Z$9,N260<$Z$10),M260,IF(N260=$Z$10,M260,0)) -> 0 | AA260: =IF(AND(N260>$AA$9,N260<$AA$10),M260,IF(N260=$AA$10,M260,0)) -> 0 | AB260: =IF(AND(N260>$AB$9,N260<$AB$10),M260,IF(N260=$AB$10,M260,0)) -> 0 | AC260: =IF(AND(N260>$AC$9,N260<$AC$10),M260,IF(N260=$AC$10,M260,0)) -> 0 | AD260: =IF(AND(N260>$AD$9,N260<$AD$10),M260,IF(N260=$AD$10,M260,0)) -> 0 | AE260: =IF(AND(N260>$AE$9,N260<$AE$10),M260,IF(N260=$AE$10,M260,0)) -> 0 | AF260: =IF(AND(N260>$AF$9,N260<$AF$10),M260,IF(N260=$AF$10,M260,0)) -> 0 | AG260: =IF(N260=$AG$9,M260,0) -> 51.78
A261: 10920011 | B261: PREPAID VALUE ADDED TAX(VAT) | C261: EP5904220000014 | D261: 100000001 | E261: NONGHYUP BANK SYDNEY BRANCH | F261: AUD | G261: 51.52 | H261: 51.52 | L261: =A261&"_"&F261&"_"&D261&"_"&E261 -> 10920011_AUD_100000001_NONGHYUP BANK SYDNEY BRANCH | M261: =IF(COUNTIF($A$2:$A$8,A261)>0,-H261,H261) -> 51.52 | N261: =IF(OR(L261=$L$2,L261=$L$3),$M$10+1,IFERROR(VLOOKUP(A261,'Repricing Maturity Adj.'!$A$3:$C$170,3,0),(IF(K261<$M$10,"Check",K261)))) -> Non_sensitive | O261: =M261=SUM(Q261:AG261) -> TRUE | P261: =IF(A261="","N/A",IF(COUNTIF($A$2:$A$7,A261)>0,"Liability",IF(COUNTIF($A$8,A261)>0,"Asset",IF(A261<20000000,"Asset",IF(AND(A261>20000000,A261<28800000),"Liability",IF(A261>28800000,"Equity","")))))) -> Asset | Q261: =IF(AND(N261>$Q$9,N261<$Q$10),M261,IF(N261=$Q$10,M261,0)) -> 0 | R261: =IF(AND(N261>$R$9,N261<$R$10),M261,IF(N261=$R$10,M261,0)) -> 0 | S261: =IF(AND(N261>$S$9,N261<$S$10),M261,IF(N261=$S$10,M261,0)) -> 0 | T261: =IF(AND(N261>$T$9,N261<$T$10),M261,IF(N261=$T$10,M261,0)) -> 0 | U261: =IF(AND(N261>$U$9,N261<$U$10),M261,IF(N261=$U$10,M261,0)) -> 0 | V261: =IF(AND(N261>$V$9,N261<$V$10),M261,IF(N261=$V$10,M261,0)) -> 0 | W261: =IF(AND(N261>$W$9,N261<$W$10),M261,IF(N261=$W$10,M261,0)) -> 0 | X261: =IF(AND(N261>$X$9,N261<$X$10),M261,IF(N261=$X$10,M261,0)) -> 0 | Y261: =IF(AND(N261>$Y$9,N261<$Y$10),M261,IF(N261=$Y$10,M261,0)) -> 0 | Z261: =IF(AND(N261>$Z$9,N261<$Z$10),M261,IF(N261=$Z$10,M261,0)) -> 0 | AA261: =IF(AND(N261>$AA$9,N261<$AA$10),M261,IF(N261=$AA$10,M261,0)) -> 0 | AB261: =IF(AND(N261>$AB$9,N261<$AB$10),M261,IF(N261=$AB$10,M261,0)) -> 0 | AC261: =IF(AND(N261>$AC$9,N261<$AC$10),M261,IF(N261=$AC$10,M261,0)) -> 0 | AD261: =IF(AND(N261>$AD$9,N261<$AD$10),M261,IF(N261=$AD$10,M261,0)) -> 0 | AE261: =IF(AND(N261>$AE$9,N261<$AE$10),M261,IF(N261=$AE$10,M261,0)) -> 0 | AF261: =IF(AND(N261>$AF$9,N261<$AF$10),M261,IF(N261=$AF$10,M261,0)) -> 0 | AG261: =IF(N261=$AG$9,M261,0) -> 51.52
A262: 10920011 | B262: PREPAID VALUE ADDED TAX(VAT) | C262: EP5904220000015 | D262: 100000001 | E262: NONGHYUP BANK SYDNEY BRANCH | F262: AUD | G262: 70.38 | H262: 70.38 | L262: =A262&"_"&F262&"_"&D262&"_"&E262 -> 10920011_AUD_100000001_NONGHYUP BANK SYDNEY BRANCH | M262: =IF(COUNTIF($A$2:$A$8,A262)>0,-H262,H262) -> 70.38 | N262: =IF(OR(L262=$L$2,L262=$L$3),$M$10+1,IFERROR(VLOOKUP(A262,'Repricing Maturity Adj.'!$A$3:$C$170,3,0),(IF(K262<$M$10,"Check",K262)))) -> Non_sensitive | O262: =M262=SUM(Q262:AG262) -> TRUE | P262: =IF(A262="","N/A",IF(COUNTIF($A$2:$A$7,A262)>0,"Liability",IF(COUNTIF($A$8,A262)>0,"Asset",IF(A262<20000000,"Asset",IF(AND(A262>20000000,A262<28800000),"Liability",IF(A262>28800000,"Equity","")))))) -> Asset | Q262: =IF(AND(N262>$Q$9,N262<$Q$10),M262,IF(N262=$Q$10,M262,0)) -> 0 | R262: =IF(AND(N262>$R$9,N262<$R$10),M262,IF(N262=$R$10,M262,0)) -> 0 | S262: =IF(AND(N262>$S$9,N262<$S$10),M262,IF(N262=$S$10,M262,0)) -> 0 | T262: =IF(AND(N262>$T$9,N262<$T$10),M262,IF(N262=$T$10,M262,0)) -> 0 | U262: =IF(AND(N262>$U$9,N262<$U$10),M262,IF(N262=$U$10,M262,0)) -> 0 | V262: =IF(AND(N262>$V$9,N262<$V$10),M262,IF(N262=$V$10,M262,0)) -> 0 | W262: =IF(AND(N262>$W$9,N262<$W$10),M262,IF(N262=$W$10,M262,0)) -> 0 | X262: =IF(AND(N262>$X$9,N262<$X$10),M262,IF(N262=$X$10,M262,0)) -> 0 | Y262: =IF(AND(N262>$Y$9,N262<$Y$10),M262,IF(N262=$Y$10,M262,0)) -> 0 | Z262: =IF(AND(N262>$Z$9,N262<$Z$10),M262,IF(N262=$Z$10,M262,0)) -> 0 | AA262: =IF(AND(N262>$AA$9,N262<$AA$10),M262,IF(N262=$AA$10,M262,0)) -> 0 | AB262: =IF(AND(N262>$AB$9,N262<$AB$10),M262,IF(N262=$AB$10,M262,0)) -> 0 | AC262: =IF(AND(N262>$AC$9,N262<$AC$10),M262,IF(N262=$AC$10,M262,0)) -> 0 | AD262: =IF(AND(N262>$AD$9,N262<$AD$10),M262,IF(N262=$AD$10,M262,0)) -> 0 | AE262: =IF(AND(N262>$AE$9,N262<$AE$10),M262,IF(N262=$AE$10,M262,0)) -> 0 | AF262: =IF(AND(N262>$AF$9,N262<$AF$10),M262,IF(N262=$AF$10,M262,0)) -> 0 | AG262: =IF(N262=$AG$9,M262,0) -> 70.38
A263: 10920011 | B263: PREPAID VALUE ADDED TAX(VAT) | C263: EP5904220000034 | D263: 100000001 | E263: NONGHYUP BANK SYDNEY BRANCH | F263: AUD | G263: 1424.8 | H263: 1424.8 | L263: =A263&"_"&F263&"_"&D263&"_"&E263 -> 10920011_AUD_100000001_NONGHYUP BANK SYDNEY BRANCH | M263: =IF(COUNTIF($A$2:$A$8,A263)>0,-H263,H263) -> 1424.8 | N263: =IF(OR(L263=$L$2,L263=$L$3),$M$10+1,IFERROR(VLOOKUP(A263,'Repricing Maturity Adj.'!$A$3:$C$170,3,0),(IF(K263<$M$10,"Check",K263)))) -> Non_sensitive | O263: =M263=SUM(Q263:AG263) -> TRUE | P263: =IF(A263="","N/A",IF(COUNTIF($A$2:$A$7,A263)>0,"Liability",IF(COUNTIF($A$8,A263)>0,"Asset",IF(A263<20000000,"Asset",IF(AND(A263>20000000,A263<28800000),"Liability",IF(A263>28800000,"Equity","")))))) -> Asset | Q263: =IF(AND(N263>$Q$9,N263<$Q$10),M263,IF(N263=$Q$10,M263,0)) -> 0 | R263: =IF(AND(N263>$R$9,N263<$R$10),M263,IF(N263=$R$10,M263,0)) -> 0 | S263: =IF(AND(N263>$S$9,N263<$S$10),M263,IF(N263=$S$10,M263,0)) -> 0 | T263: =IF(AND(N263>$T$9,N263<$T$10),M263,IF(N263=$T$10,M263,0)) -> 0 | U263: =IF(AND(N263>$U$9,N263<$U$10),M263,IF(N263=$U$10,M263,0)) -> 0 | V263: =IF(AND(N263>$V$9,N263<$V$10),M263,IF(N263=$V$10,M263,0)) -> 0 | W263: =IF(AND(N263>$W$9,N263<$W$10),M263,IF(N263=$W$10,M263,0)) -> 0 | X263: =IF(AND(N263>$X$9,N263<$X$10),M263,IF(N263=$X$10,M263,0)) -> 0 | Y263: =IF(AND(N263>$Y$9,N263<$Y$10),M263,IF(N263=$Y$10,M263,0)) -> 0 | Z263: =IF(AND(N263>$Z$9,N263<$Z$10),M263,IF(N263=$Z$10,M263,0)) -> 0 | AA263: =IF(AND(N263>$AA$9,N263<$AA$10),M263,IF(N263=$AA$10,M263,0)) -> 0 | AB263: =IF(AND(N263>$AB$9,N263<$AB$10),M263,IF(N263=$AB$10,M263,0)) -> 0 | AC263: =IF(AND(N263>$AC$9,N263<$AC$10),M263,IF(N263=$AC$10,M263,0)) -> 0 | AD263: =IF(AND(N263>$AD$9,N263<$AD$10),M263,IF(N263=$AD$10,M263,0)) -> 0 | AE263: =IF(AND(N263>$AE$9,N263<$AE$10),M263,IF(N263=$AE$10,M263,0)) -> 0 | AF263: =IF(AND(N263>$AF$9,N263<$AF$10),M263,IF(N263=$AF$10,M263,0)) -> 0 | AG263: =IF(N263=$AG$9,M263,0) -> 1424.8
A264: 10920011 | B264: PREPAID VALUE ADDED TAX(VAT) | C264: EP5904220000036 | D264: 100000001 | E264: NONGHYUP BANK SYDNEY BRANCH | F264: AUD | G264: 83.5 | H264: 83.5 | L264: =A264&"_"&F264&"_"&D264&"_"&E264 -> 10920011_AUD_100000001_NONGHYUP BANK SYDNEY BRANCH | M264: =IF(COUNTIF($A$2:$A$8,A264)>0,-H264,H264) -> 83.5 | N264: =IF(OR(L264=$L$2,L264=$L$3),$M$10+1,IFERROR(VLOOKUP(A264,'Repricing Maturity Adj.'!$A$3:$C$170,3,0),(IF(K264<$M$10,"Check",K264)))) -> Non_sensitive | O264: =M264=SUM(Q264:AG264) -> TRUE | P264: =IF(A264="","N/A",IF(COUNTIF($A$2:$A$7,A264)>0,"Liability",IF(COUNTIF($A$8,A264)>0,"Asset",IF(A264<20000000,"Asset",IF(AND(A264>20000000,A264<28800000),"Liability",IF(A264>28800000,"Equity","")))))) -> Asset | Q264: =IF(AND(N264>$Q$9,N264<$Q$10),M264,IF(N264=$Q$10,M264,0)) -> 0 | R264: =IF(AND(N264>$R$9,N264<$R$10),M264,IF(N264=$R$10,M264,0)) -> 0 | S264: =IF(AND(N264>$S$9,N264<$S$10),M264,IF(N264=$S$10,M264,0)) -> 0 | T264: =IF(AND(N264>$T$9,N264<$T$10),M264,IF(N264=$T$10,M264,0)) -> 0 | U264: =IF(AND(N264>$U$9,N264<$U$10),M264,IF(N264=$U$10,M264,0)) -> 0 | V264: =IF(AND(N264>$V$9,N264<$V$10),M264,IF(N264=$V$10,M264,0)) -> 0 | W264: =IF(AND(N264>$W$9,N264<$W$10),M264,IF(N264=$W$10,M264,0)) -> 0 | X264: =IF(AND(N264>$X$9,N264<$X$10),M264,IF(N264=$X$10,M264,0)) -> 0 | Y264: =IF(AND(N264>$Y$9,N264<$Y$10),M264,IF(N264=$Y$10,M264,0)) -> 0 | Z264: =IF(AND(N264>$Z$9,N264<$Z$10),M264,IF(N264=$Z$10,M264,0)) -> 0 | AA264: =IF(AND(N264>$AA$9,N264<$AA$10),M264,IF(N264=$AA$10,M264,0)) -> 0 | AB264: =IF(AND(N264>$AB$9,N264<$AB$10),M264,IF(N264=$AB$10,M264,0)) -> 0 | AC264: =IF(AND(N264>$AC$9,N264<$AC$10),M264,IF(N264=$AC$10,M264,0)) -> 0 | AD264: =IF(AND(N264>$AD$9,N264<$AD$10),M264,IF(N264=$AD$10,M264,0)) -> 0 | AE264: =IF(AND(N264>$AE$9,N264<$AE$10),M264,IF(N264=$AE$10,M264,0)) -> 0 | AF264: =IF(AND(N264>$AF$9,N264<$AF$10),M264,IF(N264=$AF$10,M264,0)) -> 0 | AG264: =IF(N264=$AG$9,M264,0) -> 83.5
A265: 10920011 | B265: PREPAID VALUE ADDED TAX(VAT) | C265: EP5904220000038 | D265: 100000001 | E265: NONGHYUP BANK SYDNEY BRANCH | F265: AUD | G265: 4 | H265: 4 | L265: =A265&"_"&F265&"_"&D265&"_"&E265 -> 10920011_AUD_100000001_NONGHYUP BANK SYDNEY BRANCH | M265: =IF(COUNTIF($A$2:$A$8,A265)>0,-H265,H265) -> 4 | N265: =IF(OR(L265=$L$2,L265=$L$3),$M$10+1,IFERROR(VLOOKUP(A265,'Repricing Maturity Adj.'!$A$3:$C$170,3,0),(IF(K265<$M$10,"Check",K265)))) -> Non_sensitive | O265: =M265=SUM(Q265:AG265) -> TRUE | P265: =IF(A265="","N/A",IF(COUNTIF($A$2:$A$7,A265)>0,"Liability",IF(COUNTIF($A$8,A265)>0,"Asset",IF(A265<20000000,"Asset",IF(AND(A265>20000000,A265<28800000),"Liability",IF(A265>28800000,"Equity","")))))) -> Asset | Q265: =IF(AND(N265>$Q$9,N265<$Q$10),M265,IF(N265=$Q$10,M265,0)) -> 0 | R265: =IF(AND(N265>$R$9,N265<$R$10),M265,IF(N265=$R$10,M265,0)) -> 0 | S265: =IF(AND(N265>$S$9,N265<$S$10),M265,IF(N265=$S$10,M265,0)) -> 0 | T265: =IF(AND(N265>$T$9,N265<$T$10),M265,IF(N265=$T$10,M265,0)) -> 0 | U265: =IF(AND(N265>$U$9,N265<$U$10),M265,IF(N265=$U$10,M265,0)) -> 0 | V265: =IF(AND(N265>$V$9,N265<$V$10),M265,IF(N265=$V$10,M265,0)) -> 0 | W265: =IF(AND(N265>$W$9,N265<$W$10),M265,IF(N265=$W$10,M265,0)) -> 0 | X265: =IF(AND(N265>$X$9,N265<$X$10),M265,IF(N265=$X$10,M265,0)) -> 0 | Y265: =IF(AND(N265>$Y$9,N265<$Y$10),M265,IF(N265=$Y$10,M265,0)) -> 0 | Z265: =IF(AND(N265>$Z$9,N265<$Z$10),M265,IF(N265=$Z$10,M265,0)) -> 0 | AA265: =IF(AND(N265>$AA$9,N265<$AA$10),M265,IF(N265=$AA$10,M265,0)) -> 0 | AB265: =IF(AND(N265>$AB$9,N265<$AB$10),M265,IF(N265=$AB$10,M265,0)) -> 0 | AC265: =IF(AND(N265>$AC$9,N265<$AC$10),M265,IF(N265=$AC$10,M265,0)) -> 0 | AD265: =IF(AND(N265>$AD$9,N265<$AD$10),M265,IF(N265=$AD$10,M265,0)) -> 0 | AE265: =IF(AND(N265>$AE$9,N265<$AE$10),M265,IF(N265=$AE$10,M265,0)) -> 0 | AF265: =IF(AND(N265>$AF$9,N265<$AF$10),M265,IF(N265=$AF$10,M265,0)) -> 0 | AG265: =IF(N265=$AG$9,M265,0) -> 4
A266: 10920011 | B266: PREPAID VALUE ADDED TAX(VAT) | C266: EP5904220000042 | D266: 100000001 | E266: NONGHYUP BANK SYDNEY BRANCH | F266: AUD | G266: 1721.03 | H266: 1721.03 | L266: =A266&"_"&F266&"_"&D266&"_"&E266 -> 10920011_AUD_100000001_NONGHYUP BANK SYDNEY BRANCH | M266: =IF(COUNTIF($A$2:$A$8,A266)>0,-H266,H266) -> 1721.03 | N266: =IF(OR(L266=$L$2,L266=$L$3),$M$10+1,IFERROR(VLOOKUP(A266,'Repricing Maturity Adj.'!$A$3:$C$170,3,0),(IF(K266<$M$10,"Check",K266)))) -> Non_sensitive | O266: =M266=SUM(Q266:AG266) -> TRUE | P266: =IF(A266="","N/A",IF(COUNTIF($A$2:$A$7,A266)>0,"Liability",IF(COUNTIF($A$8,A266)>0,"Asset",IF(A266<20000000,"Asset",IF(AND(A266>20000000,A266<28800000),"Liability",IF(A266>28800000,"Equity","")))))) -> Asset | Q266: =IF(AND(N266>$Q$9,N266<$Q$10),M266,IF(N266=$Q$10,M266,0)) -> 0 | R266: =IF(AND(N266>$R$9,N266<$R$10),M266,IF(N266=$R$10,M266,0)) -> 0 | S266: =IF(AND(N266>$S$9,N266<$S$10),M266,IF(N266=$S$10,M266,0)) -> 0 | T266: =IF(AND(N266>$T$9,N266<$T$10),M266,IF(N266=$T$10,M266,0)) -> 0 | U266: =IF(AND(N266>$U$9,N266<$U$10),M266,IF(N266=$U$10,M266,0)) -> 0 | V266: =IF(AND(N266>$V$9,N266<$V$10),M266,IF(N266=$V$10,M266,0)) -> 0 | W266: =IF(AND(N266>$W$9,N266<$W$10),M266,IF(N266=$W$10,M266,0)) -> 0 | X266: =IF(AND(N266>$X$9,N266<$X$10),M266,IF(N266=$X$10,M266,0)) -> 0 | Y266: =IF(AND(N266>$Y$9,N266<$Y$10),M266,IF(N266=$Y$10,M266,0)) -> 0 | Z266: =IF(AND(N266>$Z$9,N266<$Z$10),M266,IF(N266=$Z$10,M266,0)) -> 0 | AA266: =IF(AND(N266>$AA$9,N266<$AA$10),M266,IF(N266=$AA$10,M266,0)) -> 0 | AB266: =IF(AND(N266>$AB$9,N266<$AB$10),M266,IF(N266=$AB$10,M266,0)) -> 0 | AC266: =IF(AND(N266>$AC$9,N266<$AC$10),M266,IF(N266=$AC$10,M266,0)) -> 0 | AD266: =IF(AND(N266>$AD$9,N266<$AD$10),M266,IF(N266=$AD$10,M266,0)) -> 0 | AE266: =IF(AND(N266>$AE$9,N266<$AE$10),M266,IF(N266=$AE$10,M266,0)) -> 0 | AF266: =IF(AND(N266>$AF$9,N266<$AF$10),M266,IF(N266=$AF$10,M266,0)) -> 0 | AG266: =IF(N266=$AG$9,M266,0) -> 1721.03
A267: 10920011 | B267: PREPAID VALUE ADDED TAX(VAT) | C267: EP5904220000048 | D267: 100000001 | E267: NONGHYUP BANK SYDNEY BRANCH | F267: AUD | G267: 44.31 | H267: 44.31 | L267: =A267&"_"&F267&"_"&D267&"_"&E267 -> 10920011_AUD_100000001_NONGHYUP BANK SYDNEY BRANCH | M267: =IF(COUNTIF($A$2:$A$8,A267)>0,-H267,H267) -> 44.31 | N267: =IF(OR(L267=$L$2,L267=$L$3),$M$10+1,IFERROR(VLOOKUP(A267,'Repricing Maturity Adj.'!$A$3:$C$170,3,0),(IF(K267<$M$10,"Check",K267)))) -> Non_sensitive | O267: =M267=SUM(Q267:AG267) -> TRUE | P267: =IF(A267="","N/A",IF(COUNTIF($A$2:$A$7,A267)>0,"Liability",IF(COUNTIF($A$8,A267)>0,"Asset",IF(A267<20000000,"Asset",IF(AND(A267>20000000,A267<28800000),"Liability",IF(A267>28800000,"Equity","")))))) -> Asset | Q267: =IF(AND(N267>$Q$9,N267<$Q$10),M267,IF(N267=$Q$10,M267,0)) -> 0 | R267: =IF(AND(N267>$R$9,N267<$R$10),M267,IF(N267=$R$10,M267,0)) -> 0 | S267: =IF(AND(N267>$S$9,N267<$S$10),M267,IF(N267=$S$10,M267,0)) -> 0 | T267: =IF(AND(N267>$T$9,N267<$T$10),M267,IF(N267=$T$10,M267,0)) -> 0 | U267: =IF(AND(N267>$U$9,N267<$U$10),M267,IF(N267=$U$10,M267,0)) -> 0 | V267: =IF(AND(N267>$V$9,N267<$V$10),M267,IF(N267=$V$10,M267,0)) -> 0 | W267: =IF(AND(N267>$W$9,N267<$W$10),M267,IF(N267=$W$10,M267,0)) -> 0 | X267: =IF(AND(N267>$X$9,N267<$X$10),M267,IF(N267=$X$10,M267,0)) -> 0 | Y267: =IF(AND(N267>$Y$9,N267<$Y$10),M267,IF(N267=$Y$10,M267,0)) -> 0 | Z267: =IF(AND(N267>$Z$9,N267<$Z$10),M267,IF(N267=$Z$10,M267,0)) -> 0 | AA267: =IF(AND(N267>$AA$9,N267<$AA$10),M267,IF(N267=$AA$10,M267,0)) -> 0 | AB267: =IF(AND(N267>$AB$9,N267<$AB$10),M267,IF(N267=$AB$10,M267,0)) -> 0 | AC267: =IF(AND(N267>$AC$9,N267<$AC$10),M267,IF(N267=$AC$10,M267,0)) -> 0 | AD267: =IF(AND(N267>$AD$9,N267<$AD$10),M267,IF(N267=$AD$10,M267,0)) -> 0 | AE267: =IF(AND(N267>$AE$9,N267<$AE$10),M267,IF(N267=$AE$10,M267,0)) -> 0 | AF267: =IF(AND(N267>$AF$9,N267<$AF$10),M267,IF(N267=$AF$10,M267,0)) -> 0 | AG267: =IF(N267=$AG$9,M267,0) -> 44.31
A268: 10920011 | B268: PREPAID VALUE ADDED TAX(VAT) | C268: EP5904220000052 | D268: 100000001 | E268: NONGHYUP BANK SYDNEY BRANCH | F268: AUD | G268: 526.87 | H268: 526.87 | L268: =A268&"_"&F268&"_"&D268&"_"&E268 -> 10920011_AUD_100000001_NONGHYUP BANK SYDNEY BRANCH | M268: =IF(COUNTIF($A$2:$A$8,A268)>0,-H268,H268) -> 526.87 | N268: =IF(OR(L268=$L$2,L268=$L$3),$M$10+1,IFERROR(VLOOKUP(A268,'Repricing Maturity Adj.'!$A$3:$C$170,3,0),(IF(K268<$M$10,"Check",K268)))) -> Non_sensitive | O268: =M268=SUM(Q268:AG268) -> TRUE | P268: =IF(A268="","N/A",IF(COUNTIF($A$2:$A$7,A268)>0,"Liability",IF(COUNTIF($A$8,A268)>0,"Asset",IF(A268<20000000,"Asset",IF(AND(A268>20000000,A268<28800000),"Liability",IF(A268>28800000,"Equity","")))))) -> Asset | Q268: =IF(AND(N268>$Q$9,N268<$Q$10),M268,IF(N268=$Q$10,M268,0)) -> 0 | R268: =IF(AND(N268>$R$9,N268<$R$10),M268,IF(N268=$R$10,M268,0)) -> 0 | S268: =IF(AND(N268>$S$9,N268<$S$10),M268,IF(N268=$S$10,M268,0)) -> 0 | T268: =IF(AND(N268>$T$9,N268<$T$10),M268,IF(N268=$T$10,M268,0)) -> 0 | U268: =IF(AND(N268>$U$9,N268<$U$10),M268,IF(N268=$U$10,M268,0)) -> 0 | V268: =IF(AND(N268>$V$9,N268<$V$10),M268,IF(N268=$V$10,M268,0)) -> 0 | W268: =IF(AND(N268>$W$9,N268<$W$10),M268,IF(N268=$W$10,M268,0)) -> 0 | X268: =IF(AND(N268>$X$9,N268<$X$10),M268,IF(N268=$X$10,M268,0)) -> 0 | Y268: =IF(AND(N268>$Y$9,N268<$Y$10),M268,IF(N268=$Y$10,M268,0)) -> 0 | Z268: =IF(AND(N268>$Z$9,N268<$Z$10),M268,IF(N268=$Z$10,M268,0)) -> 0 | AA268: =IF(AND(N268>$AA$9,N268<$AA$10),M268,IF(N268=$AA$10,M268,0)) -> 0 | AB268: =IF(AND(N268>$AB$9,N268<$AB$10),M268,IF(N268=$AB$10,M268,0)) -> 0 | AC268: =IF(AND(N268>$AC$9,N268<$AC$10),M268,IF(N268=$AC$10,M268,0)) -> 0 | AD268: =IF(AND(N268>$AD$9,N268<$AD$10),M268,IF(N268=$AD$10,M268,0)) -> 0 | AE268: =IF(AND(N268>$AE$9,N268<$AE$10),M268,IF(N268=$AE$10,M268,0)) -> 0 | AF268: =IF(AND(N268>$AF$9,N268<$AF$10),M268,IF(N268=$AF$10,M268,0)) -> 0 | AG268: =IF(N268=$AG$9,M268,0) -> 526.87
A269: 10920011 | B269: PREPAID VALUE ADDED TAX(VAT) | C269: EP5904220000054 | D269: 100000001 | E269: NONGHYUP BANK SYDNEY BRANCH | F269: AUD | G269: 508.28 | H269: 508.28 | L269: =A269&"_"&F269&"_"&D269&"_"&E269 -> 10920011_AUD_100000001_NONGHYUP BANK SYDNEY BRANCH | M269: =IF(COUNTIF($A$2:$A$8,A269)>0,-H269,H269) -> 508.28 | N269: =IF(OR(L269=$L$2,L269=$L$3),$M$10+1,IFERROR(VLOOKUP(A269,'Repricing Maturity Adj.'!$A$3:$C$170,3,0),(IF(K269<$M$10,"Check",K269)))) -> Non_sensitive | O269: =M269=SUM(Q269:AG269) -> TRUE | P269: =IF(A269="","N/A",IF(COUNTIF($A$2:$A$7,A269)>0,"Liability",IF(COUNTIF($A$8,A269)>0,"Asset",IF(A269<20000000,"Asset",IF(AND(A269>20000000,A269<28800000),"Liability",IF(A269>28800000,"Equity","")))))) -> Asset | Q269: =IF(AND(N269>$Q$9,N269<$Q$10),M269,IF(N269=$Q$10,M269,0)) -> 0 | R269: =IF(AND(N269>$R$9,N269<$R$10),M269,IF(N269=$R$10,M269,0)) -> 0 | S269: =IF(AND(N269>$S$9,N269<$S$10),M269,IF(N269=$S$10,M269,0)) -> 0 | T269: =IF(AND(N269>$T$9,N269<$T$10),M269,IF(N269=$T$10,M269,0)) -> 0 | U269: =IF(AND(N269>$U$9,N269<$U$10),M269,IF(N269=$U$10,M269,0)) -> 0 | V269: =IF(AND(N269>$V$9,N269<$V$10),M269,IF(N269=$V$10,M269,0)) -> 0 | W269: =IF(AND(N269>$W$9,N269<$W$10),M269,IF(N269=$W$10,M269,0)) -> 0 | X269: =IF(AND(N269>$X$9,N269<$X$10),M269,IF(N269=$X$10,M269,0)) -> 0 | Y269: =IF(AND(N269>$Y$9,N269<$Y$10),M269,IF(N269=$Y$10,M269,0)) -> 0 | Z269: =IF(AND(N269>$Z$9,N269<$Z$10),M269,IF(N269=$Z$10,M269,0)) -> 0 | AA269: =IF(AND(N269>$AA$9,N269<$AA$10),M269,IF(N269=$AA$10,M269,0)) -> 0 | AB269: =IF(AND(N269>$AB$9,N269<$AB$10),M269,IF(N269=$AB$10,M269,0)) -> 0 | AC269: =IF(AND(N269>$AC$9,N269<$AC$10),M269,IF(N269=$AC$10,M269,0)) -> 0 | AD269: =IF(AND(N269>$AD$9,N269<$AD$10),M269,IF(N269=$AD$10,M269,0)) -> 0 | AE269: =IF(AND(N269>$AE$9,N269<$AE$10),M269,IF(N269=$AE$10,M269,0)) -> 0 | AF269: =IF(AND(N269>$AF$9,N269<$AF$10),M269,IF(N269=$AF$10,M269,0)) -> 0 | AG269: =IF(N269=$AG$9,M269,0) -> 508.28
A270: 10920011 | B270: PREPAID VALUE ADDED TAX(VAT) | C270: EP5904220000056 | D270: 100000001 | E270: NONGHYUP BANK SYDNEY BRANCH | F270: AUD | G270: 23817.31 | H270: 23817.31 | L270: =A270&"_"&F270&"_"&D270&"_"&E270 -> 10920011_AUD_100000001_NONGHYUP BANK SYDNEY BRANCH | M270: =IF(COUNTIF($A$2:$A$8,A270)>0,-H270,H270) -> 23817.31 | N270: =IF(OR(L270=$L$2,L270=$L$3),$M$10+1,IFERROR(VLOOKUP(A270,'Repricing Maturity Adj.'!$A$3:$C$170,3,0),(IF(K270<$M$10,"Check",K270)))) -> Non_sensitive | O270: =M270=SUM(Q270:AG270) -> TRUE | P270: =IF(A270="","N/A",IF(COUNTIF($A$2:$A$7,A270)>0,"Liability",IF(COUNTIF($A$8,A270)>0,"Asset",IF(A270<20000000,"Asset",IF(AND(A270>20000000,A270<28800000),"Liability",IF(A270>28800000,"Equity","")))))) -> Asset | Q270: =IF(AND(N270>$Q$9,N270<$Q$10),M270,IF(N270=$Q$10,M270,0)) -> 0 | R270: =IF(AND(N270>$R$9,N270<$R$10),M270,IF(N270=$R$10,M270,0)) -> 0 | S270: =IF(AND(N270>$S$9,N270<$S$10),M270,IF(N270=$S$10,M270,0)) -> 0 | T270: =IF(AND(N270>$T$9,N270<$T$10),M270,IF(N270=$T$10,M270,0)) -> 0 | U270: =IF(AND(N270>$U$9,N270<$U$10),M270,IF(N270=$U$10,M270,0)) -> 0 | V270: =IF(AND(N270>$V$9,N270<$V$10),M270,IF(N270=$V$10,M270,0)) -> 0 | W270: =IF(AND(N270>$W$9,N270<$W$10),M270,IF(N270=$W$10,M270,0)) -> 0 | X270: =IF(AND(N270>$X$9,N270<$X$10),M270,IF(N270=$X$10,M270,0)) -> 0 | Y270: =IF(AND(N270>$Y$9,N270<$Y$10),M270,IF(N270=$Y$10,M270,0)) -> 0 | Z270: =IF(AND(N270>$Z$9,N270<$Z$10),M270,IF(N270=$Z$10,M270,0)) -> 0 | AA270: =IF(AND(N270>$AA$9,N270<$AA$10),M270,IF(N270=$AA$10,M270,0)) -> 0 | AB270: =IF(AND(N270>$AB$9,N270<$AB$10),M270,IF(N270=$AB$10,M270,0)) -> 0 | AC270: =IF(AND(N270>$AC$9,N270<$AC$10),M270,IF(N270=$AC$10,M270,0)) -> 0 | AD270: =IF(AND(N270>$AD$9,N270<$AD$10),M270,IF(N270=$AD$10,M270,0)) -> 0 | AE270: =IF(AND(N270>$AE$9,N270<$AE$10),M270,IF(N270=$AE$10,M270,0)) -> 0 | AF270: =IF(AND(N270>$AF$9,N270<$AF$10),M270,IF(N270=$AF$10,M270,0)) -> 0 | AG270: =IF(N270=$AG$9,M270,0) -> 23817.31
... A302: 10999002 | B302: SECURITY DEPOSIT | C302: OT5904260000013 | D302: 100000001 | E302: NONGHYUP BANK SYDNEY BRANCH | F302: AUD | G302: 4600 | H302: 4600 | L302: =A302&"_"&F302&"_"&D302&"_"&E302 -> 10999002_AUD_100000001_NONGHYUP BANK SYDNEY BRANCH | M302: =IF(COUNTIF($A$2:$A$8,A302)>0,-H302,H302) -> 4600 | N302: =IF(OR(L302=$L$2,L302=$L$3),$M$10+1,IFERROR(VLOOKUP(A302,'Repricing Maturity Adj.'!$A$3:$C$170,3,0),(IF(K302<$M$10,"Check",K302)))) -> Non_sensitive | O302: =M302=SUM(Q302:AG302) -> TRUE | P302: =IF(A302="","N/A",IF(COUNTIF($A$2:$A$7,A302)>0,"Liability",IF(COUNTIF($A$8,A302)>0,"Asset",IF(A302<20000000,"Asset",IF(AND(A302>20000000,A302<28800000),"Liability",IF(A302>28800000,"Equity","")))))) -> Asset | Q302: =IF(AND(N302>$Q$9,N302<$Q$10),M302,IF(N302=$Q$10,M302,0)) -> 0 | R302: =IF(AND(N302>$R$9,N302<$R$10),M302,IF(N302=$R$10,M302,0)) -> 0 | S302: =IF(AND(N302>$S$9,N302<$S$10),M302,IF(N302=$S$10,M302,0)) -> 0 | T302: =IF(AND(N302>$T$9,N302<$T$10),M302,IF(N302=$T$10,M302,0)) -> 0 | U302: =IF(AND(N302>$U$9,N302<$U$10),M302,IF(N302=$U$10,M302,0)) -> 0 | V302: =IF(AND(N302>$V$9,N302<$V$10),M302,IF(N302=$V$10,M302,0)) -> 0 | W302: =IF(AND(N302>$W$9,N302<$W$10),M302,IF(N302=$W$10,M302,0)) -> 0 | X302: =IF(AND(N302>$X$9,N302<$X$10),M302,IF(N302=$X$10,M302,0)) -> 0 | Y302: =IF(AND(N302>$Y$9,N302<$Y$10),M302,IF(N302=$Y$10,M302,0)) -> 0 | Z302: =IF(AND(N302>$Z$9,N302<$Z$10),M302,IF(N302=$Z$10,M302,0)) -> 0 | AA302: =IF(AND(N302>$AA$9,N302<$AA$10),M302,IF(N302=$AA$10,M302,0)) -> 0 | AB302: =IF(AND(N302>$AB$9,N302<$AB$10),M302,IF(N302=$AB$10,M302,0)) -> 0 | AC302: =IF(AND(N302>$AC$9,N302<$AC$10),M302,IF(N302=$AC$10,M302,0)) -> 0 | AD302: =IF(AND(N302>$AD$9,N302<$AD$10),M302,IF(N302=$AD$10,M302,0)) -> 0 | AE302: =IF(AND(N302>$AE$9,N302<$AE$10),M302,IF(N302=$AE$10,M302,0)) -> 0 | AF302: =IF(AND(N302>$AF$9,N302<$AF$10),M302,IF(N302=$AF$10,M302,0)) -> 0 | AG302: =IF(N302=$AG$9,M302,0) -> 4600
A303: 12110002 | B303: Information Technology system Tools | C303: FA5904220000003 | D303: 100000001 | E303: NONGHYUP BANK SYDNEY BRANCH | F303: AUD | G303: 2512.96 | H303: 2512.96 | I303: 44621 | J303: 45961 | L303: =A303&"_"&F303&"_"&D303&"_"&E303 -> 12110002_AUD_100000001_NONGHYUP BANK SYDNEY BRANCH | M303: =IF(COUNTIF($A$2:$A$8,A303)>0,-H303,H303) -> 2512.96 | N303: =IF(OR(L303=$L$2,L303=$L$3),$M$10+1,IFERROR(VLOOKUP(A303,'Repricing Maturity Adj.'!$A$3:$C$170,3,0),(IF(K303<$M$10,"Check",K303)))) -> Non_sensitive | O303: =M303=SUM(Q303:AG303) -> TRUE | P303: =IF(A303="","N/A",IF(COUNTIF($A$2:$A$7,A303)>0,"Liability",IF(COUNTIF($A$8,A303)>0,"Asset",IF(A303<20000000,"Asset",IF(AND(A303>20000000,A303<28800000),"Liability",IF(A303>28800000,"Equity","")))))) -> Asset | Q303: =IF(AND(N303>$Q$9,N303<$Q$10),M303,IF(N303=$Q$10,M303,0)) -> 0 | R303: =IF(AND(N303>$R$9,N303<$R$10),M303,IF(N303=$R$10,M303,0)) -> 0 | S303: =IF(AND(N303>$S$9,N303<$S$10),M303,IF(N303=$S$10,M303,0)) -> 0 | T303: =IF(AND(N303>$T$9,N303<$T$10),M303,IF(N303=$T$10,M303,0)) -> 0 | U303: =IF(AND(N303>$U$9,N303<$U$10),M303,IF(N303=$U$10,M303,0)) -> 0 | V303: =IF(AND(N303>$V$9,N303<$V$10),M303,IF(N303=$V$10,M303,0)) -> 0 | W303: =IF(AND(N303>$W$9,N303<$W$10),M303,IF(N303=$W$10,M303,0)) -> 0 | X303: =IF(AND(N303>$X$9,N303<$X$10),M303,IF(N303=$X$10,M303,0)) -> 0 | Y303: =IF(AND(N303>$Y$9,N303<$Y$10),M303,IF(N303=$Y$10,M303,0)) -> 0 | Z303: =IF(AND(N303>$Z$9,N303<$Z$10),M303,IF(N303=$Z$10,M303,0)) -> 0 | AA303: =IF(AND(N303>$AA$9,N303<$AA$10),M303,IF(N303=$AA$10,M303,0)) -> 0 | AB303: =IF(AND(N303>$AB$9,N303<$AB$10),M303,IF(N303=$AB$10,M303,0)) -> 0 | AC303: =IF(AND(N303>$AC$9,N303<$AC$10),M303,IF(N303=$AC$10,M303,0)) -> 0 | AD303: =IF(AND(N303>$AD$9,N303<$AD$10),M303,IF(N303=$AD$10,M303,0)) -> 0 | AE303: =IF(AND(N303>$AE$9,N303<$AE$10),M303,IF(N303=$AE$10,M303,0)) -> 0 | AF303: =IF(AND(N303>$AF$9,N303<$AF$10),M303,IF(N303=$AF$10,M303,0)) -> 0 | AG303: =IF(N303=$AG$9,M303,0) -> 2512.96
A304: 12110002 | B304: Information Technology system Tools | C304: FA5904220000005 | D304: 100000001 | E304: NONGHYUP BANK SYDNEY BRANCH | F304: AUD | G304: 1396.32 | H304: 1396.32 | I304: 44621 | J304: 45961 | L304: =A304&"_"&F304&"_"&D304&"_"&E304 -> 12110002_AUD_100000001_NONGHYUP BANK SYDNEY BRANCH | M304: =IF(COUNTIF($A$2:$A$8,A304)>0,-H304,H304) -> 1396.32 | N304: =IF(OR(L304=$L$2,L304=$L$3),$M$10+1,IFERROR(VLOOKUP(A304,'Repricing Maturity Adj.'!$A$3:$C$170,3,0),(IF(K304<$M$10,"Check",K304)))) -> Non_sensitive | O304: =M304=SUM(Q304:AG304) -> TRUE | P304: =IF(A304="","N/A",IF(COUNTIF($A$2:$A$7,A304)>0,"Liability",IF(COUNTIF($A$8,A304)>0,"Asset",IF(A304<20000000,"Asset",IF(AND(A304>20000000,A304<28800000),"Liability",IF(A304>28800000,"Equity","")))))) -> Asset | Q304: =IF(AND(N304>$Q$9,N304<$Q$10),M304,IF(N304=$Q$10,M304,0)) -> 0 | R304: =IF(AND(N304>$R$9,N304<$R$10),M304,IF(N304=$R$10,M304,0)) -> 0 | S304: =IF(AND(N304>$S$9,N304<$S$10),M304,IF(N304=$S$10,M304,0)) -> 0 | T304: =IF(AND(N304>$T$9,N304<$T$10),M304,IF(N304=$T$10,M304,0)) -> 0 | U304: =IF(AND(N304>$U$9,N304<$U$10),M304,IF(N304=$U$10,M304,0)) -> 0 | V304: =IF(AND(N304>$V$9,N304<$V$10),M304,IF(N304=$V$10,M304,0)) -> 0 | W304: =IF(AND(N304>$W$9,N304<$W$10),M304,IF(N304=$W$10,M304,0)) -> 0 | X304: =IF(AND(N304>$X$9,N304<$X$10),M304,IF(N304=$X$10,M304,0)) -> 0 | Y304: =IF(AND(N304>$Y$9,N304<$Y$10),M304,IF(N304=$Y$10,M304,0)) -> 0 | Z304: =IF(AND(N304>$Z$9,N304<$Z$10),M304,IF(N304=$Z$10,M304,0)) -> 0 | AA304: =IF(AND(N304>$AA$9,N304<$AA$10),M304,IF(N304=$AA$10,M304,0)) -> 0 | AB304: =IF(AND(N304>$AB$9,N304<$AB$10),M304,IF(N304=$AB$10,M304,0)) -> 0 | AC304: =IF(AND(N304>$AC$9,N304<$AC$10),M304,IF(N304=$AC$10,M304,0)) -> 0 | AD304: =IF(AND(N304>$AD$9,N304<$AD$10),M304,IF(N304=$AD$10,M304,0)) -> 0 | AE304: =IF(AND(N304>$AE$9,N304<$AE$10),M304,IF(N304=$AE$10,M304,0)) -> 0 | AF304: =IF(AND(N304>$AF$9,N304<$AF$10),M304,IF(N304=$AF$10,M304,0)) -> 0 | AG304: =IF(N304=$AG$9,M304,0) -> 1396.32
A305: 12110002 | B305: Information Technology system Tools | C305: FA5904220000006 | D305: 100000001 | E305: NONGHYUP BANK SYDNEY BRANCH | F305: AUD | G305: 9939.6 | H305: 9939.6 | I305: 44621 | J305: 45961 | L305: =A305&"_"&F305&"_"&D305&"_"&E305 -> 12110002_AUD_100000001_NONGHYUP BANK SYDNEY BRANCH | M305: =IF(COUNTIF($A$2:$A$8,A305)>0,-H305,H305) -> 9939.6 | N305: =IF(OR(L305=$L$2,L305=$L$3),$M$10+1,IFERROR(VLOOKUP(A305,'Repricing Maturity Adj.'!$A$3:$C$170,3,0),(IF(K305<$M$10,"Check",K305)))) -> Non_sensitive | O305: =M305=SUM(Q305:AG305) -> TRUE | P305: =IF(A305="","N/A",IF(COUNTIF($A$2:$A$7,A305)>0,"Liability",IF(COUNTIF($A$8,A305)>0,"Asset",IF(A305<20000000,"Asset",IF(AND(A305>20000000,A305<28800000),"Liability",IF(A305>28800000,"Equity","")))))) -> Asset | Q305: =IF(AND(N305>$Q$9,N305<$Q$10),M305,IF(N305=$Q$10,M305,0)) -> 0 | R305: =IF(AND(N305>$R$9,N305<$R$10),M305,IF(N305=$R$10,M305,0)) -> 0 | S305: =IF(AND(N305>$S$9,N305<$S$10),M305,IF(N305=$S$10,M305,0)) -> 0 | T305: =IF(AND(N305>$T$9,N305<$T$10),M305,IF(N305=$T$10,M305,0)) -> 0 | U305: =IF(AND(N305>$U$9,N305<$U$10),M305,IF(N305=$U$10,M305,0)) -> 0 | V305: =IF(AND(N305>$V$9,N305<$V$10),M305,IF(N305=$V$10,M305,0)) -> 0 | W305: =IF(AND(N305>$W$9,N305<$W$10),M305,IF(N305=$W$10,M305,0)) -> 0 | X305: =IF(AND(N305>$X$9,N305<$X$10),M305,IF(N305=$X$10,M305,0)) -> 0 | Y305: =IF(AND(N305>$Y$9,N305<$Y$10),M305,IF(N305=$Y$10,M305,0)) -> 0 | Z305: =IF(AND(N305>$Z$9,N305<$Z$10),M305,IF(N305=$Z$10,M305,0)) -> 0 | AA305: =IF(AND(N305>$AA$9,N305<$AA$10),M305,IF(N305=$AA$10,M305,0)) -> 0 | AB305: =IF(AND(N305>$AB$9,N305<$AB$10),M305,IF(N305=$AB$10,M305,0)) -> 0 | AC305: =IF(AND(N305>$AC$9,N305<$AC$10),M305,IF(N305=$AC$10,M305,0)) -> 0 | AD305: =IF(AND(N305>$AD$9,N305<$AD$10),M305,IF(N305=$AD$10,M305,0)) -> 0 | AE305: =IF(AND(N305>$AE$9,N305<$AE$10),M305,IF(N305=$AE$10,M305,0)) -> 0 | AF305: =IF(AND(N305>$AF$9,N305<$AF$10),M305,IF(N305=$AF$10,M305,0)) -> 0 | AG305: =IF(N305=$AG$9,M305,0) -> 9939.6
A306: 12110002 | B306: Information Technology system Tools | C306: FA5904220000008 | D306: 100000001 | E306: NONGHYUP BANK SYDNEY BRANCH | F306: AUD | G306: 2588.43 | H306: 2588.43 | I306: 44621 | J306: 45961 | L306: =A306&"_"&F306&"_"&D306&"_"&E306 -> 12110002_AUD_100000001_NONGHYUP BANK SYDNEY BRANCH | M306: =IF(COUNTIF($A$2:$A$8,A306)>0,-H306,H306) -> 2588.43 | N306: =IF(OR(L306=$L$2,L306=$L$3),$M$10+1,IFERROR(VLOOKUP(A306,'Repricing Maturity Adj.'!$A$3:$C$170,3,0),(IF(K306<$M$10,"Check",K306)))) -> Non_sensitive | O306: =M306=SUM(Q306:AG306) -> TRUE | P306: =IF(A306="","N/A",IF(COUNTIF($A$2:$A$7,A306)>0,"Liability",IF(COUNTIF($A$8,A306)>0,"Asset",IF(A306<20000000,"Asset",IF(AND(A306>20000000,A306<28800000),"Liability",IF(A306>28800000,"Equity","")))))) -> Asset | Q306: =IF(AND(N306>$Q$9,N306<$Q$10),M306,IF(N306=$Q$10,M306,0)) -> 0 | R306: =IF(AND(N306>$R$9,N306<$R$10),M306,IF(N306=$R$10,M306,0)) -> 0 | S306: =IF(AND(N306>$S$9,N306<$S$10),M306,IF(N306=$S$10,M306,0)) -> 0 | T306: =IF(AND(N306>$T$9,N306<$T$10),M306,IF(N306=$T$10,M306,0)) -> 0 | U306: =IF(AND(N306>$U$9,N306<$U$10),M306,IF(N306=$U$10,M306,0)) -> 0 | V306: =IF(AND(N306>$V$9,N306<$V$10),M306,IF(N306=$V$10,M306,0)) -> 0 | W306: =IF(AND(N306>$W$9,N306<$W$10),M306,IF(N306=$W$10,M306,0)) -> 0 | X306: =IF(AND(N306>$X$9,N306<$X$10),M306,IF(N306=$X$10,M306,0)) -> 0 | Y306: =IF(AND(N306>$Y$9,N306<$Y$10),M306,IF(N306=$Y$10,M306,0)) -> 0 | Z306: =IF(AND(N306>$Z$9,N306<$Z$10),M306,IF(N306=$Z$10,M306,0)) -> 0 | AA306: =IF(AND(N306>$AA$9,N306<$AA$10),M306,IF(N306=$AA$10,M306,0)) -> 0 | AB306: =IF(AND(N306>$AB$9,N306<$AB$10),M306,IF(N306=$AB$10,M306,0)) -> 0 | AC306: =IF(AND(N306>$AC$9,N306<$AC$10),M306,IF(N306=$AC$10,M306,0)) -> 0 | AD306: =IF(AND(N306>$AD$9,N306<$AD$10),M306,IF(N306=$AD$10,M306,0)) -> 0 | AE306: =IF(AND(N306>$AE$9,N306<$AE$10),M306,IF(N306=$AE$10,M306,0)) -> 0 | AF306: =IF(AND(N306>$AF$9,N306<$AF$10),M306,IF(N306=$AF$10,M306,0)) -> 0 | AG306: =IF(N306=$AG$9,M306,0) -> 2588.43
A307: 12110002 | B307: Information Technology system Tools | C307: FA5904220000009 | D307: 100000001 | E307: NONGHYUP BANK SYDNEY BRANCH | F307: AUD | G307: 2019.88 | H307: 2019.88 | I307: 44621 | J307: 45961 | L307: =A307&"_"&F307&"_"&D307&"_"&E307 -> 12110002_AUD_100000001_NONGHYUP BANK SYDNEY BRANCH | M307: =IF(COUNTIF($A$2:$A$8,A307)>0,-H307,H307) -> 2019.88 | N307: =IF(OR(L307=$L$2,L307=$L$3),$M$10+1,IFERROR(VLOOKUP(A307,'Repricing Maturity Adj.'!$A$3:$C$170,3,0),(IF(K307<$M$10,"Check",K307)))) -> Non_sensitive | O307: =M307=SUM(Q307:AG307) -> TRUE | P307: =IF(A307="","N/A",IF(COUNTIF($A$2:$A$7,A307)>0,"Liability",IF(COUNTIF($A$8,A307)>0,"Asset",IF(A307<20000000,"Asset",IF(AND(A307>20000000,A307<28800000),"Liability",IF(A307>28800000,"Equity","")))))) -> Asset | Q307: =IF(AND(N307>$Q$9,N307<$Q$10),M307,IF(N307=$Q$10,M307,0)) -> 0 | R307: =IF(AND(N307>$R$9,N307<$R$10),M307,IF(N307=$R$10,M307,0)) -> 0 | S307: =IF(AND(N307>$S$9,N307<$S$10),M307,IF(N307=$S$10,M307,0)) -> 0 | T307: =IF(AND(N307>$T$9,N307<$T$10),M307,IF(N307=$T$10,M307,0)) -> 0 | U307: =IF(AND(N307>$U$9,N307<$U$10),M307,IF(N307=$U$10,M307,0)) -> 0 | V307: =IF(AND(N307>$V$9,N307<$V$10),M307,IF(N307=$V$10,M307,0)) -> 0 | W307: =IF(AND(N307>$W$9,N307<$W$10),M307,IF(N307=$W$10,M307,0)) -> 0 | X307: =IF(AND(N307>$X$9,N307<$X$10),M307,IF(N307=$X$10,M307,0)) -> 0 | Y307: =IF(AND(N307>$Y$9,N307<$Y$10),M307,IF(N307=$Y$10,M307,0)) -> 0 | Z307: =IF(AND(N307>$Z$9,N307<$Z$10),M307,IF(N307=$Z$10,M307,0)) -> 0 | AA307: =IF(AND(N307>$AA$9,N307<$AA$10),M307,IF(N307=$AA$10,M307,0)) -> 0 | AB307: =IF(AND(N307>$AB$9,N307<$AB$10),M307,IF(N307=$AB$10,M307,0)) -> 0 | AC307: =IF(AND(N307>$AC$9,N307<$AC$10),M307,IF(N307=$AC$10,M307,0)) -> 0 | AD307: =IF(AND(N307>$AD$9,N307<$AD$10),M307,IF(N307=$AD$10,M307,0)) -> 0 | AE307: =IF(AND(N307>$AE$9,N307<$AE$10),M307,IF(N307=$AE$10,M307,0)) -> 0 | AF307: =IF(AND(N307>$AF$9,N307<$AF$10),M307,IF(N307=$AF$10,M307,0)) -> 0 | AG307: =IF(N307=$AG$9,M307,0) -> 2019.88
A308: 12110002 | B308: Information Technology system Tools | C308: FA5904220000010 | D308: 100000001 | E308: NONGHYUP BANK SYDNEY BRANCH | F308: AUD | G308: 3457.21 | H308: 3457.21 | I308: 44621 | J308: 46387 | L308: =A308&"_"&F308&"_"&D308&"_"&E308 -> 12110002_AUD_100000001_NONGHYUP BANK SYDNEY BRANCH | M308: =IF(COUNTIF($A$2:$A$8,A308)>0,-H308,H308) -> 3457.21 | N308: =IF(OR(L308=$L$2,L308=$L$3),$M$10+1,IFERROR(VLOOKUP(A308,'Repricing Maturity Adj.'!$A$3:$C$170,3,0),(IF(K308<$M$10,"Check",K308)))) -> Non_sensitive | O308: =M308=SUM(Q308:AG308) -> TRUE | P308: =IF(A308="","N/A",IF(COUNTIF($A$2:$A$7,A308)>0,"Liability",IF(COUNTIF($A$8,A308)>0,"Asset",IF(A308<20000000,"Asset",IF(AND(A308>20000000,A308<28800000),"Liability",IF(A308>28800000,"Equity","")))))) -> Asset | Q308: =IF(AND(N308>$Q$9,N308<$Q$10),M308,IF(N308=$Q$10,M308,0)) -> 0 | R308: =IF(AND(N308>$R$9,N308<$R$10),M308,IF(N308=$R$10,M308,0)) -> 0 | S308: =IF(AND(N308>$S$9,N308<$S$10),M308,IF(N308=$S$10,M308,0)) -> 0 | T308: =IF(AND(N308>$T$9,N308<$T$10),M308,IF(N308=$T$10,M308,0)) -> 0 | U308: =IF(AND(N308>$U$9,N308<$U$10),M308,IF(N308=$U$10,M308,0)) -> 0 | V308: =IF(AND(N308>$V$9,N308<$V$10),M308,IF(N308=$V$10,M308,0)) -> 0 | W308: =IF(AND(N308>$W$9,N308<$W$10),M308,IF(N308=$W$10,M308,0)) -> 0 | X308: =IF(AND(N308>$X$9,N308<$X$10),M308,IF(N308=$X$10,M308,0)) -> 0 | Y308: =IF(AND(N308>$Y$9,N308<$Y$10),M308,IF(N308=$Y$10,M308,0)) -> 0 | Z308: =IF(AND(N308>$Z$9,N308<$Z$10),M308,IF(N308=$Z$10,M308,0)) -> 0 | AA308: =IF(AND(N308>$AA$9,N308<$AA$10),M308,IF(N308=$AA$10,M308,0)) -> 0 | AB308: =IF(AND(N308>$AB$9,N308<$AB$10),M308,IF(N308=$AB$10,M308,0)) -> 0 | AC308: =IF(AND(N308>$AC$9,N308<$AC$10),M308,IF(N308=$AC$10,M308,0)) -> 0 | AD308: =IF(AND(N308>$AD$9,N308<$AD$10),M308,IF(N308=$AD$10,M308,0)) -> 0 | AE308: =IF(AND(N308>$AE$9,N308<$AE$10),M308,IF(N308=$AE$10,M308,0)) -> 0 | AF308: =IF(AND(N308>$AF$9,N308<$AF$10),M308,IF(N308=$AF$10,M308,0)) -> 0 | AG308: =IF(N308=$AG$9,M308,0) -> 3457.21
A309: 12110002 | B309: Information Technology system Tools | C309: FA5904220000011 | D309: 100000001 | E309: NONGHYUP BANK SYDNEY BRANCH | F309: AUD | G309: 411.68 | H309: 411.68 | I309: 44621 | J309: 45961 | L309: =A309&"_"&F309&"_"&D309&"_"&E309 -> 12110002_AUD_100000001_NONGHYUP BANK SYDNEY BRANCH | M309: =IF(COUNTIF($A$2:$A$8,A309)>0,-H309,H309) -> 411.68 | N309: =IF(OR(L309=$L$2,L309=$L$3),$M$10+1,IFERROR(VLOOKUP(A309,'Repricing Maturity Adj.'!$A$3:$C$170,3,0),(IF(K309<$M$10,"Check",K309)))) -> Non_sensitive | O309: =M309=SUM(Q309:AG309) -> TRUE | P309: =IF(A309="","N/A",IF(COUNTIF($A$2:$A$7,A309)>0,"Liability",IF(COUNTIF($A$8,A309)>0,"Asset",IF(A309<20000000,"Asset",IF(AND(A309>20000000,A309<28800000),"Liability",IF(A309>28800000,"Equity","")))))) -> Asset | Q309: =IF(AND(N309>$Q$9,N309<$Q$10),M309,IF(N309=$Q$10,M309,0)) -> 0 | R309: =IF(AND(N309>$R$9,N309<$R$10),M309,IF(N309=$R$10,M309,0)) -> 0 | S309: =IF(AND(N309>$S$9,N309<$S$10),M309,IF(N309=$S$10,M309,0)) -> 0 | T309: =IF(AND(N309>$T$9,N309<$T$10),M309,IF(N309=$T$10,M309,0)) -> 0 | U309: =IF(AND(N309>$U$9,N309<$U$10),M309,IF(N309=$U$10,M309,0)) -> 0 | V309: =IF(AND(N309>$V$9,N309<$V$10),M309,IF(N309=$V$10,M309,0)) -> 0 | W309: =IF(AND(N309>$W$9,N309<$W$10),M309,IF(N309=$W$10,M309,0)) -> 0 | X309: =IF(AND(N309>$X$9,N309<$X$10),M309,IF(N309=$X$10,M309,0)) -> 0 | Y309: =IF(AND(N309>$Y$9,N309<$Y$10),M309,IF(N309=$Y$10,M309,0)) -> 0 | Z309: =IF(AND(N309>$Z$9,N309<$Z$10),M309,IF(N309=$Z$10,M309,0)) -> 0 | AA309: =IF(AND(N309>$AA$9,N309<$AA$10),M309,IF(N309=$AA$10,M309,0)) -> 0 | AB309: =IF(AND(N309>$AB$9,N309<$AB$10),M309,IF(N309=$AB$10,M309,0)) -> 0 | AC309: =IF(AND(N309>$AC$9,N309<$AC$10),M309,IF(N309=$AC$10,M309,0)) -> 0 | AD309: =IF(AND(N309>$AD$9,N309<$AD$10),M309,IF(N309=$AD$10,M309,0)) -> 0 | AE309: =IF(AND(N309>$AE$9,N309<$AE$10),M309,IF(N309=$AE$10,M309,0)) -> 0 | AF309: =IF(AND(N309>$AF$9,N309<$AF$10),M309,IF(N309=$AF$10,M309,0)) -> 0 | AG309: =IF(N309=$AG$9,M309,0) -> 411.68
A310: 12110002 | B310: Information Technology system Tools | C310: FA5904220000012 | D310: 100000001 | E310: NONGHYUP BANK SYDNEY BRANCH | F310: AUD | G310: 20530.54 | H310: 20530.54 | I310: 44621 | J310: 46387 | L310: =A310&"_"&F310&"_"&D310&"_"&E310 -> 12110002_AUD_100000001_NONGHYUP BANK SYDNEY BRANCH | M310: =IF(COUNTIF($A$2:$A$8,A310)>0,-H310,H310) -> 20530.54 | N310: =IF(OR(L310=$L$2,L310=$L$3),$M$10+1,IFERROR(VLOOKUP(A310,'Repricing Maturity Adj.'!$A$3:$C$170,3,0),(IF(K310<$M$10,"Check",K310)))) -> Non_sensitive | O310: =M310=SUM(Q310:AG310) -> TRUE | P310: =IF(A310="","N/A",IF(COUNTIF($A$2:$A$7,A310)>0,"Liability",IF(COUNTIF($A$8,A310)>0,"Asset",IF(A310<20000000,"Asset",IF(AND(A310>20000000,A310<28800000),"Liability",IF(A310>28800000,"Equity","")))))) -> Asset | Q310: =IF(AND(N310>$Q$9,N310<$Q$10),M310,IF(N310=$Q$10,M310,0)) -> 0 | R310: =IF(AND(N310>$R$9,N310<$R$10),M310,IF(N310=$R$10,M310,0)) -> 0 | S310: =IF(AND(N310>$S$9,N310<$S$10),M310,IF(N310=$S$10,M310,0)) -> 0 | T310: =IF(AND(N310>$T$9,N310<$T$10),M310,IF(N310=$T$10,M310,0)) -> 0 | U310: =IF(AND(N310>$U$9,N310<$U$10),M310,IF(N310=$U$10,M310,0)) -> 0 | V310: =IF(AND(N310>$V$9,N310<$V$10),M310,IF(N310=$V$10,M310,0)) -> 0 | W310: =IF(AND(N310>$W$9,N310<$W$10),M310,IF(N310=$W$10,M310,0)) -> 0 | X310: =IF(AND(N310>$X$9,N310<$X$10),M310,IF(N310=$X$10,M310,0)) -> 0 | Y310: =IF(AND(N310>$Y$9,N310<$Y$10),M310,IF(N310=$Y$10,M310,0)) -> 0 | Z310: =IF(AND(N310>$Z$9,N310<$Z$10),M310,IF(N310=$Z$10,M310,0)) -> 0 | AA310: =IF(AND(N310>$AA$9,N310<$AA$10),M310,IF(N310=$AA$10,M310,0)) -> 0 | AB310: =IF(AND(N310>$AB$9,N310<$AB$10),M310,IF(N310=$AB$10,M310,0)) -> 0 | AC310: =IF(AND(N310>$AC$9,N310<$AC$10),M310,IF(N310=$AC$10,M310,0)) -> 0 | AD310: =IF(AND(N310>$AD$9,N310<$AD$10),M310,IF(N310=$AD$10,M310,0)) -> 0 | AE310: =IF(AND(N310>$AE$9,N310<$AE$10),M310,IF(N310=$AE$10,M310,0)) -> 0 | AF310: =IF(AND(N310>$AF$9,N310<$AF$10),M310,IF(N310=$AF$10,M310,0)) -> 0 | AG310: =IF(N310=$AG$9,M310,0) -> 20530.54
A311: 12110002 | B311: Information Technology system Tools | C311: FA5904220000013 | D311: 100000001 | E311: NONGHYUP BANK SYDNEY BRANCH | F311: AUD | G311: 1217.84 | H311: 1217.84 | I311: 44621 | J311: 45961 | L311: =A311&"_"&F311&"_"&D311&"_"&E311 -> 12110002_AUD_100000001_NONGHYUP BANK SYDNEY BRANCH | M311: =IF(COUNTIF($A$2:$A$8,A311)>0,-H311,H311) -> 1217.84 | N311: =IF(OR(L311=$L$2,L311=$L$3),$M$10+1,IFERROR(VLOOKUP(A311,'Repricing Maturity Adj.'!$A$3:$C$170,3,0),(IF(K311<$M$10,"Check",K311)))) -> Non_sensitive | O311: =M311=SUM(Q311:AG311) -> TRUE | P311: =IF(A311="","N/A",IF(COUNTIF($A$2:$A$7,A311)>0,"Liability",IF(COUNTIF($A$8,A311)>0,"Asset",IF(A311<20000000,"Asset",IF(AND(A311>20000000,A311<28800000),"Liability",IF(A311>28800000,"Equity","")))))) -> Asset | Q311: =IF(AND(N311>$Q$9,N311<$Q$10),M311,IF(N311=$Q$10,M311,0)) -> 0 | R311: =IF(AND(N311>$R$9,N311<$R$10),M311,IF(N311=$R$10,M311,0)) -> 0 | S311: =IF(AND(N311>$S$9,N311<$S$10),M311,IF(N311=$S$10,M311,0)) -> 0 | T311: =IF(AND(N311>$T$9,N311<$T$10),M311,IF(N311=$T$10,M311,0)) -> 0 | U311: =IF(AND(N311>$U$9,N311<$U$10),M311,IF(N311=$U$10,M311,0)) -> 0 | V311: =IF(AND(N311>$V$9,N311<$V$10),M311,IF(N311=$V$10,M311,0)) -> 0 | W311: =IF(AND(N311>$W$9,N311<$W$10),M311,IF(N311=$W$10,M311,0)) -> 0 | X311: =IF(AND(N311>$X$9,N311<$X$10),M311,IF(N311=$X$10,M311,0)) -> 0 | Y311: =IF(AND(N311>$Y$9,N311<$Y$10),M311,IF(N311=$Y$10,M311,0)) -> 0 | Z311: =IF(AND(N311>$Z$9,N311<$Z$10),M311,IF(N311=$Z$10,M311,0)) -> 0 | AA311: =IF(AND(N311>$AA$9,N311<$AA$10),M311,IF(N311=$AA$10,M311,0)) -> 0 | AB311: =IF(AND(N311>$AB$9,N311<$AB$10),M311,IF(N311=$AB$10,M311,0)) -> 0 | AC311: =IF(AND(N311>$AC$9,N311<$AC$10),M311,IF(N311=$AC$10,M311,0)) -> 0 | AD311: =IF(AND(N311>$AD$9,N311<$AD$10),M311,IF(N311=$AD$10,M311,0)) -> 0 | AE311: =IF(AND(N311>$AE$9,N311<$AE$10),M311,IF(N311=$AE$10,M311,0)) -> 0 | AF311: =IF(AND(N311>$AF$9,N311<$AF$10),M311,IF(N311=$AF$10,M311,0)) -> 0 | AG311: =IF(N311=$AG$9,M311,0) -> 1217.84
A312: 12110002 | B312: Information Technology system Tools | C312: FA5904220000015 | D312: 100000001 | E312: NONGHYUP BANK SYDNEY BRANCH | F312: AUD | G312: 446.28 | H312: 446.28 | I312: 44621 | J312: 46387 | L312: =A312&"_"&F312&"_"&D312&"_"&E312 -> 12110002_AUD_100000001_NONGHYUP BANK SYDNEY BRANCH | M312: =IF(COUNTIF($A$2:$A$8,A312)>0,-H312,H312) -> 446.28 | N312: =IF(OR(L312=$L$2,L312=$L$3),$M$10+1,IFERROR(VLOOKUP(A312,'Repricing Maturity Adj.'!$A$3:$C$170,3,0),(IF(K312<$M$10,"Check",K312)))) -> Non_sensitive | O312: =M312=SUM(Q312:AG312) -> TRUE | P312: =IF(A312="","N/A",IF(COUNTIF($A$2:$A$7,A312)>0,"Liability",IF(COUNTIF($A$8,A312)>0,"Asset",IF(A312<20000000,"Asset",IF(AND(A312>20000000,A312<28800000),"Liability",IF(A312>28800000,"Equity","")))))) -> Asset | Q312: =IF(AND(N312>$Q$9,N312<$Q$10),M312,IF(N312=$Q$10,M312,0)) -> 0 | R312: =IF(AND(N312>$R$9,N312<$R$10),M312,IF(N312=$R$10,M312,0)) -> 0 | S312: =IF(AND(N312>$S$9,N312<$S$10),M312,IF(N312=$S$10,M312,0)) -> 0 | T312: =IF(AND(N312>$T$9,N312<$T$10),M312,IF(N312=$T$10,M312,0)) -> 0 | U312: =IF(AND(N312>$U$9,N312<$U$10),M312,IF(N312=$U$10,M312,0)) -> 0 | V312: =IF(AND(N312>$V$9,N312<$V$10),M312,IF(N312=$V$10,M312,0)) -> 0 | W312: =IF(AND(N312>$W$9,N312<$W$10),M312,IF(N312=$W$10,M312,0)) -> 0 | X312: =IF(AND(N312>$X$9,N312<$X$10),M312,IF(N312=$X$10,M312,0)) -> 0 | Y312: =IF(AND(N312>$Y$9,N312<$Y$10),M312,IF(N312=$Y$10,M312,0)) -> 0 | Z312: =IF(AND(N312>$Z$9,N312<$Z$10),M312,IF(N312=$Z$10,M312,0)) -> 0 | AA312: =IF(AND(N312>$AA$9,N312<$AA$10),M312,IF(N312=$AA$10,M312,0)) -> 0 | AB312: =IF(AND(N312>$AB$9,N312<$AB$10),M312,IF(N312=$AB$10,M312,0)) -> 0 | AC312: =IF(AND(N312>$AC$9,N312<$AC$10),M312,IF(N312=$AC$10,M312,0)) -> 0 | AD312: =IF(AND(N312>$AD$9,N312<$AD$10),M312,IF(N312=$AD$10,M312,0)) -> 0 | AE312: =IF(AND(N312>$AE$9,N312<$AE$10),M312,IF(N312=$AE$10,M312,0)) -> 0 | AF312: =IF(AND(N312>$AF$9,N312<$AF$10),M312,IF(N312=$AF$10,M312,0)) -> 0 | AG312: =IF(N312=$AG$9,M312,0) -> 446.28
A313: 12110002 | B313: Information Technology system Tools | C313: FA5904220000018 | D313: 100000001 | E313: NONGHYUP BANK SYDNEY BRANCH | F313: AUD | G313: 3984.87 | H313: 3984.87 | I313: 44621 | J313: 46387 | L313: =A313&"_"&F313&"_"&D313&"_"&E313 -> 12110002_AUD_100000001_NONGHYUP BANK SYDNEY BRANCH | M313: =IF(COUNTIF($A$2:$A$8,A313)>0,-H313,H313) -> 3984.87 | N313: =IF(OR(L313=$L$2,L313=$L$3),$M$10+1,IFERROR(VLOOKUP(A313,'Repricing Maturity Adj.'!$A$3:$C$170,3,0),(IF(K313<$M$10,"Check",K313)))) -> Non_sensitive | O313: =M313=SUM(Q313:AG313) -> TRUE | P313: =IF(A313="","N/A",IF(COUNTIF($A$2:$A$7,A313)>0,"Liability",IF(COUNTIF($A$8,A313)>0,"Asset",IF(A313<20000000,"Asset",IF(AND(A313>20000000,A313<28800000),"Liability",IF(A313>28800000,"Equity","")))))) -> Asset | Q313: =IF(AND(N313>$Q$9,N313<$Q$10),M313,IF(N313=$Q$10,M313,0)) -> 0 | R313: =IF(AND(N313>$R$9,N313<$R$10),M313,IF(N313=$R$10,M313,0)) -> 0 | S313: =IF(AND(N313>$S$9,N313<$S$10),M313,IF(N313=$S$10,M313,0)) -> 0 | T313: =IF(AND(N313>$T$9,N313<$T$10),M313,IF(N313=$T$10,M313,0)) -> 0 | U313: =IF(AND(N313>$U$9,N313<$U$10),M313,IF(N313=$U$10,M313,0)) -> 0 | V313: =IF(AND(N313>$V$9,N313<$V$10),M313,IF(N313=$V$10,M313,0)) -> 0 | W313: =IF(AND(N313>$W$9,N313<$W$10),M313,IF(N313=$W$10,M313,0)) -> 0 | X313: =IF(AND(N313>$X$9,N313<$X$10),M313,IF(N313=$X$10,M313,0)) -> 0 | Y313: =IF(AND(N313>$Y$9,N313<$Y$10),M313,IF(N313=$Y$10,M313,0)) -> 0 | Z313: =IF(AND(N313>$Z$9,N313<$Z$10),M313,IF(N313=$Z$10,M313,0)) -> 0 | AA313: =IF(AND(N313>$AA$9,N313<$AA$10),M313,IF(N313=$AA$10,M313,0)) -> 0 | AB313: =IF(AND(N313>$AB$9,N313<$AB$10),M313,IF(N313=$AB$10,M313,0)) -> 0 | AC313: =IF(AND(N313>$AC$9,N313<$AC$10),M313,IF(N313=$AC$10,M313,0)) -> 0 | AD313: =IF(AND(N313>$AD$9,N313<$AD$10),M313,IF(N313=$AD$10,M313,0)) -> 0 | AE313: =IF(AND(N313>$AE$9,N313<$AE$10),M313,IF(N313=$AE$10,M313,0)) -> 0 | AF313: =IF(AND(N313>$AF$9,N313<$AF$10),M313,IF(N313=$AF$10,M313,0)) -> 0 | AG313: =IF(N313=$AG$9,M313,0) -> 3984.87
A314: 12110002 | B314: Information Technology system Tools | C314: FA5904220000019 | D314: 100000001 | E314: NONGHYUP BANK SYDNEY BRANCH | F314: AUD | G314: 88233.69 | H314: 88233.69 | I314: 44621 | J314: 46387 | L314: =A314&"_"&F314&"_"&D314&"_"&E314 -> 12110002_AUD_100000001_NONGHYUP BANK SYDNEY BRANCH | M314: =IF(COUNTIF($A$2:$A$8,A314)>0,-H314,H314) -> 88233.69 | N314: =IF(OR(L314=$L$2,L314=$L$3),$M$10+1,IFERROR(VLOOKUP(A314,'Repricing Maturity Adj.'!$A$3:$C$170,3,0),(IF(K314<$M$10,"Check",K314)))) -> Non_sensitive | O314: =M314=SUM(Q314:AG314) -> TRUE | P314: =IF(A314="","N/A",IF(COUNTIF($A$2:$A$7,A314)>0,"Liability",IF(COUNTIF($A$8,A314)>0,"Asset",IF(A314<20000000,"Asset",IF(AND(A314>20000000,A314<28800000),"Liability",IF(A314>28800000,"Equity","")))))) -> Asset | Q314: =IF(AND(N314>$Q$9,N314<$Q$10),M314,IF(N314=$Q$10,M314,0)) -> 0 | R314: =IF(AND(N314>$R$9,N314<$R$10),M314,IF(N314=$R$10,M314,0)) -> 0 | S314: =IF(AND(N314>$S$9,N314<$S$10),M314,IF(N314=$S$10,M314,0)) -> 0 | T314: =IF(AND(N314>$T$9,N314<$T$10),M314,IF(N314=$T$10,M314,0)) -> 0 | U314: =IF(AND(N314>$U$9,N314<$U$10),M314,IF(N314=$U$10,M314,0)) -> 0 | V314: =IF(AND(N314>$V$9,N314<$V$10),M314,IF(N314=$V$10,M314,0)) -> 0 | W314: =IF(AND(N314>$W$9,N314<$W$10),M314,IF(N314=$W$10,M314,0)) -> 0 | X314: =IF(AND(N314>$X$9,N314<$X$10),M314,IF(N314=$X$10,M314,0)) -> 0 | Y314: =IF(AND(N314>$Y$9,N314<$Y$10),M314,IF(N314=$Y$10,M314,0)) -> 0 | Z314: =IF(AND(N314>$Z$9,N314<$Z$10),M314,IF(N314=$Z$10,M314,0)) -> 0 | AA314: =IF(AND(N314>$AA$9,N314<$AA$10),M314,IF(N314=$AA$10,M314,0)) -> 0 | AB314: =IF(AND(N314>$AB$9,N314<$AB$10),M314,IF(N314=$AB$10,M314,0)) -> 0 | AC314: =IF(AND(N314>$AC$9,N314<$AC$10),M314,IF(N314=$AC$10,M314,0)) -> 0 | AD314: =IF(AND(N314>$AD$9,N314<$AD$10),M314,IF(N314=$AD$10,M314,0)) -> 0 | AE314: =IF(AND(N314>$AE$9,N314<$AE$10),M314,IF(N314=$AE$10,M314,0)) -> 0 | AF314: =IF(AND(N314>$AF$9,N314<$AF$10),M314,IF(N314=$AF$10,M314,0)) -> 0 | AG314: =IF(N314=$AG$9,M314,0) -> 88233.69
... A343: 12110002 | B343: Information Technology system Tools | C343: FA5904250000010 | D343: 100000001 | E343: NONGHYUP BANK SYDNEY BRANCH | F343: AUD | G343: 1698.99 | H343: 1698.99 | I343: 45727 | J343: 47177 | L343: =A343&"_"&F343&"_"&D343&"_"&E343 -> 12110002_AUD_100000001_NONGHYUP BANK SYDNEY BRANCH | M343: =IF(COUNTIF($A$2:$A$8,A343)>0,-H343,H343) -> 1698.99 | N343: =IF(OR(L343=$L$2,L343=$L$3),$M$10+1,IFERROR(VLOOKUP(A343,'Repricing Maturity Adj.'!$A$3:$C$170,3,0),(IF(K343<$M$10,"Check",K343)))) -> Non_sensitive | O343: =M343=SUM(Q343:AG343) -> TRUE | P343: =IF(A343="","N/A",IF(COUNTIF($A$2:$A$7,A343)>0,"Liability",IF(COUNTIF($A$8,A343)>0,"Asset",IF(A343<20000000,"Asset",IF(AND(A343>20000000,A343<28800000),"Liability",IF(A343>28800000,"Equity","")))))) -> Asset | Q343: =IF(AND(N343>$Q$9,N343<$Q$10),M343,IF(N343=$Q$10,M343,0)) -> 0 | R343: =IF(AND(N343>$R$9,N343<$R$10),M343,IF(N343=$R$10,M343,0)) -> 0 | S343: =IF(AND(N343>$S$9,N343<$S$10),M343,IF(N343=$S$10,M343,0)) -> 0 | T343: =IF(AND(N343>$T$9,N343<$T$10),M343,IF(N343=$T$10,M343,0)) -> 0 | U343: =IF(AND(N343>$U$9,N343<$U$10),M343,IF(N343=$U$10,M343,0)) -> 0 | V343: =IF(AND(N343>$V$9,N343<$V$10),M343,IF(N343=$V$10,M343,0)) -> 0 | W343: =IF(AND(N343>$W$9,N343<$W$10),M343,IF(N343=$W$10,M343,0)) -> 0 | X343: =IF(AND(N343>$X$9,N343<$X$10),M343,IF(N343=$X$10,M343,0)) -> 0 | Y343: =IF(AND(N343>$Y$9,N343<$Y$10),M343,IF(N343=$Y$10,M343,0)) -> 0 | Z343: =IF(AND(N343>$Z$9,N343<$Z$10),M343,IF(N343=$Z$10,M343,0)) -> 0 | AA343: =IF(AND(N343>$AA$9,N343<$AA$10),M343,IF(N343=$AA$10,M343,0)) -> 0 | AB343: =IF(AND(N343>$AB$9,N343<$AB$10),M343,IF(N343=$AB$10,M343,0)) -> 0 | AC343: =IF(AND(N343>$AC$9,N343<$AC$10),M343,IF(N343=$AC$10,M343,0)) -> 0 | AD343: =IF(AND(N343>$AD$9,N343<$AD$10),M343,IF(N343=$AD$10,M343,0)) -> 0 | AE343: =IF(AND(N343>$AE$9,N343<$AE$10),M343,IF(N343=$AE$10,M343,0)) -> 0 | AF343: =IF(AND(N343>$AF$9,N343<$AF$10),M343,IF(N343=$AF$10,M343,0)) -> 0 | AG343: =IF(N343=$AG$9,M343,0) -> 1698.99
A344: 12110002 | B344: Information Technology system Tools | C344: OT5904INPT001AUD | D344: 100000001 | E344: NONGHYUP BANK SYDNEY BRANCH | F344: AUD | G344: -424.08 | H344: -424.08 | L344: =A344&"_"&F344&"_"&D344&"_"&E344 -> 12110002_AUD_100000001_NONGHYUP BANK SYDNEY BRANCH | M344: =IF(COUNTIF($A$2:$A$8,A344)>0,-H344,H344) -> -424.08 | N344: =IF(OR(L344=$L$2,L344=$L$3),$M$10+1,IFERROR(VLOOKUP(A344,'Repricing Maturity Adj.'!$A$3:$C$170,3,0),(IF(K344<$M$10,"Check",K344)))) -> Non_sensitive | O344: =M344=SUM(Q344:AG344) -> TRUE | P344: =IF(A344="","N/A",IF(COUNTIF($A$2:$A$7,A344)>0,"Liability",IF(COUNTIF($A$8,A344)>0,"Asset",IF(A344<20000000,"Asset",IF(AND(A344>20000000,A344<28800000),"Liability",IF(A344>28800000,"Equity","")))))) -> Asset | Q344: =IF(AND(N344>$Q$9,N344<$Q$10),M344,IF(N344=$Q$10,M344,0)) -> 0 | R344: =IF(AND(N344>$R$9,N344<$R$10),M344,IF(N344=$R$10,M344,0)) -> 0 | S344: =IF(AND(N344>$S$9,N344<$S$10),M344,IF(N344=$S$10,M344,0)) -> 0 | T344: =IF(AND(N344>$T$9,N344<$T$10),M344,IF(N344=$T$10,M344,0)) -> 0 | U344: =IF(AND(N344>$U$9,N344<$U$10),M344,IF(N344=$U$10,M344,0)) -> 0 | V344: =IF(AND(N344>$V$9,N344<$V$10),M344,IF(N344=$V$10,M344,0)) -> 0 | W344: =IF(AND(N344>$W$9,N344<$W$10),M344,IF(N344=$W$10,M344,0)) -> 0 | X344: =IF(AND(N344>$X$9,N344<$X$10),M344,IF(N344=$X$10,M344,0)) -> 0 | Y344: =IF(AND(N344>$Y$9,N344<$Y$10),M344,IF(N344=$Y$10,M344,0)) -> 0 | Z344: =IF(AND(N344>$Z$9,N344<$Z$10),M344,IF(N344=$Z$10,M344,0)) -> 0 | AA344: =IF(AND(N344>$AA$9,N344<$AA$10),M344,IF(N344=$AA$10,M344,0)) -> 0 | AB344: =IF(AND(N344>$AB$9,N344<$AB$10),M344,IF(N344=$AB$10,M344,0)) -> 0 | AC344: =IF(AND(N344>$AC$9,N344<$AC$10),M344,IF(N344=$AC$10,M344,0)) -> 0 | AD344: =IF(AND(N344>$AD$9,N344<$AD$10),M344,IF(N344=$AD$10,M344,0)) -> 0 | AE344: =IF(AND(N344>$AE$9,N344<$AE$10),M344,IF(N344=$AE$10,M344,0)) -> 0 | AF344: =IF(AND(N344>$AF$9,N344<$AF$10),M344,IF(N344=$AF$10,M344,0)) -> 0 | AG344: =IF(N344=$AG$9,M344,0) -> -424.08
A345: 12110004 | B345: Equipment and management tools | C345: FA5904220000007 | D345: 100000001 | E345: NONGHYUP BANK SYDNEY BRANCH | F345: AUD | G345: 3408 | H345: 3408 | I345: 44621 | J345: 46446 | L345: =A345&"_"&F345&"_"&D345&"_"&E345 -> 12110004_AUD_100000001_NONGHYUP BANK SYDNEY BRANCH | M345: =IF(COUNTIF($A$2:$A$8,A345)>0,-H345,H345) -> 3408 | N345: =IF(OR(L345=$L$2,L345=$L$3),$M$10+1,IFERROR(VLOOKUP(A345,'Repricing Maturity Adj.'!$A$3:$C$170,3,0),(IF(K345<$M$10,"Check",K345)))) -> Non_sensitive | O345: =M345=SUM(Q345:AG345) -> TRUE | P345: =IF(A345="","N/A",IF(COUNTIF($A$2:$A$7,A345)>0,"Liability",IF(COUNTIF($A$8,A345)>0,"Asset",IF(A345<20000000,"Asset",IF(AND(A345>20000000,A345<28800000),"Liability",IF(A345>28800000,"Equity","")))))) -> Asset | Q345: =IF(AND(N345>$Q$9,N345<$Q$10),M345,IF(N345=$Q$10,M345,0)) -> 0 | R345: =IF(AND(N345>$R$9,N345<$R$10),M345,IF(N345=$R$10,M345,0)) -> 0 | S345: =IF(AND(N345>$S$9,N345<$S$10),M345,IF(N345=$S$10,M345,0)) -> 0 | T345: =IF(AND(N345>$T$9,N345<$T$10),M345,IF(N345=$T$10,M345,0)) -> 0 | U345: =IF(AND(N345>$U$9,N345<$U$10),M345,IF(N345=$U$10,M345,0)) -> 0 | V345: =IF(AND(N345>$V$9,N345<$V$10),M345,IF(N345=$V$10,M345,0)) -> 0 | W345: =IF(AND(N345>$W$9,N345<$W$10),M345,IF(N345=$W$10,M345,0)) -> 0 | X345: =IF(AND(N345>$X$9,N345<$X$10),M345,IF(N345=$X$10,M345,0)) -> 0 | Y345: =IF(AND(N345>$Y$9,N345<$Y$10),M345,IF(N345=$Y$10,M345,0)) -> 0 | Z345: =IF(AND(N345>$Z$9,N345<$Z$10),M345,IF(N345=$Z$10,M345,0)) -> 0 | AA345: =IF(AND(N345>$AA$9,N345<$AA$10),M345,IF(N345=$AA$10,M345,0)) -> 0 | AB345: =IF(AND(N345>$AB$9,N345<$AB$10),M345,IF(N345=$AB$10,M345,0)) -> 0 | AC345: =IF(AND(N345>$AC$9,N345<$AC$10),M345,IF(N345=$AC$10,M345,0)) -> 0 | AD345: =IF(AND(N345>$AD$9,N345<$AD$10),M345,IF(N345=$AD$10,M345,0)) -> 0 | AE345: =IF(AND(N345>$AE$9,N345<$AE$10),M345,IF(N345=$AE$10,M345,0)) -> 0 | AF345: =IF(AND(N345>$AF$9,N345<$AF$10),M345,IF(N345=$AF$10,M345,0)) -> 0 | AG345: =IF(N345=$AG$9,M345,0) -> 3408
A346: 12110004 | B346: Equipment and management tools | C346: FA5904220000024 | D346: 100000001 | E346: NONGHYUP BANK SYDNEY BRANCH | F346: AUD | G346: 985.68 | H346: 985.68 | I346: 44621 | J346: 46387 | L346: =A346&"_"&F346&"_"&D346&"_"&E346 -> 12110004_AUD_100000001_NONGHYUP BANK SYDNEY BRANCH | M346: =IF(COUNTIF($A$2:$A$8,A346)>0,-H346,H346) -> 985.68 | N346: =IF(OR(L346=$L$2,L346=$L$3),$M$10+1,IFERROR(VLOOKUP(A346,'Repricing Maturity Adj.'!$A$3:$C$170,3,0),(IF(K346<$M$10,"Check",K346)))) -> Non_sensitive | O346: =M346=SUM(Q346:AG346) -> TRUE | P346: =IF(A346="","N/A",IF(COUNTIF($A$2:$A$7,A346)>0,"Liability",IF(COUNTIF($A$8,A346)>0,"Asset",IF(A346<20000000,"Asset",IF(AND(A346>20000000,A346<28800000),"Liability",IF(A346>28800000,"Equity","")))))) -> Asset | Q346: =IF(AND(N346>$Q$9,N346<$Q$10),M346,IF(N346=$Q$10,M346,0)) -> 0 | R346: =IF(AND(N346>$R$9,N346<$R$10),M346,IF(N346=$R$10,M346,0)) -> 0 | S346: =IF(AND(N346>$S$9,N346<$S$10),M346,IF(N346=$S$10,M346,0)) -> 0 | T346: =IF(AND(N346>$T$9,N346<$T$10),M346,IF(N346=$T$10,M346,0)) -> 0 | U346: =IF(AND(N346>$U$9,N346<$U$10),M346,IF(N346=$U$10,M346,0)) -> 0 | V346: =IF(AND(N346>$V$9,N346<$V$10),M346,IF(N346=$V$10,M346,0)) -> 0 | W346: =IF(AND(N346>$W$9,N346<$W$10),M346,IF(N346=$W$10,M346,0)) -> 0 | X346: =IF(AND(N346>$X$9,N346<$X$10),M346,IF(N346=$X$10,M346,0)) -> 0 | Y346: =IF(AND(N346>$Y$9,N346<$Y$10),M346,IF(N346=$Y$10,M346,0)) -> 0 | Z346: =IF(AND(N346>$Z$9,N346<$Z$10),M346,IF(N346=$Z$10,M346,0)) -> 0 | AA346: =IF(AND(N346>$AA$9,N346<$AA$10),M346,IF(N346=$AA$10,M346,0)) -> 0 | AB346: =IF(AND(N346>$AB$9,N346<$AB$10),M346,IF(N346=$AB$10,M346,0)) -> 0 | AC346: =IF(AND(N346>$AC$9,N346<$AC$10),M346,IF(N346=$AC$10,M346,0)) -> 0 | AD346: =IF(AND(N346>$AD$9,N346<$AD$10),M346,IF(N346=$AD$10,M346,0)) -> 0 | AE346: =IF(AND(N346>$AE$9,N346<$AE$10),M346,IF(N346=$AE$10,M346,0)) -> 0 | AF346: =IF(AND(N346>$AF$9,N346<$AF$10),M346,IF(N346=$AF$10,M346,0)) -> 0 | AG346: =IF(N346=$AG$9,M346,0) -> 985.68
A347: 12110004 | B347: Equipment and management tools | C347: FA5904220000026 | D347: 100000001 | E347: NONGHYUP BANK SYDNEY BRANCH | F347: AUD | G347: 2919.56 | H347: 2919.56 | I347: 44621 | J347: 46387 | L347: =A347&"_"&F347&"_"&D347&"_"&E347 -> 12110004_AUD_100000001_NONGHYUP BANK SYDNEY BRANCH | M347: =IF(COUNTIF($A$2:$A$8,A347)>0,-H347,H347) -> 2919.56 | N347: =IF(OR(L347=$L$2,L347=$L$3),$M$10+1,IFERROR(VLOOKUP(A347,'Repricing Maturity Adj.'!$A$3:$C$170,3,0),(IF(K347<$M$10,"Check",K347)))) -> Non_sensitive | O347: =M347=SUM(Q347:AG347) -> TRUE | P347: =IF(A347="","N/A",IF(COUNTIF($A$2:$A$7,A347)>0,"Liability",IF(COUNTIF($A$8,A347)>0,"Asset",IF(A347<20000000,"Asset",IF(AND(A347>20000000,A347<28800000),"Liability",IF(A347>28800000,"Equity","")))))) -> Asset | Q347: =IF(AND(N347>$Q$9,N347<$Q$10),M347,IF(N347=$Q$10,M347,0)) -> 0 | R347: =IF(AND(N347>$R$9,N347<$R$10),M347,IF(N347=$R$10,M347,0)) -> 0 | S347: =IF(AND(N347>$S$9,N347<$S$10),M347,IF(N347=$S$10,M347,0)) -> 0 | T347: =IF(AND(N347>$T$9,N347<$T$10),M347,IF(N347=$T$10,M347,0)) -> 0 | U347: =IF(AND(N347>$U$9,N347<$U$10),M347,IF(N347=$U$10,M347,0)) -> 0 | V347: =IF(AND(N347>$V$9,N347<$V$10),M347,IF(N347=$V$10,M347,0)) -> 0 | W347: =IF(AND(N347>$W$9,N347<$W$10),M347,IF(N347=$W$10,M347,0)) -> 0 | X347: =IF(AND(N347>$X$9,N347<$X$10),M347,IF(N347=$X$10,M347,0)) -> 0 | Y347: =IF(AND(N347>$Y$9,N347<$Y$10),M347,IF(N347=$Y$10,M347,0)) -> 0 | Z347: =IF(AND(N347>$Z$9,N347<$Z$10),M347,IF(N347=$Z$10,M347,0)) -> 0 | AA347: =IF(AND(N347>$AA$9,N347<$AA$10),M347,IF(N347=$AA$10,M347,0)) -> 0 | AB347: =IF(AND(N347>$AB$9,N347<$AB$10),M347,IF(N347=$AB$10,M347,0)) -> 0 | AC347: =IF(AND(N347>$AC$9,N347<$AC$10),M347,IF(N347=$AC$10,M347,0)) -> 0 | AD347: =IF(AND(N347>$AD$9,N347<$AD$10),M347,IF(N347=$AD$10,M347,0)) -> 0 | AE347: =IF(AND(N347>$AE$9,N347<$AE$10),M347,IF(N347=$AE$10,M347,0)) -> 0 | AF347: =IF(AND(N347>$AF$9,N347<$AF$10),M347,IF(N347=$AF$10,M347,0)) -> 0 | AG347: =IF(N347=$AG$9,M347,0) -> 2919.56
A348: 12110004 | B348: Equipment and management tools | C348: FA5904220000028 | D348: 100000001 | E348: NONGHYUP BANK SYDNEY BRANCH | F348: AUD | G348: 15078.57 | H348: 15078.57 | I348: 44621 | J348: 46387 | L348: =A348&"_"&F348&"_"&D348&"_"&E348 -> 12110004_AUD_100000001_NONGHYUP BANK SYDNEY BRANCH | M348: =IF(COUNTIF($A$2:$A$8,A348)>0,-H348,H348) -> 15078.57 | N348: =IF(OR(L348=$L$2,L348=$L$3),$M$10+1,IFERROR(VLOOKUP(A348,'Repricing Maturity Adj.'!$A$3:$C$170,3,0),(IF(K348<$M$10,"Check",K348)))) -> Non_sensitive | O348: =M348=SUM(Q348:AG348) -> TRUE | P348: =IF(A348="","N/A",IF(COUNTIF($A$2:$A$7,A348)>0,"Liability",IF(COUNTIF($A$8,A348)>0,"Asset",IF(A348<20000000,"Asset",IF(AND(A348>20000000,A348<28800000),"Liability",IF(A348>28800000,"Equity","")))))) -> Asset | Q348: =IF(AND(N348>$Q$9,N348<$Q$10),M348,IF(N348=$Q$10,M348,0)) -> 0 | R348: =IF(AND(N348>$R$9,N348<$R$10),M348,IF(N348=$R$10,M348,0)) -> 0 | S348: =IF(AND(N348>$S$9,N348<$S$10),M348,IF(N348=$S$10,M348,0)) -> 0 | T348: =IF(AND(N348>$T$9,N348<$T$10),M348,IF(N348=$T$10,M348,0)) -> 0 | U348: =IF(AND(N348>$U$9,N348<$U$10),M348,IF(N348=$U$10,M348,0)) -> 0 | V348: =IF(AND(N348>$V$9,N348<$V$10),M348,IF(N348=$V$10,M348,0)) -> 0 | W348: =IF(AND(N348>$W$9,N348<$W$10),M348,IF(N348=$W$10,M348,0)) -> 0 | X348: =IF(AND(N348>$X$9,N348<$X$10),M348,IF(N348=$X$10,M348,0)) -> 0 | Y348: =IF(AND(N348>$Y$9,N348<$Y$10),M348,IF(N348=$Y$10,M348,0)) -> 0 | Z348: =IF(AND(N348>$Z$9,N348<$Z$10),M348,IF(N348=$Z$10,M348,0)) -> 0 | AA348: =IF(AND(N348>$AA$9,N348<$AA$10),M348,IF(N348=$AA$10,M348,0)) -> 0 | AB348: =IF(AND(N348>$AB$9,N348<$AB$10),M348,IF(N348=$AB$10,M348,0)) -> 0 | AC348: =IF(AND(N348>$AC$9,N348<$AC$10),M348,IF(N348=$AC$10,M348,0)) -> 0 | AD348: =IF(AND(N348>$AD$9,N348<$AD$10),M348,IF(N348=$AD$10,M348,0)) -> 0 | AE348: =IF(AND(N348>$AE$9,N348<$AE$10),M348,IF(N348=$AE$10,M348,0)) -> 0 | AF348: =IF(AND(N348>$AF$9,N348<$AF$10),M348,IF(N348=$AF$10,M348,0)) -> 0 | AG348: =IF(N348=$AG$9,M348,0) -> 15078.57
A349: 12110004 | B349: Equipment and management tools | C349: FA5904230000011 | D349: 100000001 | E349: NONGHYUP BANK SYDNEY BRANCH | F349: AUD | G349: 19445.8 | H349: 19445.8 | I349: 45252 | J349: 47087 | L349: =A349&"_"&F349&"_"&D349&"_"&E349 -> 12110004_AUD_100000001_NONGHYUP BANK SYDNEY BRANCH | M349: =IF(COUNTIF($A$2:$A$8,A349)>0,-H349,H349) -> 19445.8 | N349: =IF(OR(L349=$L$2,L349=$L$3),$M$10+1,IFERROR(VLOOKUP(A349,'Repricing Maturity Adj.'!$A$3:$C$170,3,0),(IF(K349<$M$10,"Check",K349)))) -> Non_sensitive | O349: =M349=SUM(Q349:AG349) -> TRUE | P349: =IF(A349="","N/A",IF(COUNTIF($A$2:$A$7,A349)>0,"Liability",IF(COUNTIF($A$8,A349)>0,"Asset",IF(A349<20000000,"Asset",IF(AND(A349>20000000,A349<28800000),"Liability",IF(A349>28800000,"Equity","")))))) -> Asset | Q349: =IF(AND(N349>$Q$9,N349<$Q$10),M349,IF(N349=$Q$10,M349,0)) -> 0 | R349: =IF(AND(N349>$R$9,N349<$R$10),M349,IF(N349=$R$10,M349,0)) -> 0 | S349: =IF(AND(N349>$S$9,N349<$S$10),M349,IF(N349=$S$10,M349,0)) -> 0 | T349: =IF(AND(N349>$T$9,N349<$T$10),M349,IF(N349=$T$10,M349,0)) -> 0 | U349: =IF(AND(N349>$U$9,N349<$U$10),M349,IF(N349=$U$10,M349,0)) -> 0 | V349: =IF(AND(N349>$V$9,N349<$V$10),M349,IF(N349=$V$10,M349,0)) -> 0 | W349: =IF(AND(N349>$W$9,N349<$W$10),M349,IF(N349=$W$10,M349,0)) -> 0 | X349: =IF(AND(N349>$X$9,N349<$X$10),M349,IF(N349=$X$10,M349,0)) -> 0 | Y349: =IF(AND(N349>$Y$9,N349<$Y$10),M349,IF(N349=$Y$10,M349,0)) -> 0 | Z349: =IF(AND(N349>$Z$9,N349<$Z$10),M349,IF(N349=$Z$10,M349,0)) -> 0 | AA349: =IF(AND(N349>$AA$9,N349<$AA$10),M349,IF(N349=$AA$10,M349,0)) -> 0 | AB349: =IF(AND(N349>$AB$9,N349<$AB$10),M349,IF(N349=$AB$10,M349,0)) -> 0 | AC349: =IF(AND(N349>$AC$9,N349<$AC$10),M349,IF(N349=$AC$10,M349,0)) -> 0 | AD349: =IF(AND(N349>$AD$9,N349<$AD$10),M349,IF(N349=$AD$10,M349,0)) -> 0 | AE349: =IF(AND(N349>$AE$9,N349<$AE$10),M349,IF(N349=$AE$10,M349,0)) -> 0 | AF349: =IF(AND(N349>$AF$9,N349<$AF$10),M349,IF(N349=$AF$10,M349,0)) -> 0 | AG349: =IF(N349=$AG$9,M349,0) -> 19445.8
A350: 12110004 | B350: Equipment and management tools | C350: FA5904250000011 | D350: 100000001 | E350: NONGHYUP BANK SYDNEY BRANCH | F350: AUD | G350: 1662 | H350: 1662 | I350: 45750 | J350: 47573 | L350: =A350&"_"&F350&"_"&D350&"_"&E350 -> 12110004_AUD_100000001_NONGHYUP BANK SYDNEY BRANCH | M350: =IF(COUNTIF($A$2:$A$8,A350)>0,-H350,H350) -> 1662 | N350: =IF(OR(L350=$L$2,L350=$L$3),$M$10+1,IFERROR(VLOOKUP(A350,'Repricing Maturity Adj.'!$A$3:$C$170,3,0),(IF(K350<$M$10,"Check",K350)))) -> Non_sensitive | O350: =M350=SUM(Q350:AG350) -> TRUE | P350: =IF(A350="","N/A",IF(COUNTIF($A$2:$A$7,A350)>0,"Liability",IF(COUNTIF($A$8,A350)>0,"Asset",IF(A350<20000000,"Asset",IF(AND(A350>20000000,A350<28800000),"Liability",IF(A350>28800000,"Equity","")))))) -> Asset | Q350: =IF(AND(N350>$Q$9,N350<$Q$10),M350,IF(N350=$Q$10,M350,0)) -> 0 | R350: =IF(AND(N350>$R$9,N350<$R$10),M350,IF(N350=$R$10,M350,0)) -> 0 | S350: =IF(AND(N350>$S$9,N350<$S$10),M350,IF(N350=$S$10,M350,0)) -> 0 | T350: =IF(AND(N350>$T$9,N350<$T$10),M350,IF(N350=$T$10,M350,0)) -> 0 | U350: =IF(AND(N350>$U$9,N350<$U$10),M350,IF(N350=$U$10,M350,0)) -> 0 | V350: =IF(AND(N350>$V$9,N350<$V$10),M350,IF(N350=$V$10,M350,0)) -> 0 | W350: =IF(AND(N350>$W$9,N350<$W$10),M350,IF(N350=$W$10,M350,0)) -> 0 | X350: =IF(AND(N350>$X$9,N350<$X$10),M350,IF(N350=$X$10,M350,0)) -> 0 | Y350: =IF(AND(N350>$Y$9,N350<$Y$10),M350,IF(N350=$Y$10,M350,0)) -> 0 | Z350: =IF(AND(N350>$Z$9,N350<$Z$10),M350,IF(N350=$Z$10,M350,0)) -> 0 | AA350: =IF(AND(N350>$AA$9,N350<$AA$10),M350,IF(N350=$AA$10,M350,0)) -> 0 | AB350: =IF(AND(N350>$AB$9,N350<$AB$10),M350,IF(N350=$AB$10,M350,0)) -> 0 | AC350: =IF(AND(N350>$AC$9,N350<$AC$10),M350,IF(N350=$AC$10,M350,0)) -> 0 | AD350: =IF(AND(N350>$AD$9,N350<$AD$10),M350,IF(N350=$AD$10,M350,0)) -> 0 | AE350: =IF(AND(N350>$AE$9,N350<$AE$10),M350,IF(N350=$AE$10,M350,0)) -> 0 | AF350: =IF(AND(N350>$AF$9,N350<$AF$10),M350,IF(N350=$AF$10,M350,0)) -> 0 | AG350: =IF(N350=$AG$9,M350,0) -> 1662
...

Sheet Summary_IRRBB
D3: Overnight (O/N) | E3: 0 to <1 month (excluding O/N) | F3: 1 to < 2 months | G3: 2 to < 3 months | H3: 3 to < 6 months | I3: 6 to < 9 months | J3: 9 to < 12 months | K3: 1 to < 2 years | L3: 2 to < 3 years | M3: 3 to < 4 years | N3: 4 to < 5 years | O3: 5 to < 7 years | P3: 7 to < 10 years | Q3: 10 to < 15 years | R3: 15 to < 20 years | S3: 20+ years | T3: Non-interest rate sensitive
C4: Asset | D4: ='RE33(IRRBB)'!Q3 -> 1.3026423e+08 | E4: ='RE33(IRRBB)'!R3 -> 82224385 | F4: ='RE33(IRRBB)'!S3 -> 17184061 | G4: ='RE33(IRRBB)'!T3 -> 28000000 | H4: ='RE33(IRRBB)'!U3 -> 10000000 | I4: ='RE33(IRRBB)'!V3 -> 5053962.5 | J4: ='RE33(IRRBB)'!W3 -> 0 | K4: ='RE33(IRRBB)'!X3 -> 16463021 | ... T4: ='RE33(IRRBB)'!AG3 -> 2765808.7
C5: Liability | D5: ='RE33(IRRBB)'!Q4 -> 0 | E5: ='RE33(IRRBB)'!R4 -> 1.1426042e+08 | F5: ='RE33(IRRBB)'!S4 -> 74955979 | G5: ='RE33(IRRBB)'!T4 -> 31437554 | H5: ='RE33(IRRBB)'!U4 -> 15718777 | I5: ='RE33(IRRBB)'!V4 -> 0 | J5: ='RE33(IRRBB)'!W4 -> 0 | K5: ='RE33(IRRBB)'!X4 -> 0 | ... T5: ='RE33(IRRBB)'!AG4 -> 55129544
C7: Net position/gap | D7: ='RE33(IRRBB)'!Q7 -> 1.3026423e+08 | E7: ='RE33(IRRBB)'!R7 -> -32036037 | F7: ='RE33(IRRBB)'!S7 -> -57771918 | G7: ='RE33(IRRBB)'!T7 -> -3437553.6 | H7: ='RE33(IRRBB)'!U7 -> -5718776.8 | I7: ='RE33(IRRBB)'!V7 -> 5053962.5 | J7: ='RE33(IRRBB)'!W7 -> 0 | K7: ='RE33(IRRBB)'!X7 -> 16463021 | ... T7: ='RE33(IRRBB)'!AG7 -> -52363735
C9: Weighting factors used in calculation of interest rate sensitivities in Table 3 (ARS 117.0)
C10: Parallel shock up | D10: 0 | E10: 0.0012 | F10: 0.0036 | G10: 0.006 | H10: 0.0107 | I10: 0.0179 | J10: 0.025 | K10: 0.0415 | L10: 0.0674 | M10: 0.0921 | N10: 0.1156 | O10: 0.1523 | P10: 0.1989 | Q10: 0.2675 | R10: 0.3364 | S10: 0.3904 | T10: 0
C11: =SUM(D11:T11) -> 445442.92 | D11: =$D$7*D10 -> 0 | E11: =$E$7*E10 -> -38443.245 | F11: =$F$7*F10 -> -207978.91 | G11: =$G$7*G10 -> -20625.321 | H11: =$H$7*H10 -> -61190.912 | I11: =$I$7*I10 -> 90465.929 | J11: =$J$7*J10 -> 0 | K11: =$K$7*K10 -> 683215.38 | L11: =$L$7*L10 -> 0 | M11: =$M$7*M10 -> 0 | N11: =$N$7*N10 -> 0 | O11: =$O$7*O10 -> 0 | P11: =$P$7*P10 -> 0 | Q11: =$Q$7*Q10 -> 0 | R11: =$R$7*R10 -> 0 | S11: =$S$7*S10 -> 0 | T11: =$T$7*T10 -> 0
C12: Parallel shock down | D12: 0 | E12: -0.0012 | F12: -0.0036 | G12: -0.006 | H12: -0.0107 | I12: -0.0179 | J12: -0.025 | K12: -0.0415 | L12: -0.0674 | M12: -0.0921 | N12: -0.1156 | O12: -0.1523 | P12: -0.1989 | Q12: -0.2675 | R12: -0.3364 | S12: -0.3904 | T12: 0
C13: =SUM(D13:T13) -> -445442.92 | D13: =$D$7*D12 -> 0 | E13: =$E$7*E12 -> 38443.245 | F13: =$F$7*F12 -> 207978.91 | G13: =$G$7*G12 -> 20625.321 | H13: =$H$7*H12 -> 61190.912 | I13: =$I$7*I12 -> -90465.929 | J13: =$J$7*J12 -> 0 | K13: =$K$7*K12 -> -683215.38 | L13: =$L$7*L12 -> 0 | M13: =$M$7*M12 -> 0 | N13: =$N$7*N12 -> 0 | O13: =$O$7*O12 -> 0 | P13: =$P$7*P12 -> 0 | Q13: =$Q$7*Q12 -> 0 | R13: =$R$7*R12 -> 0 | S13: =$S$7*S12 -> 0 | T13: =$T$7*T12 -> 0
C14: Steepener shock | D14: 0 | E14: -0.0011 | F14: -0.0033 | G14: -0.0053 | H14: -0.0089 | I14: -0.0133 | J14: -0.0166 | K14: -0.02 | L14: -0.0164 | M14: -0.0052 | N14: 0.0103 | O14: 0.0378 | P14: 0.0819 | Q14: 0.142 | R14: 0.1952 | S14: 0.232 | T14: 0
C15: =SUM(D15:T15) -> -101475.01 | D15: =$D$7*D14 -> 0 | E15: =$E$7*E14 -> 35239.641 | F15: =$F$7*F14 -> 190647.33 | G15: =$G$7*G14 -> 18219.034 | H15: =$H$7*H14 -> 50897.114 | I15: =$I$7*I14 -> -67217.701 | J15: =$J$7*J14 -> 0 | K15: =$K$7*K14 -> -329260.42 | L15: =$L$7*L14 -> 0 | M15: =$M$7*M14 -> 0 | N15: =$N$7*N14 -> 0 | O15: =$O$7*O14 -> 0 | P15: =$P$7*P14 -> 0 | Q15: =$Q$7*Q14 -> 0 | R15: =$R$7*R14 -> 0 | S15: =$S$7*S14 -> 0 | T15: =$T$7*T14 -> 0
C16: Flattener shock | D16: 0 | E16: 0.0014 | F16: 0.0041 | G16: 0.0067 | H16: 0.0113 | I16: 0.0173 | J16: 0.0221 | K16: 0.029 | L16: 0.0308 | M16: 0.0246 | N16: 0.0138 | O16: -0.0065 | P16: -0.0416 | Q16: -0.0882 | R16: -0.1278 | S16: -0.1539 | T16: 0
C17: =SUM(D17:T17) -> 195492.06 | D17: =$D$7*D16 -> 0 | E17: =$E$7*E16 -> -44850.452 | F17: =$F$7*F16 -> -236864.86 | G17: =$G$7*G16 -> -23031.609 | H17: =$H$7*H16 -> -64622.178 | I17: =$I$7*I16 -> 87433.551 | J17: =$J$7*J16 -> 0 | K17: =$K$7*K16 -> 477427.61 | L17: =$L$7*L16 -> 0 | M17: =$M$7*M16 -> 0 | N17: =$N$7*N16 -> 0 | O17: =$O$7*O16 -> 0 | P17: =$P$7*P16 -> 0 | Q17: =$Q$7*Q16 -> 0 | R17: =$R$7*R16 -> 0 | S17: =$S$7*S16 -> 0 | T17: =$T$7*T16 -> 0
C18: Short rate shock up | D18: 0 | E18: 0.0018 | F18: 0.0052 | G18: 0.0085 | H18: 0.0146 | I18: 0.0229 | J18: 0.0301 | K18: 0.0428 | L18: 0.0541 | M18: 0.0576 | N18: 0.0563 | O18: 0.051 | P18: 0.0356 | Q18: 0.0176 | R18: 0.0064 | S18: 0.0021 | T18: 0
C19: =SUM(D19:T19) -> 349560.86 | D19: =$D$7*D18 -> 0 | E19: =$E$7*E18 -> -57664.867 | F19: =$F$7*F18 -> -300413.97 | G19: =$G$7*G18 -> -29219.205 | H19: =$H$7*H18 -> -83494.141 | I19: =$I$7*I18 -> 115735.74 | J19: =$J$7*J18 -> 0 | K19: =$K$7*K18 -> 704617.31 | L19: =$L$7*L18 -> 0 | M19: =$M$7*M18 -> 0 | N19: =$N$7*N18 -> 0 | O19: =$O$7*O18 -> 0 | P19: =$P$7*P18 -> 0 | Q19: =$Q$7*Q18 -> 0 | R19: =$R$7*R18 -> 0 | S19: =$S$7*S18 -> 0 | T19: =$T$7*T18 -> 0
C20: Short rate shock down | D20: 0 | E20: -0.0018 | F20: -0.0052 | G20: -0.0085 | H20: -0.0146 | I20: -0.0229 | J20: -0.0301 | K20: -0.0428 | L20: -0.0541 | M20: -0.0576 | N20: -0.0563 | O20: -0.051 | P20: -0.0356 | Q20: -0.0176 | R20: -0.0064 | S20: -0.0021 | T20: 0
C21: =SUM(D21:T21) -> -349560.86 | D21: =$D$7*D20 -> 0 | E21: =$E$7*E20 -> 57664.867 | F21: =$F$7*F20 -> 300413.97 | G21: =$G$7*G20 -> 29219.205 | H21: =$H$7*H20 -> 83494.141 | I21: =$I$7*I20 -> -115735.74 | J21: =$J$7*J20 -> 0 | K21: =$K$7*K20 -> -704617.31 | L21: =$L$7*L20 -> 0 | M21: =$M$7*M20 -> 0 | N21: =$N$7*N20 -> 0 | O21: =$O$7*O20 -> 0 | P21: =$P$7*P20 -> 0 | Q21: =$Q$7*Q20 -> 0 | R21: =$R$7*R20 -> 0 | S21: =$S$7*S20 -> 0 | T21: =$T$7*T20 -> 0
C23: IRRBB_Worst Aggregated Reductions | AK23: =$Q$7*Q20/100 -> 0
C24: =MIN(C11,C13,C15,C17,C19,C21) -> -445442.92
J26: 0.03 | O26: Interest rate-sensitive Assets repricing within one year | P26: =SUM(D4:J4) -> 2.7272664e+08
D27: Overnight (O/N) | E27: 0 to <1 month (excluding O/N) | F27: 1 to < 2 months | G27: 2 to < 3 months | H27: 3 to < 6 months | I27: 6 to < 9 months | J27: 9 to < 12 months | O27: Interest rate-sensitive Liabilities repricing within one year | P27: =SUM(D5:J5) -> 2.3637273e+08
C28: EaR: impact period | D28: =364/365 -> 0.99726027 | E28: =(12-0.5)/12 -> 0.95833333 | F28: =(12-1.5)/12 -> 0.875 | G28: =(12-2.5)/12 -> 0.79166667 | H28: =(12-4.5)/12 -> 0.625 | I28: =(12-7.5)/12 -> 0.375 | J28: =(12-10.5)/12 -> 0.125 | O28: Net position/gap within one year | P28: =ABS(P26-P27) -> 36353911
D29: =D7*$J$26*D28 -> 3897220.4 | E29: =E7*$J$26*E28 -> -921036.07 | F29: =F7*$J$26*F28 -> -1516512.8 | G29: =G7*$J$26*G28 -> -81641.898 | H29: =H7*$J$26*H28 -> -107227.07 | I29: =I7*$J$26*I28 -> 56857.078 | J29: =J7*$J$26*J28 -> 0 | O29: Total Interest rate-sensitive Assets | P29: =SUM(D4:S4) -> 2.8918966e+08
O30: Interest rate-sensitive Gap Ratio(12M) | P30: =P28/P29 -> 0.12570958
J31: =SUM(D29:J29) -> 1327659.6
D34: Int. Rate KRI Calculation (The risk of economic value or loss in earnings caused by a change in the overall level of interest rates)
E36: Info.(A$)
E37: VaR(+-) | F37: =ABS(C24) -> 445442.92
E38: EaR(+-) | F38: =ABS(J31) -> 1327659.6
E39: Total Asset | F39: =SUM('RE33(IRRBB)'!Q3:AG3) -> 2.9195547e+08
E41: KRI | F41: Ratio (%) | G41: Trigger | H41: Reached ? Y or N | I41: Limit | J41: Breached ? Y or N
E42: Int. Rate VaR Ratio | F42: =F37/$F$39 -> 0.0015257221 | G42: 0.015 | H42: =IF(F42<G42,"N","Y") -> N | I42: 0.02 | J42: =IF(F42<I42,"N","Y") -> N
E43: Int. Rate EaR Ratio | F43: =F38/$F$39 -> 0.0045474728 | G43: 0.02 | H43: =IF(F43<G43,"N","Y") -> N | I43: 0.025 | J43: =IF(F43<I43,"N","Y") -> N
C48: Interest rate sensitivities Stress Test under Stress Scenarios | D48: Stress Scenarios Applied as Rate Additions (%) | E48: 1
D51: Overnight (O/N) | E51: 0 to <1 month (excluding O/N) | F51: 1 to < 2 months | G51: 2 to < 3 months | H51: 3 to < 6 months | I51: 6 to < 9 months | J51: 9 to < 12 months | K51: 1 to < 2 years | L51: 2 to < 3 years | M51: 3 to < 4 years | N51: 4 to < 5 years | O51: 5 to < 7 years | P51: 7 to < 10 years | Q51: 10 to < 15 years | R51: 15 to < 20 years | S51: 20+ years | T51: Non-interest rate sensitive
C52: Net position/gap | D52: =D7 -> 1.3026423e+08 | E52: =E7 -> -32036037 | F52: =F7 -> -57771918 | G52: =G7 -> -3437553.6 | H52: =H7 -> -5718776.8 | I52: =I7 -> 5053962.5 | J52: =J7 -> 0 | K52: =K7 -> 16463021 | ... T52: =T7 -> -52363735
C54: Weighting factors used in calculation of interest rate sensitivities under Stress Scenarios
C55: Parallel shock up | D55: ='IRBB Weighting factors'!I35 -> 0 | E55: ='IRBB Weighting factors'!I36 -> 0.0016 | F55: ='IRBB Weighting factors'!I37 -> 0.0048 | G55: ='IRBB Weighting factors'!I38 -> 0.008 | H55: ='IRBB Weighting factors'!I39 -> 0.014266667 | I55: ='IRBB Weighting factors'!I40 -> 0.023866667 | J55: ='IRBB Weighting factors'!I41 -> 0.033333333 | K55: ='IRBB Weighting factors'!I42 -> 0.055333333 | L55: ='IRBB Weighting factors'!I43 -> 0.089866667 | M55: ='IRBB Weighting factors'!I44 -> 0.1228 | N55: ='IRBB Weighting factors'!I45 -> 0.15413333 | O55: ='IRBB Weighting factors'!I46 -> 0.20306667 | P55: ='IRBB Weighting factors'!I47 -> 0.2652 | Q55: ='IRBB Weighting factors'!I48 -> 0.35666667 | R55: ='IRBB Weighting factors'!I49 -> 0.44853333 | S55: ='IRBB Weighting factors'!I50 -> 0.52053333 | T55: ='IRBB Weighting factors'!I51 -> 0
C56: =SUM(D56:T56) -> 593923.9 | D56: =$D$7*D55 -> 0 | E56: =$E$7*E55 -> -51257.659 | F56: =$F$7*F55 -> -277305.21 | G56: =$G$7*G55 -> -27500.429 | H56: =$H$7*H55 -> -81587.882 | I56: =$I$7*I55 -> 120621.24 | J56: =$J$7*J55 -> 0 | K56: =$K$7*K55 -> 910953.84 | L56: =$L$7*L55 -> 0 | M56: =$M$7*M55 -> 0 | N56: =$N$7*N55 -> 0 | O56: =$O$7*O55 -> 0 | P56: =$P$7*P55 -> 0 | Q56: =$Q$7*Q55 -> 0 | R56: =$R$7*R55 -> 0 | S56: =$S$7*S55 -> 0 | T56: =$T$7*T55 -> 0
C57: Parallel shock down | D57: ='IRBB Weighting factors'!J35 -> 0 | E57: ='IRBB Weighting factors'!J36 -> -0.0016 | F57: ='IRBB Weighting factors'!J37 -> -0.0048 | G57: ='IRBB Weighting factors'!J38 -> -0.008 | H57: ='IRBB Weighting factors'!J39 -> -0.014266667 | I57: ='IRBB Weighting factors'!J40 -> -0.023866667 | J57: ='IRBB Weighting factors'!J41 -> -0.033333333 | K57: ='IRBB Weighting factors'!J42 -> -0.055333333 | L57: ='IRBB Weighting factors'!J43 -> -0.089866667 | M57: ='IRBB Weighting factors'!J44 -> -0.1228 | N57: ='IRBB Weighting factors'!J45 -> -0.15413333 | O57: ='IRBB Weighting factors'!J46 -> -0.20306667 | P57: ='IRBB Weighting factors'!J47 -> -0.2652 | Q57: ='IRBB Weighting factors'!J48 -> -0.35666667 | R57: ='IRBB Weighting factors'!J49 -> -0.44853333 | S57: ='IRBB Weighting factors'!J50 -> -0.52053333 | T57: ='IRBB Weighting factors'!J51 -> 0
C58: =SUM(D58:T58) -> -593923.9 | D58: =$D$7*D57 -> 0 | E58: =$E$7*E57 -> 51257.659 | F58: =$F$7*F57 -> 277305.21 | G58: =$G$7*G57 -> 27500.429 | H58: =$H$7*H57 -> 81587.882 | I58: =$I$7*I57 -> -120621.24 | J58: =$J$7*J57 -> 0 | K58: =$K$7*K57 -> -910953.84 | L58: =$L$7*L57 -> 0 | M58: =$M$7*M57 -> 0 | N58: =$N$7*N57 -> 0 | O58: =$O$7*O57 -> 0 | P58: =$P$7*P57 -> 0 | Q58: =$Q$7*Q57 -> 0 | R58: =$R$7*R57 -> 0 | S58: =$S$7*S57 -> 0 | T58: =$T$7*T57 -> 0
C59: Steepener shock | D59: =INDEX('IRBB Weighting factors'!M35:N35,1) -> 0 | E59: =INDEX('IRBB Weighting factors'!M36:N36,1) -> -0.0014039692 | F59: =INDEX('IRBB Weighting factors'!M37:N37,1) -> -0.0040583263 | G59: =INDEX('IRBB Weighting factors'!M38:N38,1) -> -0.0065131838 | H59: =INDEX('IRBB Weighting factors'!M39:N39,1) -> -0.010747981 | I59: =INDEX('IRBB Weighting factors'!M40:N40,1) -> -0.015914842 | J59: =INDEX('IRBB Weighting factors'!M41:N41,1) -> -0.019517535 | K59: =INDEX('IRBB Weighting factors'!M42:N42,1) -> -0.022309573 | L59: =INDEX('IRBB Weighting factors'!M43:N43,1) -> -0.014800264 | M59: =INDEX('IRBB Weighting factors'!M44:N44,1) -> 0.0025846584 | N59: =INDEX('IRBB Weighting factors'!M45:N45,1) -> 0.025540116 | O59: =INDEX('IRBB Weighting factors'!M46:N46,1) -> 0.06598947 | P59: =INDEX('IRBB Weighting factors'!M47:N47,1) -> 0.129322 | Q59: =INDEX('IRBB Weighting factors'!M48:N48,1) -> 0.21616637 | R59: =INDEX('IRBB Weighting factors'!M49:N49,1) -> 0.29390252 | S59: =INDEX('IRBB Weighting factors'!M50:N50,1) -> 0.34841493 | T59: =INDEX('IRBB Weighting factors'!M51:N51,1) -> 0
C60: =SUM(D60:T60) -> -84426.367 | D60: =$D$7*D59 -> 0 | E60: =$E$7*E59 -> 44977.609 | F60: =$F$7*F59 -> 234457.29 | G60: =$G$7*G59 -> 22389.418 | H60: =$H$7*H59 -> 61465.302 | I60: =$I$7*I59 -> -80433.014 | J60: =$J$7*J59 -> 0 | K60: =$K$7*K59 -> -367282.97 | L60: =$L$7*L59 -> 0 | M60: =$M$7*M59 -> 0 | N60: =$N$7*N59 -> 0 | O60: =$O$7*O59 -> 0 | P60: =$P$7*P59 -> 0 | Q60: =$Q$7*Q59 -> 0 | R60: =$R$7*R59 -> 0 | S60: =$S$7*S59 -> 0 | T60: =$T$7*T59 -> 0
C61: Flattener shock | D61: =INDEX('IRBB Weighting factors'!O35:P35,1) -> 0 | E61: =INDEX('IRBB Weighting factors'!O36:P36,1) -> 0.0017342803 | F61: =INDEX('IRBB Weighting factors'!O37:P37,1) -> 0.0050510953 | G61: =INDEX('IRBB Weighting factors'!O38:P38,1) -> 0.0081707951 | H61: =INDEX('IRBB Weighting factors'!O39:P39,1) -> 0.013714419 | I61: =INDEX('IRBB Weighting factors'!O40:P40,1) -> 0.020902075 | J61: =INDEX('IRBB Weighting factors'!O41:P41,1) -> 0.026515333 | K61: =INDEX('IRBB Weighting factors'!O42:P42,1) -> 0.03404651 | L61: =INDEX('IRBB Weighting factors'!O43:P43,1) -> 0.034118349 | M61: =INDEX('IRBB Weighting factors'!O44:P44,1) -> 0.024085517 | N61: =INDEX('IRBB Weighting factors'!O45:P45,1) -> 0.0082016388 | O61: =INDEX('IRBB Weighting factors'!O46:P46,1) -> -0.021149038 | P61: =INDEX('IRBB Weighting factors'!O47:P47,1) -> -0.070245884 | Q61: =INDEX('IRBB Weighting factors'!O48:P48,1) -> -0.1362102 | R61: =INDEX('IRBB Weighting factors'!O49:P49,1) -> -0.19308839 | S61: =INDEX('IRBB Weighting factors'!O50:P50,1) -> -0.23133013 | T61: =INDEX('IRBB Weighting factors'!O51:P51,1) -> 0
C62: =SUM(D62:T62) -> 212258.55 | D62: =$D$7*D61 -> 0 | E62: =$E$7*E61 -> -55559.468 | F62: =$F$7*F61 -> -291811.46 | G62: =$G$7*G61 -> -28087.546 | H62: =$H$7*H61 -> -78429.702 | I62: =$I$7*I61 -> 105638.3 | J62: =$J$7*J61 -> 0 | K62: =$K$7*K61 -> 560508.42 | L62: =$L$7*L61 -> 0 | M62: =$M$7*M61 -> 0 | N62: =$N$7*N61 -> 0 | O62: =$O$7*O61 -> 0 | P62: =$P$7*P61 -> 0 | Q62: =$Q$7*Q61 -> 0 | R62: =$R$7*R61 -> 0 | S62: =$S$7*S61 -> 0 | T62: =$T$7*T61 -> 0
C63: Short rate shock up | D63: ='IRBB Weighting factors'!K35 -> 0 | E63: ='IRBB Weighting factors'!K36 -> 0.0021771841 | F63: ='IRBB Weighting factors'!K37 -> 0.0063969393 | G63: ='IRBB Weighting factors'!K38 -> 0.010441834 | H63: ='IRBB Weighting factors'!K39 -> 0.017861178 | I63: ='IRBB Weighting factors'!K40 -> 0.028069582 | J63: ='IRBB Weighting factors'!K41 -> 0.036828118 | K63: ='IRBB Weighting factors'!K42 -> 0.052291259 | L63: ='IRBB Weighting factors'!K43 -> 0.066140471 | M63: ='IRBB Weighting factors'!K44 -> 0.070387152 | N63: ='IRBB Weighting factors'!K45 -> 0.06880468 | O63: ='IRBB Weighting factors'!K46 -> 0.06230166 | P63: ='IRBB Weighting factors'!K47 -> 0.043551232 | Q63: ='IRBB Weighting factors'!K48 -> 0.021547405 | R63: ='IRBB Weighting factors'!K49 -> 0.0077635269 | S63: ='IRBB Weighting factors'!K50 -> 0.0025813375 | T63: ='IRBB Weighting factors'!K51 -> 0
C64: =SUM(D64:T64) -> 425384.46 | D64: =$D$7*D63 -> 0 | E64: =$E$7*E63 -> -69748.352 | F64: =$F$7*F63 -> -369563.46 | G64: =$G$7*G63 -> -35894.365 | H64: =$H$7*H63 -> -102144.09 | I64: =$I$7*I63 -> 141862.62 | J64: =$J$7*J63 -> 0 | K64: =$K$7*K63 -> 860872.11 | L64: =$L$7*L63 -> 0 | M64: =$M$7*M63 -> 0 | N64: =$N$7*N63 -> 0 | O64: =$O$7*O63 -> 0 | P64: =$P$7*P63 -> 0 | Q64: =$Q$7*Q63 -> 0 | R64: =$R$7*R63 -> 0 | S64: =$S$7*S63 -> 0 | T64: =$T$7*T63 -> 0
C65: Short rate shock down | D65: ='IRBB Weighting factors'!L35 -> 0 | E65: ='IRBB Weighting factors'!L36 -> -0.0021771841 | F65: ='IRBB Weighting factors'!L37 -> -0.0063969393 | G65: ='IRBB Weighting factors'!L38 -> -0.010441834 | H65: ='IRBB Weighting factors'!L39 -> -0.017861178 | I65: ='IRBB Weighting factors'!L40 -> -0.028069582 | J65: ='IRBB Weighting factors'!L41 -> -0.036828118 | K65: ='IRBB Weighting factors'!L42 -> -0.052291259 | L65: ='IRBB Weighting factors'!L43 -> -0.066140471 | M65: ='IRBB Weighting factors'!L44 -> -0.070387152 | N65: ='IRBB Weighting factors'!L45 -> -0.06880468 | O65: ='IRBB Weighting factors'!L46 -> -0.06230166 | P65: ='IRBB Weighting factors'!L47 -> -0.043551232 | Q65: ='IRBB Weighting factors'!L48 -> -0.021547405 | R65: ='IRBB Weighting factors'!L49 -> -0.0077635269 | S65: ='IRBB Weighting factors'!L50 -> -0.0025813375 | T65: ='IRBB Weighting factors'!L51 -> 0
C66: =SUM(D66:T66) -> -425384.46 | D66: =$D$7*D65 -> 0 | E66: =$E$7*E65 -> 69748.352 | F66: =$F$7*F65 -> 369563.46 | G66: =$G$7*G65 -> 35894.365 | H66: =$H$7*H65 -> 102144.09 | I66: =$I$7*I65 -> -141862.62 | J66: =$J$7*J65 -> 0 | K66: =$K$7*K65 -> -860872.11 | L66: =$L$7*L65 -> 0 | M66: =$M$7*M65 -> 0 | N66: =$N$7*N65 -> 0 | O66: =$O$7*O65 -> 0 | P66: =$P$7*P65 -> 0 | Q66: =$Q$7*Q65 -> 0 | R66: =$R$7*R65 -> 0 | S66: =$S$7*S65 -> 0 | T66: =$T$7*T65 -> 0
C68: IRRBB_Worst Aggregated Reductions
C69: =MIN(C56,C58,C60,C62,C64,C66) -> -593923.9
J71: =J26+(E48/100) -> 0.04
D72: Overnight (O/N) | E72: 0 to <1 month (excluding O/N) | F72: 1 to < 2 months | G72: 2 to < 3 months | H72: 3 to < 6 months | I72: 6 to < 9 months | J72: 9 to < 12 months
C73: EaR: impact period | D73: =364/365 -> 0.99726027 | E73: =(12-0.5)/12 -> 0.95833333 | F73: =(12-1.5)/12 -> 0.875 | G73: =(12-2.5)/12 -> 0.79166667 | H73: =(12-4.5)/12 -> 0.625 | I73: =(12-7.5)/12 -> 0.375 | J73: =(12-10.5)/12 -> 0.125
D74: =D52*$J$71*D73 -> 5196293.8 | E74: =E52*$J$71*E73 -> -1228048.1 | F74: =F52*$J$71*F73 -> -2022017.1 | G74: =G52*$J$71*G73 -> -108855.86 | H74: =H52*$J$71*H73 -> -142969.42 | I74: =I52*$J$71*I73 -> 75809.438 | J74: =J52*$J$71*J73 -> 0
J76: =SUM(D74:J74) -> 1770212.8
D79: Int. Rate KRI Calculation (The risk of economic value or loss in earnings caused by a change in the overall level of interest rates under Stress Test)
E81: Info.(A$)
E82: VaR(+-) | F82: =ABS(C69) -> 593923.9
E83: EaR(+-) | F83: =ABS(J76) -> 1770212.8
E84: Total Asset | F84: =F39 -> 2.9195547e+08
E86: KRI | F86: Ratio (%) | G86: Trigger | H86: Reached ? Y or N | I86: Limit | J86: Breached ? Y or N
E87: Int. Rate VaR Ratio | F87: =F82/$F$39 -> 0.0020342962 | G87: 0.015 | H87: =IF(F87<G87,"N","Y") -> N | I87: 0.02 | J87: =IF(F87<I87,"N","Y") -> N
E88: Int. Rate EaR Ratio | F88: =F83/$F$39 -> 0.0060632971 | G88: 0.02 | H88: =IF(F88<G88,"N","Y") -> N | I88: 0.025 | J88: =IF(F88<I88,"N","Y") -> N

Sheet IRBB Weighting factors
C3: Weighting factors used in calculation of interest rate sensitivities in Table 3 (ARS 117.0)
I6: Parallel shock Up Int. R (%) | J6: Parallel shock Down Int. R (%) | K6: Short rate shock Up Int. R (%) | L6: Short rate shock Down Int. R (%) | M6: Short rate shock Down Int. R (%) | N6: Long rack shock Up Int. R (%) | O6: Short rate shock Up Int. R (%) | P6: Long rack shock Down Int. R (%)
E7: APS117 | F7: Shaping scalar (Short rate shock) | G7: Shaping scalar (Long rack shock) | I7: 3 | J7: =-I7 -> -3 | K7: 4.5 | L7: =-K7 -> -4.5 | M7: =L7 -> -4.5 | N7: 2 | O7: 4.5 | P7: -2
C8: Tenor | D8: Mid (yrs) | E8: Duration (Base) | I8: Parallel shock up | J8: Parallel shock down | K8: Short rate shock up | L8: Short rate shock down | M8: Steepener shock | O8: Flattener shock
C9: Overnight (O/N) | D9: =ROUND(1/365,4) -> 0.0027 | E9: 0 | F9: =EXP(-D9/4) -> 0.99932523 | G9: =1-F9 -> 0.00067477224 | I9: =E9*$I$7 -> 0 | J9: =E9*$J$7 -> 0 | K9: =(E9*F9)*$K$7 -> 0 | L9: =(E9*F9)*$L$7 -> 0 | M9: =(((E9*F9)*$M$7)*0.65+((E9*G9)*$N$7)*0.9) -> 0 | O9: =(((E9*F9)*$O$7)*0.8+((E9*G9)*$P$7)*0.6) -> 0
C10: 0 to <1 month (excluding O/N) | D10: =ROUND(0.5/12,4) -> 0.0417 | E10: 0.0004 | F10: =EXP(-D10/4) -> 0.98962915 | G10: =1-F10 -> 0.010370848 | I10: =E10*$I$7 -> 0.0012 | J10: =E10*$J$7 -> -0.0012 | K10: =(E10*F10)*$K$7 -> 0.0017813325 | L10: =(E10*F10)*$L$7 -> -0.0017813325 | M10: =(((E10*F10)*$M$7)*0.65+((E10*G10)*$N$7)*0.9) -> -0.0011503991 | O10: =(((E10*F10)*$O$7)*0.8+((E10*G10)*$P$7)*0.6) -> 0.001420088
C11: 1 to < 2 months | D11: =ROUND(1.5/12,4) -> 0.125 | E11: 0.0012 | F11: =EXP(-D11/4) -> 0.96923323 | G11: =1-F11 -> 0.030766766 | I11: =E11*$I$7 -> 0.0036 | J11: =E11*$J$7 -> -0.0036 | K11: =(E11*F11)*$K$7 -> 0.0052338595 | L11: =(E11*F11)*$L$7 -> -0.0052338595 | M11: =(((E11*F11)*$M$7)*0.65+((E11*G11)*$N$7)*0.9) -> -0.0033355524 | O11: =(((E11*F11)*$O$7)*0.8+((E11*G11)*$P$7)*0.6) -> 0.0041427834
C12: 2 to < 3 months | D12: =ROUND(2.5/12,4) -> 0.2083 | E12: 0.002 | F12: =EXP(-D12/4) -> 0.94925767 | G12: =1-F12 -> 0.05074233 | I12: =E12*$I$7 -> 0.006 | J12: =E12*$J$7 -> -0.006 | K12: =(E12*F12)*$K$7 -> 0.008543319 | L12: =(E12*F12)*$L$7 -> -0.008543319 | M12: =(((E12*F12)*$M$7)*0.65+((E12*G12)*$N$7)*0.9) -> -0.005370485 | O12: =(((E12*F12)*$O$7)*0.8+((E12*G12)*$P$7)*0.6) -> 0.0067128736
