Workbook
Name a: #REF!
Name a: #REF!
Name a: #REF!
Name a: #REF!
Name a: #REF!
Name a: #REF!
Name a: #REF!
Name a: #REF!
Name a: #REF!
Name a: #REF!
Name a: #REF!
Name a: #REF!
Name a: #REF!
Name a: #REF!
Name AGGREGATION: #REF!
Name AGGREGATION: #REF!
Name AGGREGATION: #REF!
Name AGGREGATION: #REF!
Name AGGREGATION: #REF!
Name AGGREGATION: #REF!
Name AGGREGATION: #REF!
Name AGGREGATION: #REF!
Name AGGREGATION: #REF!
Name AGGREGATION: #REF!
Name AGGREGATION: #REF!
Name AGGREGATION: #REF!
Name AGGREGATION: #REF!
Name AGGREGATION: #REF!
Name BankCode: [1]Cover!$E$3
Name CHECK: #REF!
Name CHECK: #REF!
Name CHECK: #REF!
Name CHECK: #REF!
Name CHECK: #REF!
Name CHECK: #REF!
Name CHECK: #REF!
Name CHECK: #REF!
Name CHECK: #REF!
Name CHECK: #REF!
Name CHECK: #REF!
Name CHECK: #REF!
Name CHECK: #REF!
Name CHECK: #REF!
Name CurrencyCode: OFFSET([1]wksCurrency!$B$2:$B$27,1,0,ROWS([1]wksCurrency!$B$2:$B$27)-2)
Name CurrencyName: OFFSET([1]wksCurrency!$A$2:$A$27,1,0,ROWS([1]wksCurrency!$A$2:$A$27)-2)
Name date: [2]BSY_현지화!#REF!
Name date: [2]BSY_현지화!#REF!
Name date: [2]BSY_현지화!#REF!
Name date: [2]BSY_현지화!#REF!
Name date: [2]BSY_현지화!#REF!
Name date: [2]BSY_현지화!#REF!
Name date: [2]BSY_현지화!#REF!
Name date: [2]BSY_현지화!#REF!
Name date: [2]BSY_현지화!#REF!
Name date: [2]BSY_현지화!#REF!
Name date: [2]BSY_현지화!#REF!
Name date: [2]BSY_현지화!#REF!
Name date: [2]BSY_현지화!#REF!
Name date: [2]BSY_현지화!#REF!
Name DOMAIN: #REF!

Sheet Summary
B1: Liquidity Coverage Ratio Management | K1: =BS_RE33!N4 -> 46058
B3: LCR (%) | C3: 3M Liquidity Ratio (%)
B4: ='30 days CF Table(ALL)'!$D$119 -> #DIV/0! | C4: ='Liquidity Maturity Gap'!Q73 -> #DIV/0!
B6: KRI | C6: KRI | D6: Ratio (%) | E6: Trigger | F6: Reached ? Y or N | G6: Limit | H6: Breached ? Y or N
B7: Liquidity Gap Ratio | C7: 7D | D7: ='Liquidity Maturity Gap'!J73 -> #DIV/0! | E7: 0 | F7: =IF(D7<E7,"Y","N") -> #DIV/0! | G7: -0.05 | H7: =IF(D7<G7,"Y","N") -> #DIV/0!
C8: 1M | D8: ='Liquidity Maturity Gap'!J74 -> #DIV/0! | E8: -0.15 | F8: =IF(D8<E8,"Y","N") -> #DIV/0! | G8: -0.2 | H8: =IF(D8<G8,"Y","N") -> #DIV/0!
C9: 3M | D9: ='Liquidity Maturity Gap'!J75 -> #DIV/0! | E9: -0.4 | F9: =IF(D9<E9,"Y","N") -> #DIV/0! | G9: -0.45 | H9: =IF(D9<G9,"Y","N") -> #DIV/0!
B12: Liquidity Gap Ratio Forecast
B14: 7 day | C14: From | D14: =BS_RE33!AL9 -> 46081 | E14: =EOMONTH(D14,1) -> 46112 | F14: =EOMONTH(E14,1) -> 46142 | G14: =EOMONTH(F14,1) -> 46173 | H14: =EOMONTH(G14,1) -> 46203 | I14: =EOMONTH(H14,1) -> 46234 | J14: =EOMONTH(I14,1) -> 46265 | K14: =EOMONTH(J14,1) -> 46295
C15: To | D15: =D14+7 -> 46088 | E15: =E14+7 -> 46119 | F15: =F14+7 -> 46149 | G15: =G14+7 -> 46180 | H15: =H14+7 -> 46210 | I15: =I14+7 -> 46241 | J15: =J14+7 -> 46272 | K15: =K14+7 -> 46302
C16: Gap ratio | D16: =BS_RE33!AL17 -> #DIV/0! | E16: =BS_RE33!AM17 -> #DIV/0! | F16: =BS_RE33!AN17 -> #DIV/0! | G16: =BS_RE33!AO17 -> #DIV/0! | H16: =BS_RE33!AP17 -> #DIV/0! | I16: =BS_RE33!AQ17 -> #DIV/0! | J16: =BS_RE33!AR17 -> #DIV/0! | K16: =BS_RE33!AS17 -> #DIV/0!
C17: Trigger | D17: 0 | E17: =D17 -> 0 | F17: =E17 -> 0 | G17: =F17 -> 0 | H17: =G17 -> 0 | I17: =H17 -> 0 | J17: =I17 -> 0 | K17: =J17 -> 0
B19: 1 month | C19: From | D19: =D14 -> 46081 | E19: =EOMONTH(D19,1) -> 46112 | F19: =EOMONTH(E19,1) -> 46142 | G19: =EOMONTH(F19,1) -> 46173 | H19: =EOMONTH(G19,1) -> 46203 | I19: =EOMONTH(H19,1) -> 46234 | J19: =EOMONTH(I19,1) -> 46265 | K19: =EOMONTH(J19,1) -> 46295
C20: To | D20: =EOMONTH(D19,1) -> 46112 | E20: =EOMONTH(E19,1) -> 46142 | F20: =EOMONTH(F19,1) -> 46173 | G20: =EOMONTH(G19,1) -> 46203 | H20: =EOMONTH(H19,1) -> 46234 | I20: =EOMONTH(I19,1) -> 46265 | J20: =EOMONTH(J19,1) -> 46295 | K20: =EOMONTH(K19,1) -> 46326
C21: Gap ratio | D21: =BS_RE33!AL29 -> #DIV/0! | E21: =BS_RE33!AM29 -> #DIV/0! | F21: =BS_RE33!AN29 -> #DIV/0! | G21: =BS_RE33!AO29 -> #DIV/0! | H21: =BS_RE33!AP29 -> #DIV/0! | I21: =BS_RE33!AQ29 -> #DIV/0! | J21: =BS_RE33!AR29 -> #DIV/0! | K21: =BS_RE33!AS29 -> #DIV/0!
C22: Trigger | D22: -0.15 | E22: =D22 -> -0.15 | F22: =E22 -> -0.15 | G22: =F22 -> -0.15 | H22: =G22 -> -0.15 | I22: =H22 -> -0.15 | J22: =I22 -> -0.15 | K22: =J22 -> -0.15
B24: 3 month | C24: From | D24: =D19 -> 46081 | E24: =EOMONTH(D24,1) -> 46112 | F24: =EOMONTH(E24,1) -> 46142 | G24: =EOMONTH(F24,1) -> 46173 | H24: =EOMONTH(G24,1) -> 46203 | I24: =EOMONTH(H24,1) -> 46234 | J24: =EOMONTH(I24,1) -> 46265 | K24: =EOMONTH(J24,1) -> 46295
C25: To | D25: =EOMONTH(D24,3) -> 46173 | E25: =EOMONTH(E24,3) -> 46203 | F25: =EOMONTH(F24,3) -> 46234 | G25: =EOMONTH(G24,3) -> 46265 | H25: =EOMONTH(H24,3) -> 46295 | I25: =EOMONTH(I24,3) -> 46326 | J25: =EOMONTH(J24,3) -> 46356 | K25: =EOMONTH(K24,3) -> 46387
C26: Gap ratio | D26: =BS_RE33!AL41 -> #DIV/0! | E26: =BS_RE33!AM41 -> #DIV/0! | F26: =BS_RE33!AN41 -> #DIV/0! | G26: =BS_RE33!AO41 -> #DIV/0! | H26: =BS_RE33!AP41 -> #DIV/0! | I26: =BS_RE33!AQ41 -> #DIV/0! | J26: =BS_RE33!AR41 -> #DIV/0! | K26: =BS_RE33!AS41 -> #DIV/0!
C27: Trigger | D27: -0.4 | E27: =D27 -> -0.4 | F27: =E27 -> -0.4 | G27: =F27 -> -0.4 | H27: =G27 -> -0.4 | I27: =H27 -> -0.4 | J27: =I27 -> -0.4 | K27: =J27 -> -0.4

Sheet Liquidity Maturity Gap
C2: =BS_RE33!N4 -> 46058 | D2: =ROUND((F24-F51),0)=ROUND(SUM(H52:Q52),0) -> TRUE
C3: Category (1) | D3: Category (2) | E3: Middle Category | F3: Customer Type | G3: Ref. | H3: Overnight (O/N) | I3: 2-7 Days | J3: 8 Days to <1 month | K3: 1 to < 3 months | L3: 3 to < 6 months | M3: 6 to < 12 months | N3: 1 to < 3 years | O3: 3 to < 5 years | P3: 5 to < 10 years | Q3: 10+ years or No Maturity
C4: Asset | D4: Deposit | E4: Deposit_Asset(Our) | G4: Deposit_Asset(Our)_ | H4: =SUMIF(BS_RE33!$P$7:$P$874,G4,BS_RE33!$X$7:$X$874) -> 0 | I4: =SUMIF(BS_RE33!$P$7:$P$874,G4,BS_RE33!$Y$7:$Y$874) -> 0 | J4: =SUMIF(BS_RE33!$P$7:$P$874,G4,BS_RE33!$Z$7:$Z$874) -> 0 | K4: =SUMIF(BS_RE33!$P$7:$P$874,G4,BS_RE33!$AA$7:$AA$874) -> 0 | L4: =SUMIF(BS_RE33!$P$7:$P$874,G4,BS_RE33!$AB$7:$AB$874) -> 0 | M4: =SUMIF(BS_RE33!$P$7:$P$874,G4,BS_RE33!$AC$7:$AC$874) -> 0 | N4: =SUMIF(BS_RE33!$P$7:$P$874,G4,BS_RE33!$AD$7:$AD$874) -> 0 | O4: =SUMIF(BS_RE33!$P$7:$P$874,G4,BS_RE33!$AE$7:$AE$874) -> 0 | P4: =SUMIF(BS_RE33!$P$7:$P$874,G4,BS_RE33!$AF$7:$AF$874) -> 0 | Q4: =SUMIF(BS_RE33!$P$7:$P$874,G4,BS_RE33!$AG$7:$AG$874) -> 0
E5: Deposit_Asset | G5: Deposit_Asset_ | H5: =SUMIF(BS_RE33!$P$7:$P$874,G5,BS_RE33!$X$7:$X$874) -> 0 | I5: =SUMIF(BS_RE33!$P$7:$P$874,G5,BS_RE33!$Y$7:$Y$874) -> 0 | J5: =SUMIF(BS_RE33!$P$7:$P$874,G5,BS_RE33!$Z$7:$Z$874) -> 0 | K5: =SUMIF(BS_RE33!$P$7:$P$874,G5,BS_RE33!$AA$7:$AA$874) -> 0 | L5: =SUMIF(BS_RE33!$P$7:$P$874,G5,BS_RE33!$AB$7:$AB$874) -> 0 | M5: =SUMIF(BS_RE33!$P$7:$P$874,G5,BS_RE33!$AC$7:$AC$874) -> 0 | N5: =SUMIF(BS_RE33!$P$7:$P$874,G5,BS_RE33!$AD$7:$AD$874) -> 0 | O5: =SUMIF(BS_RE33!$P$7:$P$874,G5,BS_RE33!$AE$7:$AE$874) -> 0 | P5: =SUMIF(BS_RE33!$P$7:$P$874,G5,BS_RE33!$AF$7:$AF$874) -> 0 | Q5: =SUMIF(BS_RE33!$P$7:$P$874,G5,BS_RE33!$AG$7:$AG$874) -> 0
D6: HQLA | E6: HQLA | F6: Australian State Government or Territory Central Borrowing Authorities | G6: HQLA_Australian State Government or Territory Central Borrowing Authorities | H6: =SUMIF(BS_RE33!$P$7:$P$874,G6,BS_RE33!$X$7:$X$874) -> 0 | I6: =SUMIF(BS_RE33!$P$7:$P$874,G6,BS_RE33!$Y$7:$Y$874) -> 0 | J6: =SUMIF(BS_RE33!$P$7:$P$874,G6,BS_RE33!$Z$7:$Z$874) -> 0 | K6: =SUMIF(BS_RE33!$P$7:$P$874,G6,BS_RE33!$AA$7:$AA$874) -> 0 | L6: =SUMIF(BS_RE33!$P$7:$P$874,G6,BS_RE33!$AB$7:$AB$874) -> 0 | M6: =SUMIF(BS_RE33!$P$7:$P$874,G6,BS_RE33!$AC$7:$AC$874) -> 0 | N6: =SUMIF(BS_RE33!$P$7:$P$874,G6,BS_RE33!$AD$7:$AD$874) -> 0 | O6: =SUMIF(BS_RE33!$P$7:$P$874,G6,BS_RE33!$AE$7:$AE$874) -> 0 | P6: =SUMIF(BS_RE33!$P$7:$P$874,G6,BS_RE33!$AF$7:$AF$874) -> 0 | Q6: =SUMIF(BS_RE33!$P$7:$P$874,G6,BS_RE33!$AG$7:$AG$874) -> 0
E7: HQLA | F7: Issued or guaranteed by PSEs | G7: HQLA_Issued or guaranteed by PSEs | H7: =SUMIF(BS_RE33!$P$7:$P$874,G7,BS_RE33!$X$7:$X$874) -> 0 | I7: =SUMIF(BS_RE33!$P$7:$P$874,G7,BS_RE33!$Y$7:$Y$874) -> 0 | J7: =SUMIF(BS_RE33!$P$7:$P$874,G7,BS_RE33!$Z$7:$Z$874) -> 0 | K7: =SUMIF(BS_RE33!$P$7:$P$874,G7,BS_RE33!$AA$7:$AA$874) -> 0 | L7: =SUMIF(BS_RE33!$P$7:$P$874,G7,BS_RE33!$AB$7:$AB$874) -> 0 | M7: =SUMIF(BS_RE33!$P$7:$P$874,G7,BS_RE33!$AC$7:$AC$874) -> 0 | N7: =SUMIF(BS_RE33!$P$7:$P$874,G7,BS_RE33!$AD$7:$AD$874) -> 0 | O7: =SUMIF(BS_RE33!$P$7:$P$874,G7,BS_RE33!$AE$7:$AE$874) -> 0 | P7: =SUMIF(BS_RE33!$P$7:$P$874,G7,BS_RE33!$AF$7:$AF$874) -> 0 | Q7: =SUMIF(BS_RE33!$P$7:$P$874,G7,BS_RE33!$AG$7:$AG$874) -> 0
D8: Trade Finance | E8: Trade Finance_Asset | G8: Trade Finance_Asset_ | H8: =SUMIF(BS_RE33!$P$7:$P$874,G8,BS_RE33!$X$7:$X$874) -> 0 | I8: =SUMIF(BS_RE33!$P$7:$P$874,G8,BS_RE33!$Y$7:$Y$874) -> 0 | J8: =SUMIF(BS_RE33!$P$7:$P$874,G8,BS_RE33!$Z$7:$Z$874) -> 0 | K8: =SUMIF(BS_RE33!$P$7:$P$874,G8,BS_RE33!$AA$7:$AA$874) -> 0 | L8: =SUMIF(BS_RE33!$P$7:$P$874,G8,BS_RE33!$AB$7:$AB$874) -> 0 | M8: =SUMIF(BS_RE33!$P$7:$P$874,G8,BS_RE33!$AC$7:$AC$874) -> 0 | N8: =SUMIF(BS_RE33!$P$7:$P$874,G8,BS_RE33!$AD$7:$AD$874) -> 0 | O8: =SUMIF(BS_RE33!$P$7:$P$874,G8,BS_RE33!$AE$7:$AE$874) -> 0 | P8: =SUMIF(BS_RE33!$P$7:$P$874,G8,BS_RE33!$AF$7:$AF$874) -> 0 | Q8: =SUMIF(BS_RE33!$P$7:$P$874,G8,BS_RE33!$AG$7:$AG$874) -> 0
D9: Loan | E9: Loan | F9: Household | G9: Loan_Household | H9: =SUMIF(BS_RE33!$P$7:$P$874,G9,BS_RE33!$X$7:$X$874) -> 0 | I9: =SUMIF(BS_RE33!$P$7:$P$874,G9,BS_RE33!$Y$7:$Y$874) -> 0 | J9: =SUMIF(BS_RE33!$P$7:$P$874,G9,BS_RE33!$Z$7:$Z$874) -> 0 | K9: =SUMIF(BS_RE33!$P$7:$P$874,G9,BS_RE33!$AA$7:$AA$874) -> 0 | L9: =SUMIF(BS_RE33!$P$7:$P$874,G9,BS_RE33!$AB$7:$AB$874) -> 0 | M9: =SUMIF(BS_RE33!$P$7:$P$874,G9,BS_RE33!$AC$7:$AC$874) -> 0 | N9: =SUMIF(BS_RE33!$P$7:$P$874,G9,BS_RE33!$AD$7:$AD$874) -> 0 | O9: =SUMIF(BS_RE33!$P$7:$P$874,G9,BS_RE33!$AE$7:$AE$874) -> 0 | P9: =SUMIF(BS_RE33!$P$7:$P$874,G9,BS_RE33!$AF$7:$AF$874) -> 0 | Q9: =SUMIF(BS_RE33!$P$7:$P$874,G9,BS_RE33!$AG$7:$AG$874) -> 0
E10: Loan | F10: SME | G10: Loan_SME | H10: =SUMIF(BS_RE33!$P$7:$P$874,G10,BS_RE33!$X$7:$X$874) -> 0 | I10: =SUMIF(BS_RE33!$P$7:$P$874,G10,BS_RE33!$Y$7:$Y$874) -> 0 | J10: =SUMIF(BS_RE33!$P$7:$P$874,G10,BS_RE33!$Z$7:$Z$874) -> 0 | K10: =SUMIF(BS_RE33!$P$7:$P$874,G10,BS_RE33!$AA$7:$AA$874) -> 0 | L10: =SUMIF(BS_RE33!$P$7:$P$874,G10,BS_RE33!$AB$7:$AB$874) -> 0 | M10: =SUMIF(BS_RE33!$P$7:$P$874,G10,BS_RE33!$AC$7:$AC$874) -> 0 | N10: =SUMIF(BS_RE33!$P$7:$P$874,G10,BS_RE33!$AD$7:$AD$874) -> 0 | O10: =SUMIF(BS_RE33!$P$7:$P$874,G10,BS_RE33!$AE$7:$AE$874) -> 0 | P10: =SUMIF(BS_RE33!$P$7:$P$874,G10,BS_RE33!$AF$7:$AF$874) -> 0 | Q10: =SUMIF(BS_RE33!$P$7:$P$874,G10,BS_RE33!$AG$7:$AG$874) -> 0
E11: Loan | F11: Non-financialcorporations | G11: Loan_Non-financialcorporations | H11: =SUMIF(BS_RE33!$P$7:$P$874,G11,BS_RE33!$X$7:$X$874) -> 0 | I11: =SUMIF(BS_RE33!$P$7:$P$874,G11,BS_RE33!$Y$7:$Y$874) -> 0 | J11: =SUMIF(BS_RE33!$P$7:$P$874,G11,BS_RE33!$Z$7:$Z$874) -> 0 | K11: =SUMIF(BS_RE33!$P$7:$P$874,G11,BS_RE33!$AA$7:$AA$874) -> 0 | L11: =SUMIF(BS_RE33!$P$7:$P$874,G11,BS_RE33!$AB$7:$AB$874) -> 0 | M11: =SUMIF(BS_RE33!$P$7:$P$874,G11,BS_RE33!$AC$7:$AC$874) -> 0 | N11: =SUMIF(BS_RE33!$P$7:$P$874,G11,BS_RE33!$AD$7:$AD$874) -> 0 | O11: =SUMIF(BS_RE33!$P$7:$P$874,G11,BS_RE33!$AE$7:$AE$874) -> 0 | P11: =SUMIF(BS_RE33!$P$7:$P$874,G11,BS_RE33!$AF$7:$AF$874) -> 0 | Q11: =SUMIF(BS_RE33!$P$7:$P$874,G11,BS_RE33!$AG$7:$AG$874) -> 0
E12: Loan | F12: Advance(Loan Guarantee) | G12: Loan_Advance(Loan Guarantee) | H12: =SUMIF(BS_RE33!$P$7:$P$874,G12,BS_RE33!$X$7:$X$874) -> 0 | I12: =SUMIF(BS_RE33!$P$7:$P$874,G12,BS_RE33!$Y$7:$Y$874) -> 0 | J12: =SUMIF(BS_RE33!$P$7:$P$874,G12,BS_RE33!$Z$7:$Z$874) -> 0 | K12: =SUMIF(BS_RE33!$P$7:$P$874,G12,BS_RE33!$AA$7:$AA$874) -> 0 | L12: =SUMIF(BS_RE33!$P$7:$P$874,G12,BS_RE33!$AB$7:$AB$874) -> 0 | M12: =SUMIF(BS_RE33!$P$7:$P$874,G12,BS_RE33!$AC$7:$AC$874) -> 0 | N12: =SUMIF(BS_RE33!$P$7:$P$874,G12,BS_RE33!$AD$7:$AD$874) -> 0 | O12: =SUMIF(BS_RE33!$P$7:$P$874,G12,BS_RE33!$AE$7:$AE$874) -> 0 | P12: =SUMIF(BS_RE33!$P$7:$P$874,G12,BS_RE33!$AF$7:$AF$874) -> 0 | Q12: =SUMIF(BS_RE33!$P$7:$P$874,G12,BS_RE33!$AG$7:$AG$874) -> 0
E13: Loan | F13: Private placement-Corp Bonds | G13: Loan_Private placement-Corp Bonds | H13: =SUMIF(BS_RE33!$P$7:$P$874,G13,BS_RE33!$X$7:$X$874) -> 0 | I13: =SUMIF(BS_RE33!$P$7:$P$874,G13,BS_RE33!$Y$7:$Y$874) -> 0 | J13: =SUMIF(BS_RE33!$P$7:$P$874,G13,BS_RE33!$Z$7:$Z$874) -> 0 | K13: =SUMIF(BS_RE33!$P$7:$P$874,G13,BS_RE33!$AA$7:$AA$874) -> 0 | L13: =SUMIF(BS_RE33!$P$7:$P$874,G13,BS_RE33!$AB$7:$AB$874) -> 0 | M13: =SUMIF(BS_RE33!$P$7:$P$874,G13,BS_RE33!$AC$7:$AC$874) -> 0 | N13: =SUMIF(BS_RE33!$P$7:$P$874,G13,BS_RE33!$AD$7:$AD$874) -> 0 | O13: =SUMIF(BS_RE33!$P$7:$P$874,G13,BS_RE33!$AE$7:$AE$874) -> 0 | P13: =SUMIF(BS_RE33!$P$7:$P$874,G13,BS_RE33!$AF$7:$AF$874) -> 0 | Q13: =SUMIF(BS_RE33!$P$7:$P$874,G13,BS_RE33!$AG$7:$AG$874) -> 0
E14: Loan | F14: EUBB | G14: Loan_EUBB | H14: =SUMIF(BS_RE33!$P$7:$P$874,G14,BS_RE33!$X$7:$X$874) -> 0 | I14: =SUMIF(BS_RE33!$P$7:$P$874,G14,BS_RE33!$Y$7:$Y$874) -> 0 | J14: =SUMIF(BS_RE33!$P$7:$P$874,G14,BS_RE33!$Z$7:$Z$874) -> 0 | K14: =SUMIF(BS_RE33!$P$7:$P$874,G14,BS_RE33!$AA$7:$AA$874) -> 0 | L14: =SUMIF(BS_RE33!$P$7:$P$874,G14,BS_RE33!$AB$7:$AB$874) -> 0 | M14: =SUMIF(BS_RE33!$P$7:$P$874,G14,BS_RE33!$AC$7:$AC$874) -> 0 | N14: =SUMIF(BS_RE33!$P$7:$P$874,G14,BS_RE33!$AD$7:$AD$874) -> 0 | O14: =SUMIF(BS_RE33!$P$7:$P$874,G14,BS_RE33!$AE$7:$AE$874) -> 0 | P14: =SUMIF(BS_RE33!$P$7:$P$874,G14,BS_RE33!$AF$7:$AF$874) -> 0 | Q14: =SUMIF(BS_RE33!$P$7:$P$874,G14,BS_RE33!$AG$7:$AG$874) -> 0
E15: Loan | F15: Financialinstitutions | G15: Loan_Financialinstitutions | H15: =SUMIF(BS_RE33!$P$7:$P$874,G15,BS_RE33!$X$7:$X$874) -> 0 | I15: =SUMIF(BS_RE33!$P$7:$P$874,G15,BS_RE33!$Y$7:$Y$874) -> 0 | J15: =SUMIF(BS_RE33!$P$7:$P$874,G15,BS_RE33!$Z$7:$Z$874) -> 0 | K15: =SUMIF(BS_RE33!$P$7:$P$874,G15,BS_RE33!$AA$7:$AA$874) -> 0 | L15: =SUMIF(BS_RE33!$P$7:$P$874,G15,BS_RE33!$AB$7:$AB$874) -> 0 | M15: =SUMIF(BS_RE33!$P$7:$P$874,G15,BS_RE33!$AC$7:$AC$874) -> 0 | N15: =SUMIF(BS_RE33!$P$7:$P$874,G15,BS_RE33!$AD$7:$AD$874) -> 0 | O15: =SUMIF(BS_RE33!$P$7:$P$874,G15,BS_RE33!$AE$7:$AE$874) -> 0 | P15: =SUMIF(BS_RE33!$P$7:$P$874,G15,BS_RE33!$AF$7:$AF$874) -> 0 | Q15: =SUMIF(BS_RE33!$P$7:$P$874,G15,BS_RE33!$AG$7:$AG$874) -> 0
D16: Derivative | E16: Derivative_Asset | G16: Derivative_Asset_ | H16: =SUMIF(BS_RE33!$P$7:$P$874,G16,BS_RE33!$X$7:$X$874) -> 0 | I16: =SUMIF(BS_RE33!$P$7:$P$874,G16,BS_RE33!$Y$7:$Y$874) -> 0 | J16: =SUMIF(BS_RE33!$P$7:$P$874,G16,BS_RE33!$Z$7:$Z$874) -> 0 | K16: =SUMIF(BS_RE33!$P$7:$P$874,G16,BS_RE33!$AA$7:$AA$874) -> 0 | L16: =SUMIF(BS_RE33!$P$7:$P$874,G16,BS_RE33!$AB$7:$AB$874) -> 0 | M16: =SUMIF(BS_RE33!$P$7:$P$874,G16,BS_RE33!$AC$7:$AC$874) -> 0 | N16: =SUMIF(BS_RE33!$P$7:$P$874,G16,BS_RE33!$AD$7:$AD$874) -> 0 | O16: =SUMIF(BS_RE33!$P$7:$P$874,G16,BS_RE33!$AE$7:$AE$874) -> 0 | P16: =SUMIF(BS_RE33!$P$7:$P$874,G16,BS_RE33!$AF$7:$AF$874) -> 0 | Q16: =SUMIF(BS_RE33!$P$7:$P$874,G16,BS_RE33!$AG$7:$AG$874) -> 0
D17: Inter-office | E17: Inter-office_Asset (inter-office A) | G17: Inter-office_Asset (inter-office A)_ | H17: =SUMIF(BS_RE33!$P$7:$P$874,G17,BS_RE33!$X$7:$X$874) -> 0 | I17: =SUMIF(BS_RE33!$P$7:$P$874,G17,BS_RE33!$Y$7:$Y$874) -> 0 | J17: =SUMIF(BS_RE33!$P$7:$P$874,G17,BS_RE33!$Z$7:$Z$874) -> 0 | K17: =SUMIF(BS_RE33!$P$7:$P$874,G17,BS_RE33!$AA$7:$AA$874) -> 0 | L17: =SUMIF(BS_RE33!$P$7:$P$874,G17,BS_RE33!$AB$7:$AB$874) -> 0 | M17: =SUMIF(BS_RE33!$P$7:$P$874,G17,BS_RE33!$AC$7:$AC$874) -> 0 | N17: =SUMIF(BS_RE33!$P$7:$P$874,G17,BS_RE33!$AD$7:$AD$874) -> 0 | O17: =SUMIF(BS_RE33!$P$7:$P$874,G17,BS_RE33!$AE$7:$AE$874) -> 0 | P17: =SUMIF(BS_RE33!$P$7:$P$874,G17,BS_RE33!$AF$7:$AF$874) -> 0 | Q17: =SUMIF(BS_RE33!$P$7:$P$874,G17,BS_RE33!$AG$7:$AG$874) -> 0
E18: Inter-office_Asset (inter-office (EUBB)) | G18: Inter-office_Asset (inter-office (EUBB))_ | H18: =SUMIF(BS_RE33!$P$7:$P$874,G18,BS_RE33!$X$7:$X$874) -> 0 | I18: =SUMIF(BS_RE33!$P$7:$P$874,G18,BS_RE33!$Y$7:$Y$874) -> 0 | J18: =SUMIF(BS_RE33!$P$7:$P$874,G18,BS_RE33!$Z$7:$Z$874) -> 0 | K18: =SUMIF(BS_RE33!$P$7:$P$874,G18,BS_RE33!$AA$7:$AA$874) -> 0 | L18: =SUMIF(BS_RE33!$P$7:$P$874,G18,BS_RE33!$AB$7:$AB$874) -> 0 | M18: =SUMIF(BS_RE33!$P$7:$P$874,G18,BS_RE33!$AC$7:$AC$874) -> 0 | N18: =SUMIF(BS_RE33!$P$7:$P$874,G18,BS_RE33!$AD$7:$AD$874) -> 0 | O18: =SUMIF(BS_RE33!$P$7:$P$874,G18,BS_RE33!$AE$7:$AE$874) -> 0 | P18: =SUMIF(BS_RE33!$P$7:$P$874,G18,BS_RE33!$AF$7:$AF$874) -> 0 | Q18: =SUMIF(BS_RE33!$P$7:$P$874,G18,BS_RE33!$AG$7:$AG$874) -> 0
D19: Other Asset | E19: Other_Asset (Receivable) | G19: Other_Asset (Receivable)_ | H19: =SUMIF(BS_RE33!$P$7:$P$874,G19,BS_RE33!$X$7:$X$874) -> 0 | I19: =SUMIF(BS_RE33!$P$7:$P$874,G19,BS_RE33!$Y$7:$Y$874) -> 0 | J19: =SUMIF(BS_RE33!$P$7:$P$874,G19,BS_RE33!$Z$7:$Z$874) -> 0 | K19: =SUMIF(BS_RE33!$P$7:$P$874,G19,BS_RE33!$AA$7:$AA$874) -> 0 | L19: =SUMIF(BS_RE33!$P$7:$P$874,G19,BS_RE33!$AB$7:$AB$874) -> 0 | M19: =SUMIF(BS_RE33!$P$7:$P$874,G19,BS_RE33!$AC$7:$AC$874) -> 0 | N19: =SUMIF(BS_RE33!$P$7:$P$874,G19,BS_RE33!$AD$7:$AD$874) -> 0 | O19: =SUMIF(BS_RE33!$P$7:$P$874,G19,BS_RE33!$AE$7:$AE$874) -> 0 | P19: =SUMIF(BS_RE33!$P$7:$P$874,G19,BS_RE33!$AF$7:$AF$874) -> 0 | Q19: =SUMIF(BS_RE33!$P$7:$P$874,G19,BS_RE33!$AG$7:$AG$874) -> 0
E20: Other_Asset (Accrued Incomes) | G20: Other_Asset (Accrued Incomes)_ | H20: =SUMIF(BS_RE33!$P$7:$P$874,G20,BS_RE33!$X$7:$X$874) -> 0 | I20: =SUMIF(BS_RE33!$P$7:$P$874,G20,BS_RE33!$Y$7:$Y$874) -> 0 | J20: =SUMIF(BS_RE33!$P$7:$P$874,G20,BS_RE33!$Z$7:$Z$874) -> 0 | K20: =SUMIF(BS_RE33!$P$7:$P$874,G20,BS_RE33!$AA$7:$AA$874) -> 0 | L20: =SUMIF(BS_RE33!$P$7:$P$874,G20,BS_RE33!$AB$7:$AB$874) -> 0 | M20: =SUMIF(BS_RE33!$P$7:$P$874,G20,BS_RE33!$AC$7:$AC$874) -> 0 | N20: =SUMIF(BS_RE33!$P$7:$P$874,G20,BS_RE33!$AD$7:$AD$874) -> 0 | O20: =SUMIF(BS_RE33!$P$7:$P$874,G20,BS_RE33!$AE$7:$AE$874) -> 0 | P20: =SUMIF(BS_RE33!$P$7:$P$874,G20,BS_RE33!$AF$7:$AF$874) -> 0 | Q20: =SUMIF(BS_RE33!$P$7:$P$874,G20,BS_RE33!$AG$7:$AG$874) -> 0
E21: Other_Asset (Other assets) | G21: Other_Asset (Other assets)_ | H21: =SUMIF(BS_RE33!$P$7:$P$874,G21,BS_RE33!$X$7:$X$874) -> 0 | I21: =SUMIF(BS_RE33!$P$7:$P$874,G21,BS_RE33!$Y$7:$Y$874) -> 0 | J21: =SUMIF(BS_RE33!$P$7:$P$874,G21,BS_RE33!$Z$7:$Z$874) -> 0 | K21: =SUMIF(BS_RE33!$P$7:$P$874,G21,BS_RE33!$AA$7:$AA$874) -> 0 | L21: =SUMIF(BS_RE33!$P$7:$P$874,G21,BS_RE33!$AB$7:$AB$874) -> 0 | M21: =SUMIF(BS_RE33!$P$7:$P$874,G21,BS_RE33!$AC$7:$AC$874) -> 0 | N21: =SUMIF(BS_RE33!$P$7:$P$874,G21,BS_RE33!$AD$7:$AD$874) -> 0 | O21: =SUMIF(BS_RE33!$P$7:$P$874,G21,BS_RE33!$AE$7:$AE$874) -> 0 | P21: =SUMIF(BS_RE33!$P$7:$P$874,G21,BS_RE33!$AF$7:$AF$874) -> 0 | Q21: =SUMIF(BS_RE33!$P$7:$P$874,G21,BS_RE33!$AG$7:$AG$874) -> 0
E22: Other_Asset (Fixed assets) | G22: Other_Asset (Fixed assets)_ | H22: =SUMIF(BS_RE33!$P$7:$P$874,G22,BS_RE33!$X$7:$X$874) -> 0 | I22: =SUMIF(BS_RE33!$P$7:$P$874,G22,BS_RE33!$Y$7:$Y$874) -> 0 | J22: =SUMIF(BS_RE33!$P$7:$P$874,G22,BS_RE33!$Z$7:$Z$874) -> 0 | K22: =SUMIF(BS_RE33!$P$7:$P$874,G22,BS_RE33!$AA$7:$AA$874) -> 0 | L22: =SUMIF(BS_RE33!$P$7:$P$874,G22,BS_RE33!$AB$7:$AB$874) -> 0 | M22: =SUMIF(BS_RE33!$P$7:$P$874,G22,BS_RE33!$AC$7:$AC$874) -> 0 | N22: =SUMIF(BS_RE33!$P$7:$P$874,G22,BS_RE33!$AD$7:$AD$874) -> 0 | O22: =SUMIF(BS_RE33!$P$7:$P$874,G22,BS_RE33!$AE$7:$AE$874) -> 0 | P22: =SUMIF(BS_RE33!$P$7:$P$874,G22,BS_RE33!$AF$7:$AF$874) -> 0 | Q22: =SUMIF(BS_RE33!$P$7:$P$874,G22,BS_RE33!$AG$7:$AG$874) -> 0
E23: Other_Asset (Lease) | G23: Other_Asset (Lease)_ | H23: =SUMIF(BS_RE33!$P$7:$P$874,G23,BS_RE33!$X$7:$X$874) -> 0 | I23: =SUMIF(BS_RE33!$P$7:$P$874,G23,BS_RE33!$Y$7:$Y$874) -> 0 | J23: =SUMIF(BS_RE33!$P$7:$P$874,G23,BS_RE33!$Z$7:$Z$874) -> 0 | K23: =SUMIF(BS_RE33!$P$7:$P$874,G23,BS_RE33!$AA$7:$AA$874) -> 0 | L23: =SUMIF(BS_RE33!$P$7:$P$874,G23,BS_RE33!$AB$7:$AB$874) -> 0 | M23: =SUMIF(BS_RE33!$P$7:$P$874,G23,BS_RE33!$AC$7:$AC$874) -> 0 | N23: =SUMIF(BS_RE33!$P$7:$P$874,G23,BS_RE33!$AD$7:$AD$874) -> 0 | O23: =SUMIF(BS_RE33!$P$7:$P$874,G23,BS_RE33!$AE$7:$AE$874) -> 0 | P23: =SUMIF(BS_RE33!$P$7:$P$874,G23,BS_RE33!$AF$7:$AF$874) -> 0 | Q23: =SUMIF(BS_RE33!$P$7:$P$874,G23,BS_RE33!$AG$7:$AG$874) -> 0
D24: Total Asset : | F24: =SUM(H24:Q24) -> 0 | H24: =SUM(H4:H23) -> 0 | I24: =SUM(I4:I23) -> 0 | J24: =SUM(J4:J23) -> 0 | K24: =SUM(K4:K23) -> 0 | L24: =SUM(L4:L23) -> 0 | M24: =SUM(M4:M23) -> 0 | N24: =SUM(N4:N23) -> 0 | O24: =SUM(O4:O23) -> 0 | ... Q24: =SUM(Q4:Q23) -> 0
C25: Liability | D25: Deposit | E25: On-demand Deposit | F25: Household | G25: On-demand Deposit_Household | H25: =SUMIF(BS_RE33!$P$7:$P$874,G25,BS_RE33!$X$7:$X$874) -> 0 | I25: =SUMIF(BS_RE33!$P$7:$P$874,G25,BS_RE33!$Y$7:$Y$874) -> 0 | J25: =SUMIF(BS_RE33!$P$7:$P$874,G25,BS_RE33!$Z$7:$Z$874) -> 0 | K25: =SUMIF(BS_RE33!$P$7:$P$874,G25,BS_RE33!$AA$7:$AA$874) -> 0 | L25: =SUMIF(BS_RE33!$P$7:$P$874,G25,BS_RE33!$AB$7:$AB$874) -> 0 | M25: =SUMIF(BS_RE33!$P$7:$P$874,G25,BS_RE33!$AC$7:$AC$874) -> 0 | N25: =SUMIF(BS_RE33!$P$7:$P$874,G25,BS_RE33!$AD$7:$AD$874) -> 0 | O25: =SUMIF(BS_RE33!$P$7:$P$874,G25,BS_RE33!$AE$7:$AE$874) -> 0 | P25: =SUMIF(BS_RE33!$P$7:$P$874,G25,BS_RE33!$AF$7:$AF$874) -> 0 | Q25: =SUMIF(BS_RE33!$P$7:$P$874,G25,BS_RE33!$AG$7:$AG$874) -> 0
E26: On-demand Deposit | F26: SME | G26: On-demand Deposit_SME | H26: =SUMIF(BS_RE33!$P$7:$P$874,G26,BS_RE33!$X$7:$X$874) -> 0 | I26: =SUMIF(BS_RE33!$P$7:$P$874,G26,BS_RE33!$Y$7:$Y$874) -> 0 | J26: =SUMIF(BS_RE33!$P$7:$P$874,G26,BS_RE33!$Z$7:$Z$874) -> 0 | K26: =SUMIF(BS_RE33!$P$7:$P$874,G26,BS_RE33!$AA$7:$AA$874) -> 0 | L26: =SUMIF(BS_RE33!$P$7:$P$874,G26,BS_RE33!$AB$7:$AB$874) -> 0 | M26: =SUMIF(BS_RE33!$P$7:$P$874,G26,BS_RE33!$AC$7:$AC$874) -> 0 | N26: =SUMIF(BS_RE33!$P$7:$P$874,G26,BS_RE33!$AD$7:$AD$874) -> 0 | O26: =SUMIF(BS_RE33!$P$7:$P$874,G26,BS_RE33!$AE$7:$AE$874) -> 0 | P26: =SUMIF(BS_RE33!$P$7:$P$874,G26,BS_RE33!$AF$7:$AF$874) -> 0 | Q26: =SUMIF(BS_RE33!$P$7:$P$874,G26,BS_RE33!$AG$7:$AG$874) -> 0
E27: On-demand Deposit | F27: Non-financialcorporations | G27: On-demand Deposit_Non-financialcorporations | H27: =SUMIF(BS_RE33!$P$7:$P$874,G27,BS_RE33!$X$7:$X$874) -> 0 | I27: =SUMIF(BS_RE33!$P$7:$P$874,G27,BS_RE33!$Y$7:$Y$874) -> 0 | J27: =SUMIF(BS_RE33!$P$7:$P$874,G27,BS_RE33!$Z$7:$Z$874) -> 0 | K27: =SUMIF(BS_RE33!$P$7:$P$874,G27,BS_RE33!$AA$7:$AA$874) -> 0 | L27: =SUMIF(BS_RE33!$P$7:$P$874,G27,BS_RE33!$AB$7:$AB$874) -> 0 | M27: =SUMIF(BS_RE33!$P$7:$P$874,G27,BS_RE33!$AC$7:$AC$874) -> 0 | N27: =SUMIF(BS_RE33!$P$7:$P$874,G27,BS_RE33!$AD$7:$AD$874) -> 0 | O27: =SUMIF(BS_RE33!$P$7:$P$874,G27,BS_RE33!$AE$7:$AE$874) -> 0 | P27: =SUMIF(BS_RE33!$P$7:$P$874,G27,BS_RE33!$AF$7:$AF$874) -> 0 | Q27: =SUMIF(BS_RE33!$P$7:$P$874,G27,BS_RE33!$AG$7:$AG$874) -> 0
E28: On-demand Deposit | F28: Other Institution | G28: On-demand Deposit_Other Institution | H28: =SUMIF(BS_RE33!$P$7:$P$874,G28,BS_RE33!$X$7:$X$874) -> 0 | I28: =SUMIF(BS_RE33!$P$7:$P$874,G28,BS_RE33!$Y$7:$Y$874) -> 0 | J28: =SUMIF(BS_RE33!$P$7:$P$874,G28,BS_RE33!$Z$7:$Z$874) -> 0 | K28: =SUMIF(BS_RE33!$P$7:$P$874,G28,BS_RE33!$AA$7:$AA$874) -> 0 | L28: =SUMIF(BS_RE33!$P$7:$P$874,G28,BS_RE33!$AB$7:$AB$874) -> 0 | M28: =SUMIF(BS_RE33!$P$7:$P$874,G28,BS_RE33!$AC$7:$AC$874) -> 0 | N28: =SUMIF(BS_RE33!$P$7:$P$874,G28,BS_RE33!$AD$7:$AD$874) -> 0 | O28: =SUMIF(BS_RE33!$P$7:$P$874,G28,BS_RE33!$AE$7:$AE$874) -> 0 | P28: =SUMIF(BS_RE33!$P$7:$P$874,G28,BS_RE33!$AF$7:$AF$874) -> 0 | Q28: =SUMIF(BS_RE33!$P$7:$P$874,G28,BS_RE33!$AG$7:$AG$874) -> 0
E29: On-demand Deposit | F29: Financialinstitutions | G29: On-demand Deposit_Financialinstitutions | H29: =SUMIF(BS_RE33!$P$7:$P$874,G29,BS_RE33!$X$7:$X$874) -> 0 | I29: =SUMIF(BS_RE33!$P$7:$P$874,G29,BS_RE33!$Y$7:$Y$874) -> 0 | J29: =SUMIF(BS_RE33!$P$7:$P$874,G29,BS_RE33!$Z$7:$Z$874) -> 0 | K29: =SUMIF(BS_RE33!$P$7:$P$874,G29,BS_RE33!$AA$7:$AA$874) -> 0 | L29: =SUMIF(BS_RE33!$P$7:$P$874,G29,BS_RE33!$AB$7:$AB$874) -> 0 | M29: =SUMIF(BS_RE33!$P$7:$P$874,G29,BS_RE33!$AC$7:$AC$874) -> 0 | N29: =SUMIF(BS_RE33!$P$7:$P$874,G29,BS_RE33!$AD$7:$AD$874) -> 0 | O29: =SUMIF(BS_RE33!$P$7:$P$874,G29,BS_RE33!$AE$7:$AE$874) -> 0 | P29: =SUMIF(BS_RE33!$P$7:$P$874,G29,BS_RE33!$AF$7:$AF$874) -> 0 | Q29: =SUMIF(BS_RE33!$P$7:$P$874,G29,BS_RE33!$AG$7:$AG$874) -> 0
E30: Other deposit (Time deposit) | F30: Household | G30: Other deposit (Time deposit)_Household | H30: =SUMIF(BS_RE33!$P$7:$P$874,G30,BS_RE33!$X$7:$X$874) -> 0 | I30: =SUMIF(BS_RE33!$P$7:$P$874,G30,BS_RE33!$Y$7:$Y$874) -> 0 | J30: =SUMIF(BS_RE33!$P$7:$P$874,G30,BS_RE33!$Z$7:$Z$874) -> 0 | K30: =SUMIF(BS_RE33!$P$7:$P$874,G30,BS_RE33!$AA$7:$AA$874) -> 0 | L30: =SUMIF(BS_RE33!$P$7:$P$874,G30,BS_RE33!$AB$7:$AB$874) -> 0 | M30: =SUMIF(BS_RE33!$P$7:$P$874,G30,BS_RE33!$AC$7:$AC$874) -> 0 | N30: =SUMIF(BS_RE33!$P$7:$P$874,G30,BS_RE33!$AD$7:$AD$874) -> 0 | O30: =SUMIF(BS_RE33!$P$7:$P$874,G30,BS_RE33!$AE$7:$AE$874) -> 0 | P30: =SUMIF(BS_RE33!$P$7:$P$874,G30,BS_RE33!$AF$7:$AF$874) -> 0 | Q30: =SUMIF(BS_RE33!$P$7:$P$874,G30,BS_RE33!$AG$7:$AG$874) -> 0
E31: Other deposit (Time deposit) | F31: SME | G31: Other deposit (Time deposit)_SME | H31: =SUMIF(BS_RE33!$P$7:$P$874,G31,BS_RE33!$X$7:$X$874) -> 0 | I31: =SUMIF(BS_RE33!$P$7:$P$874,G31,BS_RE33!$Y$7:$Y$874) -> 0 | J31: =SUMIF(BS_RE33!$P$7:$P$874,G31,BS_RE33!$Z$7:$Z$874) -> 0 | K31: =SUMIF(BS_RE33!$P$7:$P$874,G31,BS_RE33!$AA$7:$AA$874) -> 0 | L31: =SUMIF(BS_RE33!$P$7:$P$874,G31,BS_RE33!$AB$7:$AB$874) -> 0 | M31: =SUMIF(BS_RE33!$P$7:$P$874,G31,BS_RE33!$AC$7:$AC$874) -> 0 | N31: =SUMIF(BS_RE33!$P$7:$P$874,G31,BS_RE33!$AD$7:$AD$874) -> 0 | O31: =SUMIF(BS_RE33!$P$7:$P$874,G31,BS_RE33!$AE$7:$AE$874) -> 0 | P31: =SUMIF(BS_RE33!$P$7:$P$874,G31,BS_RE33!$AF$7:$AF$874) -> 0 | Q31: =SUMIF(BS_RE33!$P$7:$P$874,G31,BS_RE33!$AG$7:$AG$874) -> 0
E32: Other deposit (Time deposit) | F32: Non-financialcorporations | G32: Other deposit (Time deposit)_Non-financialcorporations | H32: =SUMIF(BS_RE33!$P$7:$P$874,G32,BS_RE33!$X$7:$X$874) -> 0 | I32: =SUMIF(BS_RE33!$P$7:$P$874,G32,BS_RE33!$Y$7:$Y$874) -> 0 | J32: =SUMIF(BS_RE33!$P$7:$P$874,G32,BS_RE33!$Z$7:$Z$874) -> 0 | K32: =SUMIF(BS_RE33!$P$7:$P$874,G32,BS_RE33!$AA$7:$AA$874) -> 0 | L32: =SUMIF(BS_RE33!$P$7:$P$874,G32,BS_RE33!$AB$7:$AB$874) -> 0 | M32: =SUMIF(BS_RE33!$P$7:$P$874,G32,BS_RE33!$AC$7:$AC$874) -> 0 | N32: =SUMIF(BS_RE33!$P$7:$P$874,G32,BS_RE33!$AD$7:$AD$874) -> 0 | O32: =SUMIF(BS_RE33!$P$7:$P$874,G32,BS_RE33!$AE$7:$AE$874) -> 0 | P32: =SUMIF(BS_RE33!$P$7:$P$874,G32,BS_RE33!$AF$7:$AF$874) -> 0 | Q32: =SUMIF(BS_RE33!$P$7:$P$874,G32,BS_RE33!$AG$7:$AG$874) -> 0
E33: Other deposit (Time deposit) | F33: Other Institution | G33: Other deposit (Time deposit)_Other Institution | H33: =SUMIF(BS_RE33!$P$7:$P$874,G33,BS_RE33!$X$7:$X$874) -> 0 | I33: =SUMIF(BS_RE33!$P$7:$P$874,G33,BS_RE33!$Y$7:$Y$874) -> 0 | J33: =SUMIF(BS_RE33!$P$7:$P$874,G33,BS_RE33!$Z$7:$Z$874) -> 0 | K33: =SUMIF(BS_RE33!$P$7:$P$874,G33,BS_RE33!$AA$7:$AA$874) -> 0 | L33: =SUMIF(BS_RE33!$P$7:$P$874,G33,BS_RE33!$AB$7:$AB$874) -> 0 | M33: =SUMIF(BS_RE33!$P$7:$P$874,G33,BS_RE33!$AC$7:$AC$874) -> 0 | N33: =SUMIF(BS_RE33!$P$7:$P$874,G33,BS_RE33!$AD$7:$AD$874) -> 0 | O33: =SUMIF(BS_RE33!$P$7:$P$874,G33,BS_RE33!$AE$7:$AE$874) -> 0 | P33: =SUMIF(BS_RE33!$P$7:$P$874,G33,BS_RE33!$AF$7:$AF$874) -> 0 | Q33: =SUMIF(BS_RE33!$P$7:$P$874,G33,BS_RE33!$AG$7:$AG$874) -> 0
E34: Other deposit (Time deposit) | F34: Financialinstitutions | G34: Other deposit (Time deposit)_Financialinstitutions | H34: =SUMIF(BS_RE33!$P$7:$P$874,G34,BS_RE33!$X$7:$X$874) -> 0 | I34: =SUMIF(BS_RE33!$P$7:$P$874,G34,BS_RE33!$Y$7:$Y$874) -> 0 | J34: =SUMIF(BS_RE33!$P$7:$P$874,G34,BS_RE33!$Z$7:$Z$874) -> 0 | K34: =SUMIF(BS_RE33!$P$7:$P$874,G34,BS_RE33!$AA$7:$AA$874) -> 0 | L34: =SUMIF(BS_RE33!$P$7:$P$874,G34,BS_RE33!$AB$7:$AB$874) -> 0 | M34: =SUMIF(BS_RE33!$P$7:$P$874,G34,BS_RE33!$AC$7:$AC$874) -> 0 | N34: =SUMIF(BS_RE33!$P$7:$P$874,G34,BS_RE33!$AD$7:$AD$874) -> 0 | O34: =SUMIF(BS_RE33!$P$7:$P$874,G34,BS_RE33!$AE$7:$AE$874) -> 0 | P34: =SUMIF(BS_RE33!$P$7:$P$874,G34,BS_RE33!$AF$7:$AF$874) -> 0 | Q34: =SUMIF(BS_RE33!$P$7:$P$874,G34,BS_RE33!$AG$7:$AG$874) -> 0
D35: Certificate of Deposit (CD) | E35: Deposit (Certificate of Deposit) | G35: Deposit (Certificate of Deposit)_ | H35: =SUMIF(BS_RE33!$P$7:$P$874,G35,BS_RE33!$X$7:$X$874) -> 0 | I35: =SUMIF(BS_RE33!$P$7:$P$874,G35,BS_RE33!$Y$7:$Y$874) -> 0 | J35: =SUMIF(BS_RE33!$P$7:$P$874,G35,BS_RE33!$Z$7:$Z$874) -> 0 | K35: =SUMIF(BS_RE33!$P$7:$P$874,G35,BS_RE33!$AA$7:$AA$874) -> 0 | L35: =SUMIF(BS_RE33!$P$7:$P$874,G35,BS_RE33!$AB$7:$AB$874) -> 0 | M35: =SUMIF(BS_RE33!$P$7:$P$874,G35,BS_RE33!$AC$7:$AC$874) -> 0 | N35: =SUMIF(BS_RE33!$P$7:$P$874,G35,BS_RE33!$AD$7:$AD$874) -> 0 | O35: =SUMIF(BS_RE33!$P$7:$P$874,G35,BS_RE33!$AE$7:$AE$874) -> 0 | P35: =SUMIF(BS_RE33!$P$7:$P$874,G35,BS_RE33!$AF$7:$AF$874) -> 0 | Q35: =SUMIF(BS_RE33!$P$7:$P$874,G35,BS_RE33!$AG$7:$AG$874) -> 0
E36: Deposit (Term Certificate of Deposit) | G36: Deposit (Term Certificate of Deposit)_ | H36: =SUMIF(BS_RE33!$P$7:$P$874,G36,BS_RE33!$X$7:$X$874) -> 0 | I36: =SUMIF(BS_RE33!$P$7:$P$874,G36,BS_RE33!$Y$7:$Y$874) -> 0 | J36: =SUMIF(BS_RE33!$P$7:$P$874,G36,BS_RE33!$Z$7:$Z$874) -> 0 | K36: =SUMIF(BS_RE33!$P$7:$P$874,G36,BS_RE33!$AA$7:$AA$874) -> 0 | L36: =SUMIF(BS_RE33!$P$7:$P$874,G36,BS_RE33!$AB$7:$AB$874) -> 0 | M36: =SUMIF(BS_RE33!$P$7:$P$874,G36,BS_RE33!$AC$7:$AC$874) -> 0 | N36: =SUMIF(BS_RE33!$P$7:$P$874,G36,BS_RE33!$AD$7:$AD$874) -> 0 | O36: =SUMIF(BS_RE33!$P$7:$P$874,G36,BS_RE33!$AE$7:$AE$874) -> 0 | P36: =SUMIF(BS_RE33!$P$7:$P$874,G36,BS_RE33!$AF$7:$AF$874) -> 0 | Q36: =SUMIF(BS_RE33!$P$7:$P$874,G36,BS_RE33!$AG$7:$AG$874) -> 0
D37: Borrowing | E37: Borrowing (Short term borrowoing) | G37: Borrowing (Short term borrowoing)_ | H37: =SUMIF(BS_RE33!$P$7:$P$874,G37,BS_RE33!$X$7:$X$874) -> 0 | I37: =SUMIF(BS_RE33!$P$7:$P$874,G37,BS_RE33!$Y$7:$Y$874) -> 0 | J37: =SUMIF(BS_RE33!$P$7:$P$874,G37,BS_RE33!$Z$7:$Z$874) -> 0 | K37: =SUMIF(BS_RE33!$P$7:$P$874,G37,BS_RE33!$AA$7:$AA$874) -> 0 | L37: =SUMIF(BS_RE33!$P$7:$P$874,G37,BS_RE33!$AB$7:$AB$874) -> 0 | M37: =SUMIF(BS_RE33!$P$7:$P$874,G37,BS_RE33!$AC$7:$AC$874) -> 0 | N37: =SUMIF(BS_RE33!$P$7:$P$874,G37,BS_RE33!$AD$7:$AD$874) -> 0 | O37: =SUMIF(BS_RE33!$P$7:$P$874,G37,BS_RE33!$AE$7:$AE$874) -> 0 | P37: =SUMIF(BS_RE33!$P$7:$P$874,G37,BS_RE33!$AF$7:$AF$874) -> 0 | Q37: =SUMIF(BS_RE33!$P$7:$P$874,G37,BS_RE33!$AG$7:$AG$874) -> 0
E38: Borrowing (Long term borrowoing) | G38: Borrowing (Long term borrowoing)_ | H38: =SUMIF(BS_RE33!$P$7:$P$874,G38,BS_RE33!$X$7:$X$874) -> 0 | I38: =SUMIF(BS_RE33!$P$7:$P$874,G38,BS_RE33!$Y$7:$Y$874) -> 0 | J38: =SUMIF(BS_RE33!$P$7:$P$874,G38,BS_RE33!$Z$7:$Z$874) -> 0 | K38: =SUMIF(BS_RE33!$P$7:$P$874,G38,BS_RE33!$AA$7:$AA$874) -> 0 | L38: =SUMIF(BS_RE33!$P$7:$P$874,G38,BS_RE33!$AB$7:$AB$874) -> 0 | M38: =SUMIF(BS_RE33!$P$7:$P$874,G38,BS_RE33!$AC$7:$AC$874) -> 0 | N38: =SUMIF(BS_RE33!$P$7:$P$874,G38,BS_RE33!$AD$7:$AD$874) -> 0 | O38: =SUMIF(BS_RE33!$P$7:$P$874,G38,BS_RE33!$AE$7:$AE$874) -> 0 | P38: =SUMIF(BS_RE33!$P$7:$P$874,G38,BS_RE33!$AF$7:$AF$874) -> 0 | Q38: =SUMIF(BS_RE33!$P$7:$P$874,G38,BS_RE33!$AG$7:$AG$874) -> 0
D39: Bond | E39: Bond issued | G39: Bond issued_ | H39: =SUMIF(BS_RE33!$P$7:$P$874,G39,BS_RE33!$X$7:$X$874) -> 0 | I39: =SUMIF(BS_RE33!$P$7:$P$874,G39,BS_RE33!$Y$7:$Y$874) -> 0 | J39: =SUMIF(BS_RE33!$P$7:$P$874,G39,BS_RE33!$Z$7:$Z$874) -> 0 | K39: =SUMIF(BS_RE33!$P$7:$P$874,G39,BS_RE33!$AA$7:$AA$874) -> 0 | L39: =SUMIF(BS_RE33!$P$7:$P$874,G39,BS_RE33!$AB$7:$AB$874) -> 0 | M39: =SUMIF(BS_RE33!$P$7:$P$874,G39,BS_RE33!$AC$7:$AC$874) -> 0 | N39: =SUMIF(BS_RE33!$P$7:$P$874,G39,BS_RE33!$AD$7:$AD$874) -> 0 | O39: =SUMIF(BS_RE33!$P$7:$P$874,G39,BS_RE33!$AE$7:$AE$874) -> 0 | P39: =SUMIF(BS_RE33!$P$7:$P$874,G39,BS_RE33!$AF$7:$AF$874) -> 0 | Q39: =SUMIF(BS_RE33!$P$7:$P$874,G39,BS_RE33!$AG$7:$AG$874) -> 0
D40: Derivative | E40: Derivative_Liability | G40: Derivative_Liability_ | H40: =SUMIF(BS_RE33!$P$7:$P$874,G40,BS_RE33!$X$7:$X$874) -> 0 | I40: =SUMIF(BS_RE33!$P$7:$P$874,G40,BS_RE33!$Y$7:$Y$874) -> 0 | J40: =SUMIF(BS_RE33!$P$7:$P$874,G40,BS_RE33!$Z$7:$Z$874) -> 0 | K40: =SUMIF(BS_RE33!$P$7:$P$874,G40,BS_RE33!$AA$7:$AA$874) -> 0 | L40: =SUMIF(BS_RE33!$P$7:$P$874,G40,BS_RE33!$AB$7:$AB$874) -> 0 | M40: =SUMIF(BS_RE33!$P$7:$P$874,G40,BS_RE33!$AC$7:$AC$874) -> 0 | N40: =SUMIF(BS_RE33!$P$7:$P$874,G40,BS_RE33!$AD$7:$AD$874) -> 0 | O40: =SUMIF(BS_RE33!$P$7:$P$874,G40,BS_RE33!$AE$7:$AE$874) -> 0 | P40: =SUMIF(BS_RE33!$P$7:$P$874,G40,BS_RE33!$AF$7:$AF$874) -> 0 | Q40: =SUMIF(BS_RE33!$P$7:$P$874,G40,BS_RE33!$AG$7:$AG$874) -> 0
D41: Inter-office | E41: Inter-office (Inter-office A/Paid-in capital) | G41: Inter-office (Inter-office A/Paid-in capital)_ | H41: =SUMIF(BS_RE33!$P$7:$P$874,G41,BS_RE33!$X$7:$X$874) -> 0 | I41: =SUMIF(BS_RE33!$P$7:$P$874,G41,BS_RE33!$Y$7:$Y$874) -> 0 | J41: =SUMIF(BS_RE33!$P$7:$P$874,G41,BS_RE33!$Z$7:$Z$874) -> 0 | K41: =SUMIF(BS_RE33!$P$7:$P$874,G41,BS_RE33!$AA$7:$AA$874) -> 0 | L41: =SUMIF(BS_RE33!$P$7:$P$874,G41,BS_RE33!$AB$7:$AB$874) -> 0 | M41: =SUMIF(BS_RE33!$P$7:$P$874,G41,BS_RE33!$AC$7:$AC$874) -> 0 | N41: =SUMIF(BS_RE33!$P$7:$P$874,G41,BS_RE33!$AD$7:$AD$874) -> 0 | O41: =SUMIF(BS_RE33!$P$7:$P$874,G41,BS_RE33!$AE$7:$AE$874) -> 0 | P41: =SUMIF(BS_RE33!$P$7:$P$874,G41,BS_RE33!$AF$7:$AF$874) -> 0 | Q41: =SUMIF(BS_RE33!$P$7:$P$874,G41,BS_RE33!$AG$7:$AG$874) -> 0
E42: Inter-office (Inter-office A) | G42: Inter-office (Inter-office A)_ | H42: =SUMIF(BS_RE33!$P$7:$P$874,G42,BS_RE33!$X$7:$X$874) -> 0 | I42: =SUMIF(BS_RE33!$P$7:$P$874,G42,BS_RE33!$Y$7:$Y$874) -> 0 | J42: =SUMIF(BS_RE33!$P$7:$P$874,G42,BS_RE33!$Z$7:$Z$874) -> 0 | K42: =SUMIF(BS_RE33!$P$7:$P$874,G42,BS_RE33!$AA$7:$AA$874) -> 0 | L42: =SUMIF(BS_RE33!$P$7:$P$874,G42,BS_RE33!$AB$7:$AB$874) -> 0 | M42: =SUMIF(BS_RE33!$P$7:$P$874,G42,BS_RE33!$AC$7:$AC$874) -> 0 | N42: =SUMIF(BS_RE33!$P$7:$P$874,G42,BS_RE33!$AD$7:$AD$874) -> 0 | O42: =SUMIF(BS_RE33!$P$7:$P$874,G42,BS_RE33!$AE$7:$AE$874) -> 0 | P42: =SUMIF(BS_RE33!$P$7:$P$874,G42,BS_RE33!$AF$7:$AF$874) -> 0 | Q42: =SUMIF(BS_RE33!$P$7:$P$874,G42,BS_RE33!$AG$7:$AG$874) -> 0
E43: Inter-office (Inter-office borrowing-short term) | G43: Inter-office (Inter-office borrowing-short term)_ | H43: =SUMIF(BS_RE33!$P$7:$P$874,G43,BS_RE33!$X$7:$X$874) -> 0 | I43: =SUMIF(BS_RE33!$P$7:$P$874,G43,BS_RE33!$Y$7:$Y$874) -> 0 | J43: =SUMIF(BS_RE33!$P$7:$P$874,G43,BS_RE33!$Z$7:$Z$874) -> 0 | K43: =SUMIF(BS_RE33!$P$7:$P$874,G43,BS_RE33!$AA$7:$AA$874) -> 0 | L43: =SUMIF(BS_RE33!$P$7:$P$874,G43,BS_RE33!$AB$7:$AB$874) -> 0 | M43: =SUMIF(BS_RE33!$P$7:$P$874,G43,BS_RE33!$AC$7:$AC$874) -> 0 | N43: =SUMIF(BS_RE33!$P$7:$P$874,G43,BS_RE33!$AD$7:$AD$874) -> 0 | O43: =SUMIF(BS_RE33!$P$7:$P$874,G43,BS_RE33!$AE$7:$AE$874) -> 0 | P43: =SUMIF(BS_RE33!$P$7:$P$874,G43,BS_RE33!$AF$7:$AF$874) -> 0 | Q43: =SUMIF(BS_RE33!$P$7:$P$874,G43,BS_RE33!$AG$7:$AG$874) -> 0
D44: Other Liability | E44: Other_Liability (Payable) | G44: Other_Liability (Payable)_ | H44: =SUMIF(BS_RE33!$P$7:$P$874,G44,BS_RE33!$X$7:$X$874) -> 0 | I44: =SUMIF(BS_RE33!$P$7:$P$874,G44,BS_RE33!$Y$7:$Y$874) -> 0 | J44: =SUMIF(BS_RE33!$P$7:$P$874,G44,BS_RE33!$Z$7:$Z$874) -> 0 | K44: =SUMIF(BS_RE33!$P$7:$P$874,G44,BS_RE33!$AA$7:$AA$874) -> 0 | L44: =SUMIF(BS_RE33!$P$7:$P$874,G44,BS_RE33!$AB$7:$AB$874) -> 0 | M44: =SUMIF(BS_RE33!$P$7:$P$874,G44,BS_RE33!$AC$7:$AC$874) -> 0 | N44: =SUMIF(BS_RE33!$P$7:$P$874,G44,BS_RE33!$AD$7:$AD$874) -> 0 | O44: =SUMIF(BS_RE33!$P$7:$P$874,G44,BS_RE33!$AE$7:$AE$874) -> 0 | P44: =SUMIF(BS_RE33!$P$7:$P$874,G44,BS_RE33!$AF$7:$AF$874) -> 0 | Q44: =SUMIF(BS_RE33!$P$7:$P$874,G44,BS_RE33!$AG$7:$AG$874) -> 0
E45: Other_Liability (Accrued Expenses) | G45: Other_Liability (Accrued Expenses)_ | H45: =SUMIF(BS_RE33!$P$7:$P$874,G45,BS_RE33!$X$7:$X$874) -> 0 | I45: =SUMIF(BS_RE33!$P$7:$P$874,G45,BS_RE33!$Y$7:$Y$874) -> 0 | J45: =SUMIF(BS_RE33!$P$7:$P$874,G45,BS_RE33!$Z$7:$Z$874) -> 0 | K45: =SUMIF(BS_RE33!$P$7:$P$874,G45,BS_RE33!$AA$7:$AA$874) -> 0 | L45: =SUMIF(BS_RE33!$P$7:$P$874,G45,BS_RE33!$AB$7:$AB$874) -> 0 | M45: =SUMIF(BS_RE33!$P$7:$P$874,G45,BS_RE33!$AC$7:$AC$874) -> 0 | N45: =SUMIF(BS_RE33!$P$7:$P$874,G45,BS_RE33!$AD$7:$AD$874) -> 0 | O45: =SUMIF(BS_RE33!$P$7:$P$874,G45,BS_RE33!$AE$7:$AE$874) -> 0 | P45: =SUMIF(BS_RE33!$P$7:$P$874,G45,BS_RE33!$AF$7:$AF$874) -> 0 | Q45: =SUMIF(BS_RE33!$P$7:$P$874,G45,BS_RE33!$AG$7:$AG$874) -> 0
E46: Other_Liability (Other liabilities) | G46: Other_Liability (Other liabilities)_ | H46: =SUMIF(BS_RE33!$P$7:$P$874,G46,BS_RE33!$X$7:$X$874) -> 0 | I46: =SUMIF(BS_RE33!$P$7:$P$874,G46,BS_RE33!$Y$7:$Y$874) -> 0 | J46: =SUMIF(BS_RE33!$P$7:$P$874,G46,BS_RE33!$Z$7:$Z$874) -> 0 | K46: =SUMIF(BS_RE33!$P$7:$P$874,G46,BS_RE33!$AA$7:$AA$874) -> 0 | L46: =SUMIF(BS_RE33!$P$7:$P$874,G46,BS_RE33!$AB$7:$AB$874) -> 0 | M46: =SUMIF(BS_RE33!$P$7:$P$874,G46,BS_RE33!$AC$7:$AC$874) -> 0 | N46: =SUMIF(BS_RE33!$P$7:$P$874,G46,BS_RE33!$AD$7:$AD$874) -> 0 | O46: =SUMIF(BS_RE33!$P$7:$P$874,G46,BS_RE33!$AE$7:$AE$874) -> 0 | P46: =SUMIF(BS_RE33!$P$7:$P$874,G46,BS_RE33!$AF$7:$AF$874) -> 0 | Q46: =SUMIF(BS_RE33!$P$7:$P$874,G46,BS_RE33!$AG$7:$AG$874) -> 0
E47: Other_Liability (Unearned Incomes) | G47: Other_Liability (Unearned Incomes)_ | H47: =SUMIF(BS_RE33!$P$7:$P$874,G47,BS_RE33!$X$7:$X$874) -> 0 | I47: =SUMIF(BS_RE33!$P$7:$P$874,G47,BS_RE33!$Y$7:$Y$874) -> 0 | J47: =SUMIF(BS_RE33!$P$7:$P$874,G47,BS_RE33!$Z$7:$Z$874) -> 0 | K47: =SUMIF(BS_RE33!$P$7:$P$874,G47,BS_RE33!$AA$7:$AA$874) -> 0 | L47: =SUMIF(BS_RE33!$P$7:$P$874,G47,BS_RE33!$AB$7:$AB$874) -> 0 | M47: =SUMIF(BS_RE33!$P$7:$P$874,G47,BS_RE33!$AC$7:$AC$874) -> 0 | N47: =SUMIF(BS_RE33!$P$7:$P$874,G47,BS_RE33!$AD$7:$AD$874) -> 0 | O47: =SUMIF(BS_RE33!$P$7:$P$874,G47,BS_RE33!$AE$7:$AE$874) -> 0 | P47: =SUMIF(BS_RE33!$P$7:$P$874,G47,BS_RE33!$AF$7:$AF$874) -> 0 | Q47: =SUMIF(BS_RE33!$P$7:$P$874,G47,BS_RE33!$AG$7:$AG$874) -> 0
E48: Other_Liability (Lease) | G48: Other_Liability (Lease)_ | H48: =SUMIF(BS_RE33!$P$7:$P$874,G48,BS_RE33!$X$7:$X$874) -> 0 | I48: =SUMIF(BS_RE33!$P$7:$P$874,G48,BS_RE33!$Y$7:$Y$874) -> 0 | J48: =SUMIF(BS_RE33!$P$7:$P$874,G48,BS_RE33!$Z$7:$Z$874) -> 0 | K48: =SUMIF(BS_RE33!$P$7:$P$874,G48,BS_RE33!$AA$7:$AA$874) -> 0 | L48: =SUMIF(BS_RE33!$P$7:$P$874,G48,BS_RE33!$AB$7:$AB$874) -> 0 | M48: =SUMIF(BS_RE33!$P$7:$P$874,G48,BS_RE33!$AC$7:$AC$874) -> 0 | N48: =SUMIF(BS_RE33!$P$7:$P$874,G48,BS_RE33!$AD$7:$AD$874) -> 0 | O48: =SUMIF(BS_RE33!$P$7:$P$874,G48,BS_RE33!$AE$7:$AE$874) -> 0 | P48: =SUMIF(BS_RE33!$P$7:$P$874,G48,BS_RE33!$AF$7:$AF$874) -> 0 | Q48: =SUMIF(BS_RE33!$P$7:$P$874,G48,BS_RE33!$AG$7:$AG$874) -> 0
E49: Other_Liability (Provision) | G49: Other_Liability (Provision)_ | H49: =SUMIF(BS_RE33!$P$7:$P$874,G49,BS_RE33!$X$7:$X$874) -> 0 | I49: =SUMIF(BS_RE33!$P$7:$P$874,G49,BS_RE33!$Y$7:$Y$874) -> 0 | J49: =SUMIF(BS_RE33!$P$7:$P$874,G49,BS_RE33!$Z$7:$Z$874) -> 0 | K49: =SUMIF(BS_RE33!$P$7:$P$874,G49,BS_RE33!$AA$7:$AA$874) -> 0 | L49: =SUMIF(BS_RE33!$P$7:$P$874,G49,BS_RE33!$AB$7:$AB$874) -> 0 | M49: =SUMIF(BS_RE33!$P$7:$P$874,G49,BS_RE33!$AC$7:$AC$874) -> 0 | N49: =SUMIF(BS_RE33!$P$7:$P$874,G49,BS_RE33!$AD$7:$AD$874) -> 0 | O49: =SUMIF(BS_RE33!$P$7:$P$874,G49,BS_RE33!$AE$7:$AE$874) -> 0 | P49: =SUMIF(BS_RE33!$P$7:$P$874,G49,BS_RE33!$AF$7:$AF$874) -> 0 | Q49: =SUMIF(BS_RE33!$P$7:$P$874,G49,BS_RE33!$AG$7:$AG$874) -> 0
E50: Other_Liability (Position) | G50: Other_Liability (Position)_ | H50: =SUMIF(BS_RE33!$P$7:$P$874,G50,BS_RE33!$X$7:$X$874) -> 0 | I50: =SUMIF(BS_RE33!$P$7:$P$874,G50,BS_RE33!$Y$7:$Y$874) -> 0 | J50: =SUMIF(BS_RE33!$P$7:$P$874,G50,BS_RE33!$Z$7:$Z$874) -> 0 | K50: =SUMIF(BS_RE33!$P$7:$P$874,G50,BS_RE33!$AA$7:$AA$874) -> 0 | L50: =SUMIF(BS_RE33!$P$7:$P$874,G50,BS_RE33!$AB$7:$AB$874) -> 0 | M50: =SUMIF(BS_RE33!$P$7:$P$874,G50,BS_RE33!$AC$7:$AC$874) -> 0 | N50: =SUMIF(BS_RE33!$P$7:$P$874,G50,BS_RE33!$AD$7:$AD$874) -> 0 | O50: =SUMIF(BS_RE33!$P$7:$P$874,G50,BS_RE33!$AE$7:$AE$874) -> 0 | P50: =SUMIF(BS_RE33!$P$7:$P$874,G50,BS_RE33!$AF$7:$AF$874) -> 0 | Q50: =SUMIF(BS_RE33!$P$7:$P$874,G50,BS_RE33!$AG$7:$AG$874) -> 0
D51: Total Liability : | F51: =SUM(H51:Q51) -> 0 | H51: =SUM(H25:H50) -> 0 | I51: =SUM(I25:I50) -> 0 | J51: =SUM(J25:J50) -> 0 | K51: =SUM(K25:K50) -> 0 | L51: =SUM(L25:L50) -> 0 | M51: =SUM(M25:M50) -> 0 | N51: =SUM(N25:N50) -> 0 | O51: =SUM(O25:O50) -> 0 | ... Q51: =SUM(Q25:Q50) -> 0
C52: Equity | D52: Equity | E52: Equity | G52: Equity_ | H52: =SUMIF(BS_RE33!$P$7:$P$874,G52,BS_RE33!$X$7:$X$874) -> 0 | I52: =SUMIF(BS_RE33!$P$7:$P$874,G52,BS_RE33!$Y$7:$Y$874) -> 0 | J52: =SUMIF(BS_RE33!$P$7:$P$874,G52,BS_RE33!$Z$7:$Z$874) -> 0 | K52: =SUMIF(BS_RE33!$P$7:$P$874,G52,BS_RE33!$AA$7:$AA$874) -> 0 | L52: =SUMIF(BS_RE33!$P$7:$P$874,G52,BS_RE33!$AB$7:$AB$874) -> 0 | M52: =SUMIF(BS_RE33!$P$7:$P$874,G52,BS_RE33!$AC$7:$AC$874) -> 0 | N52: =SUMIF(BS_RE33!$P$7:$P$874,G52,BS_RE33!$AD$7:$AD$874) -> 0 | O52: =SUMIF(BS_RE33!$P$7:$P$874,G52,BS_RE33!$AE$7:$AE$874) -> 0 | P52: =SUMIF(BS_RE33!$P$7:$P$874,G52,BS_RE33!$AF$7:$AF$874) -> 0 | Q52: =SUMIF(BS_RE33!$P$7:$P$874,G52,BS_RE33!$AG$7:$AG$874) -> 0
C54: Off-Balance | D54: Forward (Buy) | E54: OFF_Ccy. Forward Buy (Outright Forward) | G54: OFF_Ccy. Forward Buy (Outright Forward)_ | H54: =SUMIF(BS_RE33!$P$7:$P$874,G54,BS_RE33!$X$7:$X$874) -> 0 | I54: =SUMIF(BS_RE33!$P$7:$P$874,G54,BS_RE33!$Y$7:$Y$874) -> 0 | J54: =SUMIF(BS_RE33!$P$7:$P$874,G54,BS_RE33!$Z$7:$Z$874) -> 0 | K54: =SUMIF(BS_RE33!$P$7:$P$874,G54,BS_RE33!$AA$7:$AA$874) -> 0 | L54: =SUMIF(BS_RE33!$P$7:$P$874,G54,BS_RE33!$AB$7:$AB$874) -> 0 | M54: =SUMIF(BS_RE33!$P$7:$P$874,G54,BS_RE33!$AC$7:$AC$874) -> 0 | N54: =SUMIF(BS_RE33!$P$7:$P$874,G54,BS_RE33!$AD$7:$AD$874) -> 0 | O54: =SUMIF(BS_RE33!$P$7:$P$874,G54,BS_RE33!$AE$7:$AE$874) -> 0 | P54: =SUMIF(BS_RE33!$P$7:$P$874,G54,BS_RE33!$AF$7:$AF$874) -> 0 | Q54: =SUMIF(BS_RE33!$P$7:$P$874,G54,BS_RE33!$AG$7:$AG$874) -> 0
D55: IRS (Buy) | E55: OFF_IRS Buy (Trade) | G55: OFF_IRS Buy (Trade)_ | H55: =SUMIF(BS_RE33!$P$7:$P$874,G55,BS_RE33!$X$7:$X$874) -> 0 | I55: =SUMIF(BS_RE33!$P$7:$P$874,G55,BS_RE33!$Y$7:$Y$874) -> 0 | J55: =SUMIF(BS_RE33!$P$7:$P$874,G55,BS_RE33!$Z$7:$Z$874) -> 0 | K55: =SUMIF(BS_RE33!$P$7:$P$874,G55,BS_RE33!$AA$7:$AA$874) -> 0 | L55: =SUMIF(BS_RE33!$P$7:$P$874,G55,BS_RE33!$AB$7:$AB$874) -> 0 | M55: =SUMIF(BS_RE33!$P$7:$P$874,G55,BS_RE33!$AC$7:$AC$874) -> 0 | N55: =SUMIF(BS_RE33!$P$7:$P$874,G55,BS_RE33!$AD$7:$AD$874) -> 0 | O55: =SUMIF(BS_RE33!$P$7:$P$874,G55,BS_RE33!$AE$7:$AE$874) -> 0 | P55: =SUMIF(BS_RE33!$P$7:$P$874,G55,BS_RE33!$AF$7:$AF$874) -> 0 | Q55: =SUMIF(BS_RE33!$P$7:$P$874,G55,BS_RE33!$AG$7:$AG$874) -> 0
E56: OFF_IRS Buy (I/O) | G56: OFF_IRS Buy (I/O)_ | H56: =SUMIF(BS_RE33!$P$7:$P$874,G56,BS_RE33!$X$7:$X$874) -> 0 | I56: =SUMIF(BS_RE33!$P$7:$P$874,G56,BS_RE33!$Y$7:$Y$874) -> 0 | J56: =SUMIF(BS_RE33!$P$7:$P$874,G56,BS_RE33!$Z$7:$Z$874) -> 0 | K56: =SUMIF(BS_RE33!$P$7:$P$874,G56,BS_RE33!$AA$7:$AA$874) -> 0 | L56: =SUMIF(BS_RE33!$P$7:$P$874,G56,BS_RE33!$AB$7:$AB$874) -> 0 | M56: =SUMIF(BS_RE33!$P$7:$P$874,G56,BS_RE33!$AC$7:$AC$874) -> 0 | N56: =SUMIF(BS_RE33!$P$7:$P$874,G56,BS_RE33!$AD$7:$AD$874) -> 0 | O56: =SUMIF(BS_RE33!$P$7:$P$874,G56,BS_RE33!$AE$7:$AE$874) -> 0 | P56: =SUMIF(BS_RE33!$P$7:$P$874,G56,BS_RE33!$AF$7:$AF$874) -> 0 | Q56: =SUMIF(BS_RE33!$P$7:$P$874,G56,BS_RE33!$AG$7:$AG$874) -> 0
D57: Trade Finance | E57: OFF_LC Issued | G57: OFF_LC Issued_ | H57: =SUMIF(BS_RE33!$P$7:$P$874,G57,BS_RE33!$X$7:$X$874) -> 0 | I57: =SUMIF(BS_RE33!$P$7:$P$874,G57,BS_RE33!$Y$7:$Y$874) -> 0 | J57: =SUMIF(BS_RE33!$P$7:$P$874,G57,BS_RE33!$Z$7:$Z$874) -> 0 | K57: =SUMIF(BS_RE33!$P$7:$P$874,G57,BS_RE33!$AA$7:$AA$874) -> 0 | L57: =SUMIF(BS_RE33!$P$7:$P$874,G57,BS_RE33!$AB$7:$AB$874) -> 0 | M57: =SUMIF(BS_RE33!$P$7:$P$874,G57,BS_RE33!$AC$7:$AC$874) -> 0 | N57: =SUMIF(BS_RE33!$P$7:$P$874,G57,BS_RE33!$AD$7:$AD$874) -> 0 | O57: =SUMIF(BS_RE33!$P$7:$P$874,G57,BS_RE33!$AE$7:$AE$874) -> 0 | P57: =SUMIF(BS_RE33!$P$7:$P$874,G57,BS_RE33!$AF$7:$AF$874) -> 0 | Q57: =SUMIF(BS_RE33!$P$7:$P$874,G57,BS_RE33!$AG$7:$AG$874) -> 0
E58: OFF_Acceptance, etc | F58: Current Liability (만기 20%) | G58: OFF_Acceptance, etc_ | H58: =SUMIF(BS_RE33!$P$7:$P$874,G58,BS_RE33!$X$7:$X$874) -> 0 | I58: =SUMIF(BS_RE33!$P$7:$P$874,G58,BS_RE33!$Y$7:$Y$874) -> 0 | J58: =SUMIF(BS_RE33!$P$7:$P$874,G58,BS_RE33!$Z$7:$Z$874) -> 0 | K58: =SUMIF(BS_RE33!$P$7:$P$874,G58,BS_RE33!$AA$7:$AA$874) -> 0 | L58: =SUMIF(BS_RE33!$P$7:$P$874,G58,BS_RE33!$AB$7:$AB$874) -> 0 | M58: =SUMIF(BS_RE33!$P$7:$P$874,G58,BS_RE33!$AC$7:$AC$874) -> 0 | N58: =SUMIF(BS_RE33!$P$7:$P$874,G58,BS_RE33!$AD$7:$AD$874) -> 0 | O58: =SUMIF(BS_RE33!$P$7:$P$874,G58,BS_RE33!$AE$7:$AE$874) -> 0 | P58: =SUMIF(BS_RE33!$P$7:$P$874,G58,BS_RE33!$AF$7:$AF$874) -> 0 | Q58: =SUMIF(BS_RE33!$P$7:$P$874,G58,BS_RE33!$AG$7:$AG$874) -> 0
D59: Guarantee | E59: OFF_Other Guarantee | G59: OFF_Other Guarantee_ | H59: =SUMIF(BS_RE33!$P$7:$P$874,G59,BS_RE33!$X$7:$X$874) -> 0 | I59: =SUMIF(BS_RE33!$P$7:$P$874,G59,BS_RE33!$Y$7:$Y$874) -> 0 | J59: =SUMIF(BS_RE33!$P$7:$P$874,G59,BS_RE33!$Z$7:$Z$874) -> 0 | K59: =SUMIF(BS_RE33!$P$7:$P$874,G59,BS_RE33!$AA$7:$AA$874) -> 0 | L59: =SUMIF(BS_RE33!$P$7:$P$874,G59,BS_RE33!$AB$7:$AB$874) -> 0 | M59: =SUMIF(BS_RE33!$P$7:$P$874,G59,BS_RE33!$AC$7:$AC$874) -> 0 | N59: =SUMIF(BS_RE33!$P$7:$P$874,G59,BS_RE33!$AD$7:$AD$874) -> 0 | O59: =SUMIF(BS_RE33!$P$7:$P$874,G59,BS_RE33!$AE$7:$AE$874) -> 0 | P59: =SUMIF(BS_RE33!$P$7:$P$874,G59,BS_RE33!$AF$7:$AF$874) -> 0 | Q59: =SUMIF(BS_RE33!$P$7:$P$874,G59,BS_RE33!$AG$7:$AG$874) -> 0
E60: OFF_Other Guarantee | G60: OFF_Other Guarantee_ | H60: =SUMIF(BS_RE33!$P$7:$P$874,G60,BS_RE33!$X$7:$X$874) -> 0 | I60: =SUMIF(BS_RE33!$P$7:$P$874,G60,BS_RE33!$Y$7:$Y$874) -> 0 | J60: =SUMIF(BS_RE33!$P$7:$P$874,G60,BS_RE33!$Z$7:$Z$874) -> 0 | K60: =SUMIF(BS_RE33!$P$7:$P$874,G60,BS_RE33!$AA$7:$AA$874) -> 0 | L60: =SUMIF(BS_RE33!$P$7:$P$874,G60,BS_RE33!$AB$7:$AB$874) -> 0 | M60: =SUMIF(BS_RE33!$P$7:$P$874,G60,BS_RE33!$AC$7:$AC$874) -> 0 | N60: =SUMIF(BS_RE33!$P$7:$P$874,G60,BS_RE33!$AD$7:$AD$874) -> 0 | O60: =SUMIF(BS_RE33!$P$7:$P$874,G60,BS_RE33!$AE$7:$AE$874) -> 0 | P60: =SUMIF(BS_RE33!$P$7:$P$874,G60,BS_RE33!$AF$7:$AF$874) -> 0 | Q60: =SUMIF(BS_RE33!$P$7:$P$874,G60,BS_RE33!$AG$7:$AG$874) -> 0
D61: Unused Loan Commitment | E61: OFF_Unused Loan Commitment | F61: Household | G61: OFF_Unused Loan Commitment_Household | H61: =SUMIF(BS_RE33!$P$7:$P$874,G61,BS_RE33!$X$7:$X$874) -> 0 | I61: =SUMIF(BS_RE33!$P$7:$P$874,G61,BS_RE33!$Y$7:$Y$874) -> 0 | J61: =SUMIF(BS_RE33!$P$7:$P$874,G61,BS_RE33!$Z$7:$Z$874) -> 0 | K61: =SUMIF(BS_RE33!$P$7:$P$874,G61,BS_RE33!$AA$7:$AA$874) -> 0 | L61: =SUMIF(BS_RE33!$P$7:$P$874,G61,BS_RE33!$AB$7:$AB$874) -> 0 | M61: =SUMIF(BS_RE33!$P$7:$P$874,G61,BS_RE33!$AC$7:$AC$874) -> 0 | N61: =SUMIF(BS_RE33!$P$7:$P$874,G61,BS_RE33!$AD$7:$AD$874) -> 0 | O61: =SUMIF(BS_RE33!$P$7:$P$874,G61,BS_RE33!$AE$7:$AE$874) -> 0 | P61: =SUMIF(BS_RE33!$P$7:$P$874,G61,BS_RE33!$AF$7:$AF$874) -> 0 | Q61: =SUMIF(BS_RE33!$P$7:$P$874,G61,BS_RE33!$AG$7:$AG$874) -> 0
E62: OFF_Unused Loan Commitment | F62: SME | G62: OFF_Unused Loan Commitment_SME | H62: =SUMIF(BS_RE33!$P$7:$P$874,G62,BS_RE33!$X$7:$X$874) -> 0 | I62: =SUMIF(BS_RE33!$P$7:$P$874,G62,BS_RE33!$Y$7:$Y$874) -> 0 | J62: =SUMIF(BS_RE33!$P$7:$P$874,G62,BS_RE33!$Z$7:$Z$874) -> 0 | K62: =SUMIF(BS_RE33!$P$7:$P$874,G62,BS_RE33!$AA$7:$AA$874) -> 0 | L62: =SUMIF(BS_RE33!$P$7:$P$874,G62,BS_RE33!$AB$7:$AB$874) -> 0 | M62: =SUMIF(BS_RE33!$P$7:$P$874,G62,BS_RE33!$AC$7:$AC$874) -> 0 | N62: =SUMIF(BS_RE33!$P$7:$P$874,G62,BS_RE33!$AD$7:$AD$874) -> 0 | O62: =SUMIF(BS_RE33!$P$7:$P$874,G62,BS_RE33!$AE$7:$AE$874) -> 0 | P62: =SUMIF(BS_RE33!$P$7:$P$874,G62,BS_RE33!$AF$7:$AF$874) -> 0 | Q62: =SUMIF(BS_RE33!$P$7:$P$874,G62,BS_RE33!$AG$7:$AG$874) -> 0
E63: OFF_Unused Loan Commitment | F63: Non-financialcorporations | G63: OFF_Unused Loan Commitment_Non-financialcorporations | H63: =SUMIF(BS_RE33!$P$7:$P$874,G63,BS_RE33!$X$7:$X$874) -> 0 | I63: =SUMIF(BS_RE33!$P$7:$P$874,G63,BS_RE33!$Y$7:$Y$874) -> 0 | J63: =SUMIF(BS_RE33!$P$7:$P$874,G63,BS_RE33!$Z$7:$Z$874) -> 0 | K63: =SUMIF(BS_RE33!$P$7:$P$874,G63,BS_RE33!$AA$7:$AA$874) -> 0 | L63: =SUMIF(BS_RE33!$P$7:$P$874,G63,BS_RE33!$AB$7:$AB$874) -> 0 | M63: =SUMIF(BS_RE33!$P$7:$P$874,G63,BS_RE33!$AC$7:$AC$874) -> 0 | N63: =SUMIF(BS_RE33!$P$7:$P$874,G63,BS_RE33!$AD$7:$AD$874) -> 0 | O63: =SUMIF(BS_RE33!$P$7:$P$874,G63,BS_RE33!$AE$7:$AE$874) -> 0 | P63: =SUMIF(BS_RE33!$P$7:$P$874,G63,BS_RE33!$AF$7:$AF$874) -> 0 | Q63: =SUMIF(BS_RE33!$P$7:$P$874,G63,BS_RE33!$AG$7:$AG$874) -> 0
E64: OFF_Unused Loan Commitment | F64: Financialinstitutions | G64: OFF_Unused Loan Commitment_Financialinstitutions | H64: =SUMIF(BS_RE33!$P$7:$P$874,G64,BS_RE33!$X$7:$X$874) -> 0 | I64: =SUMIF(BS_RE33!$P$7:$P$874,G64,BS_RE33!$Y$7:$Y$874) -> 0 | J64: =SUMIF(BS_RE33!$P$7:$P$874,G64,BS_RE33!$Z$7:$Z$874) -> 0 | K64: =SUMIF(BS_RE33!$P$7:$P$874,G64,BS_RE33!$AA$7:$AA$874) -> 0 | L64: =SUMIF(BS_RE33!$P$7:$P$874,G64,BS_RE33!$AB$7:$AB$874) -> 0 | M64: =SUMIF(BS_RE33!$P$7:$P$874,G64,BS_RE33!$AC$7:$AC$874) -> 0 | N64: =SUMIF(BS_RE33!$P$7:$P$874,G64,BS_RE33!$AD$7:$AD$874) -> 0 | O64: =SUMIF(BS_RE33!$P$7:$P$874,G64,BS_RE33!$AE$7:$AE$874) -> 0 | P64: =SUMIF(BS_RE33!$P$7:$P$874,G64,BS_RE33!$AF$7:$AF$874) -> 0 | Q64: =SUMIF(BS_RE33!$P$7:$P$874,G64,BS_RE33!$AG$7:$AG$874) -> 0
D65: Forward (Sell) | E65: OFF_Ccy. Forward Sell (Unsettled Forward among FX swaps) | G65: OFF_Ccy. Forward Sell (Unsettled Forward among FX swaps)_ | H65: =SUMIF(BS_RE33!$P$7:$P$874,G65,BS_RE33!$X$7:$X$874) -> 0 | I65: =SUMIF(BS_RE33!$P$7:$P$874,G65,BS_RE33!$Y$7:$Y$874) -> 0 | J65: =SUMIF(BS_RE33!$P$7:$P$874,G65,BS_RE33!$Z$7:$Z$874) -> 0 | K65: =SUMIF(BS_RE33!$P$7:$P$874,G65,BS_RE33!$AA$7:$AA$874) -> 0 | L65: =SUMIF(BS_RE33!$P$7:$P$874,G65,BS_RE33!$AB$7:$AB$874) -> 0 | M65: =SUMIF(BS_RE33!$P$7:$P$874,G65,BS_RE33!$AC$7:$AC$874) -> 0 | N65: =SUMIF(BS_RE33!$P$7:$P$874,G65,BS_RE33!$AD$7:$AD$874) -> 0 | O65: =SUMIF(BS_RE33!$P$7:$P$874,G65,BS_RE33!$AE$7:$AE$874) -> 0 | P65: =SUMIF(BS_RE33!$P$7:$P$874,G65,BS_RE33!$AF$7:$AF$874) -> 0 | Q65: =SUMIF(BS_RE33!$P$7:$P$874,G65,BS_RE33!$AG$7:$AG$874) -> 0
D66: Contract on Security | E66: OFF_Contract on Securities | G66: OFF_Contract on Securities_ | H66: =SUMIF(BS_RE33!$P$7:$P$874,G66,BS_RE33!$X$7:$X$874) -> 0 | I66: =SUMIF(BS_RE33!$P$7:$P$874,G66,BS_RE33!$Y$7:$Y$874) -> 0 | J66: =SUMIF(BS_RE33!$P$7:$P$874,G66,BS_RE33!$Z$7:$Z$874) -> 0 | K66: =SUMIF(BS_RE33!$P$7:$P$874,G66,BS_RE33!$AA$7:$AA$874) -> 0 | L66: =SUMIF(BS_RE33!$P$7:$P$874,G66,BS_RE33!$AB$7:$AB$874) -> 0 | M66: =SUMIF(BS_RE33!$P$7:$P$874,G66,BS_RE33!$AC$7:$AC$874) -> 0 | N66: =SUMIF(BS_RE33!$P$7:$P$874,G66,BS_RE33!$AD$7:$AD$874) -> 0 | O66: =SUMIF(BS_RE33!$P$7:$P$874,G66,BS_RE33!$AE$7:$AE$874) -> 0 | P66: =SUMIF(BS_RE33!$P$7:$P$874,G66,BS_RE33!$AF$7:$AF$874) -> 0 | Q66: =SUMIF(BS_RE33!$P$7:$P$874,G66,BS_RE33!$AG$7:$AG$874) -> 0
D67: IRS (Sell) | E67: OFF_IRS Sell (Trade) | G67: OFF_IRS Sell (Trade)_ | H67: =SUMIF(BS_RE33!$P$7:$P$874,G67,BS_RE33!$X$7:$X$874) -> 0 | I67: =SUMIF(BS_RE33!$P$7:$P$874,G67,BS_RE33!$Y$7:$Y$874) -> 0 | J67: =SUMIF(BS_RE33!$P$7:$P$874,G67,BS_RE33!$Z$7:$Z$874) -> 0 | K67: =SUMIF(BS_RE33!$P$7:$P$874,G67,BS_RE33!$AA$7:$AA$874) -> 0 | L67: =SUMIF(BS_RE33!$P$7:$P$874,G67,BS_RE33!$AB$7:$AB$874) -> 0 | M67: =SUMIF(BS_RE33!$P$7:$P$874,G67,BS_RE33!$AC$7:$AC$874) -> 0 | N67: =SUMIF(BS_RE33!$P$7:$P$874,G67,BS_RE33!$AD$7:$AD$874) -> 0 | O67: =SUMIF(BS_RE33!$P$7:$P$874,G67,BS_RE33!$AE$7:$AE$874) -> 0 | P67: =SUMIF(BS_RE33!$P$7:$P$874,G67,BS_RE33!$AF$7:$AF$874) -> 0 | Q67: =SUMIF(BS_RE33!$P$7:$P$874,G67,BS_RE33!$AG$7:$AG$874) -> 0
E68: OFF_IRS Sell (I/O) | G68: OFF_IRS Sell (I/O)_ | H68: =SUMIF(BS_RE33!$P$7:$P$874,G68,BS_RE33!$X$7:$X$874) -> 0 | I68: =SUMIF(BS_RE33!$P$7:$P$874,G68,BS_RE33!$Y$7:$Y$874) -> 0 | J68: =SUMIF(BS_RE33!$P$7:$P$874,G68,BS_RE33!$Z$7:$Z$874) -> 0 | K68: =SUMIF(BS_RE33!$P$7:$P$874,G68,BS_RE33!$AA$7:$AA$874) -> 0 | L68: =SUMIF(BS_RE33!$P$7:$P$874,G68,BS_RE33!$AB$7:$AB$874) -> 0 | M68: =SUMIF(BS_RE33!$P$7:$P$874,G68,BS_RE33!$AC$7:$AC$874) -> 0 | N68: =SUMIF(BS_RE33!$P$7:$P$874,G68,BS_RE33!$AD$7:$AD$874) -> 0 | O68: =SUMIF(BS_RE33!$P$7:$P$874,G68,BS_RE33!$AE$7:$AE$874) -> 0 | P68: =SUMIF(BS_RE33!$P$7:$P$874,G68,BS_RE33!$AF$7:$AF$874) -> 0 | Q68: =SUMIF(BS_RE33!$P$7:$P$874,G68,BS_RE33!$AG$7:$AG$874) -> 0
D69: Other | E69: OFF_Other | G69: OFF_Other_ | H69: =SUMIF(BS_RE33!$P$7:$P$874,G69,BS_RE33!$X$7:$X$874) -> 0 | I69: =SUMIF(BS_RE33!$P$7:$P$874,G69,BS_RE33!$Y$7:$Y$874) -> 0 | J69: =SUMIF(BS_RE33!$P$7:$P$874,G69,BS_RE33!$Z$7:$Z$874) -> 0 | K69: =SUMIF(BS_RE33!$P$7:$P$874,G69,BS_RE33!$AA$7:$AA$874) -> 0 | L69: =SUMIF(BS_RE33!$P$7:$P$874,G69,BS_RE33!$AB$7:$AB$874) -> 0 | M69: =SUMIF(BS_RE33!$P$7:$P$874,G69,BS_RE33!$AC$7:$AC$874) -> 0 | N69: =SUMIF(BS_RE33!$P$7:$P$874,G69,BS_RE33!$AD$7:$AD$874) -> 0 | O69: =SUMIF(BS_RE33!$P$7:$P$874,G69,BS_RE33!$AE$7:$AE$874) -> 0 | P69: =SUMIF(BS_RE33!$P$7:$P$874,G69,BS_RE33!$AF$7:$AF$874) -> 0 | Q69: =SUMIF(BS_RE33!$P$7:$P$874,G69,BS_RE33!$AG$7:$AG$874) -> 0
H72: KRI | I72: KRI | J72: Ratio (%) | K72: Trigger | L72: Reached ? Y or N | M72: Limit | N72: Breached ? Y or N | P72: LCR (%) | Q72: 3M Liquidity Ratio (%)
H73: Liquidity Gap Ratio | I73: 7D | J73: =(SUM(H24:I24)-SUM(H51:I51)-SUM($H$58:$Q$58)*20%)/$F$24 -> #DIV/0! | K73: 0 | L73: =IF(J73<K73,"Y","N") -> #DIV/0! | M73: -0.05 | N73: =IF(J73<M73,"Y","N") -> #DIV/0! | P73: ='30 days CF Table(ALL)'!$D$119 -> #DIV/0! | Q73: =SUM(H24:K24)/SUM(H51:K51) -> #DIV/0!
I74: 1M | J74: =((SUM(H24:J24)-SUM(H51:J51)-SUM($H$58:$Q$58)*20%))/$F$24 -> #DIV/0! | K74: -0.15 | L74: =IF(J74<K74,"Y","N") -> #DIV/0! | M74: -0.2 | N74: =IF(J74<M74,"Y","N") -> #DIV/0!
I75: 3M | J75: =((SUM(H24:K24)-SUM(H51:K51)-SUM($H$58:$Q$58)*20%)/$F$24) -> #DIV/0! | K75: -0.4 | L75: =IF(J75<K75,"Y","N") -> #DIV/0! | M75: -0.45 | N75: =IF(J75<M75,"Y","N") -> #DIV/0!

Sheet BS_RE33
V3: Liquidity Maturity Gap Management | X3: Overnight (O/N) | Y3: 2-7 Days | Z3: 8 Days to <1 month | AA3: 1 to < 3 months | AB3: 3 to < 6 months | AC3: 6 to < 12 months | AD3: 1 to < 3 years | AE3: 3 to < 5 years | AF3: 5 to < 10 years | AG3: 10+ years or No Maturity
M4: Mannual Entry!!! ☞ | N4: 46058 | W4: From | X4: =N4 -> 46058 | Y4: =X5+1 -> 46060 | Z4: =Y5+1 -> 46066 | AA4: =Z5+1 -> 46087 | AB4: =AA5+1 -> 46148 | AC4: =AB5+1 -> 46240 | AD4: =AC5+1 -> 46424 | AE4: =AD5+1 -> 47155 | AF4: =AE5+1 -> 47885 | AG4: =AF5+1 -> 49711
A5: 10212001 | B5: Due from Domestic Banks on Demand | C5: RCH3001AUD | D5: 100000006 | E5: AUSTRALIA AND NEW ZEALAND BANKING GROUP LTD | F5: AUD | G5: 19661.8 | H5: 19661.8 | R5: LCR Information | W5: To | X5: =$X$4+1 -> 46059 | Y5: =$X$4+7 -> 46065 | Z5: =EDATE($X$4,1) -> 46086 | AA5: =EDATE($X$4,3) -> 46147 | AB5: =EDATE($X$4,6) -> 46239 | AC5: =EDATE($X$4,12) -> 46423 | AD5: =EDATE($X$4,36) -> 47154 | AE5: =EDATE($X$4,60) -> 47884 | AF5: =EDATE($X$4,120) -> 49710 | AG5: ='Maturity Adjustment'!C6 -> 401768 | AH5: =AND(AH7:AH874) -> TRUE
A6: 10212001 | B6: Due from Domestic Banks on Demand | C6: RCH3002AUD | D6: 100000006 | E6: AUSTRALIA AND NEW ZEALAND BANKING GROUP LTD | F6: AUD | G6: 4896.04 | H6: 4896.04 | L6: Category | M6: Middle Category | N6: HQLA/Non Cash Flow Cash Inflow /Outflow | O6: Customer Type | P6: Ref. | Q6: Adjusted Base Ccy Amt | R6: Assumptions (%) | S6: LCR Maturity | T6: # of Days | U6: HQLA or Weighted Amount | V6: Liquidity Maturity | W6: Asset / Liability | X6: CA / CL AMT | Y6: CA / CL AMT | Z6: CA / CL AMT | AA6: CA / CL AMT | AB6: CA / CL AMT | AC6: CA / CL AMT | AD6: CA / CL AMT | AE6: CA / CL AMT | AF6: CA / CL AMT | AG6: CA / CL AMT | AH6: True OR False
A7: 10212001 | B7: Due from Domestic Banks on Demand | C7: RCH3003AUD | D7: 100000006 | E7: AUSTRALIA AND NEW ZEALAND BANKING GROUP LTD | F7: AUD | G7: 87377.23 | H7: 87377.23 | L7: =VLOOKUP(A7,'Account Mapping'!$A$2:$E$216,3,0) -> #N/A | M7: =VLOOKUP(A7,'Account Mapping'!$A$2:$E$216,4,0) -> #N/A | N7: =IF(OR(C7='Account Mapping'!$H$4,C7='Account Mapping'!$H$5,C7='Account Mapping'!$H$6),'Account Mapping'!$I$4,VLOOKUP(A7,'Account Mapping'!$A$2:$E$216,5,0)) -> #N/A | O7: =IF(OR(L7="Loan",L7="Deposit_Liability",L7="OFF_Unused Loan Commitment",L7="HQLA"),VLOOKUP(D7,'Customer Type'!$A$3:$C$38,3,0),"") -> #N/A | P7: =M7&"_"&O7 -> #N/A | Q7: =IF(COUNTIF('Account Mapping'!$H$12:$H$45,A7)>0,-H7,H7) -> 87377.23 | R7: =VLOOKUP(P7,Assumptions!$C$2:$D$64,2,0) -> #N/A | S7: =IFERROR(VLOOKUP(A7,'Maturity Adjustment'!$A$3:$C$81,3,0),(IF(J7<$N$4,"Tomorrow",J7))) -> Tomorrow | T7: =IF(S7="Tomorrow",1,(S7-$N$4)) -> 1 | U7: =Q7*R7 -> #N/A | V7: =IFERROR(VLOOKUP(A7,'Maturity Adjustment'!$A$86:$C$91,3,0),S7) -> Tomorrow | W7: =VLOOKUP(A7,'Account Mapping'!$A$2:$F$216,6,0) -> #N/A | X7: =IF(V7="Tomorrow",Q7,IF(AND(V7>$X$4-1,V7<$X$5),Q7,IF(V7=$X$5,Q7,0))) -> 87377.23 | Y7: =IF(AND(V7>$Y$4-1,V7<$Y$5),Q7,IF(V7=$Y$5,Q7,0)) -> 0 | Z7: =IF(AND(V7>$Z$4-1,V7<$Z$5),Q7,IF(V7=$Z$5,Q7,0)) -> 0 | AA7: =IF(AND(V7>$AA$4-1,V7<$AA$5),Q7,IF(V7=$AA$5,Q7,0)) -> 0 | AB7: =IF(AND(V7>$AB$4-1,V7<$AB$5),Q7,IF(V7=$AB$5,Q7,0)) -> 0 | AC7: =IF(AND(V7>$AC$4-1,V7<$AC$5),Q7,IF(V7=$AC$5,Q7,0)) -> 0 | AD7: =IF(AND(V7>$AD$4-1,V7<$AD$5),Q7,IF(V7=$AD$5,Q7,0)) -> 0 | AE7: =IF(AND(V7>$AE$4-1,V7<$AE$5),Q7,IF(V7=$AE$5,Q7,0)) -> 0 | AF7: =IF(AND(V7>$AF$4-1,V7<$AF$5),Q7,IF(V7=$AF$5,Q7,0)) -> 0 | AG7: =IF(AND(V7>$AG$4-1,V7<$AG$5),Q7,IF(V7=$AG$5,Q7,0)) -> 0 | AH7: =Q7=SUM(X7:AG7) -> TRUE | AJ7: Liquidity Gap Ratio
A8: 10212001 | B8: Due from Domestic Banks on Demand | C8: RCH3004AUD | D8: 100000013 | E8: KEB HANA BANK | F8: AUD | G8: 4600972.1 | H8: 4600972.1 | L8: =VLOOKUP(A8,'Account Mapping'!$A$2:$E$216,3,0) -> #N/A | M8: =VLOOKUP(A8,'Account Mapping'!$A$2:$E$216,4,0) -> #N/A | N8: =IF(OR(C8='Account Mapping'!$H$4,C8='Account Mapping'!$H$5,C8='Account Mapping'!$H$6),'Account Mapping'!$I$4,VLOOKUP(A8,'Account Mapping'!$A$2:$E$216,5,0)) -> #N/A | O8: =IF(OR(L8="Loan",L8="Deposit_Liability",L8="OFF_Unused Loan Commitment",L8="HQLA"),VLOOKUP(D8,'Customer Type'!$A$3:$C$38,3,0),"") -> #N/A | P8: =M8&"_"&O8 -> #N/A | Q8: =IF(COUNTIF('Account Mapping'!$H$12:$H$45,A8)>0,-H8,H8) -> 4600972.1 | R8: =VLOOKUP(P8,Assumptions!$C$2:$D$64,2,0) -> #N/A | S8: =IFERROR(VLOOKUP(A8,'Maturity Adjustment'!$A$3:$C$81,3,0),(IF(J8<$N$4,"Tomorrow",J8))) -> Tomorrow | T8: =IF(S8="Tomorrow",1,(S8-$N$4)) -> 1 | U8: =Q8*R8 -> #N/A | V8: =IFERROR(VLOOKUP(A8,'Maturity Adjustment'!$A$86:$C$91,3,0),S8) -> Tomorrow | W8: =VLOOKUP(A8,'Account Mapping'!$A$2:$F$216,6,0) -> #N/A | X8: =IF(V8="Tomorrow",Q8,IF(AND(V8>$X$4-1,V8<$X$5),Q8,IF(V8=$X$5,Q8,0))) -> 4600972.1 | Y8: =IF(AND(V8>$Y$4-1,V8<$Y$5),Q8,IF(V8=$Y$5,Q8,0)) -> 0 | Z8: =IF(AND(V8>$Z$4-1,V8<$Z$5),Q8,IF(V8=$Z$5,Q8,0)) -> 0 | AA8: =IF(AND(V8>$AA$4-1,V8<$AA$5),Q8,IF(V8=$AA$5,Q8,0)) -> 0 | AB8: =IF(AND(V8>$AB$4-1,V8<$AB$5),Q8,IF(V8=$AB$5,Q8,0)) -> 0 | AC8: =IF(AND(V8>$AC$4-1,V8<$AC$5),Q8,IF(V8=$AC$5,Q8,0)) -> 0 | AD8: =IF(AND(V8>$AD$4-1,V8<$AD$5),Q8,IF(V8=$AD$5,Q8,0)) -> 0 | AE8: =IF(AND(V8>$AE$4-1,V8<$AE$5),Q8,IF(V8=$AE$5,Q8,0)) -> 0 | AF8: =IF(AND(V8>$AF$4-1,V8<$AF$5),Q8,IF(V8=$AF$5,Q8,0)) -> 0 | AG8: =IF(AND(V8>$AG$4-1,V8<$AG$5),Q8,IF(V8=$AG$5,Q8,0)) -> 0 | AH8: =Q8=SUM(X8:AG8) -> TRUE
A9: 10212001 | B9: Due from Domestic Banks on Demand | C9: RCH3004USD | D9: 100000013 | E9: KEB HANA BANK | F9: USD | G9: 1351406.1 | H9: 1923983.7 | L9: =VLOOKUP(A9,'Account Mapping'!$A$2:$E$216,3,0) -> #N/A | M9: =VLOOKUP(A9,'Account Mapping'!$A$2:$E$216,4,0) -> #N/A | N9: =IF(OR(C9='Account Mapping'!$H$4,C9='Account Mapping'!$H$5,C9='Account Mapping'!$H$6),'Account Mapping'!$I$4,VLOOKUP(A9,'Account Mapping'!$A$2:$E$216,5,0)) -> #N/A | O9: =IF(OR(L9="Loan",L9="Deposit_Liability",L9="OFF_Unused Loan Commitment",L9="HQLA"),VLOOKUP(D9,'Customer Type'!$A$3:$C$38,3,0),"") -> #N/A | P9: =M9&"_"&O9 -> #N/A | Q9: =IF(COUNTIF('Account Mapping'!$H$12:$H$45,A9)>0,-H9,H9) -> 1923983.7 | R9: =VLOOKUP(P9,Assumptions!$C$2:$D$64,2,0) -> #N/A | S9: =IFERROR(VLOOKUP(A9,'Maturity Adjustment'!$A$3:$C$81,3,0),(IF(J9<$N$4,"Tomorrow",J9))) -> Tomorrow | T9: =IF(S9="Tomorrow",1,(S9-$N$4)) -> 1 | U9: =Q9*R9 -> #N/A | V9: =IFERROR(VLOOKUP(A9,'Maturity Adjustment'!$A$86:$C$91,3,0),S9) -> Tomorrow | W9: =VLOOKUP(A9,'Account Mapping'!$A$2:$F$216,6,0) -> #N/A | X9: =IF(V9="Tomorrow",Q9,IF(AND(V9>$X$4-1,V9<$X$5),Q9,IF(V9=$X$5,Q9,0))) -> 1923983.7 | Y9: =IF(AND(V9>$Y$4-1,V9<$Y$5),Q9,IF(V9=$Y$5,Q9,0)) -> 0 | Z9: =IF(AND(V9>$Z$4-1,V9<$Z$5),Q9,IF(V9=$Z$5,Q9,0)) -> 0 | AA9: =IF(AND(V9>$AA$4-1,V9<$AA$5),Q9,IF(V9=$AA$5,Q9,0)) -> 0 | AB9: =IF(AND(V9>$AB$4-1,V9<$AB$5),Q9,IF(V9=$AB$5,Q9,0)) -> 0 | AC9: =IF(AND(V9>$AC$4-1,V9<$AC$5),Q9,IF(V9=$AC$5,Q9,0)) -> 0 | AD9: =IF(AND(V9>$AD$4-1,V9<$AD$5),Q9,IF(V9=$AD$5,Q9,0)) -> 0 | AE9: =IF(AND(V9>$AE$4-1,V9<$AE$5),Q9,IF(V9=$AE$5,Q9,0)) -> 0 | AF9: =IF(AND(V9>$AF$4-1,V9<$AF$5),Q9,IF(V9=$AF$5,Q9,0)) -> 0 | AG9: =IF(AND(V9>$AG$4-1,V9<$AG$5),Q9,IF(V9=$AG$5,Q9,0)) -> 0 | AH9: =Q9=SUM(X9:AG9) -> TRUE | AJ9: 7 day | AK9: From | AL9: =EOMONTH(N4,0) -> 46081 | AM9: =EOMONTH(AL9,1) -> 46112 | AN9: =EOMONTH(AM9,1) -> 46142 | AO9: =EOMONTH(AN9,1) -> 46173 | AP9: =EOMONTH(AO9,1) -> 46203 | AQ9: =EOMONTH(AP9,1) -> 46234 | AR9: =EOMONTH(AQ9,1) -> 46265 | AS9: =EOMONTH(AR9,1) -> 46295
A10: 10212002 | B10: Due from Oversea Banks on Demand | C10: RCH4001USD | D10: 100000016 | E10: BANK OF AMERICA N.A.(H.O.) | F10: USD | G10: 495563.29 | H10: 705528.6 | L10: =VLOOKUP(A10,'Account Mapping'!$A$2:$E$216,3,0) -> #N/A | M10: =VLOOKUP(A10,'Account Mapping'!$A$2:$E$216,4,0) -> #N/A | N10: =IF(OR(C10='Account Mapping'!$H$4,C10='Account Mapping'!$H$5,C10='Account Mapping'!$H$6),'Account Mapping'!$I$4,VLOOKUP(A10,'Account Mapping'!$A$2:$E$216,5,0)) -> Non Cash Flow | O10: =IF(OR(L10="Loan",L10="Deposit_Liability",L10="OFF_Unused Loan Commitment",L10="HQLA"),VLOOKUP(D10,'Customer Type'!$A$3:$C$38,3,0),"") -> #N/A | P10: =M10&"_"&O10 -> #N/A | Q10: =IF(COUNTIF('Account Mapping'!$H$12:$H$45,A10)>0,-H10,H10) -> 705528.6 | R10: =VLOOKUP(P10,Assumptions!$C$2:$D$64,2,0) -> #N/A | S10: =IFERROR(VLOOKUP(A10,'Maturity Adjustment'!$A$3:$C$81,3,0),(IF(J10<$N$4,"Tomorrow",J10))) -> Tomorrow | T10: =IF(S10="Tomorrow",1,(S10-$N$4)) -> 1 | U10: =Q10*R10 -> #N/A | V10: =IFERROR(VLOOKUP(A10,'Maturity Adjustment'!$A$86:$C$91,3,0),S10) -> Tomorrow | W10: =VLOOKUP(A10,'Account Mapping'!$A$2:$F$216,6,0) -> #N/A | X10: =IF(V10="Tomorrow",Q10,IF(AND(V10>$X$4-1,V10<$X$5),Q10,IF(V10=$X$5,Q10,0))) -> 705528.6 | Y10: =IF(AND(V10>$Y$4-1,V10<$Y$5),Q10,IF(V10=$Y$5,Q10,0)) -> 0 | Z10: =IF(AND(V10>$Z$4-1,V10<$Z$5),Q10,IF(V10=$Z$5,Q10,0)) -> 0 | AA10: =IF(AND(V10>$AA$4-1,V10<$AA$5),Q10,IF(V10=$AA$5,Q10,0)) -> 0 | AB10: =IF(AND(V10>$AB$4-1,V10<$AB$5),Q10,IF(V10=$AB$5,Q10,0)) -> 0 | AC10: =IF(AND(V10>$AC$4-1,V10<$AC$5),Q10,IF(V10=$AC$5,Q10,0)) -> 0 | AD10: =IF(AND(V10>$AD$4-1,V10<$AD$5),Q10,IF(V10=$AD$5,Q10,0)) -> 0 | AE10: =IF(AND(V10>$AE$4-1,V10<$AE$5),Q10,IF(V10=$AE$5,Q10,0)) -> 0 | AF10: =IF(AND(V10>$AF$4-1,V10<$AF$5),Q10,IF(V10=$AF$5,Q10,0)) -> 0 | AG10: =IF(AND(V10>$AG$4-1,V10<$AG$5),Q10,IF(V10=$AG$5,Q10,0)) -> 0 | AH10: =Q10=SUM(X10:AG10) -> TRUE | AK10: To | AL10: =AL9+7 -> 46088 | AM10: =AM9+7 -> 46119 | AN10: =AN9+7 -> 46149 | AO10: =AO9+7 -> 46180 | AP10: =AP9+7 -> 46210 | AQ10: =AQ9+7 -> 46241 | AR10: =AR9+7 -> 46272 | AS10: =AS9+7 -> 46302
A11: 10251002 | B11: Call Loan within 3M - Domestic | C11: FM5904250000051 | D11: 100000008 | E11: E.SUN COMMERCIAL BANK LTD | F11: AUD | G11: 10000000 | H11: 10000000 | I11: 46015 | J11: 46106 | K11: 46106 | L11: =VLOOKUP(A11,'Account Mapping'!$A$2:$E$216,3,0) -> #N/A | M11: =VLOOKUP(A11,'Account Mapping'!$A$2:$E$216,4,0) -> #N/A | N11: =IF(OR(C11='Account Mapping'!$H$4,C11='Account Mapping'!$H$5,C11='Account Mapping'!$H$6),'Account Mapping'!$I$4,VLOOKUP(A11,'Account Mapping'!$A$2:$E$216,5,0)) -> #N/A | O11: =IF(OR(L11="Loan",L11="Deposit_Liability",L11="OFF_Unused Loan Commitment",L11="HQLA"),VLOOKUP(D11,'Customer Type'!$A$3:$C$38,3,0),"") -> #N/A | P11: =M11&"_"&O11 -> #N/A | Q11: =IF(COUNTIF('Account Mapping'!$H$12:$H$45,A11)>0,-H11,H11) -> 10000000 | R11: =VLOOKUP(P11,Assumptions!$C$2:$D$64,2,0) -> #N/A | S11: =IFERROR(VLOOKUP(A11,'Maturity Adjustment'!$A$3:$C$81,3,0),(IF(J11<$N$4,"Tomorrow",J11))) -> 46106 | T11: =IF(S11="Tomorrow",1,(S11-$N$4)) -> 48 | U11: =Q11*R11 -> #N/A | V11: =IFERROR(VLOOKUP(A11,'Maturity Adjustment'!$A$86:$C$91,3,0),S11) -> 46106 | W11: =VLOOKUP(A11,'Account Mapping'!$A$2:$F$216,6,0) -> #N/A | X11: =IF(V11="Tomorrow",Q11,IF(AND(V11>$X$4-1,V11<$X$5),Q11,IF(V11=$X$5,Q11,0))) -> 0 | Y11: =IF(AND(V11>$Y$4-1,V11<$Y$5),Q11,IF(V11=$Y$5,Q11,0)) -> 0 | Z11: =IF(AND(V11>$Z$4-1,V11<$Z$5),Q11,IF(V11=$Z$5,Q11,0)) -> 0 | AA11: =IF(AND(V11>$AA$4-1,V11<$AA$5),Q11,IF(V11=$AA$5,Q11,0)) -> 10000000 | AB11: =IF(AND(V11>$AB$4-1,V11<$AB$5),Q11,IF(V11=$AB$5,Q11,0)) -> 0 | AC11: =IF(AND(V11>$AC$4-1,V11<$AC$5),Q11,IF(V11=$AC$5,Q11,0)) -> 0 | AD11: =IF(AND(V11>$AD$4-1,V11<$AD$5),Q11,IF(V11=$AD$5,Q11,0)) -> 0 | AE11: =IF(AND(V11>$AE$4-1,V11<$AE$5),Q11,IF(V11=$AE$5,Q11,0)) -> 0 | AF11: =IF(AND(V11>$AF$4-1,V11<$AF$5),Q11,IF(V11=$AF$5,Q11,0)) -> 0 | AG11: =IF(AND(V11>$AG$4-1,V11<$AG$5),Q11,IF(V11=$AG$5,Q11,0)) -> 0 | AH11: =Q11=SUM(X11:AG11) -> TRUE
A12: 10251002 | B12: Call Loan within 3M - Domestic | C12: FM5904260000003 | D12: 100000008 | E12: E.SUN COMMERCIAL BANK LTD | F12: AUD | G12: 3000000 | H12: 3000000 | I12: 46035 | J12: 46090 | K12: 46090 | L12: =VLOOKUP(A12,'Account Mapping'!$A$2:$E$216,3,0) -> #N/A | M12: =VLOOKUP(A12,'Account Mapping'!$A$2:$E$216,4,0) -> #N/A | N12: =IF(OR(C12='Account Mapping'!$H$4,C12='Account Mapping'!$H$5,C12='Account Mapping'!$H$6),'Account Mapping'!$I$4,VLOOKUP(A12,'Account Mapping'!$A$2:$E$216,5,0)) -> #N/A | O12: =IF(OR(L12="Loan",L12="Deposit_Liability",L12="OFF_Unused Loan Commitment",L12="HQLA"),VLOOKUP(D12,'Customer Type'!$A$3:$C$38,3,0),"") -> #N/A | P12: =M12&"_"&O12 -> #N/A | Q12: =IF(COUNTIF('Account Mapping'!$H$12:$H$45,A12)>0,-H12,H12) -> 3000000 | R12: =VLOOKUP(P12,Assumptions!$C$2:$D$64,2,0) -> #N/A | S12: =IFERROR(VLOOKUP(A12,'Maturity Adjustment'!$A$3:$C$81,3,0),(IF(J12<$N$4,"Tomorrow",J12))) -> 46090 | T12: =IF(S12="Tomorrow",1,(S12-$N$4)) -> 32 | U12: =Q12*R12 -> #N/A | V12: =IFERROR(VLOOKUP(A12,'Maturity Adjustment'!$A$86:$C$91,3,0),S12) -> 46090 | W12: =VLOOKUP(A12,'Account Mapping'!$A$2:$F$216,6,0) -> #N/A | X12: =IF(V12="Tomorrow",Q12,IF(AND(V12>$X$4-1,V12<$X$5),Q12,IF(V12=$X$5,Q12,0))) -> 0 | Y12: =IF(AND(V12>$Y$4-1,V12<$Y$5),Q12,IF(V12=$Y$5,Q12,0)) -> 0 | Z12: =IF(AND(V12>$Z$4-1,V12<$Z$5),Q12,IF(V12=$Z$5,Q12,0)) -> 0 | AA12: =IF(AND(V12>$AA$4-1,V12<$AA$5),Q12,IF(V12=$AA$5,Q12,0)) -> 3000000 | AB12: =IF(AND(V12>$AB$4-1,V12<$AB$5),Q12,IF(V12=$AB$5,Q12,0)) -> 0 | AC12: =IF(AND(V12>$AC$4-1,V12<$AC$5),Q12,IF(V12=$AC$5,Q12,0)) -> 0 | AD12: =IF(AND(V12>$AD$4-1,V12<$AD$5),Q12,IF(V12=$AD$5,Q12,0)) -> 0 | AE12: =IF(AND(V12>$AE$4-1,V12<$AE$5),Q12,IF(V12=$AE$5,Q12,0)) -> 0 | AF12: =IF(AND(V12>$AF$4-1,V12<$AF$5),Q12,IF(V12=$AF$5,Q12,0)) -> 0 | AG12: =IF(AND(V12>$AG$4-1,V12<$AG$5),Q12,IF(V12=$AG$5,Q12,0)) -> 0 | AH12: =Q12=SUM(X12:AG12) -> TRUE | AL12: =AL9 -> 46081 | AM12: =AM9 -> 46112 | AN12: =AN9 -> 46142 | AO12: =AO9 -> 46173 | AP12: =AP9 -> 46203 | AQ12: =AQ9 -> 46234 | AR12: =AR9 -> 46265 | AS12: =AS9 -> 46295
A13: 10251002 | B13: Call Loan within 3M - Domestic | C13: FM5904260000004 | D13: 100000008 | E13: E.SUN COMMERCIAL BANK LTD | F13: AUD | G13: 4000000 | H13: 4000000 | I13: 46035 | J13: 46125 | K13: 46125 | L13: =VLOOKUP(A13,'Account Mapping'!$A$2:$E$216,3,0) -> #N/A | M13: =VLOOKUP(A13,'Account Mapping'!$A$2:$E$216,4,0) -> #N/A | N13: =IF(OR(C13='Account Mapping'!$H$4,C13='Account Mapping'!$H$5,C13='Account Mapping'!$H$6),'Account Mapping'!$I$4,VLOOKUP(A13,'Account Mapping'!$A$2:$E$216,5,0)) -> #N/A | O13: =IF(OR(L13="Loan",L13="Deposit_Liability",L13="OFF_Unused Loan Commitment",L13="HQLA"),VLOOKUP(D13,'Customer Type'!$A$3:$C$38,3,0),"") -> #N/A | P13: =M13&"_"&O13 -> #N/A | Q13: =IF(COUNTIF('Account Mapping'!$H$12:$H$45,A13)>0,-H13,H13) -> 4000000 | R13: =VLOOKUP(P13,Assumptions!$C$2:$D$64,2,0) -> #N/A | S13: =IFERROR(VLOOKUP(A13,'Maturity Adjustment'!$A$3:$C$81,3,0),(IF(J13<$N$4,"Tomorrow",J13))) -> 46125 | T13: =IF(S13="Tomorrow",1,(S13-$N$4)) -> 67 | U13: =Q13*R13 -> #N/A | V13: =IFERROR(VLOOKUP(A13,'Maturity Adjustment'!$A$86:$C$91,3,0),S13) -> 46125 | W13: =VLOOKUP(A13,'Account Mapping'!$A$2:$F$216,6,0) -> #N/A | X13: =IF(V13="Tomorrow",Q13,IF(AND(V13>$X$4-1,V13<$X$5),Q13,IF(V13=$X$5,Q13,0))) -> 0 | Y13: =IF(AND(V13>$Y$4-1,V13<$Y$5),Q13,IF(V13=$Y$5,Q13,0)) -> 0 | Z13: =IF(AND(V13>$Z$4-1,V13<$Z$5),Q13,IF(V13=$Z$5,Q13,0)) -> 0 | AA13: =IF(AND(V13>$AA$4-1,V13<$AA$5),Q13,IF(V13=$AA$5,Q13,0)) -> 4000000 | AB13: =IF(AND(V13>$AB$4-1,V13<$AB$5),Q13,IF(V13=$AB$5,Q13,0)) -> 0 | AC13: =IF(AND(V13>$AC$4-1,V13<$AC$5),Q13,IF(V13=$AC$5,Q13,0)) -> 0 | AD13: =IF(AND(V13>$AD$4-1,V13<$AD$5),Q13,IF(V13=$AD$5,Q13,0)) -> 0 | AE13: =IF(AND(V13>$AE$4-1,V13<$AE$5),Q13,IF(V13=$AE$5,Q13,0)) -> 0 | AF13: =IF(AND(V13>$AF$4-1,V13<$AF$5),Q13,IF(V13=$AF$5,Q13,0)) -> 0 | AG13: =IF(AND(V13>$AG$4-1,V13<$AG$5),Q13,IF(V13=$AG$5,Q13,0)) -> 0 | AH13: =Q13=SUM(X13:AG13) -> TRUE | AK13: Asset | AL13: =SUMIFS($H$7:$H$874,$W$7:$W$874,AK13,$V$7:$V$874,">"&AL9,$V$7:$V$874,"<="&AL10)+SUMIFS($H$7:$H$874,$W$7:$W$874,AK13,$V$7:$V$874,"Tomorrow") -> 0 | AM13: =SUMIFS($H$7:$H$874,$W$7:$W$874,AK13,$V$7:$V$874,">"&AM9,$V$7:$V$874,"<="&AM10)+SUMIFS($H$7:$H$874,$W$7:$W$874,AK13,$V$7:$V$874,"Tomorrow") -> 0 | AN13: =SUMIFS($H$7:$H$874,$W$7:$W$874,AK13,$V$7:$V$874,">"&AN9,$V$7:$V$874,"<="&AN10)+SUMIFS($H$7:$H$874,$W$7:$W$874,AK13,$V$7:$V$874,"Tomorrow") -> 0 | AO13: =SUMIFS($H$7:$H$874,$W$7:$W$874,AK13,$V$7:$V$874,">"&AO9,$V$7:$V$874,"<="&AO10)+SUMIFS($H$7:$H$874,$W$7:$W$874,AK13,$V$7:$V$874,"Tomorrow") -> 0 | AP13: =SUMIFS($H$7:$H$874,$W$7:$W$874,AK13,$V$7:$V$874,">"&AP9,$V$7:$V$874,"<="&AP10)+SUMIFS($H$7:$H$874,$W$7:$W$874,AK13,$V$7:$V$874,"Tomorrow") -> 0 | AQ13: =SUMIFS($H$7:$H$874,$W$7:$W$874,AK13,$V$7:$V$874,">"&AQ9,$V$7:$V$874,"<="&AQ10)+SUMIFS($H$7:$H$874,$W$7:$W$874,AK13,$V$7:$V$874,"Tomorrow") -> 0 | AR13: =SUMIFS($H$7:$H$874,$W$7:$W$874,AK13,$V$7:$V$874,">"&AR9,$V$7:$V$874,"<="&AR10)+SUMIFS($H$7:$H$874,$W$7:$W$874,AK13,$V$7:$V$874,"Tomorrow") -> 0 | AS13: =SUMIFS($H$7:$H$874,$W$7:$W$874,AK13,$V$7:$V$874,">"&AS9,$V$7:$V$874,"<="&AS10)+SUMIFS($H$7:$H$874,$W$7:$W$874,AK13,$V$7:$V$874,"Tomorrow") -> 0
A14: 10310002 | B14: Securities - FVOCI State | C14: FB5904240000001 | D14: 100000027 | E14: TREASURY CORPORATION OF VICTORIA | F14: AUD | G14: 5054150 | H14: 5054150 | I14: 45387 | J14: 46343 | K14: 46342 | L14: =VLOOKUP(A14,'Account Mapping'!$A$2:$E$216,3,0) -> #N/A | M14: =VLOOKUP(A14,'Account Mapping'!$A$2:$E$216,4,0) -> #N/A | N14: =IF(OR(C14='Account Mapping'!$H$4,C14='Account Mapping'!$H$5,C14='Account Mapping'!$H$6),'Account Mapping'!$I$4,VLOOKUP(A14,'Account Mapping'!$A$2:$E$216,5,0)) -> #N/A | O14: =IF(OR(L14="Loan",L14="Deposit_Liability",L14="OFF_Unused Loan Commitment",L14="HQLA"),VLOOKUP(D14,'Customer Type'!$A$3:$C$38,3,0),"") -> #N/A | P14: =M14&"_"&O14 -> #N/A | Q14: =IF(COUNTIF('Account Mapping'!$H$12:$H$45,A14)>0,-H14,H14) -> 5054150 | R14: =VLOOKUP(P14,Assumptions!$C$2:$D$64,2,0) -> #N/A | S14: =IFERROR(VLOOKUP(A14,'Maturity Adjustment'!$A$3:$C$81,3,0),(IF(J14<$N$4,"Tomorrow",J14))) -> 46343 | T14: =IF(S14="Tomorrow",1,(S14-$N$4)) -> 285 | U14: =Q14*R14 -> #N/A | V14: =IFERROR(VLOOKUP(A14,'Maturity Adjustment'!$A$86:$C$91,3,0),S14) -> 46343 | W14: =VLOOKUP(A14,'Account Mapping'!$A$2:$F$216,6,0) -> #N/A | X14: =IF(V14="Tomorrow",Q14,IF(AND(V14>$X$4-1,V14<$X$5),Q14,IF(V14=$X$5,Q14,0))) -> 0 | Y14: =IF(AND(V14>$Y$4-1,V14<$Y$5),Q14,IF(V14=$Y$5,Q14,0)) -> 0 | Z14: =IF(AND(V14>$Z$4-1,V14<$Z$5),Q14,IF(V14=$Z$5,Q14,0)) -> 0 | AA14: =IF(AND(V14>$AA$4-1,V14<$AA$5),Q14,IF(V14=$AA$5,Q14,0)) -> 0 | AB14: =IF(AND(V14>$AB$4-1,V14<$AB$5),Q14,IF(V14=$AB$5,Q14,0)) -> 0 | AC14: =IF(AND(V14>$AC$4-1,V14<$AC$5),Q14,IF(V14=$AC$5,Q14,0)) -> 5054150 | AD14: =IF(AND(V14>$AD$4-1,V14<$AD$5),Q14,IF(V14=$AD$5,Q14,0)) -> 0 | AE14: =IF(AND(V14>$AE$4-1,V14<$AE$5),Q14,IF(V14=$AE$5,Q14,0)) -> 0 | AF14: =IF(AND(V14>$AF$4-1,V14<$AF$5),Q14,IF(V14=$AF$5,Q14,0)) -> 0 | AG14: =IF(AND(V14>$AG$4-1,V14<$AG$5),Q14,IF(V14=$AG$5,Q14,0)) -> 0 | AH14: =Q14=SUM(X14:AG14) -> TRUE | AK14: Liability | AL14: =SUMIFS($H$7:$H$874,$W$7:$W$874,AK14,$V$7:$V$874,">"&AL9,$V$7:$V$874,"<="&AL10)+SUMIFS($H$7:$H$874,$W$7:$W$874,AK14,$V$7:$V$874,"Tomorrow") -> 0 | AM14: =SUMIFS($H$7:$H$874,$W$7:$W$874,AK14,$V$7:$V$874,">"&AM9,$V$7:$V$874,"<="&AM10)+SUMIFS($H$7:$H$874,$W$7:$W$874,AK14,$V$7:$V$874,"Tomorrow") -> 0 | AN14: =SUMIFS($H$7:$H$874,$W$7:$W$874,AK14,$V$7:$V$874,">"&AN9,$V$7:$V$874,"<="&AN10)+SUMIFS($H$7:$H$874,$W$7:$W$874,AK14,$V$7:$V$874,"Tomorrow") -> 0 | AO14: =SUMIFS($H$7:$H$874,$W$7:$W$874,AK14,$V$7:$V$874,">"&AO9,$V$7:$V$874,"<="&AO10)+SUMIFS($H$7:$H$874,$W$7:$W$874,AK14,$V$7:$V$874,"Tomorrow") -> 0 | AP14: =SUMIFS($H$7:$H$874,$W$7:$W$874,AK14,$V$7:$V$874,">"&AP9,$V$7:$V$874,"<="&AP10)+SUMIFS($H$7:$H$874,$W$7:$W$874,AK14,$V$7:$V$874,"Tomorrow") -> 0 | AQ14: =SUMIFS($H$7:$H$874,$W$7:$W$874,AK14,$V$7:$V$874,">"&AQ9,$V$7:$V$874,"<="&AQ10)+SUMIFS($H$7:$H$874,$W$7:$W$874,AK14,$V$7:$V$874,"Tomorrow") -> 0 | AR14: =SUMIFS($H$7:$H$874,$W$7:$W$874,AK14,$V$7:$V$874,">"&AR9,$V$7:$V$874,"<="&AR10)+SUMIFS($H$7:$H$874,$W$7:$W$874,AK14,$V$7:$V$874,"Tomorrow") -> 0 | AS14: =SUMIFS($H$7:$H$874,$W$7:$W$874,AK14,$V$7:$V$874,">"&AS9,$V$7:$V$874,"<="&AS10)+SUMIFS($H$7:$H$874,$W$7:$W$874,AK14,$V$7:$V$874,"Tomorrow") -> 0
A15: 10310002 | B15: Securities - FVOCI State | C15: FB5904240000003 | D15: 100000034 | E15: WESTERN AUSTRALIAN TREASURY CORPORATION | F15: AUD | G15: 4000353.9 | H15: 4000353.9 | I15: 45552 | J15: 46091 | K15: 46090 | L15: =VLOOKUP(A15,'Account Mapping'!$A$2:$E$216,3,0) -> #N/A | M15: =VLOOKUP(A15,'Account Mapping'!$A$2:$E$216,4,0) -> #N/A | N15: =IF(OR(C15='Account Mapping'!$H$4,C15='Account Mapping'!$H$5,C15='Account Mapping'!$H$6),'Account Mapping'!$I$4,VLOOKUP(A15,'Account Mapping'!$A$2:$E$216,5,0)) -> #N/A | O15: =IF(OR(L15="Loan",L15="Deposit_Liability",L15="OFF_Unused Loan Commitment",L15="HQLA"),VLOOKUP(D15,'Customer Type'!$A$3:$C$38,3,0),"") -> #N/A | P15: =M15&"_"&O15 -> #N/A | Q15: =IF(COUNTIF('Account Mapping'!$H$12:$H$45,A15)>0,-H15,H15) -> 4000353.9 | R15: =VLOOKUP(P15,Assumptions!$C$2:$D$64,2,0) -> #N/A | S15: =IFERROR(VLOOKUP(A15,'Maturity Adjustment'!$A$3:$C$81,3,0),(IF(J15<$N$4,"Tomorrow",J15))) -> 46091 | T15: =IF(S15="Tomorrow",1,(S15-$N$4)) -> 33 | U15: =Q15*R15 -> #N/A | V15: =IFERROR(VLOOKUP(A15,'Maturity Adjustment'!$A$86:$C$91,3,0),S15) -> 46091 | W15: =VLOOKUP(A15,'Account Mapping'!$A$2:$F$216,6,0) -> #N/A | X15: =IF(V15="Tomorrow",Q15,IF(AND(V15>$X$4-1,V15<$X$5),Q15,IF(V15=$X$5,Q15,0))) -> 0 | Y15: =IF(AND(V15>$Y$4-1,V15<$Y$5),Q15,IF(V15=$Y$5,Q15,0)) -> 0 | Z15: =IF(AND(V15>$Z$4-1,V15<$Z$5),Q15,IF(V15=$Z$5,Q15,0)) -> 0 | AA15: =IF(AND(V15>$AA$4-1,V15<$AA$5),Q15,IF(V15=$AA$5,Q15,0)) -> 4000353.9 | AB15: =IF(AND(V15>$AB$4-1,V15<$AB$5),Q15,IF(V15=$AB$5,Q15,0)) -> 0 | AC15: =IF(AND(V15>$AC$4-1,V15<$AC$5),Q15,IF(V15=$AC$5,Q15,0)) -> 0 | AD15: =IF(AND(V15>$AD$4-1,V15<$AD$5),Q15,IF(V15=$AD$5,Q15,0)) -> 0 | AE15: =IF(AND(V15>$AE$4-1,V15<$AE$5),Q15,IF(V15=$AE$5,Q15,0)) -> 0 | AF15: =IF(AND(V15>$AF$4-1,V15<$AF$5),Q15,IF(V15=$AF$5,Q15,0)) -> 0 | AG15: =IF(AND(V15>$AG$4-1,V15<$AG$5),Q15,IF(V15=$AG$5,Q15,0)) -> 0 | AH15: =Q15=SUM(X15:AG15) -> TRUE | AK15: Gap | AL15: =AL13-AL14 -> 0 | AM15: =AM13-AM14 -> 0 | AN15: =AN13-AN14 -> 0 | AO15: =AO13-AO14 -> 0 | AP15: =AP13-AP14 -> 0 | AQ15: =AQ13-AQ14 -> 0 | AR15: =AR13-AR14 -> 0 | AS15: =AS13-AS14 -> 0
A16: 10310002 | B16: Securities - FVOCI State | C16: FB5904250000003 | D16: 100000038 | E16: TASMANIAN PUBLIC FINANCE CORPORATION | F16: AUD | G16: 4891616.1 | H16: 4891616.1 | I16: 45755 | J16: 46776 | K16: 46775 | L16: =VLOOKUP(A16,'Account Mapping'!$A$2:$E$216,3,0) -> #N/A | M16: =VLOOKUP(A16,'Account Mapping'!$A$2:$E$216,4,0) -> #N/A | N16: =IF(OR(C16='Account Mapping'!$H$4,C16='Account Mapping'!$H$5,C16='Account Mapping'!$H$6),'Account Mapping'!$I$4,VLOOKUP(A16,'Account Mapping'!$A$2:$E$216,5,0)) -> #N/A | O16: =IF(OR(L16="Loan",L16="Deposit_Liability",L16="OFF_Unused Loan Commitment",L16="HQLA"),VLOOKUP(D16,'Customer Type'!$A$3:$C$38,3,0),"") -> #N/A | P16: =M16&"_"&O16 -> #N/A | Q16: =IF(COUNTIF('Account Mapping'!$H$12:$H$45,A16)>0,-H16,H16) -> 4891616.1 | R16: =VLOOKUP(P16,Assumptions!$C$2:$D$64,2,0) -> #N/A | S16: =IFERROR(VLOOKUP(A16,'Maturity Adjustment'!$A$3:$C$81,3,0),(IF(J16<$N$4,"Tomorrow",J16))) -> 46776 | T16: =IF(S16="Tomorrow",1,(S16-$N$4)) -> 718 | U16: =Q16*R16 -> #N/A | V16: =IFERROR(VLOOKUP(A16,'Maturity Adjustment'!$A$86:$C$91,3,0),S16) -> 46776 | W16: =VLOOKUP(A16,'Account Mapping'!$A$2:$F$216,6,0) -> #N/A | X16: =IF(V16="Tomorrow",Q16,IF(AND(V16>$X$4-1,V16<$X$5),Q16,IF(V16=$X$5,Q16,0))) -> 0 | Y16: =IF(AND(V16>$Y$4-1,V16<$Y$5),Q16,IF(V16=$Y$5,Q16,0)) -> 0 | Z16: =IF(AND(V16>$Z$4-1,V16<$Z$5),Q16,IF(V16=$Z$5,Q16,0)) -> 0 | AA16: =IF(AND(V16>$AA$4-1,V16<$AA$5),Q16,IF(V16=$AA$5,Q16,0)) -> 0 | AB16: =IF(AND(V16>$AB$4-1,V16<$AB$5),Q16,IF(V16=$AB$5,Q16,0)) -> 0 | AC16: =IF(AND(V16>$AC$4-1,V16<$AC$5),Q16,IF(V16=$AC$5,Q16,0)) -> 0 | AD16: =IF(AND(V16>$AD$4-1,V16<$AD$5),Q16,IF(V16=$AD$5,Q16,0)) -> 4891616.1 | AE16: =IF(AND(V16>$AE$4-1,V16<$AE$5),Q16,IF(V16=$AE$5,Q16,0)) -> 0 | AF16: =IF(AND(V16>$AF$4-1,V16<$AF$5),Q16,IF(V16=$AF$5,Q16,0)) -> 0 | AG16: =IF(AND(V16>$AG$4-1,V16<$AG$5),Q16,IF(V16=$AG$5,Q16,0)) -> 0 | AH16: =Q16=SUM(X16:AG16) -> TRUE | AK16: Total Asset | AL16: =SUMIF($W$7:$W$874,AK13,$H$7:$H$874) -> 0 | AM16: =AL16 -> 0 | AN16: =AM16 -> 0 | AO16: =AN16 -> 0 | AP16: =AO16 -> 0 | AQ16: =AP16 -> 0 | AR16: =AQ16 -> 0 | AS16: =AR16 -> 0
A17: 10310003 | B17: Foreign GovT & Official Institution - FVOCI | C17: FB5904240000005 | D17: 100000037 | E17: THE EXPORT-IMPORT BANK OF KOREA | F17: USD | G17: 5027374.5 | H17: 7157423.8 | I17: 45624 | J17: 46677 | K17: 46128 | L17: =VLOOKUP(A17,'Account Mapping'!$A$2:$E$216,3,0) -> #N/A | M17: =VLOOKUP(A17,'Account Mapping'!$A$2:$E$216,4,0) -> #N/A | N17: =IF(OR(C17='Account Mapping'!$H$4,C17='Account Mapping'!$H$5,C17='Account Mapping'!$H$6),'Account Mapping'!$I$4,VLOOKUP(A17,'Account Mapping'!$A$2:$E$216,5,0)) -> #N/A | O17: =IF(OR(L17="Loan",L17="Deposit_Liability",L17="OFF_Unused Loan Commitment",L17="HQLA"),VLOOKUP(D17,'Customer Type'!$A$3:$C$38,3,0),"") -> #N/A | P17: =M17&"_"&O17 -> #N/A | Q17: =IF(COUNTIF('Account Mapping'!$H$12:$H$45,A17)>0,-H17,H17) -> 7157423.8 | R17: =VLOOKUP(P17,Assumptions!$C$2:$D$64,2,0) -> #N/A | S17: =IFERROR(VLOOKUP(A17,'Maturity Adjustment'!$A$3:$C$81,3,0),(IF(J17<$N$4,"Tomorrow",J17))) -> 46677 | T17: =IF(S17="Tomorrow",1,(S17-$N$4)) -> 619 | U17: =Q17*R17 -> #N/A | V17: =IFERROR(VLOOKUP(A17,'Maturity Adjustment'!$A$86:$C$91,3,0),S17) -> 46677 | W17: =VLOOKUP(A17,'Account Mapping'!$A$2:$F$216,6,0) -> #N/A | X17: =IF(V17="Tomorrow",Q17,IF(AND(V17>$X$4-1,V17<$X$5),Q17,IF(V17=$X$5,Q17,0))) -> 0 | Y17: =IF(AND(V17>$Y$4-1,V17<$Y$5),Q17,IF(V17=$Y$5,Q17,0)) -> 0 | Z17: =IF(AND(V17>$Z$4-1,V17<$Z$5),Q17,IF(V17=$Z$5,Q17,0)) -> 0 | AA17: =IF(AND(V17>$AA$4-1,V17<$AA$5),Q17,IF(V17=$AA$5,Q17,0)) -> 0 | AB17: =IF(AND(V17>$AB$4-1,V17<$AB$5),Q17,IF(V17=$AB$5,Q17,0)) -> 0 | AC17: =IF(AND(V17>$AC$4-1,V17<$AC$5),Q17,IF(V17=$AC$5,Q17,0)) -> 0 | AD17: =IF(AND(V17>$AD$4-1,V17<$AD$5),Q17,IF(V17=$AD$5,Q17,0)) -> 7157423.8 | AE17: =IF(AND(V17>$AE$4-1,V17<$AE$5),Q17,IF(V17=$AE$5,Q17,0)) -> 0 | AF17: =IF(AND(V17>$AF$4-1,V17<$AF$5),Q17,IF(V17=$AF$5,Q17,0)) -> 0 | AG17: =IF(AND(V17>$AG$4-1,V17<$AG$5),Q17,IF(V17=$AG$5,Q17,0)) -> 0 | AH17: =Q17=SUM(X17:AG17) -> TRUE | AK17: Gap ratio | AL17: =AL15/AL16 -> #DIV/0! | AM17: =AM15/AM16 -> #DIV/0! | AN17: =AN15/AN16 -> #DIV/0! | AO17: =AO15/AO16 -> #DIV/0! | AP17: =AP15/AP16 -> #DIV/0! | AQ17: =AQ15/AQ16 -> #DIV/0! | AR17: =AR15/AR16 -> #DIV/0! | AS17: =AS15/AS16 -> #DIV/0!
A18: 10310003 | B18: Foreign GovT & Official Institution - FVOCI | C18: FB5904250000001 | D18: 100000037 | E18: THE EXPORT-IMPORT BANK OF KOREA | F18: USD | G18: -15.6 | H18: -22.21 | I18: 45692 | J18: 46766 | L18: =VLOOKUP(A18,'Account Mapping'!$A$2:$E$216,3,0) -> #N/A | M18: =VLOOKUP(A18,'Account Mapping'!$A$2:$E$216,4,0) -> #N/A | N18: =IF(OR(C18='Account Mapping'!$H$4,C18='Account Mapping'!$H$5,C18='Account Mapping'!$H$6),'Account Mapping'!$I$4,VLOOKUP(A18,'Account Mapping'!$A$2:$E$216,5,0)) -> #N/A | O18: =IF(OR(L18="Loan",L18="Deposit_Liability",L18="OFF_Unused Loan Commitment",L18="HQLA"),VLOOKUP(D18,'Customer Type'!$A$3:$C$38,3,0),"") -> #N/A | P18: =M18&"_"&O18 -> #N/A | Q18: =IF(COUNTIF('Account Mapping'!$H$12:$H$45,A18)>0,-H18,H18) -> -22.21 | R18: =VLOOKUP(P18,Assumptions!$C$2:$D$64,2,0) -> #N/A | S18: =IFERROR(VLOOKUP(A18,'Maturity Adjustment'!$A$3:$C$81,3,0),(IF(J18<$N$4,"Tomorrow",J18))) -> 46766 | T18: =IF(S18="Tomorrow",1,(S18-$N$4)) -> 708 | U18: =Q18*R18 -> #N/A | V18: =IFERROR(VLOOKUP(A18,'Maturity Adjustment'!$A$86:$C$91,3,0),S18) -> 46766 | W18: =VLOOKUP(A18,'Account Mapping'!$A$2:$F$216,6,0) -> #N/A | X18: =IF(V18="Tomorrow",Q18,IF(AND(V18>$X$4-1,V18<$X$5),Q18,IF(V18=$X$5,Q18,0))) -> 0 | Y18: =IF(AND(V18>$Y$4-1,V18<$Y$5),Q18,IF(V18=$Y$5,Q18,0)) -> 0 | Z18: =IF(AND(V18>$Z$4-1,V18<$Z$5),Q18,IF(V18=$Z$5,Q18,0)) -> 0 | AA18: =IF(AND(V18>$AA$4-1,V18<$AA$5),Q18,IF(V18=$AA$5,Q18,0)) -> 0 | AB18: =IF(AND(V18>$AB$4-1,V18<$AB$5),Q18,IF(V18=$AB$5,Q18,0)) -> 0 | AC18: =IF(AND(V18>$AC$4-1,V18<$AC$5),Q18,IF(V18=$AC$5,Q18,0)) -> 0 | AD18: =IF(AND(V18>$AD$4-1,V18<$AD$5),Q18,IF(V18=$AD$5,Q18,0)) -> -22.21 | AE18: =IF(AND(V18>$AE$4-1,V18<$AE$5),Q18,IF(V18=$AE$5,Q18,0)) -> 0 | AF18: =IF(AND(V18>$AF$4-1,V18<$AF$5),Q18,IF(V18=$AF$5,Q18,0)) -> 0 | AG18: =IF(AND(V18>$AG$4-1,V18<$AG$5),Q18,IF(V18=$AG$5,Q18,0)) -> 0 | AH18: =Q18=SUM(X18:AG18) -> TRUE | AK18: Trigger | AL18: 0 | AM18: =AL18 -> 0 | AN18: =AM18 -> 0 | AO18: =AN18 -> 0 | AP18: =AO18 -> 0 | AQ18: =AP18 -> 0 | AR18: =AQ18 -> 0 | AS18: =AR18 -> 0
A19: 10310003 | B19: Foreign GovT & Official Institution - FVOCI | C19: FB5904250000002 | D19: 100000037 | E19: THE EXPORT-IMPORT BANK OF KOREA | F19: USD | G19: 5076637.9 | H19: 7227559.6 | I19: 45692 | J19: 46766 | K19: 46765 | L19: =VLOOKUP(A19,'Account Mapping'!$A$2:$E$216,3,0) -> #N/A | M19: =VLOOKUP(A19,'Account Mapping'!$A$2:$E$216,4,0) -> #N/A | N19: =IF(OR(C19='Account Mapping'!$H$4,C19='Account Mapping'!$H$5,C19='Account Mapping'!$H$6),'Account Mapping'!$I$4,VLOOKUP(A19,'Account Mapping'!$A$2:$E$216,5,0)) -> #N/A | O19: =IF(OR(L19="Loan",L19="Deposit_Liability",L19="OFF_Unused Loan Commitment",L19="HQLA"),VLOOKUP(D19,'Customer Type'!$A$3:$C$38,3,0),"") -> #N/A | P19: =M19&"_"&O19 -> #N/A | Q19: =IF(COUNTIF('Account Mapping'!$H$12:$H$45,A19)>0,-H19,H19) -> 7227559.6 | R19: =VLOOKUP(P19,Assumptions!$C$2:$D$64,2,0) -> #N/A | S19: =IFERROR(VLOOKUP(A19,'Maturity Adjustment'!$A$3:$C$81,3,0),(IF(J19<$N$4,"Tomorrow",J19))) -> 46766 | T19: =IF(S19="Tomorrow",1,(S19-$N$4)) -> 708 | U19: =Q19*R19 -> #N/A | V19: =IFERROR(VLOOKUP(A19,'Maturity Adjustment'!$A$86:$C$91,3,0),S19) -> 46766 | W19: =VLOOKUP(A19,'Account Mapping'!$A$2:$F$216,6,0) -> #N/A | X19: =IF(V19="Tomorrow",Q19,IF(AND(V19>$X$4-1,V19<$X$5),Q19,IF(V19=$X$5,Q19,0))) -> 0 | Y19: =IF(AND(V19>$Y$4-1,V19<$Y$5),Q19,IF(V19=$Y$5,Q19,0)) -> 0 | Z19: =IF(AND(V19>$Z$4-1,V19<$Z$5),Q19,IF(V19=$Z$5,Q19,0)) -> 0 | AA19: =IF(AND(V19>$AA$4-1,V19<$AA$5),Q19,IF(V19=$AA$5,Q19,0)) -> 0 | AB19: =IF(AND(V19>$AB$4-1,V19<$AB$5),Q19,IF(V19=$AB$5,Q19,0)) -> 0 | AC19: =IF(AND(V19>$AC$4-1,V19<$AC$5),Q19,IF(V19=$AC$5,Q19,0)) -> 0 | AD19: =IF(AND(V19>$AD$4-1,V19<$AD$5),Q19,IF(V19=$AD$5,Q19,0)) -> 7227559.6 | AE19: =IF(AND(V19>$AE$4-1,V19<$AE$5),Q19,IF(V19=$AE$5,Q19,0)) -> 0 | AF19: =IF(AND(V19>$AF$4-1,V19<$AF$5),Q19,IF(V19=$AF$5,Q19,0)) -> 0 | AG19: =IF(AND(V19>$AG$4-1,V19<$AG$5),Q19,IF(V19=$AG$5,Q19,0)) -> 0 | AH19: =Q19=SUM(X19:AG19) -> TRUE | AK19: (-)Shortfall | AL19: =-AL16*(AL18-AL17) -> #DIV/0! | AM19: =-AM16*(AM18-AM17) -> #DIV/0! | AN19: =-AN16*(AN18-AN17) -> #DIV/0! | AO19: =-AO16*(AO18-AO17) -> #DIV/0! | AP19: =-AP16*(AP18-AP17) -> #DIV/0! | AQ19: =-AQ16*(AQ18-AQ17) -> #DIV/0! | AR19: =-AR16*(AR18-AR17) -> #DIV/0! | AS19: =-AS16*(AS18-AS17) -> #DIV/0!
A20: 10310003 | B20: Foreign GovT & Official Institution - FVOCI | C20: FB5904250000004 | D20: 100000037 | E20: THE EXPORT-IMPORT BANK OF KOREA | F20: USD | G20: 3020995.3 | H20: 4300961.4 | I20: 45818 | J20: 46645 | K20: 46644 | L20: =VLOOKUP(A20,'Account Mapping'!$A$2:$E$216,3,0) -> #N/A | M20: =VLOOKUP(A20,'Account Mapping'!$A$2:$E$216,4,0) -> #N/A | N20: =IF(OR(C20='Account Mapping'!$H$4,C20='Account Mapping'!$H$5,C20='Account Mapping'!$H$6),'Account Mapping'!$I$4,VLOOKUP(A20,'Account Mapping'!$A$2:$E$216,5,0)) -> #N/A | O20: =IF(OR(L20="Loan",L20="Deposit_Liability",L20="OFF_Unused Loan Commitment",L20="HQLA"),VLOOKUP(D20,'Customer Type'!$A$3:$C$38,3,0),"") -> #N/A | P20: =M20&"_"&O20 -> #N/A | Q20: =IF(COUNTIF('Account Mapping'!$H$12:$H$45,A20)>0,-H20,H20) -> 4300961.4 | R20: =VLOOKUP(P20,Assumptions!$C$2:$D$64,2,0) -> #N/A | S20: =IFERROR(VLOOKUP(A20,'Maturity Adjustment'!$A$3:$C$81,3,0),(IF(J20<$N$4,"Tomorrow",J20))) -> 46645 | T20: =IF(S20="Tomorrow",1,(S20-$N$4)) -> 587 | U20: =Q20*R20 -> #N/A | V20: =IFERROR(VLOOKUP(A20,'Maturity Adjustment'!$A$86:$C$91,3,0),S20) -> 46645 | W20: =VLOOKUP(A20,'Account Mapping'!$A$2:$F$216,6,0) -> #N/A | X20: =IF(V20="Tomorrow",Q20,IF(AND(V20>$X$4-1,V20<$X$5),Q20,IF(V20=$X$5,Q20,0))) -> 0 | Y20: =IF(AND(V20>$Y$4-1,V20<$Y$5),Q20,IF(V20=$Y$5,Q20,0)) -> 0 | Z20: =IF(AND(V20>$Z$4-1,V20<$Z$5),Q20,IF(V20=$Z$5,Q20,0)) -> 0 | AA20: =IF(AND(V20>$AA$4-1,V20<$AA$5),Q20,IF(V20=$AA$5,Q20,0)) -> 0 | AB20: =IF(AND(V20>$AB$4-1,V20<$AB$5),Q20,IF(V20=$AB$5,Q20,0)) -> 0 | AC20: =IF(AND(V20>$AC$4-1,V20<$AC$5),Q20,IF(V20=$AC$5,Q20,0)) -> 0 | AD20: =IF(AND(V20>$AD$4-1,V20<$AD$5),Q20,IF(V20=$AD$5,Q20,0)) -> 4300961.4 | AE20: =IF(AND(V20>$AE$4-1,V20<$AE$5),Q20,IF(V20=$AE$5,Q20,0)) -> 0 | AF20: =IF(AND(V20>$AF$4-1,V20<$AF$5),Q20,IF(V20=$AF$5,Q20,0)) -> 0 | AG20: =IF(AND(V20>$AG$4-1,V20<$AG$5),Q20,IF(V20=$AG$5,Q20,0)) -> 0 | AH20: =Q20=SUM(X20:AG20) -> TRUE
A21: 10310003 | B21: Foreign GovT & Official Institution - FVOCI | C21: OT5904250000017 | D21: 100000037 | E21: THE EXPORT-IMPORT BANK OF KOREA | F21: USD | G21: 15.6 | H21: 22.21 | L21: =VLOOKUP(A21,'Account Mapping'!$A$2:$E$216,3,0) -> #N/A | M21: =VLOOKUP(A21,'Account Mapping'!$A$2:$E$216,4,0) -> #N/A | N21: =IF(OR(C21='Account Mapping'!$H$4,C21='Account Mapping'!$H$5,C21='Account Mapping'!$H$6),'Account Mapping'!$I$4,VLOOKUP(A21,'Account Mapping'!$A$2:$E$216,5,0)) -> #N/A | O21: =IF(OR(L21="Loan",L21="Deposit_Liability",L21="OFF_Unused Loan Commitment",L21="HQLA"),VLOOKUP(D21,'Customer Type'!$A$3:$C$38,3,0),"") -> #N/A | P21: =M21&"_"&O21 -> #N/A | Q21: =IF(COUNTIF('Account Mapping'!$H$12:$H$45,A21)>0,-H21,H21) -> 22.21 | R21: =VLOOKUP(P21,Assumptions!$C$2:$D$64,2,0) -> #N/A | S21: =IFERROR(VLOOKUP(A21,'Maturity Adjustment'!$A$3:$C$81,3,0),(IF(J21<$N$4,"Tomorrow",J21))) -> Tomorrow | T21: =IF(S21="Tomorrow",1,(S21-$N$4)) -> 1 | U21: =Q21*R21 -> #N/A | V21: =IFERROR(VLOOKUP(A21,'Maturity Adjustment'!$A$86:$C$91,3,0),S21) -> Tomorrow | W21: =VLOOKUP(A21,'Account Mapping'!$A$2:$F$216,6,0) -> #N/A | X21: =IF(V21="Tomorrow",Q21,IF(AND(V21>$X$4-1,V21<$X$5),Q21,IF(V21=$X$5,Q21,0))) -> 22.21 | Y21: =IF(AND(V21>$Y$4-1,V21<$Y$5),Q21,IF(V21=$Y$5,Q21,0)) -> 0 | Z21: =IF(AND(V21>$Z$4-1,V21<$Z$5),Q21,IF(V21=$Z$5,Q21,0)) -> 0 | AA21: =IF(AND(V21>$AA$4-1,V21<$AA$5),Q21,IF(V21=$AA$5,Q21,0)) -> 0 | AB21: =IF(AND(V21>$AB$4-1,V21<$AB$5),Q21,IF(V21=$AB$5,Q21,0)) -> 0 | AC21: =IF(AND(V21>$AC$4-1,V21<$AC$5),Q21,IF(V21=$AC$5,Q21,0)) -> 0 | AD21: =IF(AND(V21>$AD$4-1,V21<$AD$5),Q21,IF(V21=$AD$5,Q21,0)) -> 0 | AE21: =IF(AND(V21>$AE$4-1,V21<$AE$5),Q21,IF(V21=$AE$5,Q21,0)) -> 0 | AF21: =IF(AND(V21>$AF$4-1,V21<$AF$5),Q21,IF(V21=$AF$5,Q21,0)) -> 0 | AG21: =IF(AND(V21>$AG$4-1,V21<$AG$5),Q21,IF(V21=$AG$5,Q21,0)) -> 0 | AH21: =Q21=SUM(X21:AG21) -> TRUE | AJ21: 1 month | AK21: From | AL21: =AL9 -> 46081 | AM21: =EOMONTH(AL21,1) -> 46112 | AN21: =EOMONTH(AM21,1) -> 46142 | AO21: =EOMONTH(AN21,1) -> 46173 | AP21: =EOMONTH(AO21,1) -> 46203 | AQ21: =EOMONTH(AP21,1) -> 46234 | AR21: =EOMONTH(AQ21,1) -> 46265 | AS21: =EOMONTH(AR21,1) -> 46295
A22: 10610005 | B22: Loans On Bills (Operation-Short Term-Domestic) | C22: 6115904000018 | D22: 100000003 | E22: COSMAX NBT AUSTRALIA PTY LTD | F22: AUD | G22: 6000000 | H22: 6000000 | I22: 44859 | J22: 46318 | K22: 46136 | L22: =VLOOKUP(A22,'Account Mapping'!$A$2:$E$216,3,0) -> #N/A | M22: =VLOOKUP(A22,'Account Mapping'!$A$2:$E$216,4,0) -> #N/A | N22: =IF(OR(C22='Account Mapping'!$H$4,C22='Account Mapping'!$H$5,C22='Account Mapping'!$H$6),'Account Mapping'!$I$4,VLOOKUP(A22,'Account Mapping'!$A$2:$E$216,5,0)) -> #N/A | O22: =IF(OR(L22="Loan",L22="Deposit_Liability",L22="OFF_Unused Loan Commitment",L22="HQLA"),VLOOKUP(D22,'Customer Type'!$A$3:$C$38,3,0),"") -> #N/A | P22: =M22&"_"&O22 -> #N/A | Q22: =IF(COUNTIF('Account Mapping'!$H$12:$H$45,A22)>0,-H22,H22) -> 6000000 | R22: =VLOOKUP(P22,Assumptions!$C$2:$D$64,2,0) -> #N/A | S22: =IFERROR(VLOOKUP(A22,'Maturity Adjustment'!$A$3:$C$81,3,0),(IF(J22<$N$4,"Tomorrow",J22))) -> 46318 | T22: =IF(S22="Tomorrow",1,(S22-$N$4)) -> 260 | U22: =Q22*R22 -> #N/A | V22: =IFERROR(VLOOKUP(A22,'Maturity Adjustment'!$A$86:$C$91,3,0),S22) -> 46318 | W22: =VLOOKUP(A22,'Account Mapping'!$A$2:$F$216,6,0) -> #N/A | X22: =IF(V22="Tomorrow",Q22,IF(AND(V22>$X$4-1,V22<$X$5),Q22,IF(V22=$X$5,Q22,0))) -> 0 | Y22: =IF(AND(V22>$Y$4-1,V22<$Y$5),Q22,IF(V22=$Y$5,Q22,0)) -> 0 | Z22: =IF(AND(V22>$Z$4-1,V22<$Z$5),Q22,IF(V22=$Z$5,Q22,0)) -> 0 | AA22: =IF(AND(V22>$AA$4-1,V22<$AA$5),Q22,IF(V22=$AA$5,Q22,0)) -> 0 | AB22: =IF(AND(V22>$AB$4-1,V22<$AB$5),Q22,IF(V22=$AB$5,Q22,0)) -> 0 | AC22: =IF(AND(V22>$AC$4-1,V22<$AC$5),Q22,IF(V22=$AC$5,Q22,0)) -> 6000000 | AD22: =IF(AND(V22>$AD$4-1,V22<$AD$5),Q22,IF(V22=$AD$5,Q22,0)) -> 0 | AE22: =IF(AND(V22>$AE$4-1,V22<$AE$5),Q22,IF(V22=$AE$5,Q22,0)) -> 0 | AF22: =IF(AND(V22>$AF$4-1,V22<$AF$5),Q22,IF(V22=$AF$5,Q22,0)) -> 0 | AG22: =IF(AND(V22>$AG$4-1,V22<$AG$5),Q22,IF(V22=$AG$5,Q22,0)) -> 0 | AH22: =Q22=SUM(X22:AG22) -> TRUE | AK22: To | AL22: =EOMONTH(AL21,1) -> 46112 | AM22: =EOMONTH(AM21,1) -> 46142 | AN22: =EOMONTH(AN21,1) -> 46173 | AO22: =EOMONTH(AO21,1) -> 46203 | AP22: =EOMONTH(AP21,1) -> 46234 | AQ22: =EOMONTH(AQ21,1) -> 46265 | AR22: =EOMONTH(AR21,1) -> 46295 | AS22: =EOMONTH(AS21,1) -> 46326
A23: 10620001 | B23: SYN-Working Capital Loan - Domestic | C23: 6115904000139 | D23: 100000020 | E23: APA INFRASTRUCTURE LIMITED | F23: AUD | G23: 8000000 | H23: 8000000 | I23: 45240 | J23: 48883 | K23: 46153 | L23: =VLOOKUP(A23,'Account Mapping'!$A$2:$E$216,3,0) -> #N/A | M23: =VLOOKUP(A23,'Account Mapping'!$A$2:$E$216,4,0) -> #N/A | N23: =IF(OR(C23='Account Mapping'!$H$4,C23='Account Mapping'!$H$5,C23='Account Mapping'!$H$6),'Account Mapping'!$I$4,VLOOKUP(A23,'Account Mapping'!$A$2:$E$216,5,0)) -> #N/A | O23: =IF(OR(L23="Loan",L23="Deposit_Liability",L23="OFF_Unused Loan Commitment",L23="HQLA"),VLOOKUP(D23,'Customer Type'!$A$3:$C$38,3,0),"") -> #N/A | P23: =M23&"_"&O23 -> #N/A | Q23: =IF(COUNTIF('Account Mapping'!$H$12:$H$45,A23)>0,-H23,H23) -> 8000000 | R23: =VLOOKUP(P23,Assumptions!$C$2:$D$64,2,0) -> #N/A | S23: =IFERROR(VLOOKUP(A23,'Maturity Adjustment'!$A$3:$C$81,3,0),(IF(J23<$N$4,"Tomorrow",J23))) -> 48883 | T23: =IF(S23="Tomorrow",1,(S23-$N$4)) -> 2825 | U23: =Q23*R23 -> #N/A | V23: =IFERROR(VLOOKUP(A23,'Maturity Adjustment'!$A$86:$C$91,3,0),S23) -> 48883 | W23: =VLOOKUP(A23,'Account Mapping'!$A$2:$F$216,6,0) -> #N/A | X23: =IF(V23="Tomorrow",Q23,IF(AND(V23>$X$4-1,V23<$X$5),Q23,IF(V23=$X$5,Q23,0))) -> 0 | Y23: =IF(AND(V23>$Y$4-1,V23<$Y$5),Q23,IF(V23=$Y$5,Q23,0)) -> 0 | Z23: =IF(AND(V23>$Z$4-1,V23<$Z$5),Q23,IF(V23=$Z$5,Q23,0)) -> 0 | AA23: =IF(AND(V23>$AA$4-1,V23<$AA$5),Q23,IF(V23=$AA$5,Q23,0)) -> 0 | AB23: =IF(AND(V23>$AB$4-1,V23<$AB$5),Q23,IF(V23=$AB$5,Q23,0)) -> 0 | AC23: =IF(AND(V23>$AC$4-1,V23<$AC$5),Q23,IF(V23=$AC$5,Q23,0)) -> 0 | AD23: =IF(AND(V23>$AD$4-1,V23<$AD$5),Q23,IF(V23=$AD$5,Q23,0)) -> 0 | AE23: =IF(AND(V23>$AE$4-1,V23<$AE$5),Q23,IF(V23=$AE$5,Q23,0)) -> 0 | AF23: =IF(AND(V23>$AF$4-1,V23<$AF$5),Q23,IF(V23=$AF$5,Q23,0)) -> 8000000 | AG23: =IF(AND(V23>$AG$4-1,V23<$AG$5),Q23,IF(V23=$AG$5,Q23,0)) -> 0 | AH23: =Q23=SUM(X23:AG23) -> TRUE
A24: 10620001 | B24: SYN-Working Capital Loan - Domestic | C24: 6115904000300 | D24: 100000031 | E24: ORIGIN ENERGY LIMITED | F24: AUD | G24: 10000000 | H24: 10000000 | I24: 45463 | J24: 48005 | K24: 46195 | L24: =VLOOKUP(A24,'Account Mapping'!$A$2:$E$216,3,0) -> #N/A | M24: =VLOOKUP(A24,'Account Mapping'!$A$2:$E$216,4,0) -> #N/A | N24: =IF(OR(C24='Account Mapping'!$H$4,C24='Account Mapping'!$H$5,C24='Account Mapping'!$H$6),'Account Mapping'!$I$4,VLOOKUP(A24,'Account Mapping'!$A$2:$E$216,5,0)) -> #N/A | O24: =IF(OR(L24="Loan",L24="Deposit_Liability",L24="OFF_Unused Loan Commitment",L24="HQLA"),VLOOKUP(D24,'Customer Type'!$A$3:$C$38,3,0),"") -> #N/A | P24: =M24&"_"&O24 -> #N/A | Q24: =IF(COUNTIF('Account Mapping'!$H$12:$H$45,A24)>0,-H24,H24) -> 10000000 | R24: =VLOOKUP(P24,Assumptions!$C$2:$D$64,2,0) -> #N/A | S24: =IFERROR(VLOOKUP(A24,'Maturity Adjustment'!$A$3:$C$81,3,0),(IF(J24<$N$4,"Tomorrow",J24))) -> 48005 | T24: =IF(S24="Tomorrow",1,(S24-$N$4)) -> 1947 | U24: =Q24*R24 -> #N/A | V24: =IFERROR(VLOOKUP(A24,'Maturity Adjustment'!$A$86:$C$91,3,0),S24) -> 48005 | W24: =VLOOKUP(A24,'Account Mapping'!$A$2:$F$216,6,0) -> #N/A | X24: =IF(V24="Tomorrow",Q24,IF(AND(V24>$X$4-1,V24<$X$5),Q24,IF(V24=$X$5,Q24,0))) -> 0 | Y24: =IF(AND(V24>$Y$4-1,V24<$Y$5),Q24,IF(V24=$Y$5,Q24,0)) -> 0 | Z24: =IF(AND(V24>$Z$4-1,V24<$Z$5),Q24,IF(V24=$Z$5,Q24,0)) -> 0 | AA24: =IF(AND(V24>$AA$4-1,V24<$AA$5),Q24,IF(V24=$AA$5,Q24,0)) -> 0 | AB24: =IF(AND(V24>$AB$4-1,V24<$AB$5),Q24,IF(V24=$AB$5,Q24,0)) -> 0 | AC24: =IF(AND(V24>$AC$4-1,V24<$AC$5),Q24,IF(V24=$AC$5,Q24,0)) -> 0 | AD24: =IF(AND(V24>$AD$4-1,V24<$AD$5),Q24,IF(V24=$AD$5,Q24,0)) -> 0 | AE24: =IF(AND(V24>$AE$4-1,V24<$AE$5),Q24,IF(V24=$AE$5,Q24,0)) -> 0 | AF24: =IF(AND(V24>$AF$4-1,V24<$AF$5),Q24,IF(V24=$AF$5,Q24,0)) -> 10000000 | AG24: =IF(AND(V24>$AG$4-1,V24<$AG$5),Q24,IF(V24=$AG$5,Q24,0)) -> 0 | AH24: =Q24=SUM(X24:AG24) -> TRUE | AL24: =AL12 -> 46081 | AM24: =AM12 -> 46112 | AN24: =AN12 -> 46142 | AO24: =AO12 -> 46173 | AP24: =AP12 -> 46203 | AQ24: =AQ12 -> 46234 | AR24: =AR12 -> 46265 | AS24: =AS12 -> 46295
A25: 10620001 | B25: SYN-Working Capital Loan - Domestic | C25: 6115904000395 | D25: 100000033 | E25: MACQUARIE GROUP LIMITED | F25: USD | G25: 30000000 | H25: 42710706 | I25: 45565 | J25: 48136 | K25: 46107 | L25: =VLOOKUP(A25,'Account Mapping'!$A$2:$E$216,3,0) -> #N/A | M25: =VLOOKUP(A25,'Account Mapping'!$A$2:$E$216,4,0) -> #N/A | N25: =IF(OR(C25='Account Mapping'!$H$4,C25='Account Mapping'!$H$5,C25='Account Mapping'!$H$6),'Account Mapping'!$I$4,VLOOKUP(A25,'Account Mapping'!$A$2:$E$216,5,0)) -> #N/A | O25: =IF(OR(L25="Loan",L25="Deposit_Liability",L25="OFF_Unused Loan Commitment",L25="HQLA"),VLOOKUP(D25,'Customer Type'!$A$3:$C$38,3,0),"") -> #N/A | P25: =M25&"_"&O25 -> #N/A | Q25: =IF(COUNTIF('Account Mapping'!$H$12:$H$45,A25)>0,-H25,H25) -> 42710706 | R25: =VLOOKUP(P25,Assumptions!$C$2:$D$64,2,0) -> #N/A | S25: =IFERROR(VLOOKUP(A25,'Maturity Adjustment'!$A$3:$C$81,3,0),(IF(J25<$N$4,"Tomorrow",J25))) -> 48136 | T25: =IF(S25="Tomorrow",1,(S25-$N$4)) -> 2078 | U25: =Q25*R25 -> #N/A | V25: =IFERROR(VLOOKUP(A25,'Maturity Adjustment'!$A$86:$C$91,3,0),S25) -> 48136 | W25: =VLOOKUP(A25,'Account Mapping'!$A$2:$F$216,6,0) -> #N/A | X25: =IF(V25="Tomorrow",Q25,IF(AND(V25>$X$4-1,V25<$X$5),Q25,IF(V25=$X$5,Q25,0))) -> 0 | Y25: =IF(AND(V25>$Y$4-1,V25<$Y$5),Q25,IF(V25=$Y$5,Q25,0)) -> 0 | Z25: =IF(AND(V25>$Z$4-1,V25<$Z$5),Q25,IF(V25=$Z$5,Q25,0)) -> 0 | AA25: =IF(AND(V25>$AA$4-1,V25<$AA$5),Q25,IF(V25=$AA$5,Q25,0)) -> 0 | AB25: =IF(AND(V25>$AB$4-1,V25<$AB$5),Q25,IF(V25=$AB$5,Q25,0)) -> 0 | AC25: =IF(AND(V25>$AC$4-1,V25<$AC$5),Q25,IF(V25=$AC$5,Q25,0)) -> 0 | AD25: =IF(AND(V25>$AD$4-1,V25<$AD$5),Q25,IF(V25=$AD$5,Q25,0)) -> 0 | AE25: =IF(AND(V25>$AE$4-1,V25<$AE$5),Q25,IF(V25=$AE$5,Q25,0)) -> 0 | AF25: =IF(AND(V25>$AF$4-1,V25<$AF$5),Q25,IF(V25=$AF$5,Q25,0)) -> 42710706 | AG25: =IF(AND(V25>$AG$4-1,V25<$AG$5),Q25,IF(V25=$AG$5,Q25,0)) -> 0 | AH25: =Q25=SUM(X25:AG25) -> TRUE | AK25: Asset | AL25: =SUMIFS($H$7:$H$874,$W$7:$W$874,AK25,$V$7:$V$874,">"&AL21,$V$7:$V$874,"<="&AL22)+SUMIFS($H$7:$H$874,$W$7:$W$874,AK25,$V$7:$V$874,"Tomorrow") -> 0 | AM25: =SUMIFS($H$7:$H$874,$W$7:$W$874,AK25,$V$7:$V$874,">"&AM21,$V$7:$V$874,"<="&AM22)+SUMIFS($H$7:$H$874,$W$7:$W$874,AK25,$V$7:$V$874,"Tomorrow") -> 0 | AN25: =SUMIFS($H$7:$H$874,$W$7:$W$874,AK25,$V$7:$V$874,">"&AN21,$V$7:$V$874,"<="&AN22)+SUMIFS($H$7:$H$874,$W$7:$W$874,AK25,$V$7:$V$874,"Tomorrow") -> 0 | AO25: =SUMIFS($H$7:$H$874,$W$7:$W$874,AK25,$V$7:$V$874,">"&AO21,$V$7:$V$874,"<="&AO22)+SUMIFS($H$7:$H$874,$W$7:$W$874,AK25,$V$7:$V$874,"Tomorrow") -> 0 | AP25: =SUMIFS($H$7:$H$874,$W$7:$W$874,AK25,$V$7:$V$874,">"&AP21,$V$7:$V$874,"<="&AP22)+SUMIFS($H$7:$H$874,$W$7:$W$874,AK25,$V$7:$V$874,"Tomorrow") -> 0 | AQ25: =SUMIFS($H$7:$H$874,$W$7:$W$874,AK25,$V$7:$V$874,">"&AQ21,$V$7:$V$874,"<="&AQ22)+SUMIFS($H$7:$H$874,$W$7:$W$874,AK25,$V$7:$V$874,"Tomorrow") -> 0 | AR25: =SUMIFS($H$7:$H$874,$W$7:$W$874,AK25,$V$7:$V$874,">"&AR21,$V$7:$V$874,"<="&AR22)+SUMIFS($H$7:$H$874,$W$7:$W$874,AK25,$V$7:$V$874,"Tomorrow") -> 0 | AS25: =SUMIFS($H$7:$H$874,$W$7:$W$874,AK25,$V$7:$V$874,">"&AS21,$V$7:$V$874,"<="&AS22)+SUMIFS($H$7:$H$874,$W$7:$W$874,AK25,$V$7:$V$874,"Tomorrow") -> 0
A26: 10620001 | B26: SYN-Working Capital Loan - Domestic | C26: 6115904000452 | D26: 100000035 | E26: NEXTDC LIMITED | F26: AUD | G26: 20000000 | H26: 20000000 | I26: 45629 | J26: 48185 | K26: 46084 | L26: =VLOOKUP(A26,'Account Mapping'!$A$2:$E$216,3,0) -> #N/A | M26: =VLOOKUP(A26,'Account Mapping'!$A$2:$E$216,4,0) -> #N/A | N26: =IF(OR(C26='Account Mapping'!$H$4,C26='Account Mapping'!$H$5,C26='Account Mapping'!$H$6),'Account Mapping'!$I$4,VLOOKUP(A26,'Account Mapping'!$A$2:$E$216,5,0)) -> #N/A | O26: =IF(OR(L26="Loan",L26="Deposit_Liability",L26="OFF_Unused Loan Commitment",L26="HQLA"),VLOOKUP(D26,'Customer Type'!$A$3:$C$38,3,0),"") -> #N/A | P26: =M26&"_"&O26 -> #N/A | Q26: =IF(COUNTIF('Account Mapping'!$H$12:$H$45,A26)>0,-H26,H26) -> 20000000 | R26: =VLOOKUP(P26,Assumptions!$C$2:$D$64,2,0) -> #N/A | S26: =IFERROR(VLOOKUP(A26,'Maturity Adjustment'!$A$3:$C$81,3,0),(IF(J26<$N$4,"Tomorrow",J26))) -> 48185 | T26: =IF(S26="Tomorrow",1,(S26-$N$4)) -> 2127 | U26: =Q26*R26 -> #N/A | V26: =IFERROR(VLOOKUP(A26,'Maturity Adjustment'!$A$86:$C$91,3,0),S26) -> 48185 | W26: =VLOOKUP(A26,'Account Mapping'!$A$2:$F$216,6,0) -> #N/A | X26: =IF(V26="Tomorrow",Q26,IF(AND(V26>$X$4-1,V26<$X$5),Q26,IF(V26=$X$5,Q26,0))) -> 0 | Y26: =IF(AND(V26>$Y$4-1,V26<$Y$5),Q26,IF(V26=$Y$5,Q26,0)) -> 0 | Z26: =IF(AND(V26>$Z$4-1,V26<$Z$5),Q26,IF(V26=$Z$5,Q26,0)) -> 0 | AA26: =IF(AND(V26>$AA$4-1,V26<$AA$5),Q26,IF(V26=$AA$5,Q26,0)) -> 0 | AB26: =IF(AND(V26>$AB$4-1,V26<$AB$5),Q26,IF(V26=$AB$5,Q26,0)) -> 0 | AC26: =IF(AND(V26>$AC$4-1,V26<$AC$5),Q26,IF(V26=$AC$5,Q26,0)) -> 0 | AD26: =IF(AND(V26>$AD$4-1,V26<$AD$5),Q26,IF(V26=$AD$5,Q26,0)) -> 0 | AE26: =IF(AND(V26>$AE$4-1,V26<$AE$5),Q26,IF(V26=$AE$5,Q26,0)) -> 0 | AF26: =IF(AND(V26>$AF$4-1,V26<$AF$5),Q26,IF(V26=$AF$5,Q26,0)) -> 20000000 | AG26: =IF(AND(V26>$AG$4-1,V26<$AG$5),Q26,IF(V26=$AG$5,Q26,0)) -> 0 | AH26: =Q26=SUM(X26:AG26) -> TRUE | AK26: Liability | AL26: =SUMIFS($H$7:$H$874,$W$7:$W$874,AK26,$V$7:$V$874,">"&AL21,$V$7:$V$874,"<="&AL22)+SUMIFS($H$7:$H$874,$W$7:$W$874,AK26,$V$7:$V$874,"Tomorrow") -> 0 | AM26: =SUMIFS($H$7:$H$874,$W$7:$W$874,AK26,$V$7:$V$874,">"&AM21,$V$7:$V$874,"<="&AM22)+SUMIFS($H$7:$H$874,$W$7:$W$874,AK26,$V$7:$V$874,"Tomorrow") -> 0 | AN26: =SUMIFS($H$7:$H$874,$W$7:$W$874,AK26,$V$7:$V$874,">"&AN21,$V$7:$V$874,"<="&AN22)+SUMIFS($H$7:$H$874,$W$7:$W$874,AK26,$V$7:$V$874,"Tomorrow") -> 0 | AO26: =SUMIFS($H$7:$H$874,$W$7:$W$874,AK26,$V$7:$V$874,">"&AO21,$V$7:$V$874,"<="&AO22)+SUMIFS($H$7:$H$874,$W$7:$W$874,AK26,$V$7:$V$874,"Tomorrow") -> 0 | AP26: =SUMIFS($H$7:$H$874,$W$7:$W$874,AK26,$V$7:$V$874,">"&AP21,$V$7:$V$874,"<="&AP22)+SUMIFS($H$7:$H$874,$W$7:$W$874,AK26,$V$7:$V$874,"Tomorrow") -> 0 | AQ26: =SUMIFS($H$7:$H$874,$W$7:$W$874,AK26,$V$7:$V$874,">"&AQ21,$V$7:$V$874,"<="&AQ22)+SUMIFS($H$7:$H$874,$W$7:$W$874,AK26,$V$7:$V$874,"Tomorrow") -> 0 | AR26: =SUMIFS($H$7:$H$874,$W$7:$W$874,AK26,$V$7:$V$874,">"&AR21,$V$7:$V$874,"<="&AR22)+SUMIFS($H$7:$H$874,$W$7:$W$874,AK26,$V$7:$V$874,"Tomorrow") -> 0 | AS26: =SUMIFS($H$7:$H$874,$W$7:$W$874,AK26,$V$7:$V$874,">"&AS21,$V$7:$V$874,"<="&AS22)+SUMIFS($H$7:$H$874,$W$7:$W$874,AK26,$V$7:$V$874,"Tomorrow") -> 0
A27: 10620001 | B27: SYN-Working Capital Loan - Domestic | C27: 6115904000573 | D27: 100000039 | E27: QANTAS AIRWAYS LIMITED | F27: AUD | G27: 5000000 | H27: 5000000 | I27: 45791 | J27: 48341 | K27: 46066 | L27: =VLOOKUP(A27,'Account Mapping'!$A$2:$E$216,3,0) -> #N/A | M27: =VLOOKUP(A27,'Account Mapping'!$A$2:$E$216,4,0) -> #N/A | N27: =IF(OR(C27='Account Mapping'!$H$4,C27='Account Mapping'!$H$5,C27='Account Mapping'!$H$6),'Account Mapping'!$I$4,VLOOKUP(A27,'Account Mapping'!$A$2:$E$216,5,0)) -> #N/A | O27: =IF(OR(L27="Loan",L27="Deposit_Liability",L27="OFF_Unused Loan Commitment",L27="HQLA"),VLOOKUP(D27,'Customer Type'!$A$3:$C$38,3,0),"") -> #N/A | P27: =M27&"_"&O27 -> #N/A | Q27: =IF(COUNTIF('Account Mapping'!$H$12:$H$45,A27)>0,-H27,H27) -> 5000000 | R27: =VLOOKUP(P27,Assumptions!$C$2:$D$64,2,0) -> #N/A | S27: =IFERROR(VLOOKUP(A27,'Maturity Adjustment'!$A$3:$C$81,3,0),(IF(J27<$N$4,"Tomorrow",J27))) -> 48341 | T27: =IF(S27="Tomorrow",1,(S27-$N$4)) -> 2283 | U27: =Q27*R27 -> #N/A | V27: =IFERROR(VLOOKUP(A27,'Maturity Adjustment'!$A$86:$C$91,3,0),S27) -> 48341 | W27: =VLOOKUP(A27,'Account Mapping'!$A$2:$F$216,6,0) -> #N/A | X27: =IF(V27="Tomorrow",Q27,IF(AND(V27>$X$4-1,V27<$X$5),Q27,IF(V27=$X$5,Q27,0))) -> 0 | Y27: =IF(AND(V27>$Y$4-1,V27<$Y$5),Q27,IF(V27=$Y$5,Q27,0)) -> 0 | Z27: =IF(AND(V27>$Z$4-1,V27<$Z$5),Q27,IF(V27=$Z$5,Q27,0)) -> 0 | AA27: =IF(AND(V27>$AA$4-1,V27<$AA$5),Q27,IF(V27=$AA$5,Q27,0)) -> 0 | AB27: =IF(AND(V27>$AB$4-1,V27<$AB$5),Q27,IF(V27=$AB$5,Q27,0)) -> 0 | AC27: =IF(AND(V27>$AC$4-1,V27<$AC$5),Q27,IF(V27=$AC$5,Q27,0)) -> 0 | AD27: =IF(AND(V27>$AD$4-1,V27<$AD$5),Q27,IF(V27=$AD$5,Q27,0)) -> 0 | AE27: =IF(AND(V27>$AE$4-1,V27<$AE$5),Q27,IF(V27=$AE$5,Q27,0)) -> 0 | AF27: =IF(AND(V27>$AF$4-1,V27<$AF$5),Q27,IF(V27=$AF$5,Q27,0)) -> 5000000 | AG27: =IF(AND(V27>$AG$4-1,V27<$AG$5),Q27,IF(V27=$AG$5,Q27,0)) -> 0 | AH27: =Q27=SUM(X27:AG27) -> TRUE | AK27: Gap | AL27: =AL25-AL26 -> 0 | AM27: =AM25-AM26 -> 0 | AN27: =AN25-AN26 -> 0 | AO27: =AO25-AO26 -> 0 | AP27: =AP25-AP26 -> 0 | AQ27: =AQ25-AQ26 -> 0 | AR27: =AR25-AR26 -> 0 | AS27: =AS25-AS26 -> 0
A28: 10620001 | B28: SYN-Working Capital Loan - Domestic | C28: 6115904000609 | D28: 100000040 | E28: DOWNER GROUP FINANCE PTY LIMITED | F28: AUD | G28: 35000000 | H28: 35000000 | I28: 45828 | J28: 48383 | K28: 46080 | L28: =VLOOKUP(A28,'Account Mapping'!$A$2:$E$216,3,0) -> #N/A | M28: =VLOOKUP(A28,'Account Mapping'!$A$2:$E$216,4,0) -> #N/A | N28: =IF(OR(C28='Account Mapping'!$H$4,C28='Account Mapping'!$H$5,C28='Account Mapping'!$H$6),'Account Mapping'!$I$4,VLOOKUP(A28,'Account Mapping'!$A$2:$E$216,5,0)) -> #N/A | O28: =IF(OR(L28="Loan",L28="Deposit_Liability",L28="OFF_Unused Loan Commitment",L28="HQLA"),VLOOKUP(D28,'Customer Type'!$A$3:$C$38,3,0),"") -> #N/A | P28: =M28&"_"&O28 -> #N/A | Q28: =IF(COUNTIF('Account Mapping'!$H$12:$H$45,A28)>0,-H28,H28) -> 35000000 | R28: =VLOOKUP(P28,Assumptions!$C$2:$D$64,2,0) -> #N/A | S28: =IFERROR(VLOOKUP(A28,'Maturity Adjustment'!$A$3:$C$81,3,0),(IF(J28<$N$4,"Tomorrow",J28))) -> 48383 | T28: =IF(S28="Tomorrow",1,(S28-$N$4)) -> 2325 | U28: =Q28*R28 -> #N/A | V28: =IFERROR(VLOOKUP(A28,'Maturity Adjustment'!$A$86:$C$91,3,0),S28) -> 48383 | W28: =VLOOKUP(A28,'Account Mapping'!$A$2:$F$216,6,0) -> #N/A | X28: =IF(V28="Tomorrow",Q28,IF(AND(V28>$X$4-1,V28<$X$5),Q28,IF(V28=$X$5,Q28,0))) -> 0 | Y28: =IF(AND(V28>$Y$4-1,V28<$Y$5),Q28,IF(V28=$Y$5,Q28,0)) -> 0 | Z28: =IF(AND(V28>$Z$4-1,V28<$Z$5),Q28,IF(V28=$Z$5,Q28,0)) -> 0 | AA28: =IF(AND(V28>$AA$4-1,V28<$AA$5),Q28,IF(V28=$AA$5,Q28,0)) -> 0 | AB28: =IF(AND(V28>$AB$4-1,V28<$AB$5),Q28,IF(V28=$AB$5,Q28,0)) -> 0 | AC28: =IF(AND(V28>$AC$4-1,V28<$AC$5),Q28,IF(V28=$AC$5,Q28,0)) -> 0 | AD28: =IF(AND(V28>$AD$4-1,V28<$AD$5),Q28,IF(V28=$AD$5,Q28,0)) -> 0 | AE28: =IF(AND(V28>$AE$4-1,V28<$AE$5),Q28,IF(V28=$AE$5,Q28,0)) -> 0 | AF28: =IF(AND(V28>$AF$4-1,V28<$AF$5),Q28,IF(V28=$AF$5,Q28,0)) -> 35000000 | AG28: =IF(AND(V28>$AG$4-1,V28<$AG$5),Q28,IF(V28=$AG$5,Q28,0)) -> 0 | AH28: =Q28=SUM(X28:AG28) -> TRUE | AK28: Total Asset | AL28: =AL16 -> 0 | AM28: =AL28 -> 0 | AN28: =AM28 -> 0 | AO28: =AN28 -> 0 | AP28: =AO28 -> 0 | AQ28: =AP28 -> 0 | AR28: =AQ28 -> 0 | AS28: =AR28 -> 0
A29: 10620001 | B29: SYN-Working Capital Loan - Domestic | C29: 6115904000623 | D29: 100000020 | E29: APA INFRASTRUCTURE LIMITED | F29: AUD | G29: 20000000 | H29: 20000000 | I29: 45833 | J29: 48426 | K29: 46153 | L29: =VLOOKUP(A29,'Account Mapping'!$A$2:$E$216,3,0) -> #N/A | M29: =VLOOKUP(A29,'Account Mapping'!$A$2:$E$216,4,0) -> #N/A | N29: =IF(OR(C29='Account Mapping'!$H$4,C29='Account Mapping'!$H$5,C29='Account Mapping'!$H$6),'Account Mapping'!$I$4,VLOOKUP(A29,'Account Mapping'!$A$2:$E$216,5,0)) -> #N/A | O29: =IF(OR(L29="Loan",L29="Deposit_Liability",L29="OFF_Unused Loan Commitment",L29="HQLA"),VLOOKUP(D29,'Customer Type'!$A$3:$C$38,3,0),"") -> #N/A | P29: =M29&"_"&O29 -> #N/A | Q29: =IF(COUNTIF('Account Mapping'!$H$12:$H$45,A29)>0,-H29,H29) -> 20000000 | R29: =VLOOKUP(P29,Assumptions!$C$2:$D$64,2,0) -> #N/A | S29: =IFERROR(VLOOKUP(A29,'Maturity Adjustment'!$A$3:$C$81,3,0),(IF(J29<$N$4,"Tomorrow",J29))) -> 48426 | T29: =IF(S29="Tomorrow",1,(S29-$N$4)) -> 2368 | U29: =Q29*R29 -> #N/A | V29: =IFERROR(VLOOKUP(A29,'Maturity Adjustment'!$A$86:$C$91,3,0),S29) -> 48426 | W29: =VLOOKUP(A29,'Account Mapping'!$A$2:$F$216,6,0) -> #N/A | X29: =IF(V29="Tomorrow",Q29,IF(AND(V29>$X$4-1,V29<$X$5),Q29,IF(V29=$X$5,Q29,0))) -> 0 | Y29: =IF(AND(V29>$Y$4-1,V29<$Y$5),Q29,IF(V29=$Y$5,Q29,0)) -> 0 | Z29: =IF(AND(V29>$Z$4-1,V29<$Z$5),Q29,IF(V29=$Z$5,Q29,0)) -> 0 | AA29: =IF(AND(V29>$AA$4-1,V29<$AA$5),Q29,IF(V29=$AA$5,Q29,0)) -> 0 | AB29: =IF(AND(V29>$AB$4-1,V29<$AB$5),Q29,IF(V29=$AB$5,Q29,0)) -> 0 | AC29: =IF(AND(V29>$AC$4-1,V29<$AC$5),Q29,IF(V29=$AC$5,Q29,0)) -> 0 | AD29: =IF(AND(V29>$AD$4-1,V29<$AD$5),Q29,IF(V29=$AD$5,Q29,0)) -> 0 | AE29: =IF(AND(V29>$AE$4-1,V29<$AE$5),Q29,IF(V29=$AE$5,Q29,0)) -> 0 | AF29: =IF(AND(V29>$AF$4-1,V29<$AF$5),Q29,IF(V29=$AF$5,Q29,0)) -> 20000000 | AG29: =IF(AND(V29>$AG$4-1,V29<$AG$5),Q29,IF(V29=$AG$5,Q29,0)) -> 0 | AH29: =Q29=SUM(X29:AG29) -> TRUE | AK29: Gap ratio | AL29: =AL27/AL28 -> #DIV/0! | AM29: =AM27/AM28 -> #DIV/0! | AN29: =AN27/AN28 -> #DIV/0! | AO29: =AO27/AO28 -> #DIV/0! | AP29: =AP27/AP28 -> #DIV/0! | AQ29: =AQ27/AQ28 -> #DIV/0! | AR29: =AR27/AR28 -> #DIV/0! | AS29: =AS27/AS28 -> #DIV/0!
A30: 10620001 | B30: SYN-Working Capital Loan - Domestic | C30: 6115904000705 | D30: 100000039 | E30: QANTAS AIRWAYS LIMITED | F30: AUD | G30: 5000000 | H30: 5000000 | I30: 45924 | J30: 48487 | K30: 46105 | L30: =VLOOKUP(A30,'Account Mapping'!$A$2:$E$216,3,0) -> #N/A | M30: =VLOOKUP(A30,'Account Mapping'!$A$2:$E$216,4,0) -> #N/A | N30: =IF(OR(C30='Account Mapping'!$H$4,C30='Account Mapping'!$H$5,C30='Account Mapping'!$H$6),'Account Mapping'!$I$4,VLOOKUP(A30,'Account Mapping'!$A$2:$E$216,5,0)) -> #N/A | O30: =IF(OR(L30="Loan",L30="Deposit_Liability",L30="OFF_Unused Loan Commitment",L30="HQLA"),VLOOKUP(D30,'Customer Type'!$A$3:$C$38,3,0),"") -> #N/A | P30: =M30&"_"&O30 -> #N/A | Q30: =IF(COUNTIF('Account Mapping'!$H$12:$H$45,A30)>0,-H30,H30) -> 5000000 | R30: =VLOOKUP(P30,Assumptions!$C$2:$D$64,2,0) -> #N/A | S30: =IFERROR(VLOOKUP(A30,'Maturity Adjustment'!$A$3:$C$81,3,0),(IF(J30<$N$4,"Tomorrow",J30))) -> 48487 | T30: =IF(S30="Tomorrow",1,(S30-$N$4)) -> 2429 | U30: =Q30*R30 -> #N/A | V30: =IFERROR(VLOOKUP(A30,'Maturity Adjustment'!$A$86:$C$91,3,0),S30) -> 48487 | W30: =VLOOKUP(A30,'Account Mapping'!$A$2:$F$216,6,0) -> #N/A | X30: =IF(V30="Tomorrow",Q30,IF(AND(V30>$X$4-1,V30<$X$5),Q30,IF(V30=$X$5,Q30,0))) -> 0 | Y30: =IF(AND(V30>$Y$4-1,V30<$Y$5),Q30,IF(V30=$Y$5,Q30,0)) -> 0 | Z30: =IF(AND(V30>$Z$4-1,V30<$Z$5),Q30,IF(V30=$Z$5,Q30,0)) -> 0 | AA30: =IF(AND(V30>$AA$4-1,V30<$AA$5),Q30,IF(V30=$AA$5,Q30,0)) -> 0 | AB30: =IF(AND(V30>$AB$4-1,V30<$AB$5),Q30,IF(V30=$AB$5,Q30,0)) -> 0 | AC30: =IF(AND(V30>$AC$4-1,V30<$AC$5),Q30,IF(V30=$AC$5,Q30,0)) -> 0 | AD30: =IF(AND(V30>$AD$4-1,V30<$AD$5),Q30,IF(V30=$AD$5,Q30,0)) -> 0 | AE30: =IF(AND(V30>$AE$4-1,V30<$AE$5),Q30,IF(V30=$AE$5,Q30,0)) -> 0 | AF30: =IF(AND(V30>$AF$4-1,V30<$AF$5),Q30,IF(V30=$AF$5,Q30,0)) -> 5000000 | AG30: =IF(AND(V30>$AG$4-1,V30<$AG$5),Q30,IF(V30=$AG$5,Q30,0)) -> 0 | AH30: =Q30=SUM(X30:AG30) -> TRUE | AK30: Trigger | AL30: -0.15 | AM30: =AL30 -> -0.15 | AN30: =AM30 -> -0.15 | AO30: =AN30 -> -0.15 | AP30: =AO30 -> -0.15 | AQ30: =AP30 -> -0.15 | AR30: =AQ30 -> -0.15 | AS30: =AR30 -> -0.15
A31: 10620001 | B31: SYN-Working Capital Loan - Domestic | C31: 6115904000744 | D31: 100000033 | E31: MACQUARIE GROUP LIMITED | F31: USD | G31: 10000000 | H31: 14236902 | I31: 45974 | J31: 48136 | K31: 46066 | L31: =VLOOKUP(A31,'Account Mapping'!$A$2:$E$216,3,0) -> #N/A | M31: =VLOOKUP(A31,'Account Mapping'!$A$2:$E$216,4,0) -> #N/A | N31: =IF(OR(C31='Account Mapping'!$H$4,C31='Account Mapping'!$H$5,C31='Account Mapping'!$H$6),'Account Mapping'!$I$4,VLOOKUP(A31,'Account Mapping'!$A$2:$E$216,5,0)) -> #N/A | O31: =IF(OR(L31="Loan",L31="Deposit_Liability",L31="OFF_Unused Loan Commitment",L31="HQLA"),VLOOKUP(D31,'Customer Type'!$A$3:$C$38,3,0),"") -> #N/A | P31: =M31&"_"&O31 -> #N/A | Q31: =IF(COUNTIF('Account Mapping'!$H$12:$H$45,A31)>0,-H31,H31) -> 14236902 | R31: =VLOOKUP(P31,Assumptions!$C$2:$D$64,2,0) -> #N/A | S31: =IFERROR(VLOOKUP(A31,'Maturity Adjustment'!$A$3:$C$81,3,0),(IF(J31<$N$4,"Tomorrow",J31))) -> 48136 | T31: =IF(S31="Tomorrow",1,(S31-$N$4)) -> 2078 | U31: =Q31*R31 -> #N/A | V31: =IFERROR(VLOOKUP(A31,'Maturity Adjustment'!$A$86:$C$91,3,0),S31) -> 48136 | W31: =VLOOKUP(A31,'Account Mapping'!$A$2:$F$216,6,0) -> #N/A | X31: =IF(V31="Tomorrow",Q31,IF(AND(V31>$X$4-1,V31<$X$5),Q31,IF(V31=$X$5,Q31,0))) -> 0 | Y31: =IF(AND(V31>$Y$4-1,V31<$Y$5),Q31,IF(V31=$Y$5,Q31,0)) -> 0 | Z31: =IF(AND(V31>$Z$4-1,V31<$Z$5),Q31,IF(V31=$Z$5,Q31,0)) -> 0 | AA31: =IF(AND(V31>$AA$4-1,V31<$AA$5),Q31,IF(V31=$AA$5,Q31,0)) -> 0 | AB31: =IF(AND(V31>$AB$4-1,V31<$AB$5),Q31,IF(V31=$AB$5,Q31,0)) -> 0 | AC31: =IF(AND(V31>$AC$4-1,V31<$AC$5),Q31,IF(V31=$AC$5,Q31,0)) -> 0 | AD31: =IF(AND(V31>$AD$4-1,V31<$AD$5),Q31,IF(V31=$AD$5,Q31,0)) -> 0 | AE31: =IF(AND(V31>$AE$4-1,V31<$AE$5),Q31,IF(V31=$AE$5,Q31,0)) -> 0 | AF31: =IF(AND(V31>$AF$4-1,V31<$AF$5),Q31,IF(V31=$AF$5,Q31,0)) -> 14236902 | AG31: =IF(AND(V31>$AG$4-1,V31<$AG$5),Q31,IF(V31=$AG$5,Q31,0)) -> 0 | AH31: =Q31=SUM(X31:AG31) -> TRUE | AK31: (-)Shortfall | AL31: =-AL28*(AL30-AL29) -> #DIV/0! | AM31: =-AM28*(AM30-AM29) -> #DIV/0! | AN31: =-AN28*(AN30-AN29) -> #DIV/0! | AO31: =-AO28*(AO30-AO29) -> #DIV/0! | AP31: =-AP28*(AP30-AP29) -> #DIV/0! | AQ31: =-AQ28*(AQ30-AQ29) -> #DIV/0! | AR31: =-AR28*(AR30-AR29) -> #DIV/0! | AS31: =-AS28*(AS30-AS29) -> #DIV/0!
A32: 10630001 | B32: Syndicated Loans (Long Term) - Domestic | C32: 6115904000025 | D32: 100000014 | E32: PERDAMAN CHEMICALS & FERTILISERS (FINANCE)PTY LTD | F32: USD | G32: 7591892 | H32: 10808502 | I32: 45106 | J32: 47579 | K32: 46058 | L32: =VLOOKUP(A32,'Account Mapping'!$A$2:$E$216,3,0) -> #N/A | M32: =VLOOKUP(A32,'Account Mapping'!$A$2:$E$216,4,0) -> #N/A | N32: =IF(OR(C32='Account Mapping'!$H$4,C32='Account Mapping'!$H$5,C32='Account Mapping'!$H$6),'Account Mapping'!$I$4,VLOOKUP(A32,'Account Mapping'!$A$2:$E$216,5,0)) -> #N/A | O32: =IF(OR(L32="Loan",L32="Deposit_Liability",L32="OFF_Unused Loan Commitment",L32="HQLA"),VLOOKUP(D32,'Customer Type'!$A$3:$C$38,3,0),"") -> #N/A | P32: =M32&"_"&O32 -> #N/A | Q32: =IF(COUNTIF('Account Mapping'!$H$12:$H$45,A32)>0,-H32,H32) -> 10808502 | R32: =VLOOKUP(P32,Assumptions!$C$2:$D$64,2,0) -> #N/A | S32: =IFERROR(VLOOKUP(A32,'Maturity Adjustment'!$A$3:$C$81,3,0),(IF(J32<$N$4,"Tomorrow",J32))) -> 47579 | T32: =IF(S32="Tomorrow",1,(S32-$N$4)) -> 1521 | U32: =Q32*R32 -> #N/A | V32: =IFERROR(VLOOKUP(A32,'Maturity Adjustment'!$A$86:$C$91,3,0),S32) -> 47579 | W32: =VLOOKUP(A32,'Account Mapping'!$A$2:$F$216,6,0) -> #N/A | X32: =IF(V32="Tomorrow",Q32,IF(AND(V32>$X$4-1,V32<$X$5),Q32,IF(V32=$X$5,Q32,0))) -> 0 | Y32: =IF(AND(V32>$Y$4-1,V32<$Y$5),Q32,IF(V32=$Y$5,Q32,0)) -> 0 | Z32: =IF(AND(V32>$Z$4-1,V32<$Z$5),Q32,IF(V32=$Z$5,Q32,0)) -> 0 | AA32: =IF(AND(V32>$AA$4-1,V32<$AA$5),Q32,IF(V32=$AA$5,Q32,0)) -> 0 | AB32: =IF(AND(V32>$AB$4-1,V32<$AB$5),Q32,IF(V32=$AB$5,Q32,0)) -> 0 | AC32: =IF(AND(V32>$AC$4-1,V32<$AC$5),Q32,IF(V32=$AC$5,Q32,0)) -> 0 | AD32: =IF(AND(V32>$AD$4-1,V32<$AD$5),Q32,IF(V32=$AD$5,Q32,0)) -> 0 | AE32: =IF(AND(V32>$AE$4-1,V32<$AE$5),Q32,IF(V32=$AE$5,Q32,0)) -> 10808502 | AF32: =IF(AND(V32>$AF$4-1,V32<$AF$5),Q32,IF(V32=$AF$5,Q32,0)) -> 0 | AG32: =IF(AND(V32>$AG$4-1,V32<$AG$5),Q32,IF(V32=$AG$5,Q32,0)) -> 0 | AH32: =Q32=SUM(X32:AG32) -> TRUE
A33: 10630001 | B33: Syndicated Loans (Long Term) - Domestic | C33: 6115904000032 | D33: 100000014 | E33: PERDAMAN CHEMICALS & FERTILISERS (FINANCE)PTY LTD | F33: USD | G33: 129689.8 | H33: 184638.1 | I33: 45107 | J33: 47579 | K33: 46058 | L33: =VLOOKUP(A33,'Account Mapping'!$A$2:$E$216,3,0) -> #N/A | M33: =VLOOKUP(A33,'Account Mapping'!$A$2:$E$216,4,0) -> #N/A | N33: =IF(OR(C33='Account Mapping'!$H$4,C33='Account Mapping'!$H$5,C33='Account Mapping'!$H$6),'Account Mapping'!$I$4,VLOOKUP(A33,'Account Mapping'!$A$2:$E$216,5,0)) -> #N/A | O33: =IF(OR(L33="Loan",L33="Deposit_Liability",L33="OFF_Unused Loan Commitment",L33="HQLA"),VLOOKUP(D33,'Customer Type'!$A$3:$C$38,3,0),"") -> #N/A | P33: =M33&"_"&O33 -> #N/A | Q33: =IF(COUNTIF('Account Mapping'!$H$12:$H$45,A33)>0,-H33,H33) -> 184638.1 | R33: =VLOOKUP(P33,Assumptions!$C$2:$D$64,2,0) -> #N/A | S33: =IFERROR(VLOOKUP(A33,'Maturity Adjustment'!$A$3:$C$81,3,0),(IF(J33<$N$4,"Tomorrow",J33))) -> 47579 | T33: =IF(S33="Tomorrow",1,(S33-$N$4)) -> 1521 | U33: =Q33*R33 -> #N/A | V33: =IFERROR(VLOOKUP(A33,'Maturity Adjustment'!$A$86:$C$91,3,0),S33) -> 47579 | W33: =VLOOKUP(A33,'Account Mapping'!$A$2:$F$216,6,0) -> #N/A | X33: =IF(V33="Tomorrow",Q33,IF(AND(V33>$X$4-1,V33<$X$5),Q33,IF(V33=$X$5,Q33,0))) -> 0 | Y33: =IF(AND(V33>$Y$4-1,V33<$Y$5),Q33,IF(V33=$Y$5,Q33,0)) -> 0 | Z33: =IF(AND(V33>$Z$4-1,V33<$Z$5),Q33,IF(V33=$Z$5,Q33,0)) -> 0 | AA33: =IF(AND(V33>$AA$4-1,V33<$AA$5),Q33,IF(V33=$AA$5,Q33,0)) -> 0 | AB33: =IF(AND(V33>$AB$4-1,V33<$AB$5),Q33,IF(V33=$AB$5,Q33,0)) -> 0 | AC33: =IF(AND(V33>$AC$4-1,V33<$AC$5),Q33,IF(V33=$AC$5,Q33,0)) -> 0 | AD33: =IF(AND(V33>$AD$4-1,V33<$AD$5),Q33,IF(V33=$AD$5,Q33,0)) -> 0 | AE33: =IF(AND(V33>$AE$4-1,V33<$AE$5),Q33,IF(V33=$AE$5,Q33,0)) -> 184638.1 | AF33: =IF(AND(V33>$AF$4-1,V33<$AF$5),Q33,IF(V33=$AF$5,Q33,0)) -> 0 | AG33: =IF(AND(V33>$AG$4-1,V33<$AG$5),Q33,IF(V33=$AG$5,Q33,0)) -> 0 | AH33: =Q33=SUM(X33:AG33) -> TRUE | AJ33: 3 month | AK33: From | AL33: =AL21 -> 46081 | AM33: =EOMONTH(AL33,1) -> 46112 | AN33: =EOMONTH(AM33,1) -> 46142 | AO33: =EOMONTH(AN33,1) -> 46173 | AP33: =EOMONTH(AO33,1) -> 46203 | AQ33: =EOMONTH(AP33,1) -> 46234 | AR33: =EOMONTH(AQ33,1) -> 46265 | AS33: =EOMONTH(AR33,1) -> 46295
A34: 10630001 | B34: Syndicated Loans (Long Term) - Domestic | C34: 6115904000040 | D34: 100000014 | E34: PERDAMAN CHEMICALS & FERTILISERS (FINANCE)PTY LTD | F34: USD | G34: 1787648.6 | H34: 2545057.8 | I34: 45138 | J34: 47579 | K34: 46058 | L34: =VLOOKUP(A34,'Account Mapping'!$A$2:$E$216,3,0) -> #N/A | M34: =VLOOKUP(A34,'Account Mapping'!$A$2:$E$216,4,0) -> #N/A | N34: =IF(OR(C34='Account Mapping'!$H$4,C34='Account Mapping'!$H$5,C34='Account Mapping'!$H$6),'Account Mapping'!$I$4,VLOOKUP(A34,'Account Mapping'!$A$2:$E$216,5,0)) -> #N/A | O34: =IF(OR(L34="Loan",L34="Deposit_Liability",L34="OFF_Unused Loan Commitment",L34="HQLA"),VLOOKUP(D34,'Customer Type'!$A$3:$C$38,3,0),"") -> #N/A | P34: =M34&"_"&O34 -> #N/A | Q34: =IF(COUNTIF('Account Mapping'!$H$12:$H$45,A34)>0,-H34,H34) -> 2545057.8 | R34: =VLOOKUP(P34,Assumptions!$C$2:$D$64,2,0) -> #N/A | S34: =IFERROR(VLOOKUP(A34,'Maturity Adjustment'!$A$3:$C$81,3,0),(IF(J34<$N$4,"Tomorrow",J34))) -> 47579 | T34: =IF(S34="Tomorrow",1,(S34-$N$4)) -> 1521 | U34: =Q34*R34 -> #N/A | V34: =IFERROR(VLOOKUP(A34,'Maturity Adjustment'!$A$86:$C$91,3,0),S34) -> 47579 | W34: =VLOOKUP(A34,'Account Mapping'!$A$2:$F$216,6,0) -> #N/A | X34: =IF(V34="Tomorrow",Q34,IF(AND(V34>$X$4-1,V34<$X$5),Q34,IF(V34=$X$5,Q34,0))) -> 0 | Y34: =IF(AND(V34>$Y$4-1,V34<$Y$5),Q34,IF(V34=$Y$5,Q34,0)) -> 0 | Z34: =IF(AND(V34>$Z$4-1,V34<$Z$5),Q34,IF(V34=$Z$5,Q34,0)) -> 0 | AA34: =IF(AND(V34>$AA$4-1,V34<$AA$5),Q34,IF(V34=$AA$5,Q34,0)) -> 0 | AB34: =IF(AND(V34>$AB$4-1,V34<$AB$5),Q34,IF(V34=$AB$5,Q34,0)) -> 0 | AC34: =IF(AND(V34>$AC$4-1,V34<$AC$5),Q34,IF(V34=$AC$5,Q34,0)) -> 0 | AD34: =IF(AND(V34>$AD$4-1,V34<$AD$5),Q34,IF(V34=$AD$5,Q34,0)) -> 0 | AE34: =IF(AND(V34>$AE$4-1,V34<$AE$5),Q34,IF(V34=$AE$5,Q34,0)) -> 2545057.8 | AF34: =IF(AND(V34>$AF$4-1,V34<$AF$5),Q34,IF(V34=$AF$5,Q34,0)) -> 0 | AG34: =IF(AND(V34>$AG$4-1,V34<$AG$5),Q34,IF(V34=$AG$5,Q34,0)) -> 0 | AH34: =Q34=SUM(X34:AG34) -> TRUE | AK34: To | AL34: =EOMONTH(AL33,3) -> 46173 | AM34: =EOMONTH(AM33,3) -> 46203 | AN34: =EOMONTH(AN33,3) -> 46234 | AO34: =EOMONTH(AO33,3) -> 46265 | AP34: =EOMONTH(AP33,3) -> 46295 | AQ34: =EOMONTH(AQ33,3) -> 46326 | AR34: =EOMONTH(AR33,3) -> 46356 | AS34: =EOMONTH(AS33,3) -> 46387
A35: 10630001 | B35: Syndicated Loans (Long Term) - Domestic | C35: 6115904000057 | D35: 100000014 | E35: PERDAMAN CHEMICALS & FERTILISERS (FINANCE)PTY LTD | F35: USD | G35: 98518.15 | H35: 140259.33 | I35: 45138 | J35: 47579 | K35: 46058 | L35: =VLOOKUP(A35,'Account Mapping'!$A$2:$E$216,3,0) -> #N/A | M35: =VLOOKUP(A35,'Account Mapping'!$A$2:$E$216,4,0) -> #N/A | N35: =IF(OR(C35='Account Mapping'!$H$4,C35='Account Mapping'!$H$5,C35='Account Mapping'!$H$6),'Account Mapping'!$I$4,VLOOKUP(A35,'Account Mapping'!$A$2:$E$216,5,0)) -> #N/A | O35: =IF(OR(L35="Loan",L35="Deposit_Liability",L35="OFF_Unused Loan Commitment",L35="HQLA"),VLOOKUP(D35,'Customer Type'!$A$3:$C$38,3,0),"") -> #N/A | P35: =M35&"_"&O35 -> #N/A | Q35: =IF(COUNTIF('Account Mapping'!$H$12:$H$45,A35)>0,-H35,H35) -> 140259.33 | R35: =VLOOKUP(P35,Assumptions!$C$2:$D$64,2,0) -> #N/A | S35: =IFERROR(VLOOKUP(A35,'Maturity Adjustment'!$A$3:$C$81,3,0),(IF(J35<$N$4,"Tomorrow",J35))) -> 47579 | T35: =IF(S35="Tomorrow",1,(S35-$N$4)) -> 1521 | U35: =Q35*R35 -> #N/A | V35: =IFERROR(VLOOKUP(A35,'Maturity Adjustment'!$A$86:$C$91,3,0),S35) -> 47579 | W35: =VLOOKUP(A35,'Account Mapping'!$A$2:$F$216,6,0) -> #N/A | X35: =IF(V35="Tomorrow",Q35,IF(AND(V35>$X$4-1,V35<$X$5),Q35,IF(V35=$X$5,Q35,0))) -> 0 | Y35: =IF(AND(V35>$Y$4-1,V35<$Y$5),Q35,IF(V35=$Y$5,Q35,0)) -> 0 | Z35: =IF(AND(V35>$Z$4-1,V35<$Z$5),Q35,IF(V35=$Z$5,Q35,0)) -> 0 | AA35: =IF(AND(V35>$AA$4-1,V35<$AA$5),Q35,IF(V35=$AA$5,Q35,0)) -> 0 | AB35: =IF(AND(V35>$AB$4-1,V35<$AB$5),Q35,IF(V35=$AB$5,Q35,0)) -> 0 | AC35: =IF(AND(V35>$AC$4-1,V35<$AC$5),Q35,IF(V35=$AC$5,Q35,0)) -> 0 | AD35: =IF(AND(V35>$AD$4-1,V35<$AD$5),Q35,IF(V35=$AD$5,Q35,0)) -> 0 | AE35: =IF(AND(V35>$AE$4-1,V35<$AE$5),Q35,IF(V35=$AE$5,Q35,0)) -> 140259.33 | AF35: =IF(AND(V35>$AF$4-1,V35<$AF$5),Q35,IF(V35=$AF$5,Q35,0)) -> 0 | AG35: =IF(AND(V35>$AG$4-1,V35<$AG$5),Q35,IF(V35=$AG$5,Q35,0)) -> 0 | AH35: =Q35=SUM(X35:AG35) -> TRUE
A36: 10630001 | B36: Syndicated Loans (Long Term) - Domestic | C36: 6115904000064 | D36: 100000014 | E36: PERDAMAN CHEMICALS & FERTILISERS (FINANCE)PTY LTD | F36: USD | G36: 468658.73 | H36: 667224.84 | I36: 45169 | J36: 47579 | K36: 46058 | L36: =VLOOKUP(A36,'Account Mapping'!$A$2:$E$216,3,0) -> #N/A | M36: =VLOOKUP(A36,'Account Mapping'!$A$2:$E$216,4,0) -> #N/A | N36: =IF(OR(C36='Account Mapping'!$H$4,C36='Account Mapping'!$H$5,C36='Account Mapping'!$H$6),'Account Mapping'!$I$4,VLOOKUP(A36,'Account Mapping'!$A$2:$E$216,5,0)) -> #N/A | O36: =IF(OR(L36="Loan",L36="Deposit_Liability",L36="OFF_Unused Loan Commitment",L36="HQLA"),VLOOKUP(D36,'Customer Type'!$A$3:$C$38,3,0),"") -> #N/A | P36: =M36&"_"&O36 -> #N/A | Q36: =IF(COUNTIF('Account Mapping'!$H$12:$H$45,A36)>0,-H36,H36) -> 667224.84 | R36: =VLOOKUP(P36,Assumptions!$C$2:$D$64,2,0) -> #N/A | S36: =IFERROR(VLOOKUP(A36,'Maturity Adjustment'!$A$3:$C$81,3,0),(IF(J36<$N$4,"Tomorrow",J36))) -> 47579 | T36: =IF(S36="Tomorrow",1,(S36-$N$4)) -> 1521 | U36: =Q36*R36 -> #N/A | V36: =IFERROR(VLOOKUP(A36,'Maturity Adjustment'!$A$86:$C$91,3,0),S36) -> 47579 | W36: =VLOOKUP(A36,'Account Mapping'!$A$2:$F$216,6,0) -> #N/A | X36: =IF(V36="Tomorrow",Q36,IF(AND(V36>$X$4-1,V36<$X$5),Q36,IF(V36=$X$5,Q36,0))) -> 0 | Y36: =IF(AND(V36>$Y$4-1,V36<$Y$5),Q36,IF(V36=$Y$5,Q36,0)) -> 0 | Z36: =IF(AND(V36>$Z$4-1,V36<$Z$5),Q36,IF(V36=$Z$5,Q36,0)) -> 0 | AA36: =IF(AND(V36>$AA$4-1,V36<$AA$5),Q36,IF(V36=$AA$5,Q36,0)) -> 0 | AB36: =IF(AND(V36>$AB$4-1,V36<$AB$5),Q36,IF(V36=$AB$5,Q36,0)) -> 0 | AC36: =IF(AND(V36>$AC$4-1,V36<$AC$5),Q36,IF(V36=$AC$5,Q36,0)) -> 0 | AD36: =IF(AND(V36>$AD$4-1,V36<$AD$5),Q36,IF(V36=$AD$5,Q36,0)) -> 0 | AE36: =IF(AND(V36>$AE$4-1,V36<$AE$5),Q36,IF(V36=$AE$5,Q36,0)) -> 667224.84 | AF36: =IF(AND(V36>$AF$4-1,V36<$AF$5),Q36,IF(V36=$AF$5,Q36,0)) -> 0 | AG36: =IF(AND(V36>$AG$4-1,V36<$AG$5),Q36,IF(V36=$AG$5,Q36,0)) -> 0 | AH36: =Q36=SUM(X36:AG36) -> TRUE | AL36: =AL24 -> 46081 | AM36: =AM24 -> 46112 | AN36: =AN24 -> 46142 | AO36: =AO24 -> 46173 | AP36: =AP24 -> 46203 | AQ36: =AQ24 -> 46234 | AR36: =AR24 -> 46265 | AS36: =AS24 -> 46295
A37: 10630001 | B37: Syndicated Loans (Long Term) - Domestic | C37: 6115904000071 | D37: 100000014 | E37: PERDAMAN CHEMICALS & FERTILISERS (FINANCE)PTY LTD | F37: USD | G37: 111261.33 | H37: 158401.67 | I37: 45169 | J37: 47579 | K37: 46058 | L37: =VLOOKUP(A37,'Account Mapping'!$A$2:$E$216,3,0) -> #N/A | M37: =VLOOKUP(A37,'Account Mapping'!$A$2:$E$216,4,0) -> #N/A | N37: =IF(OR(C37='Account Mapping'!$H$4,C37='Account Mapping'!$H$5,C37='Account Mapping'!$H$6),'Account Mapping'!$I$4,VLOOKUP(A37,'Account Mapping'!$A$2:$E$216,5,0)) -> #N/A | O37: =IF(OR(L37="Loan",L37="Deposit_Liability",L37="OFF_Unused Loan Commitment",L37="HQLA"),VLOOKUP(D37,'Customer Type'!$A$3:$C$38,3,0),"") -> #N/A | P37: =M37&"_"&O37 -> #N/A | Q37: =IF(COUNTIF('Account Mapping'!$H$12:$H$45,A37)>0,-H37,H37) -> 158401.67 | R37: =VLOOKUP(P37,Assumptions!$C$2:$D$64,2,0) -> #N/A | S37: =IFERROR(VLOOKUP(A37,'Maturity Adjustment'!$A$3:$C$81,3,0),(IF(J37<$N$4,"Tomorrow",J37))) -> 47579 | T37: =IF(S37="Tomorrow",1,(S37-$N$4)) -> 1521 | U37: =Q37*R37 -> #N/A | V37: =IFERROR(VLOOKUP(A37,'Maturity Adjustment'!$A$86:$C$91,3,0),S37) -> 47579 | W37: =VLOOKUP(A37,'Account Mapping'!$A$2:$F$216,6,0) -> #N/A | X37: =IF(V37="Tomorrow",Q37,IF(AND(V37>$X$4-1,V37<$X$5),Q37,IF(V37=$X$5,Q37,0))) -> 0 | Y37: =IF(AND(V37>$Y$4-1,V37<$Y$5),Q37,IF(V37=$Y$5,Q37,0)) -> 0 | Z37: =IF(AND(V37>$Z$4-1,V37<$Z$5),Q37,IF(V37=$Z$5,Q37,0)) -> 0 | AA37: =IF(AND(V37>$AA$4-1,V37<$AA$5),Q37,IF(V37=$AA$5,Q37,0)) -> 0 | AB37: =IF(AND(V37>$AB$4-1,V37<$AB$5),Q37,IF(V37=$AB$5,Q37,0)) -> 0 | AC37: =IF(AND(V37>$AC$4-1,V37<$AC$5),Q37,IF(V37=$AC$5,Q37,0)) -> 0 | AD37: =IF(AND(V37>$AD$4-1,V37<$AD$5),Q37,IF(V37=$AD$5,Q37,0)) -> 0 | AE37: =IF(AND(V37>$AE$4-1,V37<$AE$5),Q37,IF(V37=$AE$5,Q37,0)) -> 158401.67 | AF37: =IF(AND(V37>$AF$4-1,V37<$AF$5),Q37,IF(V37=$AF$5,Q37,0)) -> 0 | AG37: =IF(AND(V37>$AG$4-1,V37<$AG$5),Q37,IF(V37=$AG$5,Q37,0)) -> 0 | AH37: =Q37=SUM(X37:AG37) -> TRUE | AK37: Asset | AL37: =SUMIFS($H$7:$H$874,$W$7:$W$874,AK37,$V$7:$V$874,">"&AL33,$V$7:$V$874,"<="&AL34)+SUMIFS($H$7:$H$874,$W$7:$W$874,AK37,$V$7:$V$874,"Tomorrow") -> 0 | AM37: =SUMIFS($H$7:$H$874,$W$7:$W$874,AK37,$V$7:$V$874,">"&AM33,$V$7:$V$874,"<="&AM34)+SUMIFS($H$7:$H$874,$W$7:$W$874,AK37,$V$7:$V$874,"Tomorrow") -> 0 | AN37: =SUMIFS($H$7:$H$874,$W$7:$W$874,AK37,$V$7:$V$874,">"&AN33,$V$7:$V$874,"<="&AN34)+SUMIFS($H$7:$H$874,$W$7:$W$874,AK37,$V$7:$V$874,"Tomorrow") -> 0 | AO37: =SUMIFS($H$7:$H$874,$W$7:$W$874,AK37,$V$7:$V$874,">"&AO33,$V$7:$V$874,"<="&AO34)+SUMIFS($H$7:$H$874,$W$7:$W$874,AK37,$V$7:$V$874,"Tomorrow") -> 0 | AP37: =SUMIFS($H$7:$H$874,$W$7:$W$874,AK37,$V$7:$V$874,">"&AP33,$V$7:$V$874,"<="&AP34)+SUMIFS($H$7:$H$874,$W$7:$W$874,AK37,$V$7:$V$874,"Tomorrow") -> 0 | AQ37: =SUMIFS($H$7:$H$874,$W$7:$W$874,AK37,$V$7:$V$874,">"&AQ33,$V$7:$V$874,"<="&AQ34)+SUMIFS($H$7:$H$874,$W$7:$W$874,AK37,$V$7:$V$874,"Tomorrow") -> 0 | AR37: =SUMIFS($H$7:$H$874,$W$7:$W$874,AK37,$V$7:$V$874,">"&AR33,$V$7:$V$874,"<="&AR34)+SUMIFS($H$7:$H$874,$W$7:$W$874,AK37,$V$7:$V$874,"Tomorrow") -> 0 | AS37: =SUMIFS($H$7:$H$874,$W$7:$W$874,AK37,$V$7:$V$874,">"&AS33,$V$7:$V$874,"<="&AS34)+SUMIFS($H$7:$H$874,$W$7:$W$874,AK37,$V$7:$V$874,"Tomorrow") -> 0
A38: 10630001 | B38: Syndicated Loans (Long Term) - Domestic | C38: 6115904000089 | D38: 100000014 | E38: PERDAMAN CHEMICALS & FERTILISERS (FINANCE)PTY LTD | F38: USD | G38: 1607793.1 | H38: 2288999.3 | I38: 45190 | J38: 47579 | K38: 46058 | L38: =VLOOKUP(A38,'Account Mapping'!$A$2:$E$216,3,0) -> #N/A | M38: =VLOOKUP(A38,'Account Mapping'!$A$2:$E$216,4,0) -> #N/A | N38: =IF(OR(C38='Account Mapping'!$H$4,C38='Account Mapping'!$H$5,C38='Account Mapping'!$H$6),'Account Mapping'!$I$4,VLOOKUP(A38,'Account Mapping'!$A$2:$E$216,5,0)) -> #N/A | O38: =IF(OR(L38="Loan",L38="Deposit_Liability",L38="OFF_Unused Loan Commitment",L38="HQLA"),VLOOKUP(D38,'Customer Type'!$A$3:$C$38,3,0),"") -> #N/A | P38: =M38&"_"&O38 -> #N/A | Q38: =IF(COUNTIF('Account Mapping'!$H$12:$H$45,A38)>0,-H38,H38) -> 2288999.3 | R38: =VLOOKUP(P38,Assumptions!$C$2:$D$64,2,0) -> #N/A | S38: =IFERROR(VLOOKUP(A38,'Maturity Adjustment'!$A$3:$C$81,3,0),(IF(J38<$N$4,"Tomorrow",J38))) -> 47579 | T38: =IF(S38="Tomorrow",1,(S38-$N$4)) -> 1521 | U38: =Q38*R38 -> #N/A | V38: =IFERROR(VLOOKUP(A38,'Maturity Adjustment'!$A$86:$C$91,3,0),S38) -> 47579 | W38: =VLOOKUP(A38,'Account Mapping'!$A$2:$F$216,6,0) -> #N/A | X38: =IF(V38="Tomorrow",Q38,IF(AND(V38>$X$4-1,V38<$X$5),Q38,IF(V38=$X$5,Q38,0))) -> 0 | Y38: =IF(AND(V38>$Y$4-1,V38<$Y$5),Q38,IF(V38=$Y$5,Q38,0)) -> 0 | Z38: =IF(AND(V38>$Z$4-1,V38<$Z$5),Q38,IF(V38=$Z$5,Q38,0)) -> 0 | AA38: =IF(AND(V38>$AA$4-1,V38<$AA$5),Q38,IF(V38=$AA$5,Q38,0)) -> 0 | AB38: =IF(AND(V38>$AB$4-1,V38<$AB$5),Q38,IF(V38=$AB$5,Q38,0)) -> 0 | AC38: =IF(AND(V38>$AC$4-1,V38<$AC$5),Q38,IF(V38=$AC$5,Q38,0)) -> 0 | AD38: =IF(AND(V38>$AD$4-1,V38<$AD$5),Q38,IF(V38=$AD$5,Q38,0)) -> 0 | AE38: =IF(AND(V38>$AE$4-1,V38<$AE$5),Q38,IF(V38=$AE$5,Q38,0)) -> 2288999.3 | AF38: =IF(AND(V38>$AF$4-1,V38<$AF$5),Q38,IF(V38=$AF$5,Q38,0)) -> 0 | AG38: =IF(AND(V38>$AG$4-1,V38<$AG$5),Q38,IF(V38=$AG$5,Q38,0)) -> 0 | AH38: =Q38=SUM(X38:AG38) -> TRUE | AK38: Liability | AL38: =SUMIFS($H$7:$H$874,$W$7:$W$874,AK38,$V$7:$V$874,">"&AL33,$V$7:$V$874,"<="&AL34)+SUMIFS($H$7:$H$874,$W$7:$W$874,AK38,$V$7:$V$874,"Tomorrow") -> 0 | AM38: =SUMIFS($H$7:$H$874,$W$7:$W$874,AK38,$V$7:$V$874,">"&AM33,$V$7:$V$874,"<="&AM34)+SUMIFS($H$7:$H$874,$W$7:$W$874,AK38,$V$7:$V$874,"Tomorrow") -> 0 | AN38: =SUMIFS($H$7:$H$874,$W$7:$W$874,AK38,$V$7:$V$874,">"&AN33,$V$7:$V$874,"<="&AN34)+SUMIFS($H$7:$H$874,$W$7:$W$874,AK38,$V$7:$V$874,"Tomorrow") -> 0 | AO38: =SUMIFS($H$7:$H$874,$W$7:$W$874,AK38,$V$7:$V$874,">"&AO33,$V$7:$V$874,"<="&AO34)+SUMIFS($H$7:$H$874,$W$7:$W$874,AK38,$V$7:$V$874,"Tomorrow") -> 0 | AP38: =SUMIFS($H$7:$H$874,$W$7:$W$874,AK38,$V$7:$V$874,">"&AP33,$V$7:$V$874,"<="&AP34)+SUMIFS($H$7:$H$874,$W$7:$W$874,AK38,$V$7:$V$874,"Tomorrow") -> 0 | AQ38: =SUMIFS($H$7:$H$874,$W$7:$W$874,AK38,$V$7:$V$874,">"&AQ33,$V$7:$V$874,"<="&AQ34)+SUMIFS($H$7:$H$874,$W$7:$W$874,AK38,$V$7:$V$874,"Tomorrow") -> 0 | AR38: =SUMIFS($H$7:$H$874,$W$7:$W$874,AK38,$V$7:$V$874,">"&AR33,$V$7:$V$874,"<="&AR34)+SUMIFS($H$7:$H$874,$W$7:$W$874,AK38,$V$7:$V$874,"Tomorrow") -> 0 | AS38: =SUMIFS($H$7:$H$874,$W$7:$W$874,AK38,$V$7:$V$874,">"&AS33,$V$7:$V$874,"<="&AS34)+SUMIFS($H$7:$H$874,$W$7:$W$874,AK38,$V$7:$V$874,"Tomorrow") -> 0
A39: 10630001 | B39: Syndicated Loans (Long Term) - Domestic | C39: 6115904000096 | D39: 100000014 | E39: PERDAMAN CHEMICALS & FERTILISERS (FINANCE)PTY LTD | F39: USD | G39: 103568.68 | H39: 147449.72 | I39: 45197 | J39: 47579 | K39: 46058 | L39: =VLOOKUP(A39,'Account Mapping'!$A$2:$E$216,3,0) -> #N/A | M39: =VLOOKUP(A39,'Account Mapping'!$A$2:$E$216,4,0) -> #N/A | N39: =IF(OR(C39='Account Mapping'!$H$4,C39='Account Mapping'!$H$5,C39='Account Mapping'!$H$6),'Account Mapping'!$I$4,VLOOKUP(A39,'Account Mapping'!$A$2:$E$216,5,0)) -> #N/A | O39: =IF(OR(L39="Loan",L39="Deposit_Liability",L39="OFF_Unused Loan Commitment",L39="HQLA"),VLOOKUP(D39,'Customer Type'!$A$3:$C$38,3,0),"") -> #N/A | P39: =M39&"_"&O39 -> #N/A | Q39: =IF(COUNTIF('Account Mapping'!$H$12:$H$45,A39)>0,-H39,H39) -> 147449.72 | R39: =VLOOKUP(P39,Assumptions!$C$2:$D$64,2,0) -> #N/A | S39: =IFERROR(VLOOKUP(A39,'Maturity Adjustment'!$A$3:$C$81,3,0),(IF(J39<$N$4,"Tomorrow",J39))) -> 47579 | T39: =IF(S39="Tomorrow",1,(S39-$N$4)) -> 1521 | U39: =Q39*R39 -> #N/A | V39: =IFERROR(VLOOKUP(A39,'Maturity Adjustment'!$A$86:$C$91,3,0),S39) -> 47579 | W39: =VLOOKUP(A39,'Account Mapping'!$A$2:$F$216,6,0) -> #N/A | X39: =IF(V39="Tomorrow",Q39,IF(AND(V39>$X$4-1,V39<$X$5),Q39,IF(V39=$X$5,Q39,0))) -> 0 | Y39: =IF(AND(V39>$Y$4-1,V39<$Y$5),Q39,IF(V39=$Y$5,Q39,0)) -> 0 | Z39: =IF(AND(V39>$Z$4-1,V39<$Z$5),Q39,IF(V39=$Z$5,Q39,0)) -> 0 | AA39: =IF(AND(V39>$AA$4-1,V39<$AA$5),Q39,IF(V39=$AA$5,Q39,0)) -> 0 | AB39: =IF(AND(V39>$AB$4-1,V39<$AB$5),Q39,IF(V39=$AB$5,Q39,0)) -> 0 | AC39: =IF(AND(V39>$AC$4-1,V39<$AC$5),Q39,IF(V39=$AC$5,Q39,0)) -> 0 | AD39: =IF(AND(V39>$AD$4-1,V39<$AD$5),Q39,IF(V39=$AD$5,Q39,0)) -> 0 | AE39: =IF(AND(V39>$AE$4-1,V39<$AE$5),Q39,IF(V39=$AE$5,Q39,0)) -> 147449.72 | AF39: =IF(AND(V39>$AF$4-1,V39<$AF$5),Q39,IF(V39=$AF$5,Q39,0)) -> 0 | AG39: =IF(AND(V39>$AG$4-1,V39<$AG$5),Q39,IF(V39=$AG$5,Q39,0)) -> 0 | AH39: =Q39=SUM(X39:AG39) -> TRUE | AK39: Gap | AL39: =AL37-AL38 -> 0 | AM39: =AM37-AM38 -> 0 | AN39: =AN37-AN38 -> 0 | AO39: =AO37-AO38 -> 0 | AP39: =AP37-AP38 -> 0 | AQ39: =AQ37-AQ38 -> 0 | AR39: =AR37-AR38 -> 0 | AS39: =AS37-AS38 -> 0
A40: 10630001 | B40: Syndicated Loans (Long Term) - Domestic | C40: 6115904000107 | D40: 100000014 | E40: PERDAMAN CHEMICALS & FERTILISERS (FINANCE)PTY LTD | F40: USD | G40: 120567.47 | H40: 171650.73 | I40: 45226 | J40: 47579 | K40: 46058 | L40: =VLOOKUP(A40,'Account Mapping'!$A$2:$E$216,3,0) -> #N/A | M40: =VLOOKUP(A40,'Account Mapping'!$A$2:$E$216,4,0) -> #N/A | N40: =IF(OR(C40='Account Mapping'!$H$4,C40='Account Mapping'!$H$5,C40='Account Mapping'!$H$6),'Account Mapping'!$I$4,VLOOKUP(A40,'Account Mapping'!$A$2:$E$216,5,0)) -> #N/A | O40: =IF(OR(L40="Loan",L40="Deposit_Liability",L40="OFF_Unused Loan Commitment",L40="HQLA"),VLOOKUP(D40,'Customer Type'!$A$3:$C$38,3,0),"") -> #N/A | P40: =M40&"_"&O40 -> #N/A | Q40: =IF(COUNTIF('Account Mapping'!$H$12:$H$45,A40)>0,-H40,H40) -> 171650.73 | R40: =VLOOKUP(P40,Assumptions!$C$2:$D$64,2,0) -> #N/A | S40: =IFERROR(VLOOKUP(A40,'Maturity Adjustment'!$A$3:$C$81,3,0),(IF(J40<$N$4,"Tomorrow",J40))) -> 47579 | T40: =IF(S40="Tomorrow",1,(S40-$N$4)) -> 1521 | U40: =Q40*R40 -> #N/A | V40: =IFERROR(VLOOKUP(A40,'Maturity Adjustment'!$A$86:$C$91,3,0),S40) -> 47579 | W40: =VLOOKUP(A40,'Account Mapping'!$A$2:$F$216,6,0) -> #N/A | X40: =IF(V40="Tomorrow",Q40,IF(AND(V40>$X$4-1,V40<$X$5),Q40,IF(V40=$X$5,Q40,0))) -> 0 | Y40: =IF(AND(V40>$Y$4-1,V40<$Y$5),Q40,IF(V40=$Y$5,Q40,0)) -> 0 | Z40: =IF(AND(V40>$Z$4-1,V40<$Z$5),Q40,IF(V40=$Z$5,Q40,0)) -> 0 | AA40: =IF(AND(V40>$AA$4-1,V40<$AA$5),Q40,IF(V40=$AA$5,Q40,0)) -> 0 | AB40: =IF(AND(V40>$AB$4-1,V40<$AB$5),Q40,IF(V40=$AB$5,Q40,0)) -> 0 | AC40: =IF(AND(V40>$AC$4-1,V40<$AC$5),Q40,IF(V40=$AC$5,Q40,0)) -> 0 | AD40: =IF(AND(V40>$AD$4-1,V40<$AD$5),Q40,IF(V40=$AD$5,Q40,0)) -> 0 | AE40: =IF(AND(V40>$AE$4-1,V40<$AE$5),Q40,IF(V40=$AE$5,Q40,0)) -> 171650.73 | AF40: =IF(AND(V40>$AF$4-1,V40<$AF$5),Q40,IF(V40=$AF$5,Q40,0)) -> 0 | AG40: =IF(AND(V40>$AG$4-1,V40<$AG$5),Q40,IF(V40=$AG$5,Q40,0)) -> 0 | AH40: =Q40=SUM(X40:AG40) -> TRUE | AK40: Total Asset | AL40: =AL16 -> 0 | AM40: =AL40 -> 0 | AN40: =AM40 -> 0 | AO40: =AN40 -> 0 | AP40: =AO40 -> 0 | AQ40: =AP40 -> 0 | AR40: =AQ40 -> 0 | AS40: =AR40 -> 0
A41: 10630001 | B41: Syndicated Loans (Long Term) - Domestic | C41: 6115904000114 | D41: 100000014 | E41: PERDAMAN CHEMICALS & FERTILISERS (FINANCE)PTY LTD | F41: USD | G41: 1107550.1 | H41: 1576808.3 | I41: 45230 | J41: 47579 | K41: 46058 | L41: =VLOOKUP(A41,'Account Mapping'!$A$2:$E$216,3,0) -> #N/A | M41: =VLOOKUP(A41,'Account Mapping'!$A$2:$E$216,4,0) -> #N/A | N41: =IF(OR(C41='Account Mapping'!$H$4,C41='Account Mapping'!$H$5,C41='Account Mapping'!$H$6),'Account Mapping'!$I$4,VLOOKUP(A41,'Account Mapping'!$A$2:$E$216,5,0)) -> #N/A | O41: =IF(OR(L41="Loan",L41="Deposit_Liability",L41="OFF_Unused Loan Commitment",L41="HQLA"),VLOOKUP(D41,'Customer Type'!$A$3:$C$38,3,0),"") -> #N/A | P41: =M41&"_"&O41 -> #N/A | Q41: =IF(COUNTIF('Account Mapping'!$H$12:$H$45,A41)>0,-H41,H41) -> 1576808.3 | R41: =VLOOKUP(P41,Assumptions!$C$2:$D$64,2,0) -> #N/A | S41: =IFERROR(VLOOKUP(A41,'Maturity Adjustment'!$A$3:$C$81,3,0),(IF(J41<$N$4,"Tomorrow",J41))) -> 47579 | T41: =IF(S41="Tomorrow",1,(S41-$N$4)) -> 1521 | U41: =Q41*R41 -> #N/A | V41: =IFERROR(VLOOKUP(A41,'Maturity Adjustment'!$A$86:$C$91,3,0),S41) -> 47579 | W41: =VLOOKUP(A41,'Account Mapping'!$A$2:$F$216,6,0) -> #N/A | X41: =IF(V41="Tomorrow",Q41,IF(AND(V41>$X$4-1,V41<$X$5),Q41,IF(V41=$X$5,Q41,0))) -> 0 | Y41: =IF(AND(V41>$Y$4-1,V41<$Y$5),Q41,IF(V41=$Y$5,Q41,0)) -> 0 | Z41: =IF(AND(V41>$Z$4-1,V41<$Z$5),Q41,IF(V41=$Z$5,Q41,0)) -> 0 | AA41: =IF(AND(V41>$AA$4-1,V41<$AA$5),Q41,IF(V41=$AA$5,Q41,0)) -> 0 | AB41: =IF(AND(V41>$AB$4-1,V41<$AB$5),Q41,IF(V41=$AB$5,Q41,0)) -> 0 | AC41: =IF(AND(V41>$AC$4-1,V41<$AC$5),Q41,IF(V41=$AC$5,Q41,0)) -> 0 | AD41: =IF(AND(V41>$AD$4-1,V41<$AD$5),Q41,IF(V41=$AD$5,Q41,0)) -> 0 | AE41: =IF(AND(V41>$AE$4-1,V41<$AE$5),Q41,IF(V41=$AE$5,Q41,0)) -> 1576808.3 | AF41: =IF(AND(V41>$AF$4-1,V41<$AF$5),Q41,IF(V41=$AF$5,Q41,0)) -> 0 | AG41: =IF(AND(V41>$AG$4-1,V41<$AG$5),Q41,IF(V41=$AG$5,Q41,0)) -> 0 | AH41: =Q41=SUM(X41:AG41) -> TRUE | AK41: Gap ratio | AL41: =AL39/AL40 -> #DIV/0! | AM41: =AM39/AM40 -> #DIV/0! | AN41: =AN39/AN40 -> #DIV/0! | AO41: =AO39/AO40 -> #DIV/0! | AP41: =AP39/AP40 -> #DIV/0! | AQ41: =AQ39/AQ40 -> #DIV/0! | AR41: =AR39/AR40 -> #DIV/0! | AS41: =AS39/AS40 -> #DIV/0!
A42: 10630001 | B42: Syndicated Loans (Long Term) - Domestic | C42: 6115904000146 | D42: 100000014 | E42: PERDAMAN CHEMICALS & FERTILISERS (FINANCE)PTY LTD | F42: USD | G42: 132635.54 | H42: 188831.92 | I42: 45257 | J42: 47579 | K42: 46058 | L42: =VLOOKUP(A42,'Account Mapping'!$A$2:$E$216,3,0) -> #N/A | M42: =VLOOKUP(A42,'Account Mapping'!$A$2:$E$216,4,0) -> #N/A | N42: =IF(OR(C42='Account Mapping'!$H$4,C42='Account Mapping'!$H$5,C42='Account Mapping'!$H$6),'Account Mapping'!$I$4,VLOOKUP(A42,'Account Mapping'!$A$2:$E$216,5,0)) -> #N/A | O42: =IF(OR(L42="Loan",L42="Deposit_Liability",L42="OFF_Unused Loan Commitment",L42="HQLA"),VLOOKUP(D42,'Customer Type'!$A$3:$C$38,3,0),"") -> #N/A | P42: =M42&"_"&O42 -> #N/A | Q42: =IF(COUNTIF('Account Mapping'!$H$12:$H$45,A42)>0,-H42,H42) -> 188831.92 | R42: =VLOOKUP(P42,Assumptions!$C$2:$D$64,2,0) -> #N/A | S42: =IFERROR(VLOOKUP(A42,'Maturity Adjustment'!$A$3:$C$81,3,0),(IF(J42<$N$4,"Tomorrow",J42))) -> 47579 | T42: =IF(S42="Tomorrow",1,(S42-$N$4)) -> 1521 | U42: =Q42*R42 -> #N/A | V42: =IFERROR(VLOOKUP(A42,'Maturity Adjustment'!$A$86:$C$91,3,0),S42) -> 47579 | W42: =VLOOKUP(A42,'Account Mapping'!$A$2:$F$216,6,0) -> #N/A | X42: =IF(V42="Tomorrow",Q42,IF(AND(V42>$X$4-1,V42<$X$5),Q42,IF(V42=$X$5,Q42,0))) -> 0 | Y42: =IF(AND(V42>$Y$4-1,V42<$Y$5),Q42,IF(V42=$Y$5,Q42,0)) -> 0 | Z42: =IF(AND(V42>$Z$4-1,V42<$Z$5),Q42,IF(V42=$Z$5,Q42,0)) -> 0 | AA42: =IF(AND(V42>$AA$4-1,V42<$AA$5),Q42,IF(V42=$AA$5,Q42,0)) -> 0 | AB42: =IF(AND(V42>$AB$4-1,V42<$AB$5),Q42,IF(V42=$AB$5,Q42,0)) -> 0 | AC42: =IF(AND(V42>$AC$4-1,V42<$AC$5),Q42,IF(V42=$AC$5,Q42,0)) -> 0 | AD42: =IF(AND(V42>$AD$4-1,V42<$AD$5),Q42,IF(V42=$AD$5,Q42,0)) -> 0 | AE42: =IF(AND(V42>$AE$4-1,V42<$AE$5),Q42,IF(V42=$AE$5,Q42,0)) -> 188831.92 | AF42: =IF(AND(V42>$AF$4-1,V42<$AF$5),Q42,IF(V42=$AF$5,Q42,0)) -> 0 | AG42: =IF(AND(V42>$AG$4-1,V42<$AG$5),Q42,IF(V42=$AG$5,Q42,0)) -> 0 | AH42: =Q42=SUM(X42:AG42) -> TRUE | AK42: Trigger | AL42: -0.4 | AM42: =AL42 -> -0.4 | AN42: =AM42 -> -0.4 | AO42: =AN42 -> -0.4 | AP42: =AO42 -> -0.4 | AQ42: =AP42 -> -0.4 | AR42: =AQ42 -> -0.4 | AS42: =AR42 -> -0.4
A43: 10630001 | B43: Syndicated Loans (Long Term) - Domestic | C43: 6115904000153 | D43: 100000014 | E43: PERDAMAN CHEMICALS & FERTILISERS (FINANCE)PTY LTD | F43: USD | G43: 233477.42 | H43: 332399.52 | I43: 45260 | J43: 47579 | K43: 46058 | L43: =VLOOKUP(A43,'Account Mapping'!$A$2:$E$216,3,0) -> #N/A | M43: =VLOOKUP(A43,'Account Mapping'!$A$2:$E$216,4,0) -> #N/A | N43: =IF(OR(C43='Account Mapping'!$H$4,C43='Account Mapping'!$H$5,C43='Account Mapping'!$H$6),'Account Mapping'!$I$4,VLOOKUP(A43,'Account Mapping'!$A$2:$E$216,5,0)) -> #N/A | O43: =IF(OR(L43="Loan",L43="Deposit_Liability",L43="OFF_Unused Loan Commitment",L43="HQLA"),VLOOKUP(D43,'Customer Type'!$A$3:$C$38,3,0),"") -> #N/A | P43: =M43&"_"&O43 -> #N/A | Q43: =IF(COUNTIF('Account Mapping'!$H$12:$H$45,A43)>0,-H43,H43) -> 332399.52 | R43: =VLOOKUP(P43,Assumptions!$C$2:$D$64,2,0) -> #N/A | S43: =IFERROR(VLOOKUP(A43,'Maturity Adjustment'!$A$3:$C$81,3,0),(IF(J43<$N$4,"Tomorrow",J43))) -> 47579 | T43: =IF(S43="Tomorrow",1,(S43-$N$4)) -> 1521 | U43: =Q43*R43 -> #N/A | V43: =IFERROR(VLOOKUP(A43,'Maturity Adjustment'!$A$86:$C$91,3,0),S43) -> 47579 | W43: =VLOOKUP(A43,'Account Mapping'!$A$2:$F$216,6,0) -> #N/A | X43: =IF(V43="Tomorrow",Q43,IF(AND(V43>$X$4-1,V43<$X$5),Q43,IF(V43=$X$5,Q43,0))) -> 0 | Y43: =IF(AND(V43>$Y$4-1,V43<$Y$5),Q43,IF(V43=$Y$5,Q43,0)) -> 0 | Z43: =IF(AND(V43>$Z$4-1,V43<$Z$5),Q43,IF(V43=$Z$5,Q43,0)) -> 0 | AA43: =IF(AND(V43>$AA$4-1,V43<$AA$5),Q43,IF(V43=$AA$5,Q43,0)) -> 0 | AB43: =IF(AND(V43>$AB$4-1,V43<$AB$5),Q43,IF(V43=$AB$5,Q43,0)) -> 0 | AC43: =IF(AND(V43>$AC$4-1,V43<$AC$5),Q43,IF(V43=$AC$5,Q43,0)) -> 0 | AD43: =IF(AND(V43>$AD$4-1,V43<$AD$5),Q43,IF(V43=$AD$5,Q43,0)) -> 0 | AE43: =IF(AND(V43>$AE$4-1,V43<$AE$5),Q43,IF(V43=$AE$5,Q43,0)) -> 332399.52 | AF43: =IF(AND(V43>$AF$4-1,V43<$AF$5),Q43,IF(V43=$AF$5,Q43,0)) -> 0 | AG43: =IF(AND(V43>$AG$4-1,V43<$AG$5),Q43,IF(V43=$AG$5,Q43,0)) -> 0 | AH43: =Q43=SUM(X43:AG43) -> TRUE | AK43: (-)Shortfall | AL43: =-AL40*(AL42-AL41) -> #DIV/0! | AM43: =-AM40*(AM42-AM41) -> #DIV/0! | AN43: =-AN40*(AN42-AN41) -> #DIV/0! | AO43: =-AO40*(AO42-AO41) -> #DIV/0! | AP43: =-AP40*(AP42-AP41) -> #DIV/0! | AQ43: =-AQ40*(AQ42-AQ41) -> #DIV/0! | AR43: =-AR40*(AR42-AR41) -> #DIV/0! | AS43: =-AS40*(AS42-AS41) -> #DIV/0!
A44: 10630001 | B44: Syndicated Loans (Long Term) - Domestic | C44: 6115904000160 | D44: 100000014 | E44: PERDAMAN CHEMICALS & FERTILISERS (FINANCE)PTY LTD | F44: USD | G44: 131409.16 | H44: 187085.93 | I44: 45287 | J44: 47579 | K44: 46058 | L44: =VLOOKUP(A44,'Account Mapping'!$A$2:$E$216,3,0) -> #N/A | M44: =VLOOKUP(A44,'Account Mapping'!$A$2:$E$216,4,0) -> #N/A | N44: =IF(OR(C44='Account Mapping'!$H$4,C44='Account Mapping'!$H$5,C44='Account Mapping'!$H$6),'Account Mapping'!$I$4,VLOOKUP(A44,'Account Mapping'!$A$2:$E$216,5,0)) -> #N/A | O44: =IF(OR(L44="Loan",L44="Deposit_Liability",L44="OFF_Unused Loan Commitment",L44="HQLA"),VLOOKUP(D44,'Customer Type'!$A$3:$C$38,3,0),"") -> #N/A | P44: =M44&"_"&O44 -> #N/A | Q44: =IF(COUNTIF('Account Mapping'!$H$12:$H$45,A44)>0,-H44,H44) -> 187085.93 | R44: =VLOOKUP(P44,Assumptions!$C$2:$D$64,2,0) -> #N/A | S44: =IFERROR(VLOOKUP(A44,'Maturity Adjustment'!$A$3:$C$81,3,0),(IF(J44<$N$4,"Tomorrow",J44))) -> 47579 | T44: =IF(S44="Tomorrow",1,(S44-$N$4)) -> 1521 | U44: =Q44*R44 -> #N/A | V44: =IFERROR(VLOOKUP(A44,'Maturity Adjustment'!$A$86:$C$91,3,0),S44) -> 47579 | W44: =VLOOKUP(A44,'Account Mapping'!$A$2:$F$216,6,0) -> #N/A | X44: =IF(V44="Tomorrow",Q44,IF(AND(V44>$X$4-1,V44<$X$5),Q44,IF(V44=$X$5,Q44,0))) -> 0 | Y44: =IF(AND(V44>$Y$4-1,V44<$Y$5),Q44,IF(V44=$Y$5,Q44,0)) -> 0 | Z44: =IF(AND(V44>$Z$4-1,V44<$Z$5),Q44,IF(V44=$Z$5,Q44,0)) -> 0 | AA44: =IF(AND(V44>$AA$4-1,V44<$AA$5),Q44,IF(V44=$AA$5,Q44,0)) -> 0 | AB44: =IF(AND(V44>$AB$4-1,V44<$AB$5),Q44,IF(V44=$AB$5,Q44,0)) -> 0 | AC44: =IF(AND(V44>$AC$4-1,V44<$AC$5),Q44,IF(V44=$AC$5,Q44,0)) -> 0 | AD44: =IF(AND(V44>$AD$4-1,V44<$AD$5),Q44,IF(V44=$AD$5,Q44,0)) -> 0 | AE44: =IF(AND(V44>$AE$4-1,V44<$AE$5),Q44,IF(V44=$AE$5,Q44,0)) -> 187085.93 | AF44: =IF(AND(V44>$AF$4-1,V44<$AF$5),Q44,IF(V44=$AF$5,Q44,0)) -> 0 | AG44: =IF(AND(V44>$AG$4-1,V44<$AG$5),Q44,IF(V44=$AG$5,Q44,0)) -> 0 | AH44: =Q44=SUM(X44:AG44) -> TRUE
A45: 10630001 | B45: Syndicated Loans (Long Term) - Domestic | C45: 6115904000178 | D45: 100000014 | E45: PERDAMAN CHEMICALS & FERTILISERS (FINANCE)PTY LTD | F45: USD | G45: 967741.94 | H45: 1377764.7 | I45: 45289 | J45: 47579 | K45: 46058 | L45: =VLOOKUP(A45,'Account Mapping'!$A$2:$E$216,3,0) -> #N/A | M45: =VLOOKUP(A45,'Account Mapping'!$A$2:$E$216,4,0) -> #N/A | N45: =IF(OR(C45='Account Mapping'!$H$4,C45='Account Mapping'!$H$5,C45='Account Mapping'!$H$6),'Account Mapping'!$I$4,VLOOKUP(A45,'Account Mapping'!$A$2:$E$216,5,0)) -> #N/A | O45: =IF(OR(L45="Loan",L45="Deposit_Liability",L45="OFF_Unused Loan Commitment",L45="HQLA"),VLOOKUP(D45,'Customer Type'!$A$3:$C$38,3,0),"") -> #N/A | P45: =M45&"_"&O45 -> #N/A | Q45: =IF(COUNTIF('Account Mapping'!$H$12:$H$45,A45)>0,-H45,H45) -> 1377764.7 | R45: =VLOOKUP(P45,Assumptions!$C$2:$D$64,2,0) -> #N/A | S45: =IFERROR(VLOOKUP(A45,'Maturity Adjustment'!$A$3:$C$81,3,0),(IF(J45<$N$4,"Tomorrow",J45))) -> 47579 | T45: =IF(S45="Tomorrow",1,(S45-$N$4)) -> 1521 | U45: =Q45*R45 -> #N/A | V45: =IFERROR(VLOOKUP(A45,'Maturity Adjustment'!$A$86:$C$91,3,0),S45) -> 47579 | W45: =VLOOKUP(A45,'Account Mapping'!$A$2:$F$216,6,0) -> #N/A | X45: =IF(V45="Tomorrow",Q45,IF(AND(V45>$X$4-1,V45<$X$5),Q45,IF(V45=$X$5,Q45,0))) -> 0 | Y45: =IF(AND(V45>$Y$4-1,V45<$Y$5),Q45,IF(V45=$Y$5,Q45,0)) -> 0 | Z45: =IF(AND(V45>$Z$4-1,V45<$Z$5),Q45,IF(V45=$Z$5,Q45,0)) -> 0 | AA45: =IF(AND(V45>$AA$4-1,V45<$AA$5),Q45,IF(V45=$AA$5,Q45,0)) -> 0 | AB45: =IF(AND(V45>$AB$4-1,V45<$AB$5),Q45,IF(V45=$AB$5,Q45,0)) -> 0 | AC45: =IF(AND(V45>$AC$4-1,V45<$AC$5),Q45,IF(V45=$AC$5,Q45,0)) -> 0 | AD45: =IF(AND(V45>$AD$4-1,V45<$AD$5),Q45,IF(V45=$AD$5,Q45,0)) -> 0 | AE45: =IF(AND(V45>$AE$4-1,V45<$AE$5),Q45,IF(V45=$AE$5,Q45,0)) -> 1377764.7 | AF45: =IF(AND(V45>$AF$4-1,V45<$AF$5),Q45,IF(V45=$AF$5,Q45,0)) -> 0 | AG45: =IF(AND(V45>$AG$4-1,V45<$AG$5),Q45,IF(V45=$AG$5,Q45,0)) -> 0 | AH45: =Q45=SUM(X45:AG45) -> TRUE
A46: 10630001 | B46: Syndicated Loans (Long Term) - Domestic | C46: 6115904000185 | D46: 100000014 | E46: PERDAMAN CHEMICALS & FERTILISERS (FINANCE)PTY LTD | F46: USD | G46: 133263.53 | H46: 189725.98 | I46: 45316 | J46: 47579 | K46: 46058 | L46: =VLOOKUP(A46,'Account Mapping'!$A$2:$E$216,3,0) -> #N/A | M46: =VLOOKUP(A46,'Account Mapping'!$A$2:$E$216,4,0) -> #N/A | N46: =IF(OR(C46='Account Mapping'!$H$4,C46='Account Mapping'!$H$5,C46='Account Mapping'!$H$6),'Account Mapping'!$I$4,VLOOKUP(A46,'Account Mapping'!$A$2:$E$216,5,0)) -> #N/A | O46: =IF(OR(L46="Loan",L46="Deposit_Liability",L46="OFF_Unused Loan Commitment",L46="HQLA"),VLOOKUP(D46,'Customer Type'!$A$3:$C$38,3,0),"") -> #N/A | P46: =M46&"_"&O46 -> #N/A | Q46: =IF(COUNTIF('Account Mapping'!$H$12:$H$45,A46)>0,-H46,H46) -> 189725.98 | R46: =VLOOKUP(P46,Assumptions!$C$2:$D$64,2,0) -> #N/A | S46: =IFERROR(VLOOKUP(A46,'Maturity Adjustment'!$A$3:$C$81,3,0),(IF(J46<$N$4,"Tomorrow",J46))) -> 47579 | T46: =IF(S46="Tomorrow",1,(S46-$N$4)) -> 1521 | U46: =Q46*R46 -> #N/A | V46: =IFERROR(VLOOKUP(A46,'Maturity Adjustment'!$A$86:$C$91,3,0),S46) -> 47579 | W46: =VLOOKUP(A46,'Account Mapping'!$A$2:$F$216,6,0) -> #N/A | X46: =IF(V46="Tomorrow",Q46,IF(AND(V46>$X$4-1,V46<$X$5),Q46,IF(V46=$X$5,Q46,0))) -> 0 | Y46: =IF(AND(V46>$Y$4-1,V46<$Y$5),Q46,IF(V46=$Y$5,Q46,0)) -> 0 | Z46: =IF(AND(V46>$Z$4-1,V46<$Z$5),Q46,IF(V46=$Z$5,Q46,0)) -> 0 | AA46: =IF(AND(V46>$AA$4-1,V46<$AA$5),Q46,IF(V46=$AA$5,Q46,0)) -> 0 | AB46: =IF(AND(V46>$AB$4-1,V46<$AB$5),Q46,IF(V46=$AB$5,Q46,0)) -> 0 | AC46: =IF(AND(V46>$AC$4-1,V46<$AC$5),Q46,IF(V46=$AC$5,Q46,0)) -> 0 | AD46: =IF(AND(V46>$AD$4-1,V46<$AD$5),Q46,IF(V46=$AD$5,Q46,0)) -> 0 | AE46: =IF(AND(V46>$AE$4-1,V46<$AE$5),Q46,IF(V46=$AE$5,Q46,0)) -> 189725.98 | AF46: =IF(AND(V46>$AF$4-1,V46<$AF$5),Q46,IF(V46=$AF$5,Q46,0)) -> 0 | AG46: =IF(AND(V46>$AG$4-1,V46<$AG$5),Q46,IF(V46=$AG$5,Q46,0)) -> 0 | AH46: =Q46=SUM(X46:AG46) -> TRUE
A47: 10630001 | B47: Syndicated Loans (Long Term) - Domestic | C47: 6115904000192 | D47: 100000014 | E47: PERDAMAN CHEMICALS & FERTILISERS (FINANCE)PTY LTD | F47: USD | G47: 1666666.7 | H47: 2372817 | I47: 45321 | J47: 47579 | K47: 46058 | L47: =VLOOKUP(A47,'Account Mapping'!$A$2:$E$216,3,0) -> #N/A | M47: =VLOOKUP(A47,'Account Mapping'!$A$2:$E$216,4,0) -> #N/A | N47: =IF(OR(C47='Account Mapping'!$H$4,C47='Account Mapping'!$H$5,C47='Account Mapping'!$H$6),'Account Mapping'!$I$4,VLOOKUP(A47,'Account Mapping'!$A$2:$E$216,5,0)) -> #N/A | O47: =IF(OR(L47="Loan",L47="Deposit_Liability",L47="OFF_Unused Loan Commitment",L47="HQLA"),VLOOKUP(D47,'Customer Type'!$A$3:$C$38,3,0),"") -> #N/A | P47: =M47&"_"&O47 -> #N/A | Q47: =IF(COUNTIF('Account Mapping'!$H$12:$H$45,A47)>0,-H47,H47) -> 2372817 | R47: =VLOOKUP(P47,Assumptions!$C$2:$D$64,2,0) -> #N/A | S47: =IFERROR(VLOOKUP(A47,'Maturity Adjustment'!$A$3:$C$81,3,0),(IF(J47<$N$4,"Tomorrow",J47))) -> 47579 | T47: =IF(S47="Tomorrow",1,(S47-$N$4)) -> 1521 | U47: =Q47*R47 -> #N/A | V47: =IFERROR(VLOOKUP(A47,'Maturity Adjustment'!$A$86:$C$91,3,0),S47) -> 47579 | W47: =VLOOKUP(A47,'Account Mapping'!$A$2:$F$216,6,0) -> #N/A | X47: =IF(V47="Tomorrow",Q47,IF(AND(V47>$X$4-1,V47<$X$5),Q47,IF(V47=$X$5,Q47,0))) -> 0 | Y47: =IF(AND(V47>$Y$4-1,V47<$Y$5),Q47,IF(V47=$Y$5,Q47,0)) -> 0 | Z47: =IF(AND(V47>$Z$4-1,V47<$Z$5),Q47,IF(V47=$Z$5,Q47,0)) -> 0 | AA47: =IF(AND(V47>$AA$4-1,V47<$AA$5),Q47,IF(V47=$AA$5,Q47,0)) -> 0 | AB47: =IF(AND(V47>$AB$4-1,V47<$AB$5),Q47,IF(V47=$AB$5,Q47,0)) -> 0 | AC47: =IF(AND(V47>$AC$4-1,V47<$AC$5),Q47,IF(V47=$AC$5,Q47,0)) -> 0 | AD47: =IF(AND(V47>$AD$4-1,V47<$AD$5),Q47,IF(V47=$AD$5,Q47,0)) -> 0 | AE47: =IF(AND(V47>$AE$4-1,V47<$AE$5),Q47,IF(V47=$AE$5,Q47,0)) -> 2372817 | AF47: =IF(AND(V47>$AF$4-1,V47<$AF$5),Q47,IF(V47=$AF$5,Q47,0)) -> 0 | AG47: =IF(AND(V47>$AG$4-1,V47<$AG$5),Q47,IF(V47=$AG$5,Q47,0)) -> 0 | AH47: =Q47=SUM(X47:AG47) -> TRUE
A48: 10630001 | B48: Syndicated Loans (Long Term) - Domestic | C48: 6115904000210 | D48: 100000014 | E48: PERDAMAN CHEMICALS & FERTILISERS (FINANCE)PTY LTD | F48: USD | G48: 894131.86 | H48: 1272966.8 | I48: 45344 | J48: 47579 | K48: 46058 | L48: =VLOOKUP(A48,'Account Mapping'!$A$2:$E$216,3,0) -> #N/A | M48: =VLOOKUP(A48,'Account Mapping'!$A$2:$E$216,4,0) -> #N/A | N48: =IF(OR(C48='Account Mapping'!$H$4,C48='Account Mapping'!$H$5,C48='Account Mapping'!$H$6),'Account Mapping'!$I$4,VLOOKUP(A48,'Account Mapping'!$A$2:$E$216,5,0)) -> #N/A | O48: =IF(OR(L48="Loan",L48="Deposit_Liability",L48="OFF_Unused Loan Commitment",L48="HQLA"),VLOOKUP(D48,'Customer Type'!$A$3:$C$38,3,0),"") -> #N/A | P48: =M48&"_"&O48 -> #N/A | Q48: =IF(COUNTIF('Account Mapping'!$H$12:$H$45,A48)>0,-H48,H48) -> 1272966.8 | R48: =VLOOKUP(P48,Assumptions!$C$2:$D$64,2,0) -> #N/A | S48: =IFERROR(VLOOKUP(A48,'Maturity Adjustment'!$A$3:$C$81,3,0),(IF(J48<$N$4,"Tomorrow",J48))) -> 47579 | T48: =IF(S48="Tomorrow",1,(S48-$N$4)) -> 1521 | U48: =Q48*R48 -> #N/A | V48: =IFERROR(VLOOKUP(A48,'Maturity Adjustment'!$A$86:$C$91,3,0),S48) -> 47579 | W48: =VLOOKUP(A48,'Account Mapping'!$A$2:$F$216,6,0) -> #N/A | X48: =IF(V48="Tomorrow",Q48,IF(AND(V48>$X$4-1,V48<$X$5),Q48,IF(V48=$X$5,Q48,0))) -> 0 | Y48: =IF(AND(V48>$Y$4-1,V48<$Y$5),Q48,IF(V48=$Y$5,Q48,0)) -> 0 | Z48: =IF(AND(V48>$Z$4-1,V48<$Z$5),Q48,IF(V48=$Z$5,Q48,0)) -> 0 | AA48: =IF(AND(V48>$AA$4-1,V48<$AA$5),Q48,IF(V48=$AA$5,Q48,0)) -> 0 | AB48: =IF(AND(V48>$AB$4-1,V48<$AB$5),Q48,IF(V48=$AB$5,Q48,0)) -> 0 | AC48: =IF(AND(V48>$AC$4-1,V48<$AC$5),Q48,IF(V48=$AC$5,Q48,0)) -> 0 | AD48: =IF(AND(V48>$AD$4-1,V48<$AD$5),Q48,IF(V48=$AD$5,Q48,0)) -> 0 | AE48: =IF(AND(V48>$AE$4-1,V48<$AE$5),Q48,IF(V48=$AE$5,Q48,0)) -> 1272966.8 | AF48: =IF(AND(V48>$AF$4-1,V48<$AF$5),Q48,IF(V48=$AF$5,Q48,0)) -> 0 | AG48: =IF(AND(V48>$AG$4-1,V48<$AG$5),Q48,IF(V48=$AG$5,Q48,0)) -> 0 | AH48: =Q48=SUM(X48:AG48) -> TRUE | AJ48: KRI | AK48: Risk Dimension | AL48: Qualitative Measure | AM48: Trigger | AN48: Limit | AO48: Monitoring Frequency | AQ48: Trigger Liability | AR48: Limit Liability
A49: 10630001 | B49: Syndicated Loans (Long Term) - Domestic | C49: 6115904000228 | D49: 100000014 | E49: PERDAMAN CHEMICALS & FERTILISERS (FINANCE)PTY LTD | F49: USD | G49: 142201.58 | H49: 202451 | I49: 45345 | J49: 47579 | K49: 46058 | L49: =VLOOKUP(A49,'Account Mapping'!$A$2:$E$216,3,0) -> #N/A | M49: =VLOOKUP(A49,'Account Mapping'!$A$2:$E$216,4,0) -> #N/A | N49: =IF(OR(C49='Account Mapping'!$H$4,C49='Account Mapping'!$H$5,C49='Account Mapping'!$H$6),'Account Mapping'!$I$4,VLOOKUP(A49,'Account Mapping'!$A$2:$E$216,5,0)) -> #N/A | O49: =IF(OR(L49="Loan",L49="Deposit_Liability",L49="OFF_Unused Loan Commitment",L49="HQLA"),VLOOKUP(D49,'Customer Type'!$A$3:$C$38,3,0),"") -> #N/A | P49: =M49&"_"&O49 -> #N/A | Q49: =IF(COUNTIF('Account Mapping'!$H$12:$H$45,A49)>0,-H49,H49) -> 202451 | R49: =VLOOKUP(P49,Assumptions!$C$2:$D$64,2,0) -> #N/A | S49: =IFERROR(VLOOKUP(A49,'Maturity Adjustment'!$A$3:$C$81,3,0),(IF(J49<$N$4,"Tomorrow",J49))) -> 47579 | T49: =IF(S49="Tomorrow",1,(S49-$N$4)) -> 1521 | U49: =Q49*R49 -> #N/A | V49: =IFERROR(VLOOKUP(A49,'Maturity Adjustment'!$A$86:$C$91,3,0),S49) -> 47579 | W49: =VLOOKUP(A49,'Account Mapping'!$A$2:$F$216,6,0) -> #N/A | X49: =IF(V49="Tomorrow",Q49,IF(AND(V49>$X$4-1,V49<$X$5),Q49,IF(V49=$X$5,Q49,0))) -> 0 | Y49: =IF(AND(V49>$Y$4-1,V49<$Y$5),Q49,IF(V49=$Y$5,Q49,0)) -> 0 | Z49: =IF(AND(V49>$Z$4-1,V49<$Z$5),Q49,IF(V49=$Z$5,Q49,0)) -> 0 | AA49: =IF(AND(V49>$AA$4-1,V49<$AA$5),Q49,IF(V49=$AA$5,Q49,0)) -> 0 | AB49: =IF(AND(V49>$AB$4-1,V49<$AB$5),Q49,IF(V49=$AB$5,Q49,0)) -> 0 | AC49: =IF(AND(V49>$AC$4-1,V49<$AC$5),Q49,IF(V49=$AC$5,Q49,0)) -> 0 | AD49: =IF(AND(V49>$AD$4-1,V49<$AD$5),Q49,IF(V49=$AD$5,Q49,0)) -> 0 | AE49: =IF(AND(V49>$AE$4-1,V49<$AE$5),Q49,IF(V49=$AE$5,Q49,0)) -> 202451 | AF49: =IF(AND(V49>$AF$4-1,V49<$AF$5),Q49,IF(V49=$AF$5,Q49,0)) -> 0 | AG49: =IF(AND(V49>$AG$4-1,V49<$AG$5),Q49,IF(V49=$AG$5,Q49,0)) -> 0 | AH49: =Q49=SUM(X49:AG49) -> TRUE | AJ49: Liquidity Gap Ratio | AK49: Assets minus liabilities maturing in a time frame divided by the total assets where the marketable securities are considered maturing within 7 days. | AL49: 7 day | AM49: 0 | AN49: -0.05 | AO49: Monthly | AQ49: =-(AM49*AN53-AN54) -> 0 | AR49: =-(AN49*AN53-AN54) -> 0
A50: 10630001 | B50: Syndicated Loans (Long Term) - Domestic | C50: 6115904000235 | D50: 100000014 | E50: PERDAMAN CHEMICALS & FERTILISERS (FINANCE)PTY LTD | F50: USD | G50: 144932.94 | H50: 206339.61 | I50: 45373 | J50: 47579 | K50: 46058 | L50: =VLOOKUP(A50,'Account Mapping'!$A$2:$E$216,3,0) -> #N/A | M50: =VLOOKUP(A50,'Account Mapping'!$A$2:$E$216,4,0) -> #N/A | N50: =IF(OR(C50='Account Mapping'!$H$4,C50='Account Mapping'!$H$5,C50='Account Mapping'!$H$6),'Account Mapping'!$I$4,VLOOKUP(A50,'Account Mapping'!$A$2:$E$216,5,0)) -> #N/A | O50: =IF(OR(L50="Loan",L50="Deposit_Liability",L50="OFF_Unused Loan Commitment",L50="HQLA"),VLOOKUP(D50,'Customer Type'!$A$3:$C$38,3,0),"") -> #N/A | P50: =M50&"_"&O50 -> #N/A | Q50: =IF(COUNTIF('Account Mapping'!$H$12:$H$45,A50)>0,-H50,H50) -> 206339.61 | R50: =VLOOKUP(P50,Assumptions!$C$2:$D$64,2,0) -> #N/A | S50: =IFERROR(VLOOKUP(A50,'Maturity Adjustment'!$A$3:$C$81,3,0),(IF(J50<$N$4,"Tomorrow",J50))) -> 47579 | T50: =IF(S50="Tomorrow",1,(S50-$N$4)) -> 1521 | U50: =Q50*R50 -> #N/A | V50: =IFERROR(VLOOKUP(A50,'Maturity Adjustment'!$A$86:$C$91,3,0),S50) -> 47579 | W50: =VLOOKUP(A50,'Account Mapping'!$A$2:$F$216,6,0) -> #N/A | X50: =IF(V50="Tomorrow",Q50,IF(AND(V50>$X$4-1,V50<$X$5),Q50,IF(V50=$X$5,Q50,0))) -> 0 | Y50: =IF(AND(V50>$Y$4-1,V50<$Y$5),Q50,IF(V50=$Y$5,Q50,0)) -> 0 | Z50: =IF(AND(V50>$Z$4-1,V50<$Z$5),Q50,IF(V50=$Z$5,Q50,0)) -> 0 | AA50: =IF(AND(V50>$AA$4-1,V50<$AA$5),Q50,IF(V50=$AA$5,Q50,0)) -> 0 | AB50: =IF(AND(V50>$AB$4-1,V50<$AB$5),Q50,IF(V50=$AB$5,Q50,0)) -> 0 | AC50: =IF(AND(V50>$AC$4-1,V50<$AC$5),Q50,IF(V50=$AC$5,Q50,0)) -> 0 | AD50: =IF(AND(V50>$AD$4-1,V50<$AD$5),Q50,IF(V50=$AD$5,Q50,0)) -> 0 | AE50: =IF(AND(V50>$AE$4-1,V50<$AE$5),Q50,IF(V50=$AE$5,Q50,0)) -> 206339.61 | AF50: =IF(AND(V50>$AF$4-1,V50<$AF$5),Q50,IF(V50=$AF$5,Q50,0)) -> 0 | AG50: =IF(AND(V50>$AG$4-1,V50<$AG$5),Q50,IF(V50=$AG$5,Q50,0)) -> 0 | AH50: =Q50=SUM(X50:AG50) -> TRUE | AL50: 1 month | AM50: -0.15 | AN50: -0.2 | AQ50: =-(AM50*AN53-AN54) -> 0 | AR50: =-(AN50*AN53-AN54) -> 0
A51: 10630001 | B51: Syndicated Loans (Long Term) - Domestic | C51: 6115904000242 | D51: 100000014 | E51: PERDAMAN CHEMICALS & FERTILISERS (FINANCE)PTY LTD | F51: USD | G51: 731182.8 | H51: 1040977.8 | I51: 45379 | J51: 47579 | K51: 46058 | L51: =VLOOKUP(A51,'Account Mapping'!$A$2:$E$216,3,0) -> #N/A | M51: =VLOOKUP(A51,'Account Mapping'!$A$2:$E$216,4,0) -> #N/A | N51: =IF(OR(C51='Account Mapping'!$H$4,C51='Account Mapping'!$H$5,C51='Account Mapping'!$H$6),'Account Mapping'!$I$4,VLOOKUP(A51,'Account Mapping'!$A$2:$E$216,5,0)) -> #N/A | O51: =IF(OR(L51="Loan",L51="Deposit_Liability",L51="OFF_Unused Loan Commitment",L51="HQLA"),VLOOKUP(D51,'Customer Type'!$A$3:$C$38,3,0),"") -> #N/A | P51: =M51&"_"&O51 -> #N/A | Q51: =IF(COUNTIF('Account Mapping'!$H$12:$H$45,A51)>0,-H51,H51) -> 1040977.8 | R51: =VLOOKUP(P51,Assumptions!$C$2:$D$64,2,0) -> #N/A | S51: =IFERROR(VLOOKUP(A51,'Maturity Adjustment'!$A$3:$C$81,3,0),(IF(J51<$N$4,"Tomorrow",J51))) -> 47579 | T51: =IF(S51="Tomorrow",1,(S51-$N$4)) -> 1521 | U51: =Q51*R51 -> #N/A | V51: =IFERROR(VLOOKUP(A51,'Maturity Adjustment'!$A$86:$C$91,3,0),S51) -> 47579 | W51: =VLOOKUP(A51,'Account Mapping'!$A$2:$F$216,6,0) -> #N/A | X51: =IF(V51="Tomorrow",Q51,IF(AND(V51>$X$4-1,V51<$X$5),Q51,IF(V51=$X$5,Q51,0))) -> 0 | Y51: =IF(AND(V51>$Y$4-1,V51<$Y$5),Q51,IF(V51=$Y$5,Q51,0)) -> 0 | Z51: =IF(AND(V51>$Z$4-1,V51<$Z$5),Q51,IF(V51=$Z$5,Q51,0)) -> 0 | AA51: =IF(AND(V51>$AA$4-1,V51<$AA$5),Q51,IF(V51=$AA$5,Q51,0)) -> 0 | AB51: =IF(AND(V51>$AB$4-1,V51<$AB$5),Q51,IF(V51=$AB$5,Q51,0)) -> 0 | AC51: =IF(AND(V51>$AC$4-1,V51<$AC$5),Q51,IF(V51=$AC$5,Q51,0)) -> 0 | AD51: =IF(AND(V51>$AD$4-1,V51<$AD$5),Q51,IF(V51=$AD$5,Q51,0)) -> 0 | AE51: =IF(AND(V51>$AE$4-1,V51<$AE$5),Q51,IF(V51=$AE$5,Q51,0)) -> 1040977.8 | AF51: =IF(AND(V51>$AF$4-1,V51<$AF$5),Q51,IF(V51=$AF$5,Q51,0)) -> 0 | AG51: =IF(AND(V51>$AG$4-1,V51<$AG$5),Q51,IF(V51=$AG$5,Q51,0)) -> 0 | AH51: =Q51=SUM(X51:AG51) -> TRUE | AL51: 3 month | AM51: -0.4 | AN51: -0.45 | AQ51: =-(AM51*AN53-AN54) -> 0 | AR51: =-(AN51*AN53-AN54) -> 0
A52: 10630001 | B52: Syndicated Loans (Long Term) - Domestic | C52: 6115904000250 | D52: 100000014 | E52: PERDAMAN CHEMICALS & FERTILISERS (FINANCE)PTY LTD | F52: USD | G52: 164959.99 | H52: 234851.92 | I52: 45404 | J52: 47579 | K52: 46058 | L52: =VLOOKUP(A52,'Account Mapping'!$A$2:$E$216,3,0) -> #N/A | M52: =VLOOKUP(A52,'Account Mapping'!$A$2:$E$216,4,0) -> #N/A | N52: =IF(OR(C52='Account Mapping'!$H$4,C52='Account Mapping'!$H$5,C52='Account Mapping'!$H$6),'Account Mapping'!$I$4,VLOOKUP(A52,'Account Mapping'!$A$2:$E$216,5,0)) -> #N/A | O52: =IF(OR(L52="Loan",L52="Deposit_Liability",L52="OFF_Unused Loan Commitment",L52="HQLA"),VLOOKUP(D52,'Customer Type'!$A$3:$C$38,3,0),"") -> #N/A | P52: =M52&"_"&O52 -> #N/A | Q52: =IF(COUNTIF('Account Mapping'!$H$12:$H$45,A52)>0,-H52,H52) -> 234851.92 | R52: =VLOOKUP(P52,Assumptions!$C$2:$D$64,2,0) -> #N/A | S52: =IFERROR(VLOOKUP(A52,'Maturity Adjustment'!$A$3:$C$81,3,0),(IF(J52<$N$4,"Tomorrow",J52))) -> 47579 | T52: =IF(S52="Tomorrow",1,(S52-$N$4)) -> 1521 | U52: =Q52*R52 -> #N/A | V52: =IFERROR(VLOOKUP(A52,'Maturity Adjustment'!$A$86:$C$91,3,0),S52) -> 47579 | W52: =VLOOKUP(A52,'Account Mapping'!$A$2:$F$216,6,0) -> #N/A | X52: =IF(V52="Tomorrow",Q52,IF(AND(V52>$X$4-1,V52<$X$5),Q52,IF(V52=$X$5,Q52,0))) -> 0 | Y52: =IF(AND(V52>$Y$4-1,V52<$Y$5),Q52,IF(V52=$Y$5,Q52,0)) -> 0 | Z52: =IF(AND(V52>$Z$4-1,V52<$Z$5),Q52,IF(V52=$Z$5,Q52,0)) -> 0 | AA52: =IF(AND(V52>$AA$4-1,V52<$AA$5),Q52,IF(V52=$AA$5,Q52,0)) -> 0 | AB52: =IF(AND(V52>$AB$4-1,V52<$AB$5),Q52,IF(V52=$AB$5,Q52,0)) -> 0 | AC52: =IF(AND(V52>$AC$4-1,V52<$AC$5),Q52,IF(V52=$AC$5,Q52,0)) -> 0 | AD52: =IF(AND(V52>$AD$4-1,V52<$AD$5),Q52,IF(V52=$AD$5,Q52,0)) -> 0 | AE52: =IF(AND(V52>$AE$4-1,V52<$AE$5),Q52,IF(V52=$AE$5,Q52,0)) -> 234851.92 | AF52: =IF(AND(V52>$AF$4-1,V52<$AF$5),Q52,IF(V52=$AF$5,Q52,0)) -> 0 | AG52: =IF(AND(V52>$AG$4-1,V52<$AG$5),Q52,IF(V52=$AG$5,Q52,0)) -> 0 | AH52: =Q52=SUM(X52:AG52) -> TRUE
A53: 10630001 | B53: Syndicated Loans (Long Term) - Domestic | C53: 6115904000267 | D53: 100000014 | E53: PERDAMAN CHEMICALS & FERTILISERS (FINANCE)PTY LTD | F53: USD | G53: 258064.52 | H53: 367403.93 | I53: 45412 | J53: 47579 | K53: 46058 | L53: =VLOOKUP(A53,'Account Mapping'!$A$2:$E$216,3,0) -> #N/A | M53: =VLOOKUP(A53,'Account Mapping'!$A$2:$E$216,4,0) -> #N/A | N53: =IF(OR(C53='Account Mapping'!$H$4,C53='Account Mapping'!$H$5,C53='Account Mapping'!$H$6),'Account Mapping'!$I$4,VLOOKUP(A53,'Account Mapping'!$A$2:$E$216,5,0)) -> #N/A | O53: =IF(OR(L53="Loan",L53="Deposit_Liability",L53="OFF_Unused Loan Commitment",L53="HQLA"),VLOOKUP(D53,'Customer Type'!$A$3:$C$38,3,0),"") -> #N/A | P53: =M53&"_"&O53 -> #N/A | Q53: =IF(COUNTIF('Account Mapping'!$H$12:$H$45,A53)>0,-H53,H53) -> 367403.93 | R53: =VLOOKUP(P53,Assumptions!$C$2:$D$64,2,0) -> #N/A | S53: =IFERROR(VLOOKUP(A53,'Maturity Adjustment'!$A$3:$C$81,3,0),(IF(J53<$N$4,"Tomorrow",J53))) -> 47579 | T53: =IF(S53="Tomorrow",1,(S53-$N$4)) -> 1521 | U53: =Q53*R53 -> #N/A | V53: =IFERROR(VLOOKUP(A53,'Maturity Adjustment'!$A$86:$C$91,3,0),S53) -> 47579 | W53: =VLOOKUP(A53,'Account Mapping'!$A$2:$F$216,6,0) -> #N/A | X53: =IF(V53="Tomorrow",Q53,IF(AND(V53>$X$4-1,V53<$X$5),Q53,IF(V53=$X$5,Q53,0))) -> 0 | Y53: =IF(AND(V53>$Y$4-1,V53<$Y$5),Q53,IF(V53=$Y$5,Q53,0)) -> 0 | Z53: =IF(AND(V53>$Z$4-1,V53<$Z$5),Q53,IF(V53=$Z$5,Q53,0)) -> 0 | AA53: =IF(AND(V53>$AA$4-1,V53<$AA$5),Q53,IF(V53=$AA$5,Q53,0)) -> 0 | AB53: =IF(AND(V53>$AB$4-1,V53<$AB$5),Q53,IF(V53=$AB$5,Q53,0)) -> 0 | AC53: =IF(AND(V53>$AC$4-1,V53<$AC$5),Q53,IF(V53=$AC$5,Q53,0)) -> 0 | AD53: =IF(AND(V53>$AD$4-1,V53<$AD$5),Q53,IF(V53=$AD$5,Q53,0)) -> 0 | AE53: =IF(AND(V53>$AE$4-1,V53<$AE$5),Q53,IF(V53=$AE$5,Q53,0)) -> 367403.93 | AF53: =IF(AND(V53>$AF$4-1,V53<$AF$5),Q53,IF(V53=$AF$5,Q53,0)) -> 0 | AG53: =IF(AND(V53>$AG$4-1,V53<$AG$5),Q53,IF(V53=$AG$5,Q53,0)) -> 0 | AH53: =Q53=SUM(X53:AG53) -> TRUE | AM53: Total Asset | AN53: =SUMIF($W$7:$W$874,AK13,$H$7:$H$874) -> 0 | AQ53: Monthly Max Funding | AR53: Monthly Max Funding
A54: 10630001 | B54: Syndicated Loans (Long Term) - Domestic | C54: 6115904000274 | D54: 100000014 | E54: PERDAMAN CHEMICALS & FERTILISERS (FINANCE)PTY LTD | F54: USD | G54: 612903.23 | H54: 872584.33 | I54: 45434 | J54: 47579 | K54: 46058 | L54: =VLOOKUP(A54,'Account Mapping'!$A$2:$E$216,3,0) -> #N/A | M54: =VLOOKUP(A54,'Account Mapping'!$A$2:$E$216,4,0) -> #N/A | N54: =IF(OR(C54='Account Mapping'!$H$4,C54='Account Mapping'!$H$5,C54='Account Mapping'!$H$6),'Account Mapping'!$I$4,VLOOKUP(A54,'Account Mapping'!$A$2:$E$216,5,0)) -> #N/A | O54: =IF(OR(L54="Loan",L54="Deposit_Liability",L54="OFF_Unused Loan Commitment",L54="HQLA"),VLOOKUP(D54,'Customer Type'!$A$3:$C$38,3,0),"") -> #N/A | P54: =M54&"_"&O54 -> #N/A | Q54: =IF(COUNTIF('Account Mapping'!$H$12:$H$45,A54)>0,-H54,H54) -> 872584.33 | R54: =VLOOKUP(P54,Assumptions!$C$2:$D$64,2,0) -> #N/A | S54: =IFERROR(VLOOKUP(A54,'Maturity Adjustment'!$A$3:$C$81,3,0),(IF(J54<$N$4,"Tomorrow",J54))) -> 47579 | T54: =IF(S54="Tomorrow",1,(S54-$N$4)) -> 1521 | U54: =Q54*R54 -> #N/A | V54: =IFERROR(VLOOKUP(A54,'Maturity Adjustment'!$A$86:$C$91,3,0),S54) -> 47579 | W54: =VLOOKUP(A54,'Account Mapping'!$A$2:$F$216,6,0) -> #N/A | X54: =IF(V54="Tomorrow",Q54,IF(AND(V54>$X$4-1,V54<$X$5),Q54,IF(V54=$X$5,Q54,0))) -> 0 | Y54: =IF(AND(V54>$Y$4-1,V54<$Y$5),Q54,IF(V54=$Y$5,Q54,0)) -> 0 | Z54: =IF(AND(V54>$Z$4-1,V54<$Z$5),Q54,IF(V54=$Z$5,Q54,0)) -> 0 | AA54: =IF(AND(V54>$AA$4-1,V54<$AA$5),Q54,IF(V54=$AA$5,Q54,0)) -> 0 | AB54: =IF(AND(V54>$AB$4-1,V54<$AB$5),Q54,IF(V54=$AB$5,Q54,0)) -> 0 | AC54: =IF(AND(V54>$AC$4-1,V54<$AC$5),Q54,IF(V54=$AC$5,Q54,0)) -> 0 | AD54: =IF(AND(V54>$AD$4-1,V54<$AD$5),Q54,IF(V54=$AD$5,Q54,0)) -> 0 | AE54: =IF(AND(V54>$AE$4-1,V54<$AE$5),Q54,IF(V54=$AE$5,Q54,0)) -> 872584.33 | AF54: =IF(AND(V54>$AF$4-1,V54<$AF$5),Q54,IF(V54=$AF$5,Q54,0)) -> 0 | AG54: =IF(AND(V54>$AG$4-1,V54<$AG$5),Q54,IF(V54=$AG$5,Q54,0)) -> 0 | AH54: =Q54=SUM(X54:AG54) -> TRUE | AM54: HQLA | AN54: ='30 days CF Table(ALL)'!$D$117 -> 0 | AQ54: =AQ51/3 -> 0 | AR54: =AR51/3 -> 0
A55: 10630001 | B55: Syndicated Loans (Long Term) - Domestic | C55: 6115904000281 | D55: 100000014 | E55: PERDAMAN CHEMICALS & FERTILISERS (FINANCE)PTY LTD | F55: USD | G55: 162547.93 | H55: 231417.9 | I55: 45434 | J55: 47579 | K55: 46058 | L55: =VLOOKUP(A55,'Account Mapping'!$A$2:$E$216,3,0) -> #N/A | M55: =VLOOKUP(A55,'Account Mapping'!$A$2:$E$216,4,0) -> #N/A | N55: =IF(OR(C55='Account Mapping'!$H$4,C55='Account Mapping'!$H$5,C55='Account Mapping'!$H$6),'Account Mapping'!$I$4,VLOOKUP(A55,'Account Mapping'!$A$2:$E$216,5,0)) -> #N/A | O55: =IF(OR(L55="Loan",L55="Deposit_Liability",L55="OFF_Unused Loan Commitment",L55="HQLA"),VLOOKUP(D55,'Customer Type'!$A$3:$C$38,3,0),"") -> #N/A | P55: =M55&"_"&O55 -> #N/A | Q55: =IF(COUNTIF('Account Mapping'!$H$12:$H$45,A55)>0,-H55,H55) -> 231417.9 | R55: =VLOOKUP(P55,Assumptions!$C$2:$D$64,2,0) -> #N/A | S55: =IFERROR(VLOOKUP(A55,'Maturity Adjustment'!$A$3:$C$81,3,0),(IF(J55<$N$4,"Tomorrow",J55))) -> 47579 | T55: =IF(S55="Tomorrow",1,(S55-$N$4)) -> 1521 | U55: =Q55*R55 -> #N/A | V55: =IFERROR(VLOOKUP(A55,'Maturity Adjustment'!$A$86:$C$91,3,0),S55) -> 47579 | W55: =VLOOKUP(A55,'Account Mapping'!$A$2:$F$216,6,0) -> #N/A | X55: =IF(V55="Tomorrow",Q55,IF(AND(V55>$X$4-1,V55<$X$5),Q55,IF(V55=$X$5,Q55,0))) -> 0 | Y55: =IF(AND(V55>$Y$4-1,V55<$Y$5),Q55,IF(V55=$Y$5,Q55,0)) -> 0 | Z55: =IF(AND(V55>$Z$4-1,V55<$Z$5),Q55,IF(V55=$Z$5,Q55,0)) -> 0 | AA55: =IF(AND(V55>$AA$4-1,V55<$AA$5),Q55,IF(V55=$AA$5,Q55,0)) -> 0 | AB55: =IF(AND(V55>$AB$4-1,V55<$AB$5),Q55,IF(V55=$AB$5,Q55,0)) -> 0 | AC55: =IF(AND(V55>$AC$4-1,V55<$AC$5),Q55,IF(V55=$AC$5,Q55,0)) -> 0 | AD55: =IF(AND(V55>$AD$4-1,V55<$AD$5),Q55,IF(V55=$AD$5,Q55,0)) -> 0 | AE55: =IF(AND(V55>$AE$4-1,V55<$AE$5),Q55,IF(V55=$AE$5,Q55,0)) -> 231417.9 | AF55: =IF(AND(V55>$AF$4-1,V55<$AF$5),Q55,IF(V55=$AF$5,Q55,0)) -> 0 | AG55: =IF(AND(V55>$AG$4-1,V55<$AG$5),Q55,IF(V55=$AG$5,Q55,0)) -> 0 | AH55: =Q55=SUM(X55:AG55) -> TRUE
A56: 10630001 | B56: Syndicated Loans (Long Term) - Domestic | C56: 6115904000317 | D56: 100000014 | E56: PERDAMAN CHEMICALS & FERTILISERS (FINANCE)PTY LTD | F56: USD | G56: 623655.91 | H56: 887892.81 | I56: 45464 | J56: 47579 | K56: 46058 | L56: =VLOOKUP(A56,'Account Mapping'!$A$2:$E$216,3,0) -> #N/A | M56: =VLOOKUP(A56,'Account Mapping'!$A$2:$E$216,4,0) -> #N/A | N56: =IF(OR(C56='Account Mapping'!$H$4,C56='Account Mapping'!$H$5,C56='Account Mapping'!$H$6),'Account Mapping'!$I$4,VLOOKUP(A56,'Account Mapping'!$A$2:$E$216,5,0)) -> #N/A | O56: =IF(OR(L56="Loan",L56="Deposit_Liability",L56="OFF_Unused Loan Commitment",L56="HQLA"),VLOOKUP(D56,'Customer Type'!$A$3:$C$38,3,0),"") -> #N/A | P56: =M56&"_"&O56 -> #N/A | Q56: =IF(COUNTIF('Account Mapping'!$H$12:$H$45,A56)>0,-H56,H56) -> 887892.81 | R56: =VLOOKUP(P56,Assumptions!$C$2:$D$64,2,0) -> #N/A | S56: =IFERROR(VLOOKUP(A56,'Maturity Adjustment'!$A$3:$C$81,3,0),(IF(J56<$N$4,"Tomorrow",J56))) -> 47579 | T56: =IF(S56="Tomorrow",1,(S56-$N$4)) -> 1521 | U56: =Q56*R56 -> #N/A | V56: =IFERROR(VLOOKUP(A56,'Maturity Adjustment'!$A$86:$C$91,3,0),S56) -> 47579 | W56: =VLOOKUP(A56,'Account Mapping'!$A$2:$F$216,6,0) -> #N/A | X56: =IF(V56="Tomorrow",Q56,IF(AND(V56>$X$4-1,V56<$X$5),Q56,IF(V56=$X$5,Q56,0))) -> 0 | Y56: =IF(AND(V56>$Y$4-1,V56<$Y$5),Q56,IF(V56=$Y$5,Q56,0)) -> 0 | Z56: =IF(AND(V56>$Z$4-1,V56<$Z$5),Q56,IF(V56=$Z$5,Q56,0)) -> 0 | AA56: =IF(AND(V56>$AA$4-1,V56<$AA$5),Q56,IF(V56=$AA$5,Q56,0)) -> 0 | AB56: =IF(AND(V56>$AB$4-1,V56<$AB$5),Q56,IF(V56=$AB$5,Q56,0)) -> 0 | AC56: =IF(AND(V56>$AC$4-1,V56<$AC$5),Q56,IF(V56=$AC$5,Q56,0)) -> 0 | AD56: =IF(AND(V56>$AD$4-1,V56<$AD$5),Q56,IF(V56=$AD$5,Q56,0)) -> 0 | AE56: =IF(AND(V56>$AE$4-1,V56<$AE$5),Q56,IF(V56=$AE$5,Q56,0)) -> 887892.81 | AF56: =IF(AND(V56>$AF$4-1,V56<$AF$5),Q56,IF(V56=$AF$5,Q56,0)) -> 0 | AG56: =IF(AND(V56>$AG$4-1,V56<$AG$5),Q56,IF(V56=$AG$5,Q56,0)) -> 0 | AH56: =Q56=SUM(X56:AG56) -> TRUE
A57: 10630001 | B57: Syndicated Loans (Long Term) - Domestic | C57: 6115904000324 | D57: 100000014 | E57: PERDAMAN CHEMICALS & FERTILISERS (FINANCE)PTY LTD | F57: USD | G57: 167780.4 | H57: 238867.31 | I57: 45464 | J57: 47579 | K57: 46058 | L57: =VLOOKUP(A57,'Account Mapping'!$A$2:$E$216,3,0) -> #N/A | M57: =VLOOKUP(A57,'Account Mapping'!$A$2:$E$216,4,0) -> #N/A | N57: =IF(OR(C57='Account Mapping'!$H$4,C57='Account Mapping'!$H$5,C57='Account Mapping'!$H$6),'Account Mapping'!$I$4,VLOOKUP(A57,'Account Mapping'!$A$2:$E$216,5,0)) -> #N/A | O57: =IF(OR(L57="Loan",L57="Deposit_Liability",L57="OFF_Unused Loan Commitment",L57="HQLA"),VLOOKUP(D57,'Customer Type'!$A$3:$C$38,3,0),"") -> #N/A | P57: =M57&"_"&O57 -> #N/A | Q57: =IF(COUNTIF('Account Mapping'!$H$12:$H$45,A57)>0,-H57,H57) -> 238867.31 | R57: =VLOOKUP(P57,Assumptions!$C$2:$D$64,2,0) -> #N/A | S57: =IFERROR(VLOOKUP(A57,'Maturity Adjustment'!$A$3:$C$81,3,0),(IF(J57<$N$4,"Tomorrow",J57))) -> 47579 | T57: =IF(S57="Tomorrow",1,(S57-$N$4)) -> 1521 | U57: =Q57*R57 -> #N/A | V57: =IFERROR(VLOOKUP(A57,'Maturity Adjustment'!$A$86:$C$91,3,0),S57) -> 47579 | W57: =VLOOKUP(A57,'Account Mapping'!$A$2:$F$216,6,0) -> #N/A | X57: =IF(V57="Tomorrow",Q57,IF(AND(V57>$X$4-1,V57<$X$5),Q57,IF(V57=$X$5,Q57,0))) -> 0 | Y57: =IF(AND(V57>$Y$4-1,V57<$Y$5),Q57,IF(V57=$Y$5,Q57,0)) -> 0 | Z57: =IF(AND(V57>$Z$4-1,V57<$Z$5),Q57,IF(V57=$Z$5,Q57,0)) -> 0 | AA57: =IF(AND(V57>$AA$4-1,V57<$AA$5),Q57,IF(V57=$AA$5,Q57,0)) -> 0 | AB57: =IF(AND(V57>$AB$4-1,V57<$AB$5),Q57,IF(V57=$AB$5,Q57,0)) -> 0 | AC57: =IF(AND(V57>$AC$4-1,V57<$AC$5),Q57,IF(V57=$AC$5,Q57,0)) -> 0 | AD57: =IF(AND(V57>$AD$4-1,V57<$AD$5),Q57,IF(V57=$AD$5,Q57,0)) -> 0 | AE57: =IF(AND(V57>$AE$4-1,V57<$AE$5),Q57,IF(V57=$AE$5,Q57,0)) -> 238867.31 | AF57: =IF(AND(V57>$AF$4-1,V57<$AF$5),Q57,IF(V57=$AF$5,Q57,0)) -> 0 | AG57: =IF(AND(V57>$AG$4-1,V57<$AG$5),Q57,IF(V57=$AG$5,Q57,0)) -> 0 | AH57: =Q57=SUM(X57:AG57) -> TRUE
A58: 10630001 | B58: Syndicated Loans (Long Term) - Domestic | C58: 6115904000331 | D58: 100000014 | E58: PERDAMAN CHEMICALS & FERTILISERS (FINANCE)PTY LTD | F58: USD | G58: 161159.11 | H58: 229440.65 | I58: 45492 | J58: 47579 | K58: 46058 | L58: =VLOOKUP(A58,'Account Mapping'!$A$2:$E$216,3,0) -> #N/A | M58: =VLOOKUP(A58,'Account Mapping'!$A$2:$E$216,4,0) -> #N/A | N58: =IF(OR(C58='Account Mapping'!$H$4,C58='Account Mapping'!$H$5,C58='Account Mapping'!$H$6),'Account Mapping'!$I$4,VLOOKUP(A58,'Account Mapping'!$A$2:$E$216,5,0)) -> #N/A | O58: =IF(OR(L58="Loan",L58="Deposit_Liability",L58="OFF_Unused Loan Commitment",L58="HQLA"),VLOOKUP(D58,'Customer Type'!$A$3:$C$38,3,0),"") -> #N/A | P58: =M58&"_"&O58 -> #N/A | Q58: =IF(COUNTIF('Account Mapping'!$H$12:$H$45,A58)>0,-H58,H58) -> 229440.65 | R58: =VLOOKUP(P58,Assumptions!$C$2:$D$64,2,0) -> #N/A | S58: =IFERROR(VLOOKUP(A58,'Maturity Adjustment'!$A$3:$C$81,3,0),(IF(J58<$N$4,"Tomorrow",J58))) -> 47579 | T58: =IF(S58="Tomorrow",1,(S58-$N$4)) -> 1521 | U58: =Q58*R58 -> #N/A | V58: =IFERROR(VLOOKUP(A58,'Maturity Adjustment'!$A$86:$C$91,3,0),S58) -> 47579 | W58: =VLOOKUP(A58,'Account Mapping'!$A$2:$F$216,6,0) -> #N/A | X58: =IF(V58="Tomorrow",Q58,IF(AND(V58>$X$4-1,V58<$X$5),Q58,IF(V58=$X$5,Q58,0))) -> 0 | Y58: =IF(AND(V58>$Y$4-1,V58<$Y$5),Q58,IF(V58=$Y$5,Q58,0)) -> 0 | Z58: =IF(AND(V58>$Z$4-1,V58<$Z$5),Q58,IF(V58=$Z$5,Q58,0)) -> 0 | AA58: =IF(AND(V58>$AA$4-1,V58<$AA$5),Q58,IF(V58=$AA$5,Q58,0)) -> 0 | AB58: =IF(AND(V58>$AB$4-1,V58<$AB$5),Q58,IF(V58=$AB$5,Q58,0)) -> 0 | AC58: =IF(AND(V58>$AC$4-1,V58<$AC$5),Q58,IF(V58=$AC$5,Q58,0)) -> 0 | AD58: =IF(AND(V58>$AD$4-1,V58<$AD$5),Q58,IF(V58=$AD$5,Q58,0)) -> 0 | AE58: =IF(AND(V58>$AE$4-1,V58<$AE$5),Q58,IF(V58=$AE$5,Q58,0)) -> 229440.65 | AF58: =IF(AND(V58>$AF$4-1,V58<$AF$5),Q58,IF(V58=$AF$5,Q58,0)) -> 0 | AG58: =IF(AND(V58>$AG$4-1,V58<$AG$5),Q58,IF(V58=$AG$5,Q58,0)) -> 0 | AH58: =Q58=SUM(X58:AG58) -> TRUE
A59: 10630001 | B59: Syndicated Loans (Long Term) - Domestic | C59: 6115904000349 | D59: 100000014 | E59: PERDAMAN CHEMICALS & FERTILISERS (FINANCE)PTY LTD | F59: USD | G59: 655913.98 | H59: 933818.31 | I59: 45504 | J59: 47579 | K59: 46058 | L59: =VLOOKUP(A59,'Account Mapping'!$A$2:$E$216,3,0) -> #N/A | M59: =VLOOKUP(A59,'Account Mapping'!$A$2:$E$216,4,0) -> #N/A | N59: =IF(OR(C59='Account Mapping'!$H$4,C59='Account Mapping'!$H$5,C59='Account Mapping'!$H$6),'Account Mapping'!$I$4,VLOOKUP(A59,'Account Mapping'!$A$2:$E$216,5,0)) -> #N/A | O59: =IF(OR(L59="Loan",L59="Deposit_Liability",L59="OFF_Unused Loan Commitment",L59="HQLA"),VLOOKUP(D59,'Customer Type'!$A$3:$C$38,3,0),"") -> #N/A | P59: =M59&"_"&O59 -> #N/A | Q59: =IF(COUNTIF('Account Mapping'!$H$12:$H$45,A59)>0,-H59,H59) -> 933818.31 | R59: =VLOOKUP(P59,Assumptions!$C$2:$D$64,2,0) -> #N/A | S59: =IFERROR(VLOOKUP(A59,'Maturity Adjustment'!$A$3:$C$81,3,0),(IF(J59<$N$4,"Tomorrow",J59))) -> 47579 | T59: =IF(S59="Tomorrow",1,(S59-$N$4)) -> 1521 | U59: =Q59*R59 -> #N/A | V59: =IFERROR(VLOOKUP(A59,'Maturity Adjustment'!$A$86:$C$91,3,0),S59) -> 47579 | W59: =VLOOKUP(A59,'Account Mapping'!$A$2:$F$216,6,0) -> #N/A | X59: =IF(V59="Tomorrow",Q59,IF(AND(V59>$X$4-1,V59<$X$5),Q59,IF(V59=$X$5,Q59,0))) -> 0 | Y59: =IF(AND(V59>$Y$4-1,V59<$Y$5),Q59,IF(V59=$Y$5,Q59,0)) -> 0 | Z59: =IF(AND(V59>$Z$4-1,V59<$Z$5),Q59,IF(V59=$Z$5,Q59,0)) -> 0 | AA59: =IF(AND(V59>$AA$4-1,V59<$AA$5),Q59,IF(V59=$AA$5,Q59,0)) -> 0 | AB59: =IF(AND(V59>$AB$4-1,V59<$AB$5),Q59,IF(V59=$AB$5,Q59,0)) -> 0 | AC59: =IF(AND(V59>$AC$4-1,V59<$AC$5),Q59,IF(V59=$AC$5,Q59,0)) -> 0 | AD59: =IF(AND(V59>$AD$4-1,V59<$AD$5),Q59,IF(V59=$AD$5,Q59,0)) -> 0 | AE59: =IF(AND(V59>$AE$4-1,V59<$AE$5),Q59,IF(V59=$AE$5,Q59,0)) -> 933818.31 | AF59: =IF(AND(V59>$AF$4-1,V59<$AF$5),Q59,IF(V59=$AF$5,Q59,0)) -> 0 | AG59: =IF(AND(V59>$AG$4-1,V59<$AG$5),Q59,IF(V59=$AG$5,Q59,0)) -> 0 | AH59: =Q59=SUM(X59:AG59) -> TRUE
A60: 10630001 | B60: Syndicated Loans (Long Term) - Domestic | C60: 6115904000356 | D60: 100000014 | E60: PERDAMAN CHEMICALS & FERTILISERS (FINANCE)PTY LTD | F60: USD | G60: 182210.15 | H60: 259410.81 | I60: 45523 | J60: 47579 | K60: 46058 | L60: =VLOOKUP(A60,'Account Mapping'!$A$2:$E$216,3,0) -> #N/A | M60: =VLOOKUP(A60,'Account Mapping'!$A$2:$E$216,4,0) -> #N/A | N60: =IF(OR(C60='Account Mapping'!$H$4,C60='Account Mapping'!$H$5,C60='Account Mapping'!$H$6),'Account Mapping'!$I$4,VLOOKUP(A60,'Account Mapping'!$A$2:$E$216,5,0)) -> #N/A | O60: =IF(OR(L60="Loan",L60="Deposit_Liability",L60="OFF_Unused Loan Commitment",L60="HQLA"),VLOOKUP(D60,'Customer Type'!$A$3:$C$38,3,0),"") -> #N/A | P60: =M60&"_"&O60 -> #N/A | Q60: =IF(COUNTIF('Account Mapping'!$H$12:$H$45,A60)>0,-H60,H60) -> 259410.81 | R60: =VLOOKUP(P60,Assumptions!$C$2:$D$64,2,0) -> #N/A | S60: =IFERROR(VLOOKUP(A60,'Maturity Adjustment'!$A$3:$C$81,3,0),(IF(J60<$N$4,"Tomorrow",J60))) -> 47579 | T60: =IF(S60="Tomorrow",1,(S60-$N$4)) -> 1521 | U60: =Q60*R60 -> #N/A | V60: =IFERROR(VLOOKUP(A60,'Maturity Adjustment'!$A$86:$C$91,3,0),S60) -> 47579 | W60: =VLOOKUP(A60,'Account Mapping'!$A$2:$F$216,6,0) -> #N/A | X60: =IF(V60="Tomorrow",Q60,IF(AND(V60>$X$4-1,V60<$X$5),Q60,IF(V60=$X$5,Q60,0))) -> 0 | Y60: =IF(AND(V60>$Y$4-1,V60<$Y$5),Q60,IF(V60=$Y$5,Q60,0)) -> 0 | Z60: =IF(AND(V60>$Z$4-1,V60<$Z$5),Q60,IF(V60=$Z$5,Q60,0)) -> 0 | AA60: =IF(AND(V60>$AA$4-1,V60<$AA$5),Q60,IF(V60=$AA$5,Q60,0)) -> 0 | AB60: =IF(AND(V60>$AB$4-1,V60<$AB$5),Q60,IF(V60=$AB$5,Q60,0)) -> 0 | AC60: =IF(AND(V60>$AC$4-1,V60<$AC$5),Q60,IF(V60=$AC$5,Q60,0)) -> 0 | AD60: =IF(AND(V60>$AD$4-1,V60<$AD$5),Q60,IF(V60=$AD$5,Q60,0)) -> 0 | AE60: =IF(AND(V60>$AE$4-1,V60<$AE$5),Q60,IF(V60=$AE$5,Q60,0)) -> 259410.81 | AF60: =IF(AND(V60>$AF$4-1,V60<$AF$5),Q60,IF(V60=$AF$5,Q60,0)) -> 0 | AG60: =IF(AND(V60>$AG$4-1,V60<$AG$5),Q60,IF(V60=$AG$5,Q60,0)) -> 0 | AH60: =Q60=SUM(X60:AG60) -> TRUE
A61: 10630001 | B61: Syndicated Loans (Long Term) - Domestic | C61: 6115904000363 | D61: 100000014 | E61: PERDAMAN CHEMICALS & FERTILISERS (FINANCE)PTY LTD | F61: USD | G61: 1354838.7 | H61: 1928870.6 | I61: 45534 | J61: 47579 | K61: 46058 | L61: =VLOOKUP(A61,'Account Mapping'!$A$2:$E$216,3,0) -> #N/A | M61: =VLOOKUP(A61,'Account Mapping'!$A$2:$E$216,4,0) -> #N/A | N61: =IF(OR(C61='Account Mapping'!$H$4,C61='Account Mapping'!$H$5,C61='Account Mapping'!$H$6),'Account Mapping'!$I$4,VLOOKUP(A61,'Account Mapping'!$A$2:$E$216,5,0)) -> #N/A | O61: =IF(OR(L61="Loan",L61="Deposit_Liability",L61="OFF_Unused Loan Commitment",L61="HQLA"),VLOOKUP(D61,'Customer Type'!$A$3:$C$38,3,0),"") -> #N/A | P61: =M61&"_"&O61 -> #N/A | Q61: =IF(COUNTIF('Account Mapping'!$H$12:$H$45,A61)>0,-H61,H61) -> 1928870.6 | R61: =VLOOKUP(P61,Assumptions!$C$2:$D$64,2,0) -> #N/A | S61: =IFERROR(VLOOKUP(A61,'Maturity Adjustment'!$A$3:$C$81,3,0),(IF(J61<$N$4,"Tomorrow",J61))) -> 47579 | T61: =IF(S61="Tomorrow",1,(S61-$N$4)) -> 1521 | U61: =Q61*R61 -> #N/A | V61: =IFERROR(VLOOKUP(A61,'Maturity Adjustment'!$A$86:$C$91,3,0),S61) -> 47579 | W61: =VLOOKUP(A61,'Account Mapping'!$A$2:$F$216,6,0) -> #N/A | X61: =IF(V61="Tomorrow",Q61,IF(AND(V61>$X$4-1,V61<$X$5),Q61,IF(V61=$X$5,Q61,0))) -> 0 | Y61: =IF(AND(V61>$Y$4-1,V61<$Y$5),Q61,IF(V61=$Y$5,Q61,0)) -> 0 | Z61: =IF(AND(V61>$Z$4-1,V61<$Z$5),Q61,IF(V61=$Z$5,Q61,0)) -> 0 | AA61: =IF(AND(V61>$AA$4-1,V61<$AA$5),Q61,IF(V61=$AA$5,Q61,0)) -> 0 | AB61: =IF(AND(V61>$AB$4-1,V61<$AB$5),Q61,IF(V61=$AB$5,Q61,0)) -> 0 | AC61: =IF(AND(V61>$AC$4-1,V61<$AC$5),Q61,IF(V61=$AC$5,Q61,0)) -> 0 | AD61: =IF(AND(V61>$AD$4-1,V61<$AD$5),Q61,IF(V61=$AD$5,Q61,0)) -> 0 | AE61: =IF(AND(V61>$AE$4-1,V61<$AE$5),Q61,IF(V61=$AE$5,Q61,0)) -> 1928870.6 | AF61: =IF(AND(V61>$AF$4-1,V61<$AF$5),Q61,IF(V61=$AF$5,Q61,0)) -> 0 | AG61: =IF(AND(V61>$AG$4-1,V61<$AG$5),Q61,IF(V61=$AG$5,Q61,0)) -> 0 | AH61: =Q61=SUM(X61:AG61) -> TRUE
A62: 10630001 | B62: Syndicated Loans (Long Term) - Domestic | C62: 6115904000370 | D62: 100000014 | E62: PERDAMAN CHEMICALS & FERTILISERS (FINANCE)PTY LTD | F62: USD | G62: 190219.59 | H62: 270813.77 | I62: 45554 | J62: 47579 | K62: 46058 | L62: =VLOOKUP(A62,'Account Mapping'!$A$2:$E$216,3,0) -> #N/A | M62: =VLOOKUP(A62,'Account Mapping'!$A$2:$E$216,4,0) -> #N/A | N62: =IF(OR(C62='Account Mapping'!$H$4,C62='Account Mapping'!$H$5,C62='Account Mapping'!$H$6),'Account Mapping'!$I$4,VLOOKUP(A62,'Account Mapping'!$A$2:$E$216,5,0)) -> #N/A | O62: =IF(OR(L62="Loan",L62="Deposit_Liability",L62="OFF_Unused Loan Commitment",L62="HQLA"),VLOOKUP(D62,'Customer Type'!$A$3:$C$38,3,0),"") -> #N/A | P62: =M62&"_"&O62 -> #N/A | Q62: =IF(COUNTIF('Account Mapping'!$H$12:$H$45,A62)>0,-H62,H62) -> 270813.77 | R62: =VLOOKUP(P62,Assumptions!$C$2:$D$64,2,0) -> #N/A | S62: =IFERROR(VLOOKUP(A62,'Maturity Adjustment'!$A$3:$C$81,3,0),(IF(J62<$N$4,"Tomorrow",J62))) -> 47579 | T62: =IF(S62="Tomorrow",1,(S62-$N$4)) -> 1521 | U62: =Q62*R62 -> #N/A | V62: =IFERROR(VLOOKUP(A62,'Maturity Adjustment'!$A$86:$C$91,3,0),S62) -> 47579 | W62: =VLOOKUP(A62,'Account Mapping'!$A$2:$F$216,6,0) -> #N/A | X62: =IF(V62="Tomorrow",Q62,IF(AND(V62>$X$4-1,V62<$X$5),Q62,IF(V62=$X$5,Q62,0))) -> 0 | Y62: =IF(AND(V62>$Y$4-1,V62<$Y$5),Q62,IF(V62=$Y$5,Q62,0)) -> 0 | Z62: =IF(AND(V62>$Z$4-1,V62<$Z$5),Q62,IF(V62=$Z$5,Q62,0)) -> 0 | AA62: =IF(AND(V62>$AA$4-1,V62<$AA$5),Q62,IF(V62=$AA$5,Q62,0)) -> 0 | AB62: =IF(AND(V62>$AB$4-1,V62<$AB$5),Q62,IF(V62=$AB$5,Q62,0)) -> 0 | AC62: =IF(AND(V62>$AC$4-1,V62<$AC$5),Q62,IF(V62=$AC$5,Q62,0)) -> 0 | AD62: =IF(AND(V62>$AD$4-1,V62<$AD$5),Q62,IF(V62=$AD$5,Q62,0)) -> 0 | AE62: =IF(AND(V62>$AE$4-1,V62<$AE$5),Q62,IF(V62=$AE$5,Q62,0)) -> 270813.77 | AF62: =IF(AND(V62>$AF$4-1,V62<$AF$5),Q62,IF(V62=$AF$5,Q62,0)) -> 0 | AG62: =IF(AND(V62>$AG$4-1,V62<$AG$5),Q62,IF(V62=$AG$5,Q62,0)) -> 0 | AH62: =Q62=SUM(X62:AG62) -> TRUE
A63: 10630001 | B63: Syndicated Loans (Long Term) - Domestic | C63: 6115904000388 | D63: 100000014 | E63: PERDAMAN CHEMICALS & FERTILISERS (FINANCE)PTY LTD | F63: USD | G63: 1053763.4 | H63: 1500232.7 | I63: 45565 | J63: 47579 | K63: 46058 | L63: =VLOOKUP(A63,'Account Mapping'!$A$2:$E$216,3,0) -> #N/A | M63: =VLOOKUP(A63,'Account Mapping'!$A$2:$E$216,4,0) -> #N/A | N63: =IF(OR(C63='Account Mapping'!$H$4,C63='Account Mapping'!$H$5,C63='Account Mapping'!$H$6),'Account Mapping'!$I$4,VLOOKUP(A63,'Account Mapping'!$A$2:$E$216,5,0)) -> #N/A | O63: =IF(OR(L63="Loan",L63="Deposit_Liability",L63="OFF_Unused Loan Commitment",L63="HQLA"),VLOOKUP(D63,'Customer Type'!$A$3:$C$38,3,0),"") -> #N/A | P63: =M63&"_"&O63 -> #N/A | Q63: =IF(COUNTIF('Account Mapping'!$H$12:$H$45,A63)>0,-H63,H63) -> 1500232.7 | R63: =VLOOKUP(P63,Assumptions!$C$2:$D$64,2,0) -> #N/A | S63: =IFERROR(VLOOKUP(A63,'Maturity Adjustment'!$A$3:$C$81,3,0),(IF(J63<$N$4,"Tomorrow",J63))) -> 47579 | T63: =IF(S63="Tomorrow",1,(S63-$N$4)) -> 1521 | U63: =Q63*R63 -> #N/A | V63: =IFERROR(VLOOKUP(A63,'Maturity Adjustment'!$A$86:$C$91,3,0),S63) -> 47579 | W63: =VLOOKUP(A63,'Account Mapping'!$A$2:$F$216,6,0) -> #N/A | X63: =IF(V63="Tomorrow",Q63,IF(AND(V63>$X$4-1,V63<$X$5),Q63,IF(V63=$X$5,Q63,0))) -> 0 | Y63: =IF(AND(V63>$Y$4-1,V63<$Y$5),Q63,IF(V63=$Y$5,Q63,0)) -> 0 | Z63: =IF(AND(V63>$Z$4-1,V63<$Z$5),Q63,IF(V63=$Z$5,Q63,0)) -> 0 | AA63: =IF(AND(V63>$AA$4-1,V63<$AA$5),Q63,IF(V63=$AA$5,Q63,0)) -> 0 | AB63: =IF(AND(V63>$AB$4-1,V63<$AB$5),Q63,IF(V63=$AB$5,Q63,0)) -> 0 | AC63: =IF(AND(V63>$AC$4-1,V63<$AC$5),Q63,IF(V63=$AC$5,Q63,0)) -> 0 | AD63: =IF(AND(V63>$AD$4-1,V63<$AD$5),Q63,IF(V63=$AD$5,Q63,0)) -> 0 | AE63: =IF(AND(V63>$AE$4-1,V63<$AE$5),Q63,IF(V63=$AE$5,Q63,0)) -> 1500232.7 | AF63: =IF(AND(V63>$AF$4-1,V63<$AF$5),Q63,IF(V63=$AF$5,Q63,0)) -> 0 | AG63: =IF(AND(V63>$AG$4-1,V63<$AG$5),Q63,IF(V63=$AG$5,Q63,0)) -> 0 | AH63: =Q63=SUM(X63:AG63) -> TRUE
A64: 10630001 | B64: Syndicated Loans (Long Term) - Domestic | C64: 6115904000420 | D64: 100000014 | E64: PERDAMAN CHEMICALS & FERTILISERS (FINANCE)PTY LTD | F64: USD | G64: 178768.75 | H64: 254511.32 | I64: 45583 | J64: 47579 | K64: 46058 | L64: =VLOOKUP(A64,'Account Mapping'!$A$2:$E$216,3,0) -> #N/A | M64: =VLOOKUP(A64,'Account Mapping'!$A$2:$E$216,4,0) -> #N/A | N64: =IF(OR(C64='Account Mapping'!$H$4,C64='Account Mapping'!$H$5,C64='Account Mapping'!$H$6),'Account Mapping'!$I$4,VLOOKUP(A64,'Account Mapping'!$A$2:$E$216,5,0)) -> #N/A | O64: =IF(OR(L64="Loan",L64="Deposit_Liability",L64="OFF_Unused Loan Commitment",L64="HQLA"),VLOOKUP(D64,'Customer Type'!$A$3:$C$38,3,0),"") -> #N/A | P64: =M64&"_"&O64 -> #N/A | Q64: =IF(COUNTIF('Account Mapping'!$H$12:$H$45,A64)>0,-H64,H64) -> 254511.32 | R64: =VLOOKUP(P64,Assumptions!$C$2:$D$64,2,0) -> #N/A | S64: =IFERROR(VLOOKUP(A64,'Maturity Adjustment'!$A$3:$C$81,3,0),(IF(J64<$N$4,"Tomorrow",J64))) -> 47579 | T64: =IF(S64="Tomorrow",1,(S64-$N$4)) -> 1521 | U64: =Q64*R64 -> #N/A | V64: =IFERROR(VLOOKUP(A64,'Maturity Adjustment'!$A$86:$C$91,3,0),S64) -> 47579 | W64: =VLOOKUP(A64,'Account Mapping'!$A$2:$F$216,6,0) -> #N/A | X64: =IF(V64="Tomorrow",Q64,IF(AND(V64>$X$4-1,V64<$X$5),Q64,IF(V64=$X$5,Q64,0))) -> 0 | Y64: =IF(AND(V64>$Y$4-1,V64<$Y$5),Q64,IF(V64=$Y$5,Q64,0)) -> 0 | Z64: =IF(AND(V64>$Z$4-1,V64<$Z$5),Q64,IF(V64=$Z$5,Q64,0)) -> 0 | AA64: =IF(AND(V64>$AA$4-1,V64<$AA$5),Q64,IF(V64=$AA$5,Q64,0)) -> 0 | AB64: =IF(AND(V64>$AB$4-1,V64<$AB$5),Q64,IF(V64=$AB$5,Q64,0)) -> 0 | AC64: =IF(AND(V64>$AC$4-1,V64<$AC$5),Q64,IF(V64=$AC$5,Q64,0)) -> 0 | AD64: =IF(AND(V64>$AD$4-1,V64<$AD$5),Q64,IF(V64=$AD$5,Q64,0)) -> 0 | AE64: =IF(AND(V64>$AE$4-1,V64<$AE$5),Q64,IF(V64=$AE$5,Q64,0)) -> 254511.32 | AF64: =IF(AND(V64>$AF$4-1,V64<$AF$5),Q64,IF(V64=$AF$5,Q64,0)) -> 0 | AG64: =IF(AND(V64>$AG$4-1,V64<$AG$5),Q64,IF(V64=$AG$5,Q64,0)) -> 0 | AH64: =Q64=SUM(X64:AG64) -> TRUE
A65: 10630001 | B65: Syndicated Loans (Long Term) - Domestic | C65: 6115904000438 | D65: 100000014 | E65: PERDAMAN CHEMICALS & FERTILISERS (FINANCE)PTY LTD | F65: USD | G65: 173203.83 | H65: 246588.6 | I65: 45611 | J65: 47579 | K65: 46058 | L65: =VLOOKUP(A65,'Account Mapping'!$A$2:$E$216,3,0) -> #N/A | M65: =VLOOKUP(A65,'Account Mapping'!$A$2:$E$216,4,0) -> #N/A | N65: =IF(OR(C65='Account Mapping'!$H$4,C65='Account Mapping'!$H$5,C65='Account Mapping'!$H$6),'Account Mapping'!$I$4,VLOOKUP(A65,'Account Mapping'!$A$2:$E$216,5,0)) -> #N/A | O65: =IF(OR(L65="Loan",L65="Deposit_Liability",L65="OFF_Unused Loan Commitment",L65="HQLA"),VLOOKUP(D65,'Customer Type'!$A$3:$C$38,3,0),"") -> #N/A | P65: =M65&"_"&O65 -> #N/A | Q65: =IF(COUNTIF('Account Mapping'!$H$12:$H$45,A65)>0,-H65,H65) -> 246588.6 | R65: =VLOOKUP(P65,Assumptions!$C$2:$D$64,2,0) -> #N/A | S65: =IFERROR(VLOOKUP(A65,'Maturity Adjustment'!$A$3:$C$81,3,0),(IF(J65<$N$4,"Tomorrow",J65))) -> 47579 | T65: =IF(S65="Tomorrow",1,(S65-$N$4)) -> 1521 | U65: =Q65*R65 -> #N/A | V65: =IFERROR(VLOOKUP(A65,'Maturity Adjustment'!$A$86:$C$91,3,0),S65) -> 47579 | W65: =VLOOKUP(A65,'Account Mapping'!$A$2:$F$216,6,0) -> #N/A | X65: =IF(V65="Tomorrow",Q65,IF(AND(V65>$X$4-1,V65<$X$5),Q65,IF(V65=$X$5,Q65,0))) -> 0 | Y65: =IF(AND(V65>$Y$4-1,V65<$Y$5),Q65,IF(V65=$Y$5,Q65,0)) -> 0 | Z65: =IF(AND(V65>$Z$4-1,V65<$Z$5),Q65,IF(V65=$Z$5,Q65,0)) -> 0 | AA65: =IF(AND(V65>$AA$4-1,V65<$AA$5),Q65,IF(V65=$AA$5,Q65,0)) -> 0 | AB65: =IF(AND(V65>$AB$4-1,V65<$AB$5),Q65,IF(V65=$AB$5,Q65,0)) -> 0 | AC65: =IF(AND(V65>$AC$4-1,V65<$AC$5),Q65,IF(V65=$AC$5,Q65,0)) -> 0 | AD65: =IF(AND(V65>$AD$4-1,V65<$AD$5),Q65,IF(V65=$AD$5,Q65,0)) -> 0 | AE65: =IF(AND(V65>$AE$4-1,V65<$AE$5),Q65,IF(V65=$AE$5,Q65,0)) -> 246588.6 | AF65: =IF(AND(V65>$AF$4-1,V65<$AF$5),Q65,IF(V65=$AF$5,Q65,0)) -> 0 | AG65: =IF(AND(V65>$AG$4-1,V65<$AG$5),Q65,IF(V65=$AG$5,Q65,0)) -> 0 | AH65: =Q65=SUM(X65:AG65) -> TRUE
A66: 10630001 | B66: Syndicated Loans (Long Term) - Domestic | C66: 6115904000445 | D66: 100000014 | E66: PERDAMAN CHEMICALS & FERTILISERS (FINANCE)PTY LTD | F66: USD | G66: 301075.27 | H66: 428637.91 | I66: 45625 | J66: 47579 | K66: 46058 | L66: =VLOOKUP(A66,'Account Mapping'!$A$2:$E$216,3,0) -> #N/A | M66: =VLOOKUP(A66,'Account Mapping'!$A$2:$E$216,4,0) -> #N/A | N66: =IF(OR(C66='Account Mapping'!$H$4,C66='Account Mapping'!$H$5,C66='Account Mapping'!$H$6),'Account Mapping'!$I$4,VLOOKUP(A66,'Account Mapping'!$A$2:$E$216,5,0)) -> #N/A | O66: =IF(OR(L66="Loan",L66="Deposit_Liability",L66="OFF_Unused Loan Commitment",L66="HQLA"),VLOOKUP(D66,'Customer Type'!$A$3:$C$38,3,0),"") -> #N/A | P66: =M66&"_"&O66 -> #N/A | Q66: =IF(COUNTIF('Account Mapping'!$H$12:$H$45,A66)>0,-H66,H66) -> 428637.91 | R66: =VLOOKUP(P66,Assumptions!$C$2:$D$64,2,0) -> #N/A | S66: =IFERROR(VLOOKUP(A66,'Maturity Adjustment'!$A$3:$C$81,3,0),(IF(J66<$N$4,"Tomorrow",J66))) -> 47579 | T66: =IF(S66="Tomorrow",1,(S66-$N$4)) -> 1521 | U66: =Q66*R66 -> #N/A | V66: =IFERROR(VLOOKUP(A66,'Maturity Adjustment'!$A$86:$C$91,3,0),S66) -> 47579 | W66: =VLOOKUP(A66,'Account Mapping'!$A$2:$F$216,6,0) -> #N/A | X66: =IF(V66="Tomorrow",Q66,IF(AND(V66>$X$4-1,V66<$X$5),Q66,IF(V66=$X$5,Q66,0))) -> 0 | Y66: =IF(AND(V66>$Y$4-1,V66<$Y$5),Q66,IF(V66=$Y$5,Q66,0)) -> 0 | Z66: =IF(AND(V66>$Z$4-1,V66<$Z$5),Q66,IF(V66=$Z$5,Q66,0)) -> 0 | AA66: =IF(AND(V66>$AA$4-1,V66<$AA$5),Q66,IF(V66=$AA$5,Q66,0)) -> 0 | AB66: =IF(AND(V66>$AB$4-1,V66<$AB$5),Q66,IF(V66=$AB$5,Q66,0)) -> 0 | AC66: =IF(AND(V66>$AC$4-1,V66<$AC$5),Q66,IF(V66=$AC$5,Q66,0)) -> 0 | AD66: =IF(AND(V66>$AD$4-1,V66<$AD$5),Q66,IF(V66=$AD$5,Q66,0)) -> 0 | AE66: =IF(AND(V66>$AE$4-1,V66<$AE$5),Q66,IF(V66=$AE$5,Q66,0)) -> 428637.91 | AF66: =IF(AND(V66>$AF$4-1,V66<$AF$5),Q66,IF(V66=$AF$5,Q66,0)) -> 0 | AG66: =IF(AND(V66>$AG$4-1,V66<$AG$5),Q66,IF(V66=$AG$5,Q66,0)) -> 0 | AH66: =Q66=SUM(X66:AG66) -> TRUE
... A93: 10630001 | B93: Syndicated Loans (Long Term) - Domestic | C93: 6115904000783 | D93: 100000014 | E93: PERDAMAN CHEMICALS & FERTILISERS (FINANCE)PTY LTD | F93: USD | G93: 275889.41 | H93: 392781.05 | I93: 46027 | J93: 47579 | K93: 46058 | L93: =VLOOKUP(A93,'Account Mapping'!$A$2:$E$216,3,0) -> #N/A | M93: =VLOOKUP(A93,'Account Mapping'!$A$2:$E$216,4,0) -> #N/A | N93: =IF(OR(C93='Account Mapping'!$H$4,C93='Account Mapping'!$H$5,C93='Account Mapping'!$H$6),'Account Mapping'!$I$4,VLOOKUP(A93,'Account Mapping'!$A$2:$E$216,5,0)) -> #N/A | O93: =IF(OR(L93="Loan",L93="Deposit_Liability",L93="OFF_Unused Loan Commitment",L93="HQLA"),VLOOKUP(D93,'Customer Type'!$A$3:$C$38,3,0),"") -> #N/A | P93: =M93&"_"&O93 -> #N/A | Q93: =IF(COUNTIF('Account Mapping'!$H$12:$H$45,A93)>0,-H93,H93) -> 392781.05 | R93: =VLOOKUP(P93,Assumptions!$C$2:$D$64,2,0) -> #N/A | S93: =IFERROR(VLOOKUP(A93,'Maturity Adjustment'!$A$3:$C$81,3,0),(IF(J93<$N$4,"Tomorrow",J93))) -> 47579 | T93: =IF(S93="Tomorrow",1,(S93-$N$4)) -> 1521 | U93: =Q93*R93 -> #N/A | V93: =IFERROR(VLOOKUP(A93,'Maturity Adjustment'!$A$86:$C$91,3,0),S93) -> 47579 | W93: =VLOOKUP(A93,'Account Mapping'!$A$2:$F$216,6,0) -> #N/A | X93: =IF(V93="Tomorrow",Q93,IF(AND(V93>$X$4-1,V93<$X$5),Q93,IF(V93=$X$5,Q93,0))) -> 0 | Y93: =IF(AND(V93>$Y$4-1,V93<$Y$5),Q93,IF(V93=$Y$5,Q93,0)) -> 0 | Z93: =IF(AND(V93>$Z$4-1,V93<$Z$5),Q93,IF(V93=$Z$5,Q93,0)) -> 0 | AA93: =IF(AND(V93>$AA$4-1,V93<$AA$5),Q93,IF(V93=$AA$5,Q93,0)) -> 0 | AB93: =IF(AND(V93>$AB$4-1,V93<$AB$5),Q93,IF(V93=$AB$5,Q93,0)) -> 0 | AC93: =IF(AND(V93>$AC$4-1,V93<$AC$5),Q93,IF(V93=$AC$5,Q93,0)) -> 0 | AD93: =IF(AND(V93>$AD$4-1,V93<$AD$5),Q93,IF(V93=$AD$5,Q93,0)) -> 0 | AE93: =IF(AND(V93>$AE$4-1,V93<$AE$5),Q93,IF(V93=$AE$5,Q93,0)) -> 392781.05 | AF93: =IF(AND(V93>$AF$4-1,V93<$AF$5),Q93,IF(V93=$AF$5,Q93,0)) -> 0 | AG93: =IF(AND(V93>$AG$4-1,V93<$AG$5),Q93,IF(V93=$AG$5,Q93,0)) -> 0 | AH93: =Q93=SUM(X93:AG93) -> TRUE
A94: 10690001 | B94: Allowance For Loan Losses - General | C94: OL5904220000001 | D94: 100000003 | E94: COSMAX NBT AUSTRALIA PTY LTD | F94: AUD | G94: -66801.6 | H94: -66801.6 | L94: =VLOOKUP(A94,'Account Mapping'!$A$2:$E$216,3,0) -> #N/A | M94: =VLOOKUP(A94,'Account Mapping'!$A$2:$E$216,4,0) -> #N/A | N94: =IF(OR(C94='Account Mapping'!$H$4,C94='Account Mapping'!$H$5,C94='Account Mapping'!$H$6),'Account Mapping'!$I$4,VLOOKUP(A94,'Account Mapping'!$A$2:$E$216,5,0)) -> #N/A | O94: =IF(OR(L94="Loan",L94="Deposit_Liability",L94="OFF_Unused Loan Commitment",L94="HQLA"),VLOOKUP(D94,'Customer Type'!$A$3:$C$38,3,0),"") -> #N/A | P94: =M94&"_"&O94 -> #N/A | Q94: =IF(COUNTIF('Account Mapping'!$H$12:$H$45,A94)>0,-H94,H94) -> 66801.6 | R94: =VLOOKUP(P94,Assumptions!$C$2:$D$64,2,0) -> #N/A | S94: =IFERROR(VLOOKUP(A94,'Maturity Adjustment'!$A$3:$C$81,3,0),(IF(J94<$N$4,"Tomorrow",J94))) -> Tomorrow | T94: =IF(S94="Tomorrow",1,(S94-$N$4)) -> 1 | U94: =Q94*R94 -> #N/A | V94: =IFERROR(VLOOKUP(A94,'Maturity Adjustment'!$A$86:$C$91,3,0),S94) -> Tomorrow | W94: =VLOOKUP(A94,'Account Mapping'!$A$2:$F$216,6,0) -> #N/A | X94: =IF(V94="Tomorrow",Q94,IF(AND(V94>$X$4-1,V94<$X$5),Q94,IF(V94=$X$5,Q94,0))) -> 66801.6 | Y94: =IF(AND(V94>$Y$4-1,V94<$Y$5),Q94,IF(V94=$Y$5,Q94,0)) -> 0 | Z94: =IF(AND(V94>$Z$4-1,V94<$Z$5),Q94,IF(V94=$Z$5,Q94,0)) -> 0 | AA94: =IF(AND(V94>$AA$4-1,V94<$AA$5),Q94,IF(V94=$AA$5,Q94,0)) -> 0 | AB94: =IF(AND(V94>$AB$4-1,V94<$AB$5),Q94,IF(V94=$AB$5,Q94,0)) -> 0 | AC94: =IF(AND(V94>$AC$4-1,V94<$AC$5),Q94,IF(V94=$AC$5,Q94,0)) -> 0 | AD94: =IF(AND(V94>$AD$4-1,V94<$AD$5),Q94,IF(V94=$AD$5,Q94,0)) -> 0 | AE94: =IF(AND(V94>$AE$4-1,V94<$AE$5),Q94,IF(V94=$AE$5,Q94,0)) -> 0 | AF94: =IF(AND(V94>$AF$4-1,V94<$AF$5),Q94,IF(V94=$AF$5,Q94,0)) -> 0 | AG94: =IF(AND(V94>$AG$4-1,V94<$AG$5),Q94,IF(V94=$AG$5,Q94,0)) -> 0 | AH94: =Q94=SUM(X94:AG94) -> TRUE
A95: 10690001 | B95: Allowance For Loan Losses - General | C95: OL5904230000006 | D95: 100000014 | E95: PERDAMAN CHEMICALS & FERTILISERS (FINANCE)PTY LTD | F95: USD | G95: -833.7 | H95: -1186.93 | L95: =VLOOKUP(A95,'Account Mapping'!$A$2:$E$216,3,0) -> #N/A | M95: =VLOOKUP(A95,'Account Mapping'!$A$2:$E$216,4,0) -> #N/A | N95: =IF(OR(C95='Account Mapping'!$H$4,C95='Account Mapping'!$H$5,C95='Account Mapping'!$H$6),'Account Mapping'!$I$4,VLOOKUP(A95,'Account Mapping'!$A$2:$E$216,5,0)) -> #N/A | O95: =IF(OR(L95="Loan",L95="Deposit_Liability",L95="OFF_Unused Loan Commitment",L95="HQLA"),VLOOKUP(D95,'Customer Type'!$A$3:$C$38,3,0),"") -> #N/A | P95: =M95&"_"&O95 -> #N/A | Q95: =IF(COUNTIF('Account Mapping'!$H$12:$H$45,A95)>0,-H95,H95) -> 1186.93 | R95: =VLOOKUP(P95,Assumptions!$C$2:$D$64,2,0) -> #N/A | S95: =IFERROR(VLOOKUP(A95,'Maturity Adjustment'!$A$3:$C$81,3,0),(IF(J95<$N$4,"Tomorrow",J95))) -> Tomorrow | T95: =IF(S95="Tomorrow",1,(S95-$N$4)) -> 1 | U95: =Q95*R95 -> #N/A | V95: =IFERROR(VLOOKUP(A95,'Maturity Adjustment'!$A$86:$C$91,3,0),S95) -> Tomorrow | W95: =VLOOKUP(A95,'Account Mapping'!$A$2:$F$216,6,0) -> #N/A | X95: =IF(V95="Tomorrow",Q95,IF(AND(V95>$X$4-1,V95<$X$5),Q95,IF(V95=$X$5,Q95,0))) -> 1186.93 | Y95: =IF(AND(V95>$Y$4-1,V95<$Y$5),Q95,IF(V95=$Y$5,Q95,0)) -> 0 | Z95: =IF(AND(V95>$Z$4-1,V95<$Z$5),Q95,IF(V95=$Z$5,Q95,0)) -> 0 | AA95: =IF(AND(V95>$AA$4-1,V95<$AA$5),Q95,IF(V95=$AA$5,Q95,0)) -> 0 | AB95: =IF(AND(V95>$AB$4-1,V95<$AB$5),Q95,IF(V95=$AB$5,Q95,0)) -> 0 | AC95: =IF(AND(V95>$AC$4-1,V95<$AC$5),Q95,IF(V95=$AC$5,Q95,0)) -> 0 | AD95: =IF(AND(V95>$AD$4-1,V95<$AD$5),Q95,IF(V95=$AD$5,Q95,0)) -> 0 | AE95: =IF(AND(V95>$AE$4-1,V95<$AE$5),Q95,IF(V95=$AE$5,Q95,0)) -> 0 | AF95: =IF(AND(V95>$AF$4-1,V95<$AF$5),Q95,IF(V95=$AF$5,Q95,0)) -> 0 | AG95: =IF(AND(V95>$AG$4-1,V95<$AG$5),Q95,IF(V95=$AG$5,Q95,0)) -> 0 | AH95: =Q95=SUM(X95:AG95) -> TRUE
A96: 10690001 | B96: Allowance For Loan Losses - General | C96: OL5904230000007 | D96: 100000014 | E96: PERDAMAN CHEMICALS & FERTILISERS (FINANCE)PTY LTD | F96: USD | G96: -48803.72 | H96: -69481.38 | L96: =VLOOKUP(A96,'Account Mapping'!$A$2:$E$216,3,0) -> #N/A | M96: =VLOOKUP(A96,'Account Mapping'!$A$2:$E$216,4,0) -> #N/A | N96: =IF(OR(C96='Account Mapping'!$H$4,C96='Account Mapping'!$H$5,C96='Account Mapping'!$H$6),'Account Mapping'!$I$4,VLOOKUP(A96,'Account Mapping'!$A$2:$E$216,5,0)) -> #N/A | O96: =IF(OR(L96="Loan",L96="Deposit_Liability",L96="OFF_Unused Loan Commitment",L96="HQLA"),VLOOKUP(D96,'Customer Type'!$A$3:$C$38,3,0),"") -> #N/A | P96: =M96&"_"&O96 -> #N/A | Q96: =IF(COUNTIF('Account Mapping'!$H$12:$H$45,A96)>0,-H96,H96) -> 69481.38 | R96: =VLOOKUP(P96,Assumptions!$C$2:$D$64,2,0) -> #N/A | S96: =IFERROR(VLOOKUP(A96,'Maturity Adjustment'!$A$3:$C$81,3,0),(IF(J96<$N$4,"Tomorrow",J96))) -> Tomorrow | T96: =IF(S96="Tomorrow",1,(S96-$N$4)) -> 1 | U96: =Q96*R96 -> #N/A | V96: =IFERROR(VLOOKUP(A96,'Maturity Adjustment'!$A$86:$C$91,3,0),S96) -> Tomorrow | W96: =VLOOKUP(A96,'Account Mapping'!$A$2:$F$216,6,0) -> #N/A | X96: =IF(V96="Tomorrow",Q96,IF(AND(V96>$X$4-1,V96<$X$5),Q96,IF(V96=$X$5,Q96,0))) -> 69481.38 | Y96: =IF(AND(V96>$Y$4-1,V96<$Y$5),Q96,IF(V96=$Y$5,Q96,0)) -> 0 | Z96: =IF(AND(V96>$Z$4-1,V96<$Z$5),Q96,IF(V96=$Z$5,Q96,0)) -> 0 | AA96: =IF(AND(V96>$AA$4-1,V96<$AA$5),Q96,IF(V96=$AA$5,Q96,0)) -> 0 | AB96: =IF(AND(V96>$AB$4-1,V96<$AB$5),Q96,IF(V96=$AB$5,Q96,0)) -> 0 | AC96: =IF(AND(V96>$AC$4-1,V96<$AC$5),Q96,IF(V96=$AC$5,Q96,0)) -> 0 | AD96: =IF(AND(V96>$AD$4-1,V96<$AD$5),Q96,IF(V96=$AD$5,Q96,0)) -> 0 | AE96: =IF(AND(V96>$AE$4-1,V96<$AE$5),Q96,IF(V96=$AE$5,Q96,0)) -> 0 | AF96: =IF(AND(V96>$AF$4-1,V96<$AF$5),Q96,IF(V96=$AF$5,Q96,0)) -> 0 | AG96: =IF(AND(V96>$AG$4-1,V96<$AG$5),Q96,IF(V96=$AG$5,Q96,0)) -> 0 | AH96: =Q96=SUM(X96:AG96) -> TRUE
A97: 10690001 | B97: Allowance For Loan Losses - General | C97: OL5904230000008 | D97: 100000014 | E97: PERDAMAN CHEMICALS & FERTILISERS (FINANCE)PTY LTD | F97: USD | G97: -633.31 | H97: -901.64 | L97: =VLOOKUP(A97,'Account Mapping'!$A$2:$E$216,3,0) -> #N/A | M97: =VLOOKUP(A97,'Account Mapping'!$A$2:$E$216,4,0) -> #N/A | N97: =IF(OR(C97='Account Mapping'!$H$4,C97='Account Mapping'!$H$5,C97='Account Mapping'!$H$6),'Account Mapping'!$I$4,VLOOKUP(A97,'Account Mapping'!$A$2:$E$216,5,0)) -> #N/A | O97: =IF(OR(L97="Loan",L97="Deposit_Liability",L97="OFF_Unused Loan Commitment",L97="HQLA"),VLOOKUP(D97,'Customer Type'!$A$3:$C$38,3,0),"") -> #N/A | P97: =M97&"_"&O97 -> #N/A | Q97: =IF(COUNTIF('Account Mapping'!$H$12:$H$45,A97)>0,-H97,H97) -> 901.64 | R97: =VLOOKUP(P97,Assumptions!$C$2:$D$64,2,0) -> #N/A | S97: =IFERROR(VLOOKUP(A97,'Maturity Adjustment'!$A$3:$C$81,3,0),(IF(J97<$N$4,"Tomorrow",J97))) -> Tomorrow | T97: =IF(S97="Tomorrow",1,(S97-$N$4)) -> 1 | U97: =Q97*R97 -> #N/A | V97: =IFERROR(VLOOKUP(A97,'Maturity Adjustment'!$A$86:$C$91,3,0),S97) -> Tomorrow | W97: =VLOOKUP(A97,'Account Mapping'!$A$2:$F$216,6,0) -> #N/A | X97: =IF(V97="Tomorrow",Q97,IF(AND(V97>$X$4-1,V97<$X$5),Q97,IF(V97=$X$5,Q97,0))) -> 901.64 | Y97: =IF(AND(V97>$Y$4-1,V97<$Y$5),Q97,IF(V97=$Y$5,Q97,0)) -> 0 | Z97: =IF(AND(V97>$Z$4-1,V97<$Z$5),Q97,IF(V97=$Z$5,Q97,0)) -> 0 | AA97: =IF(AND(V97>$AA$4-1,V97<$AA$5),Q97,IF(V97=$AA$5,Q97,0)) -> 0 | AB97: =IF(AND(V97>$AB$4-1,V97<$AB$5),Q97,IF(V97=$AB$5,Q97,0)) -> 0 | AC97: =IF(AND(V97>$AC$4-1,V97<$AC$5),Q97,IF(V97=$AC$5,Q97,0)) -> 0 | AD97: =IF(AND(V97>$AD$4-1,V97<$AD$5),Q97,IF(V97=$AD$5,Q97,0)) -> 0 | AE97: =IF(AND(V97>$AE$4-1,V97<$AE$5),Q97,IF(V97=$AE$5,Q97,0)) -> 0 | AF97: =IF(AND(V97>$AF$4-1,V97<$AF$5),Q97,IF(V97=$AF$5,Q97,0)) -> 0 | AG97: =IF(AND(V97>$AG$4-1,V97<$AG$5),Q97,IF(V97=$AG$5,Q97,0)) -> 0 | AH97: =Q97=SUM(X97:AG97) -> TRUE
A98: 10690001 | B98: Allowance For Loan Losses - General | C98: OL5904230000009 | D98: 100000014 | E98: PERDAMAN CHEMICALS & FERTILISERS (FINANCE)PTY LTD | F98: USD | G98: -11491.72 | H98: -16360.65 | L98: =VLOOKUP(A98,'Account Mapping'!$A$2:$E$216,3,0) -> #N/A | M98: =VLOOKUP(A98,'Account Mapping'!$A$2:$E$216,4,0) -> #N/A | N98: =IF(OR(C98='Account Mapping'!$H$4,C98='Account Mapping'!$H$5,C98='Account Mapping'!$H$6),'Account Mapping'!$I$4,VLOOKUP(A98,'Account Mapping'!$A$2:$E$216,5,0)) -> #N/A | O98: =IF(OR(L98="Loan",L98="Deposit_Liability",L98="OFF_Unused Loan Commitment",L98="HQLA"),VLOOKUP(D98,'Customer Type'!$A$3:$C$38,3,0),"") -> #N/A | P98: =M98&"_"&O98 -> #N/A | Q98: =IF(COUNTIF('Account Mapping'!$H$12:$H$45,A98)>0,-H98,H98) -> 16360.65 | R98: =VLOOKUP(P98,Assumptions!$C$2:$D$64,2,0) -> #N/A | S98: =IFERROR(VLOOKUP(A98,'Maturity Adjustment'!$A$3:$C$81,3,0),(IF(J98<$N$4,"Tomorrow",J98))) -> Tomorrow | T98: =IF(S98="Tomorrow",1,(S98-$N$4)) -> 1 | U98: =Q98*R98 -> #N/A | V98: =IFERROR(VLOOKUP(A98,'Maturity Adjustment'!$A$86:$C$91,3,0),S98) -> Tomorrow | W98: =VLOOKUP(A98,'Account Mapping'!$A$2:$F$216,6,0) -> #N/A | X98: =IF(V98="Tomorrow",Q98,IF(AND(V98>$X$4-1,V98<$X$5),Q98,IF(V98=$X$5,Q98,0))) -> 16360.65 | Y98: =IF(AND(V98>$Y$4-1,V98<$Y$5),Q98,IF(V98=$Y$5,Q98,0)) -> 0 | Z98: =IF(AND(V98>$Z$4-1,V98<$Z$5),Q98,IF(V98=$Z$5,Q98,0)) -> 0 | AA98: =IF(AND(V98>$AA$4-1,V98<$AA$5),Q98,IF(V98=$AA$5,Q98,0)) -> 0 | AB98: =IF(AND(V98>$AB$4-1,V98<$AB$5),Q98,IF(V98=$AB$5,Q98,0)) -> 0 | AC98: =IF(AND(V98>$AC$4-1,V98<$AC$5),Q98,IF(V98=$AC$5,Q98,0)) -> 0 | AD98: =IF(AND(V98>$AD$4-1,V98<$AD$5),Q98,IF(V98=$AD$5,Q98,0)) -> 0 | AE98: =IF(AND(V98>$AE$4-1,V98<$AE$5),Q98,IF(V98=$AE$5,Q98,0)) -> 0 | AF98: =IF(AND(V98>$AF$4-1,V98<$AF$5),Q98,IF(V98=$AF$5,Q98,0)) -> 0 | AG98: =IF(AND(V98>$AG$4-1,V98<$AG$5),Q98,IF(V98=$AG$5,Q98,0)) -> 0 | AH98: =Q98=SUM(X98:AG98) -> TRUE
A99: 10690001 | B99: Allowance For Loan Losses - General | C99: OL5904230000010 | D99: 100000014 | E99: PERDAMAN CHEMICALS & FERTILISERS (FINANCE)PTY LTD | F99: USD | G99: -715.23 | H99: -1018.27 | L99: =VLOOKUP(A99,'Account Mapping'!$A$2:$E$216,3,0) -> #N/A | M99: =VLOOKUP(A99,'Account Mapping'!$A$2:$E$216,4,0) -> #N/A | N99: =IF(OR(C99='Account Mapping'!$H$4,C99='Account Mapping'!$H$5,C99='Account Mapping'!$H$6),'Account Mapping'!$I$4,VLOOKUP(A99,'Account Mapping'!$A$2:$E$216,5,0)) -> #N/A | O99: =IF(OR(L99="Loan",L99="Deposit_Liability",L99="OFF_Unused Loan Commitment",L99="HQLA"),VLOOKUP(D99,'Customer Type'!$A$3:$C$38,3,0),"") -> #N/A | P99: =M99&"_"&O99 -> #N/A | Q99: =IF(COUNTIF('Account Mapping'!$H$12:$H$45,A99)>0,-H99,H99) -> 1018.27 | R99: =VLOOKUP(P99,Assumptions!$C$2:$D$64,2,0) -> #N/A | S99: =IFERROR(VLOOKUP(A99,'Maturity Adjustment'!$A$3:$C$81,3,0),(IF(J99<$N$4,"Tomorrow",J99))) -> Tomorrow | T99: =IF(S99="Tomorrow",1,(S99-$N$4)) -> 1 | U99: =Q99*R99 -> #N/A | V99: =IFERROR(VLOOKUP(A99,'Maturity Adjustment'!$A$86:$C$91,3,0),S99) -> Tomorrow | W99: =VLOOKUP(A99,'Account Mapping'!$A$2:$F$216,6,0) -> #N/A | X99: =IF(V99="Tomorrow",Q99,IF(AND(V99>$X$4-1,V99<$X$5),Q99,IF(V99=$X$5,Q99,0))) -> 1018.27 | Y99: =IF(AND(V99>$Y$4-1,V99<$Y$5),Q99,IF(V99=$Y$5,Q99,0)) -> 0 | Z99: =IF(AND(V99>$Z$4-1,V99<$Z$5),Q99,IF(V99=$Z$5,Q99,0)) -> 0 | AA99: =IF(AND(V99>$AA$4-1,V99<$AA$5),Q99,IF(V99=$AA$5,Q99,0)) -> 0 | AB99: =IF(AND(V99>$AB$4-1,V99<$AB$5),Q99,IF(V99=$AB$5,Q99,0)) -> 0 | AC99: =IF(AND(V99>$AC$4-1,V99<$AC$5),Q99,IF(V99=$AC$5,Q99,0)) -> 0 | AD99: =IF(AND(V99>$AD$4-1,V99<$AD$5),Q99,IF(V99=$AD$5,Q99,0)) -> 0 | AE99: =IF(AND(V99>$AE$4-1,V99<$AE$5),Q99,IF(V99=$AE$5,Q99,0)) -> 0 | AF99: =IF(AND(V99>$AF$4-1,V99<$AF$5),Q99,IF(V99=$AF$5,Q99,0)) -> 0 | AG99: =IF(AND(V99>$AG$4-1,V99<$AG$5),Q99,IF(V99=$AG$5,Q99,0)) -> 0 | AH99: =Q99=SUM(X99:AG99) -> TRUE
A100: 10690001 | B100: Allowance For Loan Losses - General | C100: OL5904230000011 | D100: 100000014 | E100: PERDAMAN CHEMICALS & FERTILISERS (FINANCE)PTY LTD | F100: USD | G100: -3012.73 | H100: -4289.19 | L100: =VLOOKUP(A100,'Account Mapping'!$A$2:$E$216,3,0) -> #N/A | M100: =VLOOKUP(A100,'Account Mapping'!$A$2:$E$216,4,0) -> #N/A | N100: =IF(OR(C100='Account Mapping'!$H$4,C100='Account Mapping'!$H$5,C100='Account Mapping'!$H$6),'Account Mapping'!$I$4,VLOOKUP(A100,'Account Mapping'!$A$2:$E$216,5,0)) -> #N/A | O100: =IF(OR(L100="Loan",L100="Deposit_Liability",L100="OFF_Unused Loan Commitment",L100="HQLA"),VLOOKUP(D100,'Customer Type'!$A$3:$C$38,3,0),"") -> #N/A | P100: =M100&"_"&O100 -> #N/A | Q100: =IF(COUNTIF('Account Mapping'!$H$12:$H$45,A100)>0,-H100,H100) -> 4289.19 | R100: =VLOOKUP(P100,Assumptions!$C$2:$D$64,2,0) -> #N/A | S100: =IFERROR(VLOOKUP(A100,'Maturity Adjustment'!$A$3:$C$81,3,0),(IF(J100<$N$4,"Tomorrow",J100))) -> Tomorrow | T100: =IF(S100="Tomorrow",1,(S100-$N$4)) -> 1 | U100: =Q100*R100 -> #N/A | V100: =IFERROR(VLOOKUP(A100,'Maturity Adjustment'!$A$86:$C$91,3,0),S100) -> Tomorrow | W100: =VLOOKUP(A100,'Account Mapping'!$A$2:$F$216,6,0) -> #N/A | X100: =IF(V100="Tomorrow",Q100,IF(AND(V100>$X$4-1,V100<$X$5),Q100,IF(V100=$X$5,Q100,0))) -> 4289.19 | Y100: =IF(AND(V100>$Y$4-1,V100<$Y$5),Q100,IF(V100=$Y$5,Q100,0)) -> 0 | Z100: =IF(AND(V100>$Z$4-1,V100<$Z$5),Q100,IF(V100=$Z$5,Q100,0)) -> 0 | AA100: =IF(AND(V100>$AA$4-1,V100<$AA$5),Q100,IF(V100=$AA$5,Q100,0)) -> 0 | AB100: =IF(AND(V100>$AB$4-1,V100<$AB$5),Q100,IF(V100=$AB$5,Q100,0)) -> 0 | AC100: =IF(AND(V100>$AC$4-1,V100<$AC$5),Q100,IF(V100=$AC$5,Q100,0)) -> 0 | AD100: =IF(AND(V100>$AD$4-1,V100<$AD$5),Q100,IF(V100=$AD$5,Q100,0)) -> 0 | AE100: =IF(AND(V100>$AE$4-1,V100<$AE$5),Q100,IF(V100=$AE$5,Q100,0)) -> 0 | AF100: =IF(AND(V100>$AF$4-1,V100<$AF$5),Q100,IF(V100=$AF$5,Q100,0)) -> 0 | AG100: =IF(AND(V100>$AG$4-1,V100<$AG$5),Q100,IF(V100=$AG$5,Q100,0)) -> 0 | AH100: =Q100=SUM(X100:AG100) -> TRUE
